Workbook

Sheet Tableau de bord
B2: TABLEAU DE BORD LST ET MST - OPENSTONE INFRAWORLD, COMPARTIMENT I
B3: ="Projection à partir de la fin du blocage ("&DAY(Date_depart)&"/"&RIGHT("0"&MONTH(Date_depart),2)&"/"&YEAR(Date_depart)&"), huit dates de rachat semestrielles, actif net de départ "&ROUND(AN_depart/1000000,0)&" M€. Phase : "&Phase&". Les cellules sont des formules vers les onglets de calcul." -> Projection à partir de la fin du blocage (31/12/2028), huit dates de rachat semestrielles, actif net de départ 8 M€. Phase : Montée en charge. Les cellules sont des formules vers les onglets de calcul.
B5: A. INDICATEURS DE TÊTE
B6: Indicateur | C6: Valeur | G6: Lecture
B7: Taille de lancement retenue (sélecteur de l'onglet Paramètres) | C7: =AN_depart -> 8000000 | G7: Comparatif des cinq tailles dans l'onglet dédié
B8: Écart actif - passif en régime normal (jours) | C8: =Ecart_TTL_N -> -28.93 | G8: WATTL actif moins LTTL moyen ; porté par la poche liquide et le plafonnement
B9: Écart actif - passif en S3 (jours) | C9: =Ecart_TTL_S3 -> 206.7 | G9: Justification structurelle du gate de 5 %
B10: Actifs liquides à 30 jours, normal / S3 | C10: =HQLA_N -> 0.16 | D10: =HQLA_S3 -> 0.1567 | G10: Trésorerie et fonds HY après haircut
B11: Capacité maximale de sortie sur douze mois (2 × gate) | C11: =2*Gate -> 0.1 | G11: Prospectus art. 7.2.6
B12: Part du premier porteur et dates de gate consommées | C12: =Top1 -> 0.15 | D12: =Top1_dates -> 3 | G12: Choc porteur 1
B13: Point de rupture avec plafonnement (taux par date) | C13: =Rupture_gated -> 0.05 | D13: =Rupture_suspension -> 0.075 | G13: Premier taux imposant des cessions décotées malgré le gate ; suspension dès le premier taux supérieur au gate
B14: Point de rupture sans plafonnement (taux par date) | C14: =Rupture_ungated -> 0.05 | D14: =Rupture_impossible -> 0.075 | G14: Premier taux imposant des cessions décotées ; cession impossible au-delà de la valeur en colonne D
B15: Point de rupture des appels de fonds (non-appelé, % AN) | C15: =Rupture_appels -> 0.125 | G15: Non-appelé au-delà duquel une cession s'impose en douze mois
B16: Cessions à la date 8 pour 10 % de rachats par date : avec puis sans plafonnement | C16: =Cession_gate_10 -> 0.027968824 | D16: =Cession_nogate_10 -> 0.59223059 | G16: Valeur du plafonnement : la file remplace la vente forcée
B17: Première date de triple gel en S3 | C17: =LST_S3_gel -> 47118 | G17: Collecte, distributions et capacité evergreen gelées ensemble
B19: B. VERDICTS PAR SCÉNARIO
B20: Scénario | C20: MST (creux de VL) | D20: LST (file à la date 8) | E20: Suspension | F20: Verdict conjoint | G20: Lecture
B21: S1 Base | C21: =MST_S1_creux -> 0.044637287 | D21: =LST_S1_file8 -> 0 | E21: =LST_S1_susp -> - | F21: =Joint_S1 -> Vert | G21: Rachats courants, collecte normale, marchés stables
B22: S2 Plausible | C22: =MST_S2_creux -> -0.014988138 | D22: =LST_S2_file8 -> 0 | E22: =LST_S2_susp -> - | F22: =Joint_S2 -> Rouge | G22: Correction de marché à 1,5 écart-type, rachats de 7,5 % sur deux dates, collecte divisée par deux
B23: S3 Sévère | C23: =MST_S3_creux -> -0.087196361 | D23: =LST_S3_file8 -> 0.4666904 | E23: =LST_S3_susp -> 47848 | F23: =Joint_S3 -> Rouge | G23: Réplique 2008 : pire semestre historique des proxies, rachats de 15 % sur deux dates, collecte nulle, sortie du premier porteur
B24: S4 Extrême | C24: =MST_S4_creux -> -0.17282085 | D24: =LST_S4_file8 -> 0.92475927 | E24: =LST_S4_susp -> 47848 | F24: =Joint_S4 -> Rouge | G24: Queue de distribution à 3,5 écarts-types, rachats de 25 % puis 20 %, gel des distributions, pairs saturant les fonds evergreen
B26: C. ACTIONS RECOMMANDÉES déduites des seuils de l'onglet Intégré
B27: =IF(Phase="Montée en charge","Phase de montée en charge : le risque dominant est la concentration des porteurs, pas la cascade de plafonnement ; LST mensuel jusqu'à la troisième année.","Régime de croisière : LST trimestriel avant chaque date de centralisation.") -> Phase de montée en charge : le risque dominant est la concentration des porteurs, pas la cascade de plafonnement ; LST mensuel jusqu'à la troisième année.
B28: =IF(Top1>0.1,"Premier porteur au-dessus de 10 % : convenir d'un protocole de préavis renforcé et simuler sa sortie avant chaque date.","Concentration des porteurs sous contrôle.") -> Premier porteur au-dessus de 10 % : convenir d'un protocole de préavis renforcé et simuler sa sortie avant chaque date.
B29: =IF(LST_S3_file8>0.3,"S3 : file résiduelle au-dessus de 30 % à la date 8 ; préparer la suspension et l'information de l'AMF.",IF(LST_S3_file8>0.15,"S3 : file résiduelle élevée ; pré-positionner la Prolongation du Délai de Préavis (art. 7.2.7) et la communication aux distributeurs.","S3 : file résorbable sous les outils du prospectus.")) -> S3 : file résiduelle au-dessus de 30 % à la date 8 ; préparer la suspension et l'information de l'AMF.
B30: =IF(LST_S2_poche<S_poche_orange,"S2 : poche liquide sous 15 % ; relever la trésorerie cible ou ralentir les engagements fermés.","S2 : poche liquide conforme à l'article 3.") -> S2 : poche liquide sous 15 % ; relever la trésorerie cible ou ralentir les engagements fermés.
B31: =IF(-MST_S3_creux>S_mst_rouge,"MST S3 : creux de VL au-delà de 25 % ; revoir la transmission des chocs et l'exposition dollar non couverte (51 %).","MST S3 : creux de VL contenu ; surveiller le dollar (aucune couverture possible, art. 22).") -> MST S3 : creux de VL contenu ; surveiller le dollar (aucune couverture possible, art. 22).
B32: =IF(Rupture_appels<=NA_total/AN_depart+0.0001,"Appels : le non-appelé de départ dépasse le point de rupture ; séquencer les engagements fermés.","Appels : le non-appelé de départ reste sous le point de rupture ("&ROUND(Rupture_appels*100,0)&" % de l'AN).") -> Appels : le non-appelé de départ dépasse le point de rupture ; séquencer les engagements fermés.
B33: ="Reporting : les profils ALP et LLP alimentent les questions 178 et 186 de l'Annex IV ; la concentration la question 118." -> Reporting : les profils ALP et LLP alimentent les questions 178 et 186 de l'Annex IV ; la concentration la question 118.
B35: D. HYPOTHÈSES CLÉS À VALIDER EN COMITÉ
B36: Taux de rachat par scénario et collecte (Paramètres G) : aucun historique, hypothèses de la Fonction Risques.
B37: Transmission des chocs cotés aux VL privées : 0,5 par défaut, cohérente avec le rapport VEV privée / VEV cotée du DIC (MST Données).
B38: Pression des pairs sur les gates de PG NGI et d'Ares AGI : 1 en S3 et S4 aux deux premières dates (aucun rachat récupérable).
B39: Décotes de cession secondaire : 15 % (S2), 25 % (S3), 35 % (S4) sur les fonds fermés ; 1 à 5 % sur le fonds HY.
B40: Registre des porteurs hypothétique : à remplacer avant la première VL.

Sheet Paramètres
B2: PARAMÈTRES - ANCRES DU PROSPECTUS, ALLOCATION, HYPOTHÈSES ET CALIBRATION
B3: Source unique de tous les calculs. Cellules cyan : saisies modifiables. Les autres onglets ne contiennent que des formules. Les ancres citent l'article du prospectus du 30/09/2026 (colonne Source).
B5: A. IDENTIFICATION ET DATES
B6: Paramètre | C6: Valeur | D6: Unité | E6: Source | L6: Commentaire
B7: Fonds | C7: Openstone Infraworld, Compartiment I | D7: - | E7: Prospectus, p. 1
B8: Société de Gestion | C8: Fundcraft France SAS, GP-20260008 | D8: - | E8: Prospectus, p. 1
B9: Structure | C9: Fonds de fonds evergreen investissant en direct dans deux fonds fermés, deux fonds evergreen, un fonds obligataire HY quotidien et de la trésorerie | D9: - | E9: Prospectus art. 3
B10: Date d'arrêté | C10: 46301 | D10: date | E10: -
B11: Date de première VL (lancement) | C11: 46387 | D11: date | E11: Hypothèse : constitution au T4 2026 | L11: Pilote la fin du blocage et la phase du Fonds.
B12: Fin de la Période de Blocage = première date de rachat | C12: =EDATE(Date_lancement,Blocage_mois) -> 47118 | D12: date | E12: Prospectus art. 7.2.2 : deux ans à compter de la souscription
B13: Actif net au départ de la projection | C13: =INDEX(Tailles_AN,Taille_sel) -> 8000000 | D13: EUR | E13: Taille retenue dans le bloc C
B14: Phase du Fonds | C14: =IF(YEARFRAC(Date_lancement,Date_depart)<3,"Montée en charge","Régime de croisière") -> Montée en charge | D14: - | E14: Dérivé | L14: En montée en charge, la concentration des porteurs domine le risque de plafonnement.
B15: Années depuis le lancement à la date de départ | C15: =YEARFRAC(Date_lancement,Date_depart) -> 2 | D15: ans | E15: Dérivé
B17: B. ANCRES DU PROSPECTUS (aucune valeur de passif codée ailleurs)
B18: Ancre | C18: Valeur | D18: Unité | E18: Source | L18: Commentaire
B19: Fréquence de la VL | C19: Mensuelle | D19: - | E19: Prospectus art. 6 : dernier jour calendaire de chaque mois
B20: Fréquence des souscriptions | C20: Mensuelle, centralisation 25 JO avant la VL | D20: - | E20: Prospectus art. 7.1.2
B21: Fréquence des rachats | C21: Semestrielle : VL du 30/06 et du 31/12 | D21: - | E21: Prospectus art. 7.2.1
B22: Dates de rachat par an | C22: 2 | D22: dates | E22: Prospectus art. 7.2.1
B23: Préavis : centralisation le 31/03 ou le 30/09 | C23: 91 | D23: jours cal. | E23: Prospectus art. 7.2.3 | L23: Jours entre la Date de Centralisation et la VL de rachat.
B24: Publication de la VL après la date de VL | C24: 30 | D24: JO | E24: Prospectus art. 6 et 7.1.5
B25: Règlement après publication de la VL | C25: 5 | D25: JO | E25: Prospectus art. 7.2.4 : cinq Jours Ouvrés au plus
B26: Délai VL à cash (publication + règlement) | C26: =ROUND((Publication_JO+Reglement_JO)*7/5,0) -> 49 | D26: jours cal. | E26: Dérivé
B27: Plafond de Rachats (gate) par date | C27: 0.05 | D27: % AN | E27: Prospectus art. 7.2.6 : 5 % de l'Actif Net à la VL de rachat | L27: Assiette : demandes centralisées nettes des souscriptions versées.
B28: Base du plafond | C28: AN à la VL du 30/06 ou du 31/12, demandes nettes des souscriptions | D28: - | E28: Prospectus art. 7.2.6
B29: Reports successifs avant examen d'une suspension | C29: 4 | D29: dates | E29: Prospectus art. 7.2.6 ; note de liquidité § 5 | L29: Les demandes reportées perdent la priorité ; Demandes Prioritaires après deux reports.
B30: Période de Blocage | C30: 24 | D30: mois | E30: Prospectus art. 7.2.2
B31: Déduction de sortie anticipée | C31: 0 | D31: % | E31: DIC du 29/09/2026 : aucune commission de rachat
B32: Prolongation du Délai de Préavis : préavis maximal | C32: 180 | D32: jours cal. | E32: Prospectus art. 7.2.7
B33: Prolongation du Délai de Préavis : durée maximale | C33: 12 | D33: mois | E33: Prospectus art. 7.2.7
B34: Suspension des Rachats | C34: Oui, circonstances exceptionnelles, sans plafonnement préalable | D34: - | E34: Prospectus art. 7.2.8
B35: Actifs liquides minimum | C35: 0.15 | D35: % AN | E35: Prospectus art. 3 et DIC : 15 % au moins en actifs liquides
B36: Sur-engagement maximal | C36: 1.3 | D36: % AN | E36: Prospectus art. 23
B37: Emprunts et instruments dérivés | C37: Interdits | D37: - | E37: Prospectus art. 22 ; aucune couverture de change possible
B38: Entreprises Cibles (co-investissements) au plus | C38: 0.3 | D38: % AN | E38: Prospectus art. 3
B40: C. TAILLE DU FONDS AU LANCEMENT ET ALLOCATION EN EUROS
B41: Le Fonds n'est pas lancé sous 8 M€. Les fonds Macquarie exigent 10 M$ d'engagement, dérogation écrite possible à 4 M. Règle d'allocation : trésorerie 5 %, fonds HY 10 %, fonds fermés selon les engagements négociés, solde réparti à parts égales entre PG NGI et Ares AGI. Les engagements fermés sont appelés progressivement : la part appelée à la fin du blocage est un paramètre.
B42: Taille de lancement (M€) | C42: 8 M€ | D42: 15 M€ | E42: 20 M€ | F42: 25 M€ | G42: 50 M€ | H42: Unité | L42: Commentaire
B43: Taille retenue pour les onglets de calcul (1 = 8 M€ … 5 = 50 M€) | C43: 1 | H43: 1-5 | L43: Sélecteur : toute la projection se recalcule
B44: Actif net au lancement | C44: 8000000 | D44: 15000000 | E44: 20000000 | F44: 25000000 | G44: 50000000 | H44: EUR | L44: Hypothèse de collecte
B45: Engagement MAPIF II | C45: 4000000 | D45: 4000000 | E45: 5000000 | F45: 5000000 | G45: 17000000 | H45: EUR | L45: Minimum 10 M$, dérogation à 4 M à obtenir par écrit ; 50 M€ : poids cible de la synthèse (34 %)
B46: Engagement MSIG 3 | C46: 0 | D46: 0 | E46: 5000000 | F46: 5000000 | G46: 8500000 | H46: EUR | L46: Aucune ligne sous 20 M€
B47: Part des engagements fermés appelée à la fin du blocage | C47: 0.7 | H47: % | L47: Tirage sur trois ans : deux tiers environ après deux ans
B48: MAPIF II - valeur appelée | C48: =C45*Part_appelee -> 2800000 | D48: =D45*Part_appelee -> 2800000 | E48: =E45*Part_appelee -> 3500000 | F48: =F45*Part_appelee -> 3500000 | G48: =G45*Part_appelee -> 11900000 | H48: EUR
B49: MSIG 3 - valeur appelée | C49: =C46*Part_appelee -> 0 | D49: =D46*Part_appelee -> 0 | E49: =E46*Part_appelee -> 3500000 | F49: =F46*Part_appelee -> 3500000 | G49: =G46*Part_appelee -> 5950000 | H49: EUR
B50: Non-appelé des fonds fermés | C50: =(C45+C46)*(1-Part_appelee) -> 1200000 | D50: =(D45+D46)*(1-Part_appelee) -> 1200000 | E50: =(E45+E46)*(1-Part_appelee) -> 3000000 | F50: =(F45+F46)*(1-Part_appelee) -> 3000000 | G50: =(G45+G46)*(1-Part_appelee) -> 7650000 | H50: EUR | L50: Sortie future, financée par la poche et les distributions
B51: Trésorerie (5 %) | C51: =C44*Cash_cible -> 400000 | D51: =D44*Cash_cible -> 750000 | E51: =E44*Cash_cible -> 1000000 | F51: =F44*Cash_cible -> 1250000 | G51: =G44*Cash_cible -> 2500000 | H51: EUR
B52: Fonds HY UCITS (10 %) | C52: =C44*(Liq_cible-Cash_cible) -> 880000 | D52: =D44*(Liq_cible-Cash_cible) -> 1650000 | E52: =E44*(Liq_cible-Cash_cible) -> 2200000 | F52: =F44*(Liq_cible-Cash_cible) -> 2750000 | G52: =G44*(Liq_cible-Cash_cible) -> 5500000 | H52: EUR
B53: Solde pour les fonds evergreen | C53: =C44-C48-C49-C51-C52 -> 3920000 | D53: =D44-D48-D49-D51-D52 -> 9800000 | E53: =E44-E48-E49-E51-E52 -> 9800000 | F53: =F44-F48-F49-F51-F52 -> 14000000 | G53: =G44-G48-G49-G51-G52 -> 24150000 | H53: EUR | L53: Doit rester positif
B54: PG NGI (moitié du solde) | C54: =C53/2 -> 1960000 | D54: =D53/2 -> 4900000 | E54: =E53/2 -> 4900000 | F54: =F53/2 -> 7000000 | G54: =G53/2 -> 12075000 | H54: EUR | L54: Minimum 1 M USD (classe I)
B55: Ares AGI (moitié du solde) | C55: =C53/2 -> 1960000 | D55: =D53/2 -> 4900000 | E55: =E53/2 -> 4900000 | F55: =F53/2 -> 7000000 | G55: =G53/2 -> 12075000 | H55: EUR | L55: Minimum 1 M€ (classe C)
B56: Contrôles par taille | C56: 8 M€ | D56: 15 M€ | E56: 20 M€ | F56: 25 M€ | G56: 50 M€
B57: Poids MAPIF II appelé (% AN) | C57: =C48/C44 -> 0.35 | D57: =D48/D44 -> 0.18666667 | E57: =E48/E44 -> 0.175 | F57: =F48/F44 -> 0.14 | G57: =G48/G44 -> 0.238 | H57: %
B58: Engagement MAPIF II (% AN) | C58: =C45/C44 -> 0.5 | D58: =D45/D44 -> 0.26666667 | E58: =E45/E44 -> 0.25 | F58: =F45/F44 -> 0.2 | G58: =G45/G44 -> 0.34 | H58: % | L58: Concentration sur une ligne : limite interne proposée 35 % (KRI-09)
B59: Sur-engagement (AN + non-appelé) / AN | C59: =(C44+C50)/C44 -> 1.15 | D59: =(D44+D50)/D44 -> 1.08 | E59: =(E44+E50)/E44 -> 1.15 | F59: =(F44+F50)/F44 -> 1.12 | G59: =(G44+G50)/G44 -> 1.153 | H59: % | L59: Plafond 130 % (art. 23)
B60: Dollar non couvert (% AN) | C60: =(C48+C49)/C44 -> 0.35 | D60: =(D48+D49)/D44 -> 0.18666667 | E60: =(E48+E49)/E44 -> 0.35 | F60: =(F48+F49)/F44 -> 0.28 | G60: =(G48+G49)/G44 -> 0.357 | H60: %
B61: Frais totaux du Fonds (% AN, part A1) | C61: =Frais_var+MAX(Fee_SGP,SGP_min/C44)-Fee_SGP+Frais_fixes/C44 -> 0.032599 | D61: =Frais_var+MAX(Fee_SGP,SGP_min/D44)-Fee_SGP+Frais_fixes/D44 -> 0.025879467 | E61: =Frais_var+MAX(Fee_SGP,SGP_min/E44)-Fee_SGP+Frais_fixes/E44 -> 0.0239596 | F61: =Frais_var+MAX(Fee_SGP,SGP_min/F44)-Fee_SGP+Frais_fixes/F44 -> 0.02280768 | G61: =Frais_var+MAX(Fee_SGP,SGP_min/G44)-Fee_SGP+Frais_fixes/G44 -> 0.02110384 | H61: % / an | L61: Frais variables plus prestataires et minimum de la Société de Gestion rapportés à l'encours
B62: Lancement possible (≥ 8 M€) et solde evergreen positif | C62: =IF(AND(C44>=Taille_min,C53>0,C54>=1000000),"Vert","Rouge") -> Vert | D62: =IF(AND(D44>=Taille_min,D53>0,D54>=1000000),"Vert","Rouge") -> Vert | E62: =IF(AND(E44>=Taille_min,E53>0,E54>=1000000),"Vert","Rouge") -> Vert | F62: =IF(AND(F44>=Taille_min,F53>0,F54>=1000000),"Vert","Rouge") -> Vert | G62: =IF(AND(G44>=Taille_min,G53>0,G54>=1000000),"Vert","Rouge") -> Vert | L62: Minimum de lancement et tickets minimaux
B63: Dérogation Macquarie nécessaire (engagement < 10 M) | C63: =IF(OR(AND(C45>0,C45<Ticket_Macquarie),AND(C46>0,C46<Ticket_Macquarie)),"Oui, par écrit","Non") -> Oui, par écrit | D63: =IF(OR(AND(D45>0,D45<Ticket_Macquarie),AND(D46>0,D46<Ticket_Macquarie)),"Oui, par écrit","Non") -> Oui, par écrit | E63: =IF(OR(AND(E45>0,E45<Ticket_Macquarie),AND(E46>0,E46<Ticket_Macquarie)),"Oui, par écrit","Non") -> Oui, par écrit | F63: =IF(OR(AND(F45>0,F45<Ticket_Macquarie),AND(F46>0,F46<Ticket_Macquarie)),"Oui, par écrit","Non") -> Oui, par écrit | G63: =IF(OR(AND(G45>0,G45<Ticket_Macquarie),AND(G46>0,G46<Ticket_Macquarie)),"Oui, par écrit","Non") -> Oui, par écrit
B65: C bis. ALLOCATION À LA FIN DU BLOCAGE ET TERMES DE LIQUIDITÉ DES LIGNES (taille retenue)
B66: Poids en % de l'actif net au départ. Non-appelé : part de la ligne encore à appeler (fonds fermés). Gate par trimestre et pression des pairs : fonds evergreen. TTL : délai de conversion en cash en jours, par scénario. Décote : haircut de cession sur le marché secondaire.
B67: Ligne | C67: Type | D67: Poids | E67: Non-appelé (% ligne) | F67: Gate trim. (fonds) | G67: Préavis fonds (jours) | H67: TTL normal | I67: TTL S2 | J67: TTL S3 | K67: TTL S4 | L67: Source
B68: MAPIF II | C68: Fermé | D68: =INDEX($C$48:$G$48,Taille_sel)/AN_depart -> 0.35 | E68: =IF(INDEX($C$48:$G$48,Taille_sel)>0,(1-Part_appelee)/Part_appelee,0) -> 0.42857143 | F68: 0 | G68: 0 | H68: 365 | I68: 540 | J68: 730 | K68: 1095 | L68: PPM avril 2026 : aucun rachat, cession agréée par le GP ; appels à 10 JO
B69: MSIG 3 | C69: Fermé | D69: =INDEX($C$49:$G$49,Taille_sel)/AN_depart -> 0 | E69: =IF(INDEX($C$49:$G$49,Taille_sel)>0,(1-Part_appelee)/Part_appelee,0) -> 0 | F69: 0 | G69: 45 | H69: 365 | I69: 540 | J69: 730 | K69: 1095 | L69: PPM février 2026 : retrait annuel après lock-up 3 ans payé au run-off ; traité comme fermé sur l'horizon
B70: PG NGI | C70: Ouvert | D70: =INDEX($C$54:$G$54,Taille_sel)/AN_depart -> 0.245 | E70: 0 | F70: 0.05 | G70: 63 | H70: 180 | I70: 270 | J70: 365 | K70: 540 | L70: Supplément 2 : rachats mensuels, préavis 45 JO, gate 5 % de la VL par trimestre, Special Dealing 180 j
B71: Ares AGI | C71: Ouvert | D71: =INDEX($C$55:$G$55,Taille_sel)/AN_depart -> 0.245 | E71: 0 | F71: 0.05 | G71: 30 | H71: 120 | I71: 180 | J71: 365 | K71: 540 | L71: Annexe 7 : rachats trimestriels, gate 5 % net par trimestre, limite ELTIF 27,3 %, déduction 5 % avant 24 mois
B72: Fonds HY UCITS | C72: Liquide | D72: =Liq_cible-Cash_cible -> 0.11 | E72: 0 | F72: 1 | G72: 2 | H72: 7 | I72: 14 | J72: 30 | K72: 30 | L72: OPCVM obligataire à VL quotidienne (prospectus art. 3)
B73: Trésorerie | C73: Liquide | D73: =Cash_cible -> 0.05 | E73: 0 | F73: 1 | G73: 0 | H73: 1 | I73: 1 | J73: 1 | K73: 1 | L73: Dépôts et monétaire ; cible 5 % fixée par la Fonction Risques
B74: Total | D74: =SUM(D68:D73) -> 1 | L74: Doit être égal à 100 %
B76: C ter. HYPOTHÈSES PAR LIGNE : RENDEMENT, DISTRIBUTIONS, PROXY ET TRANSMISSION DES CHOCS
B77: Rendement : TRI net cible du DIC. Distributions : % de la valeur par an. Proxy coté : composite du classeur des cours. Transmission : part du choc du proxy coté répercutée dans la VL de la ligne (1 pour un actif coté ; environ 0,5 pour une VL d'expertise, rapport VEV privée / VEV cotée du DIC). Retard : part du choc reportée au semestre suivant. Dollar : part de la ligne en dollars non couverts.
B78: Ligne | C78: Rendement net annuel | D78: Distributions annuelles | E78: Proxy coté | F78: Transmission | G78: Retard (part au semestre suivant) | H78: Dollar non couvert | I78: Courbe en J (S3, année 1-3) | J78: Haircut vente S2 | K78: Haircut vente S3 | L78: Haircut vente S4
B79: MAPIF II | C79: 0.135 | D79: 0.06 | E79: C1 Infrastructure cotée | F79: 0.5 | G79: 0.5 | H79: 1 | I79: -0.05 | J79: 0.15 | K79: 0.25 | L79: 0.35
B80: MSIG 3 | C80: 0.11 | D80: 0.07 | E80: C3 Direct lending coté | F80: 0.5 | G80: 0.5 | H80: 1 | I80: 0 | J80: 0.15 | K80: 0.25 | L80: 0.35
B81: PG NGI | C81: 0.115 | D81: 0.02 | E81: C1 Infrastructure cotée | F81: 0.5 | G81: 0.5 | H81: 0 | I81: 0 | J81: 0.05 | K81: 0.15 | L81: 0.25
B82: Ares AGI | C82: 0.095 | D82: 0.05 | E82: Mix 60 % C1, 20 % C3, 20 % C4 | F82: 0.5 | G82: 0.5 | H82: 0 | I82: -0.03 | J82: 0.05 | K82: 0.15 | L82: 0.25
B83: Fonds HY UCITS | C83: 0.06 | D83: 0 | E83: C4 Haut rendement coté | F83: 1 | G83: 0 | H83: 0 | I83: 0 | J83: 0.01 | K83: 0.03 | L83: 0.05
B84: Trésorerie | C84: 0.025 | D84: 0 | E84: Taux monétaire | F84: 0 | G84: 0 | H84: 0 | I84: 0 | J84: 0 | K84: 0 | L84: 0
B86: D. HYPOTHÈSES DE FLUX EN RÉGIME NORMAL
B87: Paramètre | C87: Valeur | D87: Unité | E87: Source | L87: Commentaire
B88: Rachats demandés par date de rachat | C88: 0.02 | D88: % AN | E88: Hypothèse : aucun historique
B89: Collecte par semestre | C89: 0.1 | D89: % AN | E89: Prévision du Conseiller à confirmer ; nulle dans les scénarios S3 et S4
B90: Appels des fonds fermés par semestre | C90: =1/6 -> 0.16666667 | D90: part du non-appelé initial | E90: Tirage sur trois ans
B91: Frais variables du Fonds hors prestataires (part A1 : gestion 0,18 %, conseil 1,07 %, distribution 0,75 %) | C91: 0.02 | D91: % AN / an | E91: Prospectus art. 27 ; classeur DIC v2.3
B92: Commission de gestion de la Société de Gestion | C92: 0.0018 | D92: % AN / an | E92: Prospectus art. 27.2.1
B93: Minimum annuel de la Société de Gestion | C93: 60000 | D93: EUR / an | E93: Prospectus art. 27.2.1
B94: Prestataires (dépositaire, valorisateur, CAC) et frais fixes | C94: 55192 | D94: EUR / an | E94: Offres du 25/03/2026 (classeur DIC)
B95: Frais totaux du Fonds à la taille retenue | C95: =Frais_var+MAX(Fee_SGP,SGP_min/AN_depart)-Fee_SGP+Frais_fixes/AN_depart -> 0.032599 | D95: % AN / an | E95: Dérivé | L95: 2,11 % à 50 M€ ; nettement plus à 8 M€ du fait des frais fixes.
B96: Taille minimale de lancement | C96: 8000000 | D96: EUR | E96: Décision de la Société de Gestion
B97: Ticket minimal des fonds Macquarie | C97: 10000000 | D97: EUR (10 M$) | E97: PPM MAPIF II et MSIG 3 ; dérogation écrite possible à 4 M
B98: Trésorerie opérationnelle minimale | C98: 0.01 | D98: % AN | E98: Fonction Risques : plancher avant toute vente
B99: Trésorerie cible | C99: 0.05 | D99: % AN | E99: Fonction Risques (5 % de cash)
B100: Poche liquide cible (trésorerie + fonds HY) | C100: 0.16 | D100: % AN | E100: Fonction Risques : un point au-dessus du minimum de 15 % de l'art. 3
B101: Poche liquide d'exécution (trésorerie + HY) sous laquelle on désinvestit les fonds cibles | C101: 0.1 | D101: % AN | E101: Note de liquidité § 5
B102: Part du premier porteur | C102: 0.15 | D102: % AN | E102: Hypothèse : registre non constitué
B103: Part des cinq premiers porteurs | C103: 0.35 | D103: % AN | E103: Hypothèse
B104: Part de l'actif net encore sous blocage à la date de départ | C104: 0.5 | D104: % AN | E104: Hypothèse : souscriptions étalées sur les deux premières années | L104: Réduit les demandes possibles aux premières dates ; sert au profil Annex IV passif.
B106: E. INTERRUPTEURS DE GOUVERNANCE 1 = actif, 0 = inactif
B107: Interrupteur | C107: Valeur | D107: Unité | E107: Source | L107: Commentaire
B108: Plafonnement appliqué (0 = la Société de Gestion renonce au gate) | C108: 1 | D108: 1/0 | E108: Prospectus art. 7.2.6 : faculté, non obligation
...

Sheet Comparatif tailles
B2: COMPARATIF DES TAILLES DE LANCEMENT : 8, 15, 20, 25 ET 50 M€
B3: Bloc A : allocation en formules (onglet Paramètres C). Bloc B : résultats du moteur pour chaque taille, obtenus par recalcul complet du classeur taille par taille (script tools/lst_mst_infraworld), valeurs figées à la date indiquée ; le sélecteur de l'onglet Paramètres permet de rejouer une taille en direct.
B5: A. ALLOCATION PAR TAILLE (formules)
B6: Ligne | C6: 8 M€ | D6: 15 M€ | E6: 20 M€ | F6: 25 M€ | G6: 50 M€ | H6: Lecture
B7: Actif net au lancement | C7: =Paramètres!C44 -> 8000000 | D7: =Paramètres!D44 -> 15000000 | E7: =Paramètres!E44 -> 20000000 | F7: =Paramètres!F44 -> 25000000 | G7: =Paramètres!G44 -> 50000000
B8: Engagement MAPIF II | C8: =Paramètres!C45 -> 4000000 | D8: =Paramètres!D45 -> 4000000 | E8: =Paramètres!E45 -> 5000000 | F8: =Paramètres!F45 -> 5000000 | G8: =Paramètres!G45 -> 17000000 | H8: 4 M sous dérogation jusqu'à 15 M€ ; 5 M à 20 et 25 M€
B9: Engagement MSIG 3 | C9: =Paramètres!C46 -> 0 | D9: =Paramètres!D46 -> 0 | E9: =Paramètres!E46 -> 5000000 | F9: =Paramètres!F46 -> 5000000 | G9: =Paramètres!G46 -> 8500000 | H9: Aucun sous 20 M€
B10: MAPIF II appelé à la fin du blocage | C10: =Paramètres!C48 -> 2800000 | D10: =Paramètres!D48 -> 2800000 | E10: =Paramètres!E48 -> 3500000 | F10: =Paramètres!F48 -> 3500000 | G10: =Paramètres!G48 -> 11900000
B11: MSIG 3 appelé à la fin du blocage | C11: =Paramètres!C49 -> 0 | D11: =Paramètres!D49 -> 0 | E11: =Paramètres!E49 -> 3500000 | F11: =Paramètres!F49 -> 3500000 | G11: =Paramètres!G49 -> 5950000
B12: Non-appelé | C12: =Paramètres!C50 -> 1200000 | D12: =Paramètres!D50 -> 1200000 | E12: =Paramètres!E50 -> 3000000 | F12: =Paramètres!F50 -> 3000000 | G12: =Paramètres!G50 -> 7650000
B13: Trésorerie | C13: =Paramètres!C51 -> 400000 | D13: =Paramètres!D51 -> 750000 | E13: =Paramètres!E51 -> 1000000 | F13: =Paramètres!F51 -> 1250000 | G13: =Paramètres!G51 -> 2500000 | H13: 5 % de l'actif net
B14: Fonds HY UCITS | C14: =Paramètres!C52 -> 880000 | D14: =Paramètres!D52 -> 1650000 | E14: =Paramètres!E52 -> 2200000 | F14: =Paramètres!F52 -> 2750000 | G14: =Paramètres!G52 -> 5500000 | H14: 10 % de l'actif net
B15: PG NGI | C15: =Paramètres!C54 -> 1960000 | D15: =Paramètres!D54 -> 4900000 | E15: =Paramètres!E54 -> 4900000 | F15: =Paramètres!F54 -> 7000000 | G15: =Paramètres!G54 -> 12075000 | H15: Moitié du solde
B16: Ares AGI | C16: =Paramètres!C55 -> 1960000 | D16: =Paramètres!D55 -> 4900000 | E16: =Paramètres!E55 -> 4900000 | F16: =Paramètres!F55 -> 7000000 | G16: =Paramètres!G55 -> 12075000 | H16: Moitié du solde
B17: Poids en % de l'actif net | C17: 8 M€ | D17: 15 M€ | E17: 20 M€ | F17: 25 M€ | G17: 50 M€
B18: MAPIF II (appelé) | C18: =Paramètres!C48/Paramètres!C44 -> 0.35 | D18: =Paramètres!D48/Paramètres!D44 -> 0.18666667 | E18: =Paramètres!E48/Paramètres!E44 -> 0.175 | F18: =Paramètres!F48/Paramètres!F44 -> 0.14 | G18: =Paramètres!G48/Paramètres!G44 -> 0.238
B19: MSIG 3 (appelé) | C19: =Paramètres!C49/Paramètres!C44 -> 0 | D19: =Paramètres!D49/Paramètres!D44 -> 0 | E19: =Paramètres!E49/Paramètres!E44 -> 0.175 | F19: =Paramètres!F49/Paramètres!F44 -> 0.14 | G19: =Paramètres!G49/Paramètres!G44 -> 0.119
B20: PG NGI | C20: =Paramètres!C54/Paramètres!C44 -> 0.245 | D20: =Paramètres!D54/Paramètres!D44 -> 0.32666667 | E20: =Paramètres!E54/Paramètres!E44 -> 0.245 | F20: =Paramètres!F54/Paramètres!F44 -> 0.28 | G20: =Paramètres!G54/Paramètres!G44 -> 0.2415
B21: Ares AGI | C21: =Paramètres!C55/Paramètres!C44 -> 0.245 | D21: =Paramètres!D55/Paramètres!D44 -> 0.32666667 | E21: =Paramètres!E55/Paramètres!E44 -> 0.245 | F21: =Paramètres!F55/Paramètres!F44 -> 0.28 | G21: =Paramètres!G55/Paramètres!G44 -> 0.2415
B22: Fonds HY UCITS | C22: =Paramètres!C52/Paramètres!C44 -> 0.11 | D22: =Paramètres!D52/Paramètres!D44 -> 0.11 | E22: =Paramètres!E52/Paramètres!E44 -> 0.11 | F22: =Paramètres!F52/Paramètres!F44 -> 0.11 | G22: =Paramètres!G52/Paramètres!G44 -> 0.11
B23: Trésorerie | C23: =Paramètres!C51/Paramètres!C44 -> 0.05 | D23: =Paramètres!D51/Paramètres!D44 -> 0.05 | E23: =Paramètres!E51/Paramètres!E44 -> 0.05 | F23: =Paramètres!F51/Paramètres!F44 -> 0.05 | G23: =Paramètres!G51/Paramètres!G44 -> 0.05
B24: Non-appelé | C24: =Paramètres!C50/Paramètres!C44 -> 0.15 | D24: =Paramètres!D50/Paramètres!D44 -> 0.08 | E24: =Paramètres!E50/Paramètres!E44 -> 0.15 | F24: =Paramètres!F50/Paramètres!F44 -> 0.12 | G24: =Paramètres!G50/Paramètres!G44 -> 0.153
B25: Engagement MAPIF II en % de l'actif net | C25: =Paramètres!C45/Paramètres!C44 -> 0.5 | D25: =Paramètres!D45/Paramètres!D44 -> 0.26666667 | E25: =Paramètres!E45/Paramètres!E44 -> 0.25 | F25: =Paramètres!F45/Paramètres!F44 -> 0.2 | G25: =Paramètres!G45/Paramètres!G44 -> 0.34 | H25: Concentration : 50 % à 8 M€
B26: Sur-engagement | C26: =(Paramètres!C44+Paramètres!C50)/Paramètres!C44 -> 1.15 | D26: =(Paramètres!D44+Paramètres!D50)/Paramètres!D44 -> 1.08 | E26: =(Paramètres!E44+Paramètres!E50)/Paramètres!E44 -> 1.15 | F26: =(Paramètres!F44+Paramètres!F50)/Paramètres!F44 -> 1.12 | G26: =(Paramètres!G44+Paramètres!G50)/Paramètres!G44 -> 1.153 | H26: Plafond 130 %
B27: Frais totaux (part A1) | C27: =Frais_var+MAX(Fee_SGP,SGP_min/Paramètres!C44)-Fee_SGP+Frais_fixes/Paramètres!C44 -> 0.032599 | D27: =Frais_var+MAX(Fee_SGP,SGP_min/Paramètres!D44)-Fee_SGP+Frais_fixes/Paramètres!D44 -> 0.025879467 | E27: =Frais_var+MAX(Fee_SGP,SGP_min/Paramètres!E44)-Fee_SGP+Frais_fixes/Paramètres!E44 -> 0.0239596 | F27: =Frais_var+MAX(Fee_SGP,SGP_min/Paramètres!F44)-Fee_SGP+Frais_fixes/Paramètres!F44 -> 0.02280768 | G27: =Frais_var+MAX(Fee_SGP,SGP_min/Paramètres!G44)-Fee_SGP+Frais_fixes/Paramètres!G44 -> 0.02110384 | H27: Frais fixes rapportés à l'encours
B29: B. RÉSULTATS DU MOTEUR PAR TAILLE (valeurs figées) recalcul du 06/10/2026
B30: S1 Base | C30: 8 M€ | D30: 15 M€ | E30: 20 M€ | F30: 25 M€ | G30: 50 M€ | H30: Lecture
B31: Creux de VL (MST) | C31: 0.044637287 | D31: 0.042085543 | E31: 0.040916919 | F31: 0.040567388 | G31: 0.042216797
B32: Dates plafonnées ou suspendues | C32: 0 | D32: 0 | E32: 0 | F32: 0 | G32: 0
B33: File résiduelle à la date 8 (% AN) | C33: 0 | D33: 0 | E33: 0 | F33: 0 | G33: 0
B34: Première suspension | C34: - | D34: - | E34: - | F34: - | G34: -
B35: Poche liquide minimale (% AN) | C35: 0.15469325 | D35: 0.15455742 | E35: 0.15439528 | F35: 0.15439616 | G35: 0.15409055
B36: Couverture à douze mois minimale | C36: 1.9163833 | D36: 2.2431677 | E36: 1.9311284 | F36: 2.0682252 | G36: 1.9073194
B37: Cessions secondaires cumulées (EUR) | C37: 0 | D37: 0 | E37: 0 | F37: 0 | G37: 0
B38: Décotes réalisées (EUR) | C38: 0 | D38: 0 | E38: 0 | F38: 0 | G38: 0
B39: Actif net à la date 8 / départ | C39: 1.3881741 | D39: 1.4063944 | E39: 1.4202084 | F39: 1.4216804 | G39: 1.4601912
B40: Verdict conjoint | C40: Vert | D40: Vert | E40: Vert | F40: Vert | G40: Vert
B42: S2 Plausible | C42: 8 M€ | D42: 15 M€ | E42: 20 M€ | F42: 25 M€ | G42: 50 M€ | H42: Lecture
B43: Creux de VL (MST) | C43: -0.014988138 | D43: -0.0038600377 | E43: -0.013024242 | F43: -0.0086478355 | G43: -0.014129608
B44: Dates plafonnées ou suspendues | C44: 0 | D44: 0 | E44: 0 | F44: 0 | G44: 0
B45: File résiduelle à la date 8 (% AN) | C45: 0 | D45: 0 | E45: 0 | F45: 0 | G45: 0
B46: Première suspension | C46: - | D46: - | E46: - | F46: - | G46: -
B47: Poche liquide minimale (% AN) | C47: 0.069401568 | D47: 0.095352754 | E47: 0.083634536 | F47: 0.095159501 | G47: 0.084945071
B48: Couverture à douze mois minimale | C48: 0.83751236 | D48: 1.4253072 | E48: 0.98948458 | F48: 1.2394261 | G48: 0.98460594
B49: Cessions secondaires cumulées (EUR) | C49: 0 | D49: 0 | E49: 0 | F49: 0 | G49: 0
B50: Décotes réalisées (EUR) | C50: 5707.8132 | D50: 5657.7505 | E50: 11496.474 | F50: 11364.377 | G50: 27785.031
B51: Actif net à la date 8 / départ | C51: 0.70437337 | D51: 0.73425734 | E51: 0.73605667 | F51: 0.74197451 | G51: 0.76185935
B52: Verdict conjoint | C52: Rouge | D52: Orange | E52: Rouge | F52: Orange | G52: Rouge
B54: S3 Sévère | C54: 8 M€ | D54: 15 M€ | E54: 20 M€ | F54: 25 M€ | G54: 50 M€ | H54: Lecture
B55: Creux de VL (MST) | C55: -0.087196361 | D55: -0.05806866 | E55: -0.092157312 | F55: -0.078739521 | G55: -0.091812632
B56: Dates plafonnées ou suspendues | C56: 8 | D56: 8 | E56: 8 | F56: 8 | G56: 8
B57: File résiduelle à la date 8 (% AN) | C57: 0.4666904 | D57: 0.44602424 | E57: 0.4563785 | F57: 0.44960029 | G57: 0.45136388
B58: Première suspension | C58: 31/12/2030 | D58: 31/12/2030 | E58: 31/12/2030 | F58: 31/12/2030 | G58: 31/12/2030
B59: Poche liquide minimale (% AN) | C59: 0.010019756 | D59: 0.010025418 | E59: 0.009971363 | F59: 0.0099840396 | G59: 0.0099511492
B60: Couverture à douze mois minimale | C60: -0.44291012 | D60: -0.13679525 | E60: -0.43530596 | F60: -0.30216663 | G60: -0.4470905
B61: Cessions secondaires cumulées (EUR) | C61: 1656335.1 | D61: 1840230.3 | E61: 3839655.2 | F61: 3968501.5 | G61: 9581193
B62: Décotes réalisées (EUR) | C62: 438615.88 | D62: 505975.93 | E62: 1021219.4 | F62: 1068706.9 | G62: 2548554.4
B63: Actif net à la date 8 / départ | C63: 0.047096622 | D63: 0.122504 | E63: 0.078264831 | F63: 0.10449607 | G63: 0.095021203
B64: Verdict conjoint | C64: Rouge | D64: Rouge | E64: Rouge | F64: Rouge | G64: Rouge
B66: S4 Extrême | C66: 8 M€ | D66: 15 M€ | E66: 20 M€ | F66: 25 M€ | G66: 50 M€ | H66: Lecture
B67: Creux de VL (MST) | C67: -0.17282085 | D67: -0.12243601 | E67: -0.18441797 | F67: -0.16076685 | G67: -0.18284165
B68: Dates plafonnées ou suspendues | C68: 8 | D68: 8 | E68: 8 | F68: 8 | G68: 8
B69: File résiduelle à la date 8 (% AN) | C69: 0.92475927 | D69: 0.8549095 | E69: 0.90997177 | F69: 0.88162424 | G69: 0.8959057
B70: Première suspension | C70: 31/12/2030 | D70: 31/12/2030 | E70: 31/12/2030 | F70: 31/12/2030 | G70: 31/12/2030
B71: Poche liquide minimale (% AN) | C71: 0.010388162 | D71: 0.010352841 | E71: 0.010328822 | F71: 0.010319273 | G71: 0.01029764
B72: Couverture à douze mois minimale | C72: -0.6908659 | D72: -0.20179261 | E72: -0.63056551 | F72: -0.39009449 | G72: -0.65067322
B73: Cessions secondaires cumulées (EUR) | C73: 1970793.6 | D73: 2527631 | E73: 4568027.3 | F73: 4958533.3 | G73: 11391668
B74: Décotes réalisées (EUR) | C74: 728824.36 | D74: 957327.42 | E74: 1696299.3 | F74: 1856983.6 | G74: 4230780.9
B75: Actif net à la date 8 / départ | C75: -0.25318516 | D75: -0.15471357 | E75: -0.23664908 | F75: -0.19749276 | G75: -0.22107694
B76: Verdict conjoint | C76: Rouge | D76: Rouge | E76: Rouge | F76: Rouge | G76: Rouge
B78: Lecture : la taille modifie peu les mécanismes de passif (gate en % de l'actif net) mais change la concentration (engagement MAPIF II jusqu'à 50 % de l'actif à 8 M€), le poids des frais fixes et l'absence de MSIG 3 sous 20 M€. Les résultats de passif par taille sont proches ; les écarts viennent du non-appelé relatif et des frais.

Sheet ALP
B2: ALP - PROFIL DE LIQUIDITÉ DE L'ACTIF (look-through, date de départ)
B3: Valeur de chaque ligne à la fin du blocage, délai de conversion en cash (TTL) par scénario et classement par tranche Annex IV. Les fonds evergreen ne sont pas liquides à 90 jours : préavis, gate trimestriel de 5 % et pression des pairs portent le délai de récupération complète au-delà de 180 jours. Le non-appelé des fonds fermés est une sortie, pas une ressource.
B5: A. VALEURS ET DÉLAIS DE CONVERSION
B6: Ligne | C6: Valeur (EUR) | D6: % AN | E6: TTL normal | F6: TTL S2 | G6: TTL S3 | H6: TTL S4 | I6: Non-appelé (EUR) | J6: Capacité de rachat par semestre, normal (EUR) | K6: Haircut S2 | L6: Haircut S3 | M6: Haircut S4
B7: MAPIF II | C7: =Paramètres!$D$68*AN_depart -> 2800000 | D7: =C7/AN_depart -> 0.35 | E7: =Paramètres!$H$68 -> 365 | F7: =Paramètres!$I$68 -> 540 | G7: =Paramètres!$J$68 -> 730 | H7: =Paramètres!$K$68 -> 1095 | I7: =C7*Paramètres!$E$68 -> 1200000 | J7: =0 -> 0 | K7: =Paramètres!$J$79 -> 0.15 | L7: =Paramètres!$K$79 -> 0.25 | M7: =Paramètres!$L$79 -> 0.35
B8: MSIG 3 | C8: =Paramètres!$D$69*AN_depart -> 0 | D8: =C8/AN_depart -> 0 | E8: =Paramètres!$H$69 -> 365 | F8: =Paramètres!$I$69 -> 540 | G8: =Paramètres!$J$69 -> 730 | H8: =Paramètres!$K$69 -> 1095 | I8: =C8*Paramètres!$E$69 -> 0 | J8: =0 -> 0 | K8: =Paramètres!$J$80 -> 0.15 | L8: =Paramètres!$K$80 -> 0.25 | M8: =Paramètres!$L$80 -> 0.35
B9: PG NGI | C9: =Paramètres!$D$70*AN_depart -> 1960000 | D9: =C9/AN_depart -> 0.245 | E9: =Paramètres!$H$70 -> 180 | F9: =Paramètres!$I$70 -> 270 | G9: =Paramètres!$J$70 -> 365 | H9: =Paramètres!$K$70 -> 540 | I9: =C9*Paramètres!$E$70 -> 0 | J9: =C9*Paramètres!$F$70*2*(1-Paramètres!$C$148) -> 137200 | K9: =Paramètres!$J$81 -> 0.05 | L9: =Paramètres!$K$81 -> 0.15 | M9: =Paramètres!$L$81 -> 0.25
B10: Ares AGI | C10: =Paramètres!$D$71*AN_depart -> 1960000 | D10: =C10/AN_depart -> 0.245 | E10: =Paramètres!$H$71 -> 120 | F10: =Paramètres!$I$71 -> 180 | G10: =Paramètres!$J$71 -> 365 | H10: =Paramètres!$K$71 -> 540 | I10: =C10*Paramètres!$E$71 -> 0 | J10: =C10*Paramètres!$F$71*2*(1-Paramètres!$C$148) -> 137200 | K10: =Paramètres!$J$82 -> 0.05 | L10: =Paramètres!$K$82 -> 0.15 | M10: =Paramètres!$L$82 -> 0.25
B11: Fonds HY UCITS | C11: =Paramètres!$D$72*AN_depart -> 880000 | D11: =C11/AN_depart -> 0.11 | E11: =Paramètres!$H$72 -> 7 | F11: =Paramètres!$I$72 -> 14 | G11: =Paramètres!$J$72 -> 30 | H11: =Paramètres!$K$72 -> 30 | I11: =C11*Paramètres!$E$72 -> 0 | J11: =C11 -> 880000 | K11: =Paramètres!$J$83 -> 0.01 | L11: =Paramètres!$K$83 -> 0.03 | M11: =Paramètres!$L$83 -> 0.05
B12: Trésorerie | C12: =Paramètres!$D$73*AN_depart -> 400000 | D12: =C12/AN_depart -> 0.05 | E12: =Paramètres!$H$73 -> 1 | F12: =Paramètres!$I$73 -> 1 | G12: =Paramètres!$J$73 -> 1 | H12: =Paramètres!$K$73 -> 1 | I12: =C12*Paramètres!$E$73 -> 0 | J12: =C12 -> 400000 | K12: =Paramètres!$J$84 -> 0 | L12: =Paramètres!$K$84 -> 0 | M12: =Paramètres!$L$84 -> 0
B13: Total | C13: =SUM(C7:C12) -> 8000000 | D13: =SUM(D7:D12) -> 1 | I13: =SUM(I7:I12) -> 1200000 | J13: =SUM(J7:J12) -> 1554400
B14: Sur-engagement au départ (AN + non-appelé) / AN | C14: =(C13+I13)/C13 -> 1.15 | J14: =IF((C13+I13)/C13>Surengagement_max,"Rouge : plafond de l'art. 23 dépassé","Vert : sous le plafond de l'art. 23") -> Vert : sous le plafond de l'art. 23
B16: B. DÉLAI MOYEN PONDÉRÉ DE CONVERSION (WATTL) ET T90
B17: WATTL = Σ valeur × TTL / actif net. T90 = TTL de la ligne où le cumul des valeurs triées par TTL atteint 90 % de l'actif net.
B18: Mesure | C18: Normal | D18: S2 | E18: S3 | F18: S4
B19: WATTL (jours) | C19: =SUMPRODUCT(C7:C12,E7:E12)/C13 -> 202.07 | D19: =SUMPRODUCT(C7:C12,F7:F12)/C13 -> 300.84 | E19: =SUMPRODUCT(C7:C12,G7:G12)/C13 -> 437.7 | F19: =SUMPRODUCT(C7:C12,H7:H12)/C13 -> 651.2
B20: T90 (jours pour liquider 90 % de l'actif) | C20: {=MIN(IF(SUMIF(E7:E12,"<="&E7:E12,C7:C12)>=0.9*C13,E7:E12,100000))} -> 365 | D20: {=MIN(IF(SUMIF(F7:F12,"<="&F7:F12,C7:C12)>=0.9*C13,F7:F12,100000))} -> 540 | E20: {=MIN(IF(SUMIF(G7:G12,"<="&G7:G12,C7:C12)>=0.9*C13,G7:G12,100000))} -> 730 | F20: {=MIN(IF(SUMIF(H7:H12,"<="&H7:H12,C7:C12)>=0.9*C13,H7:H12,100000))} -> 1095
B21: Actifs liquides à 30 jours (HQLA), % AN | C21: =SUMIF(E7:E12,"<=30",C7:C12)/C13 -> 0.16 | D21: =SUMIF(F7:F12,"<=30",C7:C12)/C13 -> 0.16 | E21: =SUMIF(G7:G12,"<=30",C7:C12)/C13 -> 0.16 | F21: =SUMIF(H7:H12,"<=30",C7:C12)/C13 -> 0.16
B22: HQLA après haircut, % AN | C22: =SUMIF(E7:E12,"<=30",C7:C12)/C13 -> 0.16 | D22: =SUMPRODUCT((F7:F12<=30)*C7:C12*(1-K7:K12))/C13 -> 0.1589 | E22: =SUMPRODUCT((G7:G12<=30)*C7:C12*(1-L7:L12))/C13 -> 0.1567 | F22: =SUMPRODUCT((H7:H12<=30)*C7:C12*(1-M7:M12))/C13 -> 0.1545
B23: Capacité de rachat des fonds evergreen sur douze mois, % AN | C23: =Cap_normal*2/AN_depart -> 0.3886 | D23: =Cap_normal*2*(1-Paramètres!$C$149)/(1-Paramètres!$C$148)/AN_depart -> 0.27757143 | E23: =Cap_normal*2*(1-Paramètres!$C$150)/(1-Paramètres!$C$148)/AN_depart -> 0 | F23: =Cap_normal*2*(1-Paramètres!$C$151)/(1-Paramètres!$C$148)/AN_depart -> 0
B25: C. PROFIL ANNEX IV, CÔTÉ ACTIF % de l'actif net liquidable par tranche (AIFMD Annex IV, section 2, question 178)
B26: Tranche | C26: Normal | D26: S2 | E26: S3 | F26: S4 | G26: Champ Annex IV
B27: 1 jour | C27: =SUMPRODUCT((E7:E12>0)*(E7:E12<=1)*C7:C12)/C13 -> 0.05 | D27: =SUMPRODUCT((F7:F12>0)*(F7:F12<=1)*C7:C12)/C13 -> 0.05 | E27: =SUMPRODUCT((G7:G12>0)*(G7:G12<=1)*C7:C12)/C13 -> 0.05 | F27: =SUMPRODUCT((H7:H12>0)*(H7:H12<=1)*C7:C12)/C13 -> 0.05 | G27: 1 day
B28: 2 à 7 jours | C28: =SUMPRODUCT((E7:E12>1)*(E7:E12<=7)*C7:C12)/C13 -> 0.11 | D28: =SUMPRODUCT((F7:F12>1)*(F7:F12<=7)*C7:C12)/C13 -> 0 | E28: =SUMPRODUCT((G7:G12>1)*(G7:G12<=7)*C7:C12)/C13 -> 0 | F28: =SUMPRODUCT((H7:H12>1)*(H7:H12<=7)*C7:C12)/C13 -> 0 | G28: 2-7 days
B29: 8 à 30 jours | C29: =SUMPRODUCT((E7:E12>7)*(E7:E12<=30)*C7:C12)/C13 -> 0 | D29: =SUMPRODUCT((F7:F12>7)*(F7:F12<=30)*C7:C12)/C13 -> 0.11 | E29: =SUMPRODUCT((G7:G12>7)*(G7:G12<=30)*C7:C12)/C13 -> 0.11 | F29: =SUMPRODUCT((H7:H12>7)*(H7:H12<=30)*C7:C12)/C13 -> 0.11 | G29: 8-30 days
B30: 31 à 90 jours | C30: =SUMPRODUCT((E7:E12>30)*(E7:E12<=90)*C7:C12)/C13 -> 0 | D30: =SUMPRODUCT((F7:F12>30)*(F7:F12<=90)*C7:C12)/C13 -> 0 | E30: =SUMPRODUCT((G7:G12>30)*(G7:G12<=90)*C7:C12)/C13 -> 0 | F30: =SUMPRODUCT((H7:H12>30)*(H7:H12<=90)*C7:C12)/C13 -> 0 | G30: 31-90 days
B31: 91 à 180 jours | C31: =SUMPRODUCT((E7:E12>90)*(E7:E12<=180)*C7:C12)/C13 -> 0.49 | D31: =SUMPRODUCT((F7:F12>90)*(F7:F12<=180)*C7:C12)/C13 -> 0.245 | E31: =SUMPRODUCT((G7:G12>90)*(G7:G12<=180)*C7:C12)/C13 -> 0 | F31: =SUMPRODUCT((H7:H12>90)*(H7:H12<=180)*C7:C12)/C13 -> 0 | G31: 91-180 days
B32: 181 à 365 jours | C32: =SUMPRODUCT((E7:E12>180)*(E7:E12<=365)*C7:C12)/C13 -> 0.35 | D32: =SUMPRODUCT((F7:F12>180)*(F7:F12<=365)*C7:C12)/C13 -> 0.245 | E32: =SUMPRODUCT((G7:G12>180)*(G7:G12<=365)*C7:C12)/C13 -> 0.49 | F32: =SUMPRODUCT((H7:H12>180)*(H7:H12<=365)*C7:C12)/C13 -> 0 | G32: 181-365 days
B33: Plus de 365 jours | C33: =SUMPRODUCT((E7:E12>365)*(E7:E12<=100000)*C7:C12)/C13 -> 0 | D33: =SUMPRODUCT((F7:F12>365)*(F7:F12<=100000)*C7:C12)/C13 -> 0.35 | E33: =SUMPRODUCT((G7:G12>365)*(G7:G12<=100000)*C7:C12)/C13 -> 0.35 | F33: =SUMPRODUCT((H7:H12>365)*(H7:H12<=100000)*C7:C12)/C13 -> 0.84 | G33: more than 365 days
B34: Total | C34: =SUM(C27:C33) -> 1 | D34: =SUM(D27:D33) -> 1 | E34: =SUM(E27:E33) -> 1 | F34: =SUM(F27:F33) -> 1 | G34: Doit être égal à 100 %
B36: Convention TTL : trésorerie 1 jour ; OPCVM HY 7 jours (30 en S3) ; fonds evergreen 180 jours en régime normal (préavis 45 JO ou 30 jours, gate trimestriel, règlement), 365 jours et plus en S3 lorsque les pairs saturent le gate ; fonds fermés 365 jours (cession secondaire agréée) à 1 095 jours en S4 (marché secondaire fermé). Les haircuts de cession s'appliquent aux ventes forcées dans le moteur LST.

Sheet LLP
B2: LLP - PROFIL DE LIQUIDITÉ DU PASSIF ET ADÉQUATION ACTIF-PASSIF
B3: Délai de liquidité du passif (LTTL) du point de vue du porteur : préavis, attente de la prochaine date de rachat, publication et règlement. Comparaison au WATTL de l'actif par scénario. Profil Annex IV côté passif.
B5: A. DÉLAI DE LIQUIDITÉ DU PASSIF (LTTL), EN JOURS CALENDAIRES
B6: Composante | C6: Minimum | D6: Moyen | E6: Maximum | F6: Préavis prolongé | G6: Source
B7: Préavis (centralisation à VL) | C7: =Preavis_j -> 91 | D7: =Preavis_j -> 91 | E7: =Preavis_j -> 91 | F7: =Preavis_max_j -> 180 | G7: Prospectus art. 7.2.3 et 7.2.7
B8: Attente de la prochaine date de centralisation | C8: 0 | D8: =ROUND(365/Rachats_par_an/2,0) -> 91 | E8: =ROUND(365/Rachats_par_an,0) -> 183 | F8: =ROUND(365/Rachats_par_an/2,0) -> 91 | G8: Deux dates par an : 0 à 182 jours, 91 en moyenne
B9: Publication de la VL et règlement | C9: =Reglement_cal -> 49 | D9: =Reglement_cal -> 49 | E9: =Reglement_cal -> 49 | F9: =Reglement_cal -> 49 | G9: Prospectus art. 6 et 7.2.4
B10: LTTL hors blocage | C10: =SUM(C7:C9) -> 140 | D10: =SUM(D7:D9) -> 231 | E10: =SUM(E7:E9) -> 323 | F10: =SUM(F7:F9) -> 320 | G10: Délai entre la décision de sortir et le cash
B11: Porteurs encore sous blocage à la date de départ | C11: =Part_bloquee -> 0.5 | G11: Paramètres D : part de l'actif net souscrite depuis moins de 24 mois
B12: LTTL moyen pondéré du passif (blocage résiduel moyen de 12 mois pour la part bloquée) | C12: =(1-Part_bloquee)*LTTL_moy+Part_bloquee*(365+LTTL_moy) -> 413.5 | G12: Dérivé
B14: B. ADÉQUATION ACTIF-PASSIF écart = WATTL actif - LTTL moyen (jours). Positif : l'actif se convertit plus lentement que le passif ne sort ; l'écart est porté par la poche liquide, les flux entrants et le plafonnement.
B15: Mesure | C15: Normal | D15: S2 | E15: S3 | F15: S4 | G15: Lecture
B16: WATTL actif (jours) | C16: =WATTL_N -> 202.07 | D16: =WATTL_S2 -> 300.84 | E16: =WATTL_S3 -> 437.7 | F16: =WATTL_S4 -> 651.2 | G16: Onglet ALP
B17: LTTL moyen du passif (jours) | C17: =LTTL_moy -> 231 | D17: =LTTL_moy -> 231 | E17: =LTTL_moy -> 231 | F17: =LTTL_prol -> 320 | G17: S4 : préavis prolongé à 180 jours (art. 7.2.7)
B18: Écart actif - passif (jours) | C18: =C16-C17 -> -28.93 | D18: =D16-D17 -> 69.84 | E18: =E16-E17 -> 206.7 | F18: =F16-F17 -> 331.2 | G18: Vert < 100 ; Orange 100 à 250 ; Rouge > 250
B19: Verdict | C19: =IF(C18>250,"Rouge",IF(C18>100,"Orange","Vert")) -> Vert | D19: =IF(D18>250,"Rouge",IF(D18>100,"Orange","Vert")) -> Vert | E19: =IF(E18>250,"Rouge",IF(E18>100,"Orange","Vert")) -> Orange | F19: =IF(F18>250,"Rouge",IF(F18>100,"Orange","Vert")) -> Rouge | G19: Le plafonnement de 5 % est la réponse structurelle à cet écart
B20: Couverture de la sortie maximale sur douze mois (2 × gate) par l'actif convertible dans le LTTL maximal, S3 | C20: =SUMPRODUCT((ALP!G7:G12<=LTTL_max)*ALP!C7:C12*(1-ALP!L7:L12))/(2*Gate*AN_depart) -> 1.567 | G20: Doit dépasser 1 : la poche liquide couvre deux dates plafonnées
B22: C. PROFIL ANNEX IV, CÔTÉ PASSIF % de l'actif net rachetable par tranche (question 186), hypothèse de porteurs répartis uniformément
B23: Tranche | C23: Normal | D23: S2 (gate actif) | E23: S3 (gate et suspension) | F23: Préavis prolongé | G23: Champ Annex IV
B24: 1 jour | C24: 0 | D24: 0 | E24: 0 | F24: 0 | G24: 1 day
B25: 2 à 7 jours | C25: 0 | D25: 0 | E25: 0 | F25: 0 | G25: 2-7 days
B26: 8 à 30 jours | C26: 0 | D26: 0 | E26: 0 | F26: 0 | G26: 8-30 days
B27: 31 à 90 jours | C27: 0 | D27: 0 | E27: 0 | F27: 0 | G27: 31-90 days
B28: 91 à 180 jours | C28: =(1-Part_bloquee)*0.5 -> 0.25 | D28: =MIN(Gate,(1-Part_bloquee)*0.5) -> 0.05 | E28: 0 | F28: 0 | G28: 91-180 days ; une date de rachat au plus dans la fenêtre
B29: 181 à 365 jours | C29: =(1-Part_bloquee)*0.5 -> 0.25 | D29: =MIN(Gate,(1-Part_bloquee)*0.5) -> 0.05 | E29: =MIN(Gate,(1-Part_bloquee)) -> 0.05 | F29: =MIN(2*Gate,(1-Part_bloquee)) -> 0.1 | G29: 181-365 days ; deuxième date, LTTL max 322 jours
B30: Plus de 365 jours | C30: =1-SUM(C24:C29) -> 0.5 | D30: =1-SUM(D24:D29) -> 0.9 | E30: =1-SUM(E24:E29) -> 0.95 | F30: =1-SUM(F24:F29) -> 0.9 | G30: more than 365 days ; porteurs bloqués et demandes reportées
B31: Total | C31: =SUM(C24:C30) -> 1 | D31: =SUM(D24:D30) -> 1 | E31: =SUM(E24:E30) -> 1 | F31: =SUM(F24:F30) -> 1
B32: Hypothèses : les porteurs hors blocage demandent au plus le plafond par date ; en S3 la première date est plafonnée puis suspendue ; en préavis prolongé la première date glisse de 89 jours. Ce profil alimente la question 186 du reporting Annex IV ; le profil d'actif (ALP) la question 178.

Sheet LST Moteur
B2: LST - MOTEUR DE PROJECTION PAR SCÉNARIO : HUIT DATES DE RACHAT SEMESTRIELLES
B3: Pour chaque scénario : passif (demandes, report, plafond, suspension), flux des lignes (appels, distributions, chocs de marché du MST), cascade de ressources (trésorerie au-dessus du plancher, vente du fonds HY, rachats evergreen sous gate et pression des pairs, cession secondaire décotée), puis indicateurs et verdict par date. Tous les paramètres viennent de l'onglet Paramètres.
B5: S1 - BASE Rachats courants, collecte normale, marchés stables
B6: Date de rachat | C6: 1 | D6: 2 | E6: 3 | F6: 4 | G6: 5 | H6: 6 | I6: 7 | J6: 8 | K6: Formule et lecture
B7: Date de VL de rachat | C7: =EDATE(Date_depart,0) -> 47118 | D7: =EDATE(Date_depart,6) -> 47299 | E7: =EDATE(Date_depart,12) -> 47483 | F7: =EDATE(Date_depart,18) -> 47664 | G7: =EDATE(Date_depart,24) -> 47848 | H7: =EDATE(Date_depart,30) -> 48029 | I7: =EDATE(Date_depart,36) -> 48213 | J7: =EDATE(Date_depart,42) -> 48395
B8: Actif net de début de période | C8: =AN_depart -> 8000000 | D8: =C59 -> 8866702.3 | E8: =D59 -> 9846937.1 | F8: =E59 -> 10999515 | G8: =F59 -> 12286513 | H8: =G59 -> 13722954 | I8: =H59 -> 15325805 | J8: =I59 -> 17113948 | K8: t = 1 : AN de départ ; ensuite AN de fin précédent
B9: Souscriptions versées sur la période | C9: =Collecte_norm*Paramètres!$C$133*C8 -> 800000 | D9: =Collecte_norm*Paramètres!$D$133*D8 -> 886670.23 | E9: =Collecte_norm*Paramètres!$E$133*E8 -> 984693.71 | F9: =Collecte_norm*Paramètres!$F$133*F8 -> 1099951.5 | G9: =Collecte_norm*Paramètres!$G$133*G8 -> 1228651.3 | H9: =Collecte_norm*Paramètres!$H$133*H8 -> 1372295.4 | I9: =Collecte_norm*Paramètres!$I$133*I8 -> 1532580.5 | J9: =Collecte_norm*Paramètres!$J$133*J8 -> 1711394.8 | K9: Collecte normale × multiplicateur du scénario
B10: Demandes de rachat nouvelles | C10: =(Paramètres!$C$128+Paramètres!$C$153*Top1)*C8 -> 160000 | D10: =(Paramètres!$D$128+Paramètres!$D$153*Top1)*D8 -> 177334.05 | E10: =(Paramètres!$E$128+Paramètres!$E$153*Top1)*E8 -> 196938.74 | F10: =(Paramètres!$F$128+Paramètres!$F$153*Top1)*F8 -> 219990.29 | G10: =(Paramètres!$G$128+Paramètres!$G$153*Top1)*G8 -> 245730.25 | H10: =(Paramètres!$H$128+Paramètres!$H$153*Top1)*H8 -> 274459.08 | I10: =(Paramètres!$I$128+Paramètres!$I$153*Top1)*I8 -> 306516.1 | J10: =(Paramètres!$J$128+Paramètres!$J$153*Top1)*J8 -> 342278.95 | K10: Taux du scénario × AN, plus sortie du premier porteur le cas échéant
B11: Demandes reportées des dates précédentes | C11: =0 -> 0 | D11: =C16 -> 0 | E11: =D16 -> 0 | F11: =E16 -> 0 | G11: =F16 -> 0 | H11: =G16 -> 0 | I11: =H16 -> 0 | J11: =I16 -> 0 | K11: Report automatique (art. 7.2.6)
B12: Demandes totales à la date | C12: =C10+C11 -> 160000 | D12: =D10+D11 -> 177334.05 | E12: =E10+E11 -> 196938.74 | F12: =F10+F11 -> 219990.29 | G12: =G10+G11 -> 245730.25 | H12: =H10+H11 -> 274459.08 | I12: =I10+I11 -> 306516.1 | J12: =J10+J11 -> 342278.95
B13: Montant exécutable (plafond net des souscriptions) | C13: =IF(Gate_actif=1,Gate*C8+C9,C12) -> 1200000 | D13: =IF(Gate_actif=1,Gate*D8+D9,D12) -> 1330005.3 | E13: =IF(Gate_actif=1,Gate*E8+E9,E12) -> 1477040.6 | F13: =IF(Gate_actif=1,Gate*F8+F9,F12) -> 1649927.2 | G13: =IF(Gate_actif=1,Gate*G8+G9,G12) -> 1842976.9 | H13: =IF(Gate_actif=1,Gate*H8+H9,H12) -> 2058443.1 | I13: =IF(Gate_actif=1,Gate*I8+I9,I12) -> 2298870.7 | J13: =IF(Gate_actif=1,Gate*J8+J9,J12) -> 2567092.1 | K13: Gate × AN + souscriptions versées ; sans limite si le gate est levé
B14: Suspension des rachats active (1/0) | C14: =0 -> 0 | D14: =IF(OR(C14=1,AND(Suspension_auto=1,C18>=Reports_max)),1,0) -> 0 | E14: =IF(OR(D14=1,AND(Suspension_auto=1,D18>=Reports_max)),1,0) -> 0 | F14: =IF(OR(E14=1,AND(Suspension_auto=1,E18>=Reports_max)),1,0) -> 0 | G14: =IF(OR(F14=1,AND(Suspension_auto=1,F18>=Reports_max)),1,0) -> 0 | H14: =IF(OR(G14=1,AND(Suspension_auto=1,G18>=Reports_max)),1,0) -> 0 | I14: =IF(OR(H14=1,AND(Suspension_auto=1,H18>=Reports_max)),1,0) -> 0 | J14: =IF(OR(I14=1,AND(Suspension_auto=1,I18>=Reports_max)),1,0) -> 0 | K14: Déclenchée après le nombre maximal de reports consécutifs (Paramètres E)
B15: Rachats exécutés | C15: =IF(C14=1,0,MIN(C12,C13)) -> 160000 | D15: =IF(D14=1,0,MIN(D12,D13)) -> 177334.05 | E15: =IF(E14=1,0,MIN(E12,E13)) -> 196938.74 | F15: =IF(F14=1,0,MIN(F12,F13)) -> 219990.29 | G15: =IF(G14=1,0,MIN(G12,G13)) -> 245730.25 | H15: =IF(H14=1,0,MIN(H12,H13)) -> 274459.08 | I15: =IF(I14=1,0,MIN(I12,I13)) -> 306516.1 | J15: =IF(J14=1,0,MIN(J12,J13)) -> 342278.95 | K15: Zéro en suspension
B16: Demandes reportées à la date suivante | C16: =C12-C15 -> 0 | D16: =D12-D15 -> 0 | E16: =E12-E15 -> 0 | F16: =F12-F15 -> 0 | G16: =G12-G15 -> 0 | H16: =H12-H15 -> 0 | I16: =I12-I15 -> 0 | J16: =J12-J15 -> 0
B17: Date plafonnée ou suspendue (1/0) | C17: =IF(C16>1,1,0) -> 0 | D17: =IF(D16>1,1,0) -> 0 | E17: =IF(E16>1,1,0) -> 0 | F17: =IF(F16>1,1,0) -> 0 | G17: =IF(G16>1,1,0) -> 0 | H17: =IF(H16>1,1,0) -> 0 | I17: =IF(I16>1,1,0) -> 0 | J17: =IF(J16>1,1,0) -> 0
B18: Dates plafonnées consécutives | C18: =C17 -> 0 | D18: =IF(D17=1,C18+1,0) -> 0 | E18: =IF(E17=1,D18+1,0) -> 0 | F18: =IF(F17=1,E18+1,0) -> 0 | G18: =IF(G17=1,F18+1,0) -> 0 | H18: =IF(H17=1,G18+1,0) -> 0 | I18: =IF(I17=1,H18+1,0) -> 0 | J18: =IF(J17=1,I18+1,0) -> 0
B19: File d'attente en % de l'AN de début | C19: =C16/C8 -> 0 | D19: =D16/D8 -> 0 | E19: =E16/E8 -> 0 | F19: =F16/F8 -> 0 | G19: =G16/G8 -> 0 | H19: =H16/H8 -> 0 | I19: =I16/I8 -> 0 | J19: =J16/J8 -> 0
B21: MAPIF II - valeur de début | C21: =Paramètres!$D$68*AN_depart -> 2800000 | D21: =C53 -> 3084337.6 | E21: =D53 -> 3377239.5 | F21: =E53 -> 3703886 | G21: =F53 -> 4042781.8 | H21: =G53 -> 4394386.1 | I21: =H53 -> 4759175.5 | J21: =I53 -> 4937644.6
B22: MSIG 3 - valeur de début | C22: =Paramètres!$D$69*AN_depart -> 0 | D22: =C54 -> 0 | E22: =D54 -> 0 | F22: =E54 -> 0 | G22: =F54 -> 0 | H22: =G54 -> 0 | I22: =H54 -> 0 | J22: =I54 -> 0
B23: PG NGI - valeur de début | C23: =Paramètres!$D$70*AN_depart -> 1960000 | D23: =C55 -> 2225703.3 | E23: =D55 -> 2524051.2 | F23: =E55 -> 2885119.1 | G23: =F55 -> 3297633.3 | H23: =G55 -> 3772913.4 | I23: =H55 -> 4318826.2 | J23: =I55 -> 5044138.4
B24: Ares AGI - valeur de début | C24: =Paramètres!$D$71*AN_depart -> 1960000 | D24: =C56 -> 2174261.4 | E24: =D56 -> 2413480.1 | F24: =E56 -> 2708958.9 | G24: =F56 -> 3045381.5 | H24: =G56 -> 3432545.1 | I24: =H56 -> 3876476.8 | J24: =I56 -> 4483865.4
B25: Fonds HY UCITS - valeur de début | C25: =Paramètres!$D$72*AN_depart -> 880000 | D25: =C57 -> 950400 | E25: =D57 -> 1053364.2 | F25: =E57 -> 1169816.1 | G25: =F57 -> 1306742.4 | H25: =G57 -> 1459637.7 | I25: =H57 -> 1630286.9 | J25: =I57 -> 1820705.6
B26: Trésorerie de début | C26: =W_cash*AN_depart -> 400000 | D26: =C51 -> 432000 | E26: =D51 -> 478801.92 | F26: =E51 -> 531734.6 | G26: =F51 -> 593973.8 | H26: =G51 -> 663471.69 | I26: =H51 -> 741039.51 | J26: =I51 -> 827593.47
B27: Non-appelé de début (fonds fermés) | C27: =NA_total -> 1200000 | D27: =C58 -> 1000000 | E27: =D58 -> 800000 | F27: =E58 -> 600000 | G27: =F58 -> 400000 | H27: =G58 -> 200000 | I27: =H58 -> 0 | J27: =I58 -> 0 | K27: Engagements restant à appeler
B29: Appels de fonds des fonds fermés | C29: =MIN(C27,NA_total*Appels_base*Paramètres!$C$143) -> 200000 | D29: =MIN(D27,NA_total*Appels_base*Paramètres!$D$143) -> 200000 | E29: =MIN(E27,NA_total*Appels_base*Paramètres!$E$143) -> 200000 | F29: =MIN(F27,NA_total*Appels_base*Paramètres!$F$143) -> 200000 | G29: =MIN(G27,NA_total*Appels_base*Paramètres!$G$143) -> 200000 | H29: =MIN(H27,NA_total*Appels_base*Paramètres!$H$143) -> 200000 | I29: =MIN(I27,NA_total*Appels_base*Paramètres!$I$143) -> 0 | J29: =MIN(J27,NA_total*Appels_base*Paramètres!$J$143) -> 0 | K29: Rythme normal × multiplicateur ; MAPIF II 60 %, MSIG 3 40 % du non-appelé
B30: Distributions des fonds fermés | C30: =(C21*Paramètres!$D$79+C22*Paramètres!$D$80)/2*Paramètres!$C$138 -> 84000 | D30: =(D21*Paramètres!$D$79+D22*Paramètres!$D$80)/2*Paramètres!$D$138 -> 92530.127 | E30: =(E21*Paramètres!$D$79+E22*Paramètres!$D$80)/2*Paramètres!$E$138 -> 101317.19 | F30: =(F21*Paramètres!$D$79+F22*Paramètres!$D$80)/2*Paramètres!$F$138 -> 111116.58 | G30: =(G21*Paramètres!$D$79+G22*Paramètres!$D$80)/2*Paramètres!$G$138 -> 121283.45 | H30: =(H21*Paramètres!$D$79+H22*Paramètres!$D$80)/2*Paramètres!$H$138 -> 131831.58 | I30: =(I21*Paramètres!$D$79+I22*Paramètres!$D$80)/2*Paramètres!$I$138 -> 142775.27 | J30: =(J21*Paramètres!$D$79+J22*Paramètres!$D$80)/2*Paramètres!$J$138 -> 148129.34 | K30: Valeur × taux annuel / 2 × multiplicateur
B31: Distributions des fonds evergreen | C31: =(C23*Paramètres!$D$81+C24*Paramètres!$D$82)/2*Paramètres!$C$138 -> 68600 | D31: =(D23*Paramètres!$D$81+D24*Paramètres!$D$82)/2*Paramètres!$D$138 -> 76613.569 | E31: =(E23*Paramètres!$D$81+E24*Paramètres!$D$82)/2*Paramètres!$E$138 -> 85577.516 | F31: =(F23*Paramètres!$D$81+F24*Paramètres!$D$82)/2*Paramètres!$F$138 -> 96575.163 | G31: =(G23*Paramètres!$D$81+G24*Paramètres!$D$82)/2*Paramètres!$G$138 -> 109110.87 | H31: =(H23*Paramètres!$D$81+H24*Paramètres!$D$82)/2*Paramètres!$H$138 -> 123542.76 | I31: =(I23*Paramètres!$D$81+I24*Paramètres!$D$82)/2*Paramètres!$I$138 -> 140100.18 | J31: =(J23*Paramètres!$D$81+J24*Paramètres!$D$82)/2*Paramètres!$J$138 -> 162538.02 | K31: Imputées sur la capacité de rachat des fonds (PG NGI)
B32: Frais du Fonds | C32: =Frais_an/2*C8 -> 130396 | D32: =Frais_an/2*D8 -> 144522.81 | E32: =Frais_an/2*E8 -> 160500.15 | F32: =Frais_an/2*F8 -> 179286.59 | G32: =Frais_an/2*G8 -> 200264.01 | H32: =Frais_an/2*H8 -> 223677.29 | I32: =Frais_an/2*I8 -> 249802.96 | J32: =Frais_an/2*J8 -> 278948.79
B33: Produits de trésorerie | C33: =C26*Paramètres!$C$84/2 -> 5000 | D33: =D26*Paramètres!$C$84/2 -> 5400 | E33: =E26*Paramètres!$C$84/2 -> 5985.0241 | F33: =F26*Paramètres!$C$84/2 -> 6646.6825 | G33: =G26*Paramètres!$C$84/2 -> 7424.6725 | H33: =H26*Paramètres!$C$84/2 -> 8293.3961 | I33: =I26*Paramètres!$C$84/2 -> 9262.9939 | J33: =J26*Paramètres!$C$84/2 -> 10344.918
B34: Besoin de trésorerie brut | C34: =C15+C29+C32-C9-C30-C31-C33 -> -467204 | D34: =D15+D29+D32-D9-D30-D31-D33 -> -539357.07 | E34: =E15+E29+E32-E9-E30-E31-E33 -> -620134.54 | F34: =F15+F29+F32-F9-F30-F31-F33 -> -715013.02 | G34: =G15+G29+G32-G9-G30-G31-G33 -> -820476 | H34: =H15+H29+H32-H9-H30-H31-H33 -> -937826.77 | I34: =I15+I29+I32-I9-I30-I31-I33 -> -1268399.9 | J34: =J15+J29+J32-J9-J30-J31-J33 -> -1411179.3 | K34: Sorties moins entrées de la période
B35: Trésorerie mobilisable au-dessus du plancher | C35: =MAX(0,C26-Cash_min*C8) -> 320000 | D35: =MAX(0,D26-Cash_min*D8) -> 343332.98 | E35: =MAX(0,E26-Cash_min*E8) -> 380332.55 | F35: =MAX(0,F26-Cash_min*F8) -> 421739.45 | G35: =MAX(0,G26-Cash_min*G8) -> 471108.67 | H35: =MAX(0,H26-Cash_min*H8) -> 526242.15 | I35: =MAX(0,I26-Cash_min*I8) -> 587781.46 | J35: =MAX(0,J26-Cash_min*J8) -> 656453.99 | K35: Plancher opérationnel (Paramètres D)
B36: Besoin après trésorerie | C36: =MAX(0,C34-C35) -> 0 | D36: =MAX(0,D34-D35) -> 0 | E36: =MAX(0,E34-E35) -> 0 | F36: =MAX(0,F34-F35) -> 0 | G36: =MAX(0,G34-G35) -> 0 | H36: =MAX(0,H34-H35) -> 0 | I36: =MAX(0,I34-I35) -> 0 | J36: =MAX(0,J34-J35) -> 0
B37: Vente du fonds HY | C37: =MIN(C36,C25*(1+'MST Scénarios'!C20)) -> 0 | D37: =MIN(D36,D25*(1+'MST Scénarios'!D20)) -> 0 | E37: =MIN(E36,E25*(1+'MST Scénarios'!E20)) -> 0 | F37: =MIN(F36,F25*(1+'MST Scénarios'!F20)) -> 0 | G37: =MIN(G36,G25*(1+'MST Scénarios'!G20)) -> 0 | H37: =MIN(H36,H25*(1+'MST Scénarios'!H20)) -> 0 | I37: =MIN(I36,I25*(1+'MST Scénarios'!I20)) -> 0 | J37: =MIN(J36,J25*(1+'MST Scénarios'!J20)) -> 0 | K37: Première ressource après la trésorerie
B38: Décote réalisée sur la vente HY | C38: =C37*0 -> 0 | D38: =D37*0 -> 0 | E38: =E37*0 -> 0 | F38: =F37*0 -> 0 | G38: =G37*0 -> 0 | H38: =H37*0 -> 0 | I38: =I37*0 -> 0 | J38: =J37*0 -> 0 | K38: Haircut S2 à S4 (Paramètres C bis)
B39: Besoin après vente HY | C39: =MAX(0,C36-C37*(1-0)) -> 0 | D39: =MAX(0,D36-D37*(1-0)) -> 0 | E39: =MAX(0,E36-E37*(1-0)) -> 0 | F39: =MAX(0,F36-F37*(1-0)) -> 0 | G39: =MAX(0,G36-G37*(1-0)) -> 0 | H39: =MAX(0,H36-H37*(1-0)) -> 0 | I39: =MAX(0,I36-I37*(1-0)) -> 0 | J39: =MAX(0,J36-J37*(1-0)) -> 0
B40: Capacité de rachat des fonds evergreen (gates, pairs, distributions) | C40: =MAX(0,(C23*Paramètres!$F$70+C24*Paramètres!$F$71)*2*(1-Paramètres!$C$148)-C31) -> 205800 | D40: =MAX(0,(D23*Paramètres!$F$70+D24*Paramètres!$F$71)*2*(1-Paramètres!$D$148)-D31) -> 231383.96 | E40: =MAX(0,(E23*Paramètres!$F$70+E24*Paramètres!$F$71)*2*(1-Paramètres!$E$148)-E31) -> 260049.68 | F40: =MAX(0,(F23*Paramètres!$F$70+F24*Paramètres!$F$71)*2*(1-Paramètres!$F$148)-F31) -> 295010.3 | G40: =MAX(0,(G23*Paramètres!$F$70+G24*Paramètres!$F$71)*2*(1-Paramètres!$G$148)-G31) -> 334900.17 | H40: =MAX(0,(H23*Paramètres!$F$70+H24*Paramètres!$F$71)*2*(1-Paramètres!$H$148)-H31) -> 380839.33 | I40: =MAX(0,(I23*Paramètres!$F$70+I24*Paramètres!$F$71)*2*(1-Paramètres!$I$148)-I31) -> 433571.03 | J40: =MAX(0,(J23*Paramètres!$F$70+J24*Paramètres!$F$71)*2*(1-Paramètres!$J$148)-J31) -> 504422.25 | K40: Deux trimestres de gate à 5 %, part des pairs déduite
B41: Rachats evergreen demandés : besoin résiduel et reconstitution de la poche d'exécution | C41: =MAX(C39,Poche_min_exec*C8-(C26-C34+C37*(1-0)+C25*(1+'MST Scénarios'!C20)-C37)) -> 0 | D41: =MAX(D39,Poche_min_exec*D8-(D26-D34+D37*(1-0)+D25*(1+'MST Scénarios'!D20)-D37)) -> 0 | E41: =MAX(E39,Poche_min_exec*E8-(E26-E34+E37*(1-0)+E25*(1+'MST Scénarios'!E20)-E37)) -> 0 | F41: =MAX(F39,Poche_min_exec*F8-(F26-F34+F37*(1-0)+F25*(1+'MST Scénarios'!F20)-F37)) -> 0 | G41: =MAX(G39,Poche_min_exec*G8-(G26-G34+G37*(1-0)+G25*(1+'MST Scénarios'!G20)-G37)) -> 0 | H41: =MAX(H39,Poche_min_exec*H8-(H26-H34+H37*(1-0)+H25*(1+'MST Scénarios'!H20)-H37)) -> 0 | I41: =MAX(I39,Poche_min_exec*I8-(I26-I34+I37*(1-0)+I25*(1+'MST Scénarios'!I20)-I37)) -> 0 | J41: =MAX(J39,Poche_min_exec*J8-(J26-J34+J37*(1-0)+J25*(1+'MST Scénarios'!J20)-J37)) -> 0 | K41: La Fonction Risques demande le rachat dès que trésorerie + HY passent sous la poche d'exécution (Paramètres D)
B42: Rachats obtenus des fonds evergreen | C42: =MAX(0,MIN(C41,C40)) -> 0 | D42: =MAX(0,MIN(D41,D40)) -> 0 | E42: =MAX(0,MIN(E41,E40)) -> 0 | F42: =MAX(0,MIN(F41,F40)) -> 0 | G42: =MAX(0,MIN(G41,G40)) -> 0 | H42: =MAX(0,MIN(H41,H40)) -> 0 | I42: =MAX(0,MIN(I41,I40)) -> 0 | J42: =MAX(0,MIN(J41,J40)) -> 0 | K42: Au prorata PG NGI / Ares AGI, dans la limite de la capacité sous gate
B43: Besoin résiduel | C43: =MAX(0,C39-C42) -> 0 | D43: =MAX(0,D39-D42) -> 0 | E43: =MAX(0,E39-E42) -> 0 | F43: =MAX(0,F39-F42) -> 0 | G43: =MAX(0,G39-G42) -> 0 | H43: =MAX(0,H39-H42) -> 0 | I43: =MAX(0,I39-I42) -> 0 | J43: =MAX(0,J39-J42) -> 0
B44: Cession secondaire des fonds fermés (valeur cédée) | C44: =IF(Cession_autorisee=1,MIN(C43/(1-0),C21+C22),0) -> 0 | D44: =IF(Cession_autorisee=1,MIN(D43/(1-0),D21+D22),0) -> 0 | E44: =IF(Cession_autorisee=1,MIN(E43/(1-0),E21+E22),0) -> 0 | F44: =IF(Cession_autorisee=1,MIN(F43/(1-0),F21+F22),0) -> 0 | G44: =IF(Cession_autorisee=1,MIN(G43/(1-0),G21+G22),0) -> 0 | H44: =IF(Cession_autorisee=1,MIN(H43/(1-0),H21+H22),0) -> 0 | I44: =IF(Cession_autorisee=1,MIN(I43/(1-0),I21+I22),0) -> 0 | J44: =IF(Cession_autorisee=1,MIN(J43/(1-0),J21+J22),0) -> 0 | K44: Montant à céder pour encaisser le besoin après décote
B45: Décote réalisée sur la cession | C45: =C44*0 -> 0 | D45: =D44*0 -> 0 | E45: =E44*0 -> 0 | F45: =F44*0 -> 0 | G45: =G44*0 -> 0 | H45: =H44*0 -> 0 | I45: =I44*0 -> 0 | J45: =J44*0 -> 0
B46: Défaut de liquidité (besoin non couvert) | C46: =MAX(0,C43-C44*(1-0)) -> 0 | D46: =MAX(0,D43-D44*(1-0)) -> 0 | E46: =MAX(0,E43-E44*(1-0)) -> 0 | F46: =MAX(0,F43-F44*(1-0)) -> 0 | G46: =MAX(0,G43-G44*(1-0)) -> 0 | H46: =MAX(0,H43-H44*(1-0)) -> 0 | I46: =MAX(0,I43-I44*(1-0)) -> 0 | J46: =MAX(0,J43-J44*(1-0)) -> 0 | K46: Doit rester nul ; sinon la suspension s'impose
B47: Trésorerie avant réinvestissement | C47: =C26-C34+C37*(1-0)+C42+C44*(1-0)+C46 -> 867204 | D47: =D26-D34+D37*(1-0)+D42+D44*(1-0)+D46 -> 971357.07 | E47: =E26-E34+E37*(1-0)+E42+E44*(1-0)+E46 -> 1098936.5 | F47: =F26-F34+F37*(1-0)+F42+F44*(1-0)+F46 -> 1246747.6 | G47: =G26-G34+G37*(1-0)+G42+G44*(1-0)+G46 -> 1414449.8 | H47: =H26-H34+H37*(1-0)+H42+H44*(1-0)+H46 -> 1601298.5 | I47: =I26-I34+I37*(1-0)+I42+I44*(1-0)+I46 -> 2009439.4 | J47: =J26-J34+J37*(1-0)+J42+J44*(1-0)+J46 -> 2238772.8 | K47: Le défaut est réintégré pour garder un solde cohérent (rachat non payé)
B48: Excédent de trésorerie au-dessus de la cible | C48: =MAX(0,C47-Cash_cible*(C8+C9-C15))*Reinvest_actif -> 435204 | D48: =MAX(0,D47-Cash_cible*(D8+D9-D15))*Reinvest_actif -> 492555.14 | E48: =MAX(0,E47-Cash_cible*(E8+E9-E15))*Reinvest_actif -> 567201.86 | F48: =MAX(0,F47-Cash_cible*(F8+F9-F15))*Reinvest_actif -> 652773.82 | G48: =MAX(0,G47-Cash_cible*(G8+G9-G15))*Reinvest_actif -> 750978.11 | H48: =MAX(0,H47-Cash_cible*(H8+H9-H15))*Reinvest_actif -> 860258.94 | I48: =MAX(0,I47-Cash_cible*(I8+I9-I15))*Reinvest_actif -> 1181845.9 | J48: =MAX(0,J47-Cash_cible*(J8+J9-J15))*Reinvest_actif -> 1314619.6 | K48: Réinvesti si l'interrupteur est actif (Paramètres E)
B49: Réinvestissement dans le fonds HY (retour au poids cible) | C49: =MIN(C48,MAX(0,(Liq_cible-Cash_cible)*(C8+C9-C15)-(C25*(1+'MST Scénarios'!C20)-C37))) -> 61070.007 | D49: =MIN(D48,MAX(0,(Liq_cible-Cash_cible)*(D8+D9-D15)-(D25*(1+'MST Scénarios'!D20)-D37))) -> 74452.233 | E49: =MIN(E48,MAX(0,(Liq_cible-Cash_cible)*(E8+E9-E15)-(E25*(1+'MST Scénarios'!E20)-E37))) -> 84850.962 | F49: =MIN(F48,MAX(0,(Liq_cible-Cash_cible)*(F8+F9-F15)-(F25*(1+'MST Scénarios'!F20)-F37))) -> 101831.75 | G49: =MIN(G48,MAX(0,(Liq_cible-Cash_cible)*(G8+G9-G15)-(G25*(1+'MST Scénarios'!G20)-G37))) -> 113693.09 | H49: =MIN(H48,MAX(0,(Liq_cible-Cash_cible)*(H8+H9-H15)-(H25*(1+'MST Scénarios'!H20)-H37))) -> 126860.09 | I49: =MIN(I48,MAX(0,(Liq_cible-Cash_cible)*(I8+I9-I15)-(I25*(1+'MST Scénarios'!I20)-I37))) -> 141510.09 | J49: =MIN(J48,MAX(0,(Liq_cible-Cash_cible)*(J8+J9-J15)-(J25*(1+'MST Scénarios'!J20)-J37))) -> 157810.17
B50: Réinvestissement dans les fonds evergreen (moitié PG NGI, moitié Ares AGI) | C50: =C48-C49 -> 374133.99 | D50: =D48-D49 -> 418102.91 | E50: =E48-E49 -> 482350.9 | F50: =F48-F49 -> 550942.08 | G50: =G48-G49 -> 637285.02 | H50: =H48-H49 -> 733398.85 | I50: =I48-I49 -> 1040335.8 | J50: =J48-J49 -> 1156809.4 | K50: Les fonds fermés ne reçoivent que les appels
B51: Trésorerie de fin | C51: =C47-C49-C50 -> 432000 | D51: =D47-D49-D50 -> 478801.92 | E51: =E47-E49-E50 -> 531734.6 | F51: =F47-F49-F50 -> 593973.8 | G51: =G47-G49-G50 -> 663471.69 | H51: =H47-H49-H50 -> 741039.51 | I51: =I47-I49-I50 -> 827593.47 | J51: =J47-J49-J50 -> 924153.17
B53: MAPIF II - valeur de fin | C53: =C21*(1+'MST Scénarios'!C16)+C29*Paramètres!$E$68*Paramètres!$D$68/(Paramètres!$E$68*Paramètres!$D$68+Paramètres!$E$69*Paramètres!$D$69)-C21*Paramètres!$D$79/2*Paramètres!$C$138-C44*C21/(C21+C22) -> 3084337.6 | D53: =D21*(1+'MST Scénarios'!D16)+D29*Paramètres!$E$68*Paramètres!$D$68/(Paramètres!$E$68*Paramètres!$D$68+Paramètres!$E$69*Paramètres!$D$69)-D21*Paramètres!$D$79/2*Paramètres!$D$138-D44*D21/(D21+D22) -> 3377239.5 | E53: =E21*(1+'MST Scénarios'!E16)+E29*Paramètres!$E$68*Paramètres!$D$68/(Paramètres!$E$68*Paramètres!$D$68+Paramètres!$E$69*Paramètres!$D$69)-E21*Paramètres!$D$79/2*Paramètres!$E$138-E44*E21/(E21+E22) -> 3703886 | F53: =F21*(1+'MST Scénarios'!F16)+F29*Paramètres!$E$68*Paramètres!$D$68/(Paramètres!$E$68*Paramètres!$D$68+Paramètres!$E$69*Paramètres!$D$69)-F21*Paramètres!$D$79/2*Paramètres!$F$138-F44*F21/(F21+F22) -> 4042781.8 | G53: =G21*(1+'MST Scénarios'!G16)+G29*Paramètres!$E$68*Paramètres!$D$68/(Paramètres!$E$68*Paramètres!$D$68+Paramètres!$E$69*Paramètres!$D$69)-G21*Paramètres!$D$79/2*Paramètres!$G$138-G44*G21/(G21+G22) -> 4394386.1 | H53: =H21*(1+'MST Scénarios'!H16)+H29*Paramètres!$E$68*Paramètres!$D$68/(Paramètres!$E$68*Paramètres!$D$68+Paramètres!$E$69*Paramètres!$D$69)-H21*Paramètres!$D$79/2*Paramètres!$H$138-H44*H21/(H21+H22) -> 4759175.5 | I53: =I21*(1+'MST Scénarios'!I16)+I29*Paramètres!$E$68*Paramètres!$D$68/(Paramètres!$E$68*Paramètres!$D$68+Paramètres!$E$69*Paramètres!$D$69)-I21*Paramètres!$D$79/2*Paramètres!$I$138-I44*I21/(I21+I22) -> 4937644.6 | J53: =J21*(1+'MST Scénarios'!J16)+J29*Paramètres!$E$68*Paramètres!$D$68/(Paramètres!$E$68*Paramètres!$D$68+Paramètres!$E$69*Paramètres!$D$69)-J21*Paramètres!$D$79/2*Paramètres!$J$138-J44*J21/(J21+J22) -> 5122806.3 | K53: Valeur × (1 + rendement MST) + appels - distributions - cession
B54: MSIG 3 - valeur de fin | C54: =C22*(1+'MST Scénarios'!C17)+C29*Paramètres!$E$69*Paramètres!$D$69/(Paramètres!$E$68*Paramètres!$D$68+Paramètres!$E$69*Paramètres!$D$69)-C22*Paramètres!$D$80/2*Paramètres!$C$138-C44*C22/(C21+C22) -> 0 | D54: =D22*(1+'MST Scénarios'!D17)+D29*Paramètres!$E$69*Paramètres!$D$69/(Paramètres!$E$68*Paramètres!$D$68+Paramètres!$E$69*Paramètres!$D$69)-D22*Paramètres!$D$80/2*Paramètres!$D$138-D44*D22/(D21+D22) -> 0 | E54: =E22*(1+'MST Scénarios'!E17)+E29*Paramètres!$E$69*Paramètres!$D$69/(Paramètres!$E$68*Paramètres!$D$68+Paramètres!$E$69*Paramètres!$D$69)-E22*Paramètres!$D$80/2*Paramètres!$E$138-E44*E22/(E21+E22) -> 0 | F54: =F22*(1+'MST Scénarios'!F17)+F29*Paramètres!$E$69*Paramètres!$D$69/(Paramètres!$E$68*Paramètres!$D$68+Paramètres!$E$69*Paramètres!$D$69)-F22*Paramètres!$D$80/2*Paramètres!$F$138-F44*F22/(F21+F22) -> 0 | G54: =G22*(1+'MST Scénarios'!G17)+G29*Paramètres!$E$69*Paramètres!$D$69/(Paramètres!$E$68*Paramètres!$D$68+Paramètres!$E$69*Paramètres!$D$69)-G22*Paramètres!$D$80/2*Paramètres!$G$138-G44*G22/(G21+G22) -> 0 | H54: =H22*(1+'MST Scénarios'!H17)+H29*Paramètres!$E$69*Paramètres!$D$69/(Paramètres!$E$68*Paramètres!$D$68+Paramètres!$E$69*Paramètres!$D$69)-H22*Paramètres!$D$80/2*Paramètres!$H$138-H44*H22/(H21+H22) -> 0 | I54: =I22*(1+'MST Scénarios'!I17)+I29*Paramètres!$E$69*Paramètres!$D$69/(Paramètres!$E$68*Paramètres!$D$68+Paramètres!$E$69*Paramètres!$D$69)-I22*Paramètres!$D$80/2*Paramètres!$I$138-I44*I22/(I21+I22) -> 0 | J54: =J22*(1+'MST Scénarios'!J17)+J29*Paramètres!$E$69*Paramètres!$D$69/(Paramètres!$E$68*Paramètres!$D$68+Paramètres!$E$69*Paramètres!$D$69)-J22*Paramètres!$D$80/2*Paramètres!$J$138-J44*J22/(J21+J22) -> 0
B55: PG NGI - valeur de fin | C55: =C23*(1+'MST Scénarios'!C18)-C23*Paramètres!$D$81/2*Paramètres!$C$138-C42*C23/(C23+C24)+C50/2 -> 2225703.3 | D55: =D23*(1+'MST Scénarios'!D18)-D23*Paramètres!$D$81/2*Paramètres!$D$138-D42*D23/(D23+D24)+D50/2 -> 2524051.2 | E55: =E23*(1+'MST Scénarios'!E18)-E23*Paramètres!$D$81/2*Paramètres!$E$138-E42*E23/(E23+E24)+E50/2 -> 2885119.1 | F55: =F23*(1+'MST Scénarios'!F18)-F23*Paramètres!$D$81/2*Paramètres!$F$138-F42*F23/(F23+F24)+F50/2 -> 3297633.3 | G55: =G23*(1+'MST Scénarios'!G18)-G23*Paramètres!$D$81/2*Paramètres!$G$138-G42*G23/(G23+G24)+G50/2 -> 3772913.4 | H55: =H23*(1+'MST Scénarios'!H18)-H23*Paramètres!$D$81/2*Paramètres!$H$138-H42*H23/(H23+H24)+H50/2 -> 4318826.2 | I55: =I23*(1+'MST Scénarios'!I18)-I23*Paramètres!$D$81/2*Paramètres!$I$138-I42*I23/(I23+I24)+I50/2 -> 5044138.4 | J55: =J23*(1+'MST Scénarios'!J18)-J23*Paramètres!$D$81/2*Paramètres!$J$138-J42*J23/(J23+J24)+J50/2 -> 5862139.6 | K55: Rendement MST, distributions, rachats obtenus au prorata, réinvestissement
B56: Ares AGI - valeur de fin | C56: =C24*(1+'MST Scénarios'!C19)-C24*Paramètres!$D$82/2*Paramètres!$C$138-C42*C24/(C23+C24)+C50/2 -> 2174261.4 | D56: =D24*(1+'MST Scénarios'!D19)-D24*Paramètres!$D$82/2*Paramètres!$D$138-D42*D24/(D23+D24)+D50/2 -> 2413480.1 | E56: =E24*(1+'MST Scénarios'!E19)-E24*Paramètres!$D$82/2*Paramètres!$E$138-E42*E24/(E23+E24)+E50/2 -> 2708958.9 | F56: =F24*(1+'MST Scénarios'!F19)-F24*Paramètres!$D$82/2*Paramètres!$F$138-F42*F24/(F23+F24)+F50/2 -> 3045381.5 | G56: =G24*(1+'MST Scénarios'!G19)-G24*Paramètres!$D$82/2*Paramètres!$G$138-G42*G24/(G23+G24)+G50/2 -> 3432545.1 | H56: =H24*(1+'MST Scénarios'!H19)-H24*Paramètres!$D$82/2*Paramètres!$H$138-H42*H24/(H23+H24)+H50/2 -> 3876476.8 | I56: =I24*(1+'MST Scénarios'!I19)-I24*Paramètres!$D$82/2*Paramètres!$I$138-I42*I24/(I23+I24)+I50/2 -> 4483865.4 | J56: =J24*(1+'MST Scénarios'!J19)-J24*Paramètres!$D$82/2*Paramètres!$J$138-J42*J24/(J23+J24)+J50/2 -> 5163157.1
B57: Fonds HY UCITS - valeur de fin | C57: =C25*(1+'MST Scénarios'!C20)-C37+C49 -> 950400 | D57: =D25*(1+'MST Scénarios'!D20)-D37+D49 -> 1053364.2 | E57: =E25*(1+'MST Scénarios'!E20)-E37+E49 -> 1169816.1 | F57: =F25*(1+'MST Scénarios'!F20)-F37+F49 -> 1306742.4 | G57: =G25*(1+'MST Scénarios'!G20)-G37+G49 -> 1459637.7 | H57: =H25*(1+'MST Scénarios'!H20)-H37+H49 -> 1630286.9 | I57: =I25*(1+'MST Scénarios'!I20)-I37+I49 -> 1820705.6 | J57: =J25*(1+'MST Scénarios'!J20)-J37+J49 -> 2033137
B58: Non-appelé de fin | C58: =C27-C29-C44*C27/(C21+C22+C27) -> 1000000 | D58: =D27-D29-D44*D27/(D21+D22+D27) -> 800000 | E58: =E27-E29-E44*E27/(E21+E22+E27) -> 600000 | F58: =F27-F29-F44*F27/(F21+F22+F27) -> 400000 | G58: =G27-G29-G44*G27/(G21+G22+G27) -> 200000 | H58: =H27-H29-H44*H27/(H21+H22+H27) -> 0 | I58: =I27-I29-I44*I27/(I21+I22+I27) -> 0 | J58: =J27-J29-J44*J27/(J21+J22+J27) -> 0 | K58: La cession emporte sa part de non-appelé
B59: Actif net de fin | C59: =C53+C54+C55+C56+C57+C51 -> 8866702.3 | D59: =D53+D54+D55+D56+D57+D51 -> 9846937.1 | E59: =E53+E54+E55+E56+E57+E51 -> 10999515 | F59: =F53+F54+F55+F56+F57+F51 -> 12286513 | G59: =G53+G54+G55+G56+G57+G51 -> 13722954 | H59: =H53+H54+H55+H56+H57+H51 -> 15325805 | I59: =I53+I54+I55+I56+I57+I51 -> 17113948 | J59: =J53+J54+J55+J56+J57+J51 -> 19105393 | K59: Somme des lignes et de la trésorerie
B60: Contrôle : AN fin - (AN début + souscriptions - rachats - frais + P&L lignes - décotes) | C60: =ROUND(C59-(C8+C9-C15+C46-C32+C33+C21*'MST Scénarios'!C16+C22*'MST Scénarios'!C17+C23*'MST Scénarios'!C18+C24*'MST Scénarios'!C19+C25*'MST Scénarios'!C20-C38-C45),0) -> 0 | D60: =ROUND(D59-(D8+D9-D15+D46-D32+D33+D21*'MST Scénarios'!D16+D22*'MST Scénarios'!D17+D23*'MST Scénarios'!D18+D24*'MST Scénarios'!D19+D25*'MST Scénarios'!D20-D38-D45),0) -> 0 | E60: =ROUND(E59-(E8+E9-E15+E46-E32+E33+E21*'MST Scénarios'!E16+E22*'MST Scénarios'!E17+E23*'MST Scénarios'!E18+E24*'MST Scénarios'!E19+E25*'MST Scénarios'!E20-E38-E45),0) -> 0 | F60: =ROUND(F59-(F8+F9-F15+F46-F32+F33+F21*'MST Scénarios'!F16+F22*'MST Scénarios'!F17+F23*'MST Scénarios'!F18+F24*'MST Scénarios'!F19+F25*'MST Scénarios'!F20-F38-F45),0) -> 0 | G60: =ROUND(G59-(G8+G9-G15+G46-G32+G33+G21*'MST Scénarios'!G16+G22*'MST Scénarios'!G17+G23*'MST Scénarios'!G18+G24*'MST Scénarios'!G19+G25*'MST Scénarios'!G20-G38-G45),0) -> 0 | H60: =ROUND(H59-(H8+H9-H15+H46-H32+H33+H21*'MST Scénarios'!H16+H22*'MST Scénarios'!H17+H23*'MST Scénarios'!H18+H24*'MST Scénarios'!H19+H25*'MST Scénarios'!H20-H38-H45),0) -> 0 | I60: =ROUND(I59-(I8+I9-I15+I46-I32+I33+I21*'MST Scénarios'!I16+I22*'MST Scénarios'!I17+I23*'MST Scénarios'!I18+I24*'MST Scénarios'!I19+I25*'MST Scénarios'!I20-I38-I45),0) -> 0 | J60: =ROUND(J59-(J8+J9-J15+J46-J32+J33+J21*'MST Scénarios'!J16+J22*'MST Scénarios'!J17+J23*'MST Scénarios'!J18+J24*'MST Scénarios'!J19+J25*'MST Scénarios'!J20-J38-J45),0) -> 0 | K60: Doit être nul
B62: Poche liquide de fin (trésorerie + HY), % AN | C62: =(C51+C57)/C59 -> 0.15590915 | D62: =(D51+D57)/D59 -> 0.15559825 | E62: =(E51+E57)/E59 -> 0.15469325 | F62: =(F51+F57)/F59 -> 0.1546994 | G62: =(G51+G57)/G59 -> 0.15471227 | H62: =(H51+H57)/H59 -> 0.15472769 | I62: =(I51+I57)/I59 -> 0.15474508 | J62: =(J51+J57)/J59 -> 0.15478824 | K62: Rouge < 5 % ; Orange < 15 %
B63: Couverture à douze mois : ressources mobilisables / deux dates au plafond | C63: =(C51+C57+2*C40+2*(C30+C31)-2*MIN(C58,NA_total*Appels_base*Paramètres!$D$143))/(2*Gate*C59) -> 1.9163833 | D63: =(D51+D57+2*D40+2*(D30+D31)-2*MIN(D58,NA_total*Appels_base*Paramètres!$E$143))/(2*Gate*D59) -> 1.9632719 | E63: =(E51+E57+2*E40+2*(E30+E31)-2*MIN(E58,NA_total*Appels_base*Paramètres!$F$143))/(2*Gate*E59) -> 1.9959421 | F63: =(F51+F57+2*F40+2*(F30+F31)-2*MIN(F58,NA_total*Appels_base*Paramètres!$G$143))/(2*Gate*F59) -> 2.0397327 | G63: =(G51+G57+2*G40+2*(G30+G31)-2*MIN(G58,NA_total*Appels_base*Paramètres!$H$143))/(2*Gate*G59) -> 2.0795074 | H63: =(H51+H57+2*H40+2*(H30+H31)-2*MIN(H58,NA_total*Appels_base*Paramètres!$I$143))/(2*Gate*H59) -> 2.3775285 | I63: =(I51+I57+2*I40+2*(I30+I31)-2*MIN(I58,NA_total*Appels_base*Paramètres!$J$143))/(2*Gate*I59) -> 2.3847169 | J63: =(J51+J57+2*J40+2*(J30+J31)-2*MIN(J58,NA_total*Appels_base*Paramètres!$J$143))/(2*Gate*J59) -> 2.4011384 | K63: Rouge < 1,0 ; Orange < 1,5
B64: Sur-engagement (AN + non-appelé) / AN | C64: =(C59+C58)/C59 -> 1.1127815 | D64: =(D59+D58)/D59 -> 1.0812435 | E64: =(E59+E58)/E59 -> 1.0545479 | F64: =(F59+F58)/F59 -> 1.032556 | G64: =(G59+G58)/G59 -> 1.0145741 | H64: =(H59+H58)/H59 -> 1 | I64: =(I59+I58)/I59 -> 1 | J64: =(J59+J58)/J59 -> 1 | K64: Plafond 130 % (art. 23)
B65: Exposition dollar non couverte, % AN | C65: =(C53*Paramètres!$H$79+C54*Paramètres!$H$80)/C59 -> 0.34785622 | D65: =(D53*Paramètres!$H$79+D54*Paramètres!$H$80)/D59 -> 0.34297361 | E65: =(E53*Paramètres!$H$79+E54*Paramètres!$H$80)/E59 -> 0.33673177 | F65: =(F53*Paramètres!$H$79+F54*Paramètres!$H$80)/F59 -> 0.32904225 | G65: =(G53*Paramètres!$H$79+G54*Paramètres!$H$80)/G59 -> 0.32022159 | H65: =(H53*Paramètres!$H$79+H54*Paramètres!$H$80)/H59 -> 0.31053348 | I65: =(I53*Paramètres!$H$79+I54*Paramètres!$H$80)/I59 -> 0.28851582 | J65: =(J53*Paramètres!$H$79+J54*Paramètres!$H$80)/J59 -> 0.26813404
B66: Triple gel (collecte, distributions et capacité evergreen simultanément réduites de moitié) | C66: =IF(AND(Paramètres!$C$133<0.5,Paramètres!$C$138<0.5,(1-Paramètres!$C$148)<0.5*(1-Paramètres!$C$148)),1,0) -> 0 | D66: =IF(AND(Paramètres!$D$133<0.5,Paramètres!$D$138<0.5,(1-Paramètres!$D$148)<0.5*(1-Paramètres!$D$148)),1,0) -> 0 | E66: =IF(AND(Paramètres!$E$133<0.5,Paramètres!$E$138<0.5,(1-Paramètres!$E$148)<0.5*(1-Paramètres!$E$148)),1,0) -> 0 | F66: =IF(AND(Paramètres!$F$133<0.5,Paramètres!$F$138<0.5,(1-Paramètres!$F$148)<0.5*(1-Paramètres!$F$148)),1,0) -> 0 | G66: =IF(AND(Paramètres!$G$133<0.5,Paramètres!$G$138<0.5,(1-Paramètres!$G$148)<0.5*(1-Paramètres!$G$148)),1,0) -> 0 | H66: =IF(AND(Paramètres!$H$133<0.5,Paramètres!$H$138<0.5,(1-Paramètres!$H$148)<0.5*(1-Paramètres!$H$148)),1,0) -> 0 | I66: =IF(AND(Paramètres!$I$133<0.5,Paramètres!$I$138<0.5,(1-Paramètres!$I$148)<0.5*(1-Paramètres!$I$148)),1,0) -> 0 | J66: =IF(AND(Paramètres!$J$133<0.5,Paramètres!$J$138<0.5,(1-Paramètres!$J$148)<0.5*(1-Paramètres!$J$148)),1,0) -> 0 | K66: Signature de risque evergreen (ESMA 34-39-882)
B67: Verdict de la date | C67: =IF(OR(C14=1,C46>1,C19>S_file_rouge,C62<S_poche_rouge,C63<S_couv_rouge),"Rouge",IF(OR(C17=1,C62<S_poche_orange,C63<S_couv_orange,C66=1),"Orange","Vert")) -> Vert | D67: =IF(OR(D14=1,D46>1,D19>S_file_rouge,D62<S_poche_rouge,D63<S_couv_rouge),"Rouge",IF(OR(D17=1,D62<S_poche_orange,D63<S_couv_orange,D66=1),"Orange","Vert")) -> Vert | E67: =IF(OR(E14=1,E46>1,E19>S_file_rouge,E62<S_poche_rouge,E63<S_couv_rouge),"Rouge",IF(OR(E17=1,E62<S_poche_orange,E63<S_couv_orange,E66=1),"Orange","Vert")) -> Vert | F67: =IF(OR(F14=1,F46>1,F19>S_file_rouge,F62<S_poche_rouge,F63<S_couv_rouge),"Rouge",IF(OR(F17=1,F62<S_poche_orange,F63<S_couv_orange,F66=1),"Orange","Vert")) -> Vert | G67: =IF(OR(G14=1,G46>1,G19>S_file_rouge,G62<S_poche_rouge,G63<S_couv_rouge),"Rouge",IF(OR(G17=1,G62<S_poche_orange,G63<S_couv_orange,G66=1),"Orange","Vert")) -> Vert | H67: =IF(OR(H14=1,H46>1,H19>S_file_rouge,H62<S_poche_rouge,H63<S_couv_rouge),"Rouge",IF(OR(H17=1,H62<S_poche_orange,H63<S_couv_orange,H66=1),"Orange","Vert")) -> Vert | I67: =IF(OR(I14=1,I46>1,I19>S_file_rouge,I62<S_poche_rouge,I63<S_couv_rouge),"Rouge",IF(OR(I17=1,I62<S_poche_orange,I63<S_couv_orange,I66=1),"Orange","Vert")) -> Vert | J67: =IF(OR(J14=1,J46>1,J19>S_file_rouge,J62<S_poche_rouge,J63<S_couv_rouge),"Rouge",IF(OR(J17=1,J62<S_poche_orange,J63<S_couv_orange,J66=1),"Orange","Vert")) -> Vert | K67: Seuils de l'onglet Paramètres F
B69: Synthèse du scénario | C69: Valeur | K69: Lecture
B70: Dates plafonnées ou suspendues | C70: =SUM(C17:J17) -> 0
B71: File d'attente maximale, % AN | C71: =MAX(C19:J19) -> 0
B72: File résiduelle à la date 8, % AN | C72: =J19 -> 0 | K72: Indicateur unique du Conducting Officer (< 5 % vert, 5 à 15 % orange, 15 à 30 % élevé, > 30 % sévère)
B73: Première date de suspension | C73: =IFERROR(INDEX(C7:J7,MATCH(1,C14:J14,0)),"-") -> -
B74: Poche liquide minimale, % AN | C74: =MIN(C62:J62) -> 0.15469325
B75: Couverture à douze mois minimale | C75: =MIN(C63:J63) -> 1.9163833
B76: Rachats obtenus des fonds evergreen, cumul (EUR) | C76: =SUM(C42:J42) -> 0
B77: Cessions secondaires, cumul (EUR) | C77: =SUM(C44:J44) -> 0
B78: Décotes réalisées, cumul (EUR) | C78: =SUM(C38:J38)+SUM(C45:J45) -> 0
B79: Défaut de liquidité, cumul (EUR) | C79: =SUM(C46:J46) -> 0
B80: Actif net à la date 8 / actif net de départ | C80: =J59/AN_depart-1 -> 1.3881741
B81: Première date de triple gel | C81: =IFERROR(INDEX(C7:J7,MATCH(1,C66:J66,0)),"-") -> -
B82: Sur-engagement maximal | C82: =MAX(C64:J64) -> 1.1127815
B83: Verdict LST du scénario | C83: =IF(COUNTIF(C67:J67,"Rouge")>0,"Rouge",IF(COUNTIF(C67:J67,"Orange")>0,"Orange","Vert")) -> Vert | K83: Pire verdict des huit dates
B86: S2 - PLAUSIBLE Correction de marché à 1,5 écart-type, rachats de 7,5 % sur deux dates, collecte divisée par deux
B87: Date de rachat | C87: 1 | D87: 2 | E87: 3 | F87: 4 | G87: 5 | H87: 6 | I87: 7 | J87: 8 | K87: Formule et lecture
B88: Date de VL de rachat | C88: =EDATE(Date_depart,0) -> 47118 | D88: =EDATE(Date_depart,6) -> 47299 | E88: =EDATE(Date_depart,12) -> 47483 | F88: =EDATE(Date_depart,18) -> 47664 | G88: =EDATE(Date_depart,24) -> 47848 | H88: =EDATE(Date_depart,30) -> 48029 | I88: =EDATE(Date_depart,36) -> 48213 | J88: =EDATE(Date_depart,42) -> 48395
B89: Actif net de début de période | C89: =AN_depart -> 8000000 | D89: =C140 -> 7548713.1 | E89: =D140 -> 7495511.3 | F89: =E140 -> 7856045.7 | G89: =F140 -> 8649028.3 | H89: =G140 -> 9748122.2 | I89: =H140 -> 10907011 | J89: =I140 -> 12197371 | K89: t = 1 : AN de départ ; ensuite AN de fin précédent
B90: Souscriptions versées sur la période | C90: =Collecte_norm*Paramètres!$C$134*C89 -> 400000 | D90: =Collecte_norm*Paramètres!$D$134*D89 -> 377435.66 | E90: =Collecte_norm*Paramètres!$E$134*E89 -> 374775.56 | F90: =Collecte_norm*Paramètres!$F$134*F89 -> 589203.43 | G90: =Collecte_norm*Paramètres!$G$134*G89 -> 864902.83 | H90: =Collecte_norm*Paramètres!$H$134*H89 -> 974812.22 | I90: =Collecte_norm*Paramètres!$I$134*I89 -> 1090701.1 | J90: =Collecte_norm*Paramètres!$J$134*J89 -> 1219737.1 | K90: Collecte normale × multiplicateur du scénario
B91: Demandes de rachat nouvelles | C91: =(Paramètres!$C$129+Paramètres!$C$154*Top1)*C89 -> 600000 | D91: =(Paramètres!$D$129+Paramètres!$D$154*Top1)*D89 -> 566153.49 | E91: =(Paramètres!$E$129+Paramètres!$E$154*Top1)*E89 -> 374775.56 | F91: =(Paramètres!$F$129+Paramètres!$F$154*Top1)*F89 -> 235681.37 | G91: =(Paramètres!$G$129+Paramètres!$G$154*Top1)*G89 -> 172980.57 | H91: =(Paramètres!$H$129+Paramètres!$H$154*Top1)*H89 -> 194962.44 | I91: =(Paramètres!$I$129+Paramètres!$I$154*Top1)*I89 -> 218140.21 | J91: =(Paramètres!$J$129+Paramètres!$J$154*Top1)*J89 -> 243947.43 | K91: Taux du scénario × AN, plus sortie du premier porteur le cas échéant
B92: Demandes reportées des dates précédentes | C92: =0 -> 0 | D92: =C97 -> 0 | E92: =D97 -> 0 | F92: =E97 -> 0 | G92: =F97 -> 0 | H92: =G97 -> 0 | I92: =H97 -> 0 | J92: =I97 -> 0 | K92: Report automatique (art. 7.2.6)
B93: Demandes totales à la date | C93: =C91+C92 -> 600000 | D93: =D91+D92 -> 566153.49 | E93: =E91+E92 -> 374775.56 | F93: =F91+F92 -> 235681.37 | G93: =G91+G92 -> 172980.57 | H93: =H91+H92 -> 194962.44 | I93: =I91+I92 -> 218140.21 | J93: =J91+J92 -> 243947.43
B94: Montant exécutable (plafond net des souscriptions) | C94: =IF(Gate_actif=1,Gate*C89+C90,C93) -> 800000 | D94: =IF(Gate_actif=1,Gate*D89+D90,D93) -> 754871.31 | E94: =IF(Gate_actif=1,Gate*E89+E90,E93) -> 749551.13 | F94: =IF(Gate_actif=1,Gate*F89+F90,F93) -> 982005.71 | G94: =IF(Gate_actif=1,Gate*G89+G90,G93) -> 1297354.2 | H94: =IF(Gate_actif=1,Gate*H89+H90,H93) -> 1462218.3 | I94: =IF(Gate_actif=1,Gate*I89+I90,I93) -> 1636051.6 | J94: =IF(Gate_actif=1,Gate*J89+J90,J93) -> 1829605.7 | K94: Gate × AN + souscriptions versées ; sans limite si le gate est levé
B95: Suspension des rachats active (1/0) | C95: =0 -> 0 | D95: =IF(OR(C95=1,AND(Suspension_auto=1,C99>=Reports_max)),1,0) -> 0 | E95: =IF(OR(D95=1,AND(Suspension_auto=1,D99>=Reports_max)),1,0) -> 0 | F95: =IF(OR(E95=1,AND(Suspension_auto=1,E99>=Reports_max)),1,0) -> 0 | G95: =IF(OR(F95=1,AND(Suspension_auto=1,F99>=Reports_max)),1,0) -> 0 | H95: =IF(OR(G95=1,AND(Suspension_auto=1,G99>=Reports_max)),1,0) -> 0 | I95: =IF(OR(H95=1,AND(Suspension_auto=1,H99>=Reports_max)),1,0) -> 0 | J95: =IF(OR(I95=1,AND(Suspension_auto=1,I99>=Reports_max)),1,0) -> 0 | K95: Déclenchée après le nombre maximal de reports consécutifs (Paramètres E)
B96: Rachats exécutés | C96: =IF(C95=1,0,MIN(C93,C94)) -> 600000 | D96: =IF(D95=1,0,MIN(D93,D94)) -> 566153.49 | E96: =IF(E95=1,0,MIN(E93,E94)) -> 374775.56 | F96: =IF(F95=1,0,MIN(F93,F94)) -> 235681.37 | G96: =IF(G95=1,0,MIN(G93,G94)) -> 172980.57 | H96: =IF(H95=1,0,MIN(H93,H94)) -> 194962.44 | I96: =IF(I95=1,0,MIN(I93,I94)) -> 218140.21 | J96: =IF(J95=1,0,MIN(J93,J94)) -> 243947.43 | K96: Zéro en suspension
B97: Demandes reportées à la date suivante | C97: =C93-C96 -> 0 | D97: =D93-D96 -> 0 | E97: =E93-E96 -> 0 | F97: =F93-F96 -> 0 | G97: =G93-G96 -> 0 | H97: =H93-H96 -> 0 | I97: =I93-I96 -> 0 | J97: =J93-J96 -> 0
B98: Date plafonnée ou suspendue (1/0) | C98: =IF(C97>1,1,0) -> 0 | D98: =IF(D97>1,1,0) -> 0 | E98: =IF(E97>1,1,0) -> 0 | F98: =IF(F97>1,1,0) -> 0 | G98: =IF(G97>1,1,0) -> 0 | H98: =IF(H97>1,1,0) -> 0 | I98: =IF(I97>1,1,0) -> 0 | J98: =IF(J97>1,1,0) -> 0
B99: Dates plafonnées consécutives | C99: =C98 -> 0 | D99: =IF(D98=1,C99+1,0) -> 0 | E99: =IF(E98=1,D99+1,0) -> 0 | F99: =IF(F98=1,E99+1,0) -> 0 | G99: =IF(G98=1,F99+1,0) -> 0 | H99: =IF(H98=1,G99+1,0) -> 0 | I99: =IF(I98=1,H99+1,0) -> 0 | J99: =IF(J98=1,I99+1,0) -> 0
B100: File d'attente en % de l'AN de début | C100: =C97/C89 -> 0 | D100: =D97/D89 -> 0 | E100: =E97/E89 -> 0 | F100: =F97/F89 -> 0 | G100: =G97/G89 -> 0 | H100: =H97/H89 -> 0 | I100: =I97/I89 -> 0 | J100: =J97/J89 -> 0
B102: MAPIF II - valeur de début | C102: =Paramètres!$D$68*AN_depart -> 2800000 | D102: =C134 -> 2788212.7 | E102: =D134 -> 3064502.9 | F102: =E134 -> 3429616.6 | G102: =F134 -> 3824277.8 | H102: =G134 -> 4195909.2 | I102: =H134 -> 4553255.8 | J102: =I134 -> 4724002.9
B103: MSIG 3 - valeur de début | C103: =Paramètres!$D$69*AN_depart -> 0 | D103: =C135 -> 0 | E103: =D135 -> 0 | F103: =E135 -> 0 | G103: =F135 -> 0 | H103: =G135 -> 0 | I103: =H135 -> 0 | J103: =I135 -> 0
B104: PG NGI - valeur de début | C104: =Paramètres!$D$70*AN_depart -> 1960000 | D104: =C136 -> 2015096 | E104: =D136 -> 1994420.7 | F104: =E136 -> 2034162 | G104: =F136 -> 2136549.6 | H104: =G136 -> 2253802.2 | I104: =H136 -> 2512090.5 | J104: =I136 -> 3007163.2
B105: Ares AGI - valeur de début | C105: =Paramètres!$D$71*AN_depart -> 1960000 | D105: =C137 -> 1908790.4 | E105: =D137 -> 1845804.6 | F105: =E137 -> 1847045.2 | G105: =F137 -> 1902596.4 | H105: =G137 -> 1961815.2 | I105: =H137 -> 2157188.8 | J105: =I137 -> 2581473.9
B106: Fonds HY UCITS - valeur de début | C106: =Paramètres!$D$72*AN_depart -> 880000 | D106: =C138 -> 756613.98 | E106: =D138 -> 363977.45 | F106: =E138 -> 325086.74 | G106: =F138 -> 375126.18 | H106: =G138 -> 869547.97 | I106: =H138 -> 1158076.9 | J106: =I138 -> 1295752.9
B107: Trésorerie de début | C107: =W_cash*AN_depart -> 400000 | D107: =C132 -> 80000 | E107: =D132 -> 226805.67 | F107: =E132 -> 220135.15 | G107: =F132 -> 410478.39 | H107: =G132 -> 467047.53 | I107: =H132 -> 526398.6 | J107: =I132 -> 588978.58
B108: Non-appelé de début (fonds fermés) | C108: =NA_total -> 1200000 | D108: =C139 -> 1000000 | E108: =D139 -> 800000 | F108: =E139 -> 600000 | G108: =F139 -> 400000 | H108: =G139 -> 200000 | I108: =H139 -> 0 | J108: =I139 -> 0 | K108: Engagements restant à appeler
B110: Appels de fonds des fonds fermés | C110: =MIN(C108,NA_total*Appels_base*Paramètres!$C$144) -> 200000 | D110: =MIN(D108,NA_total*Appels_base*Paramètres!$D$144) -> 200000 | E110: =MIN(E108,NA_total*Appels_base*Paramètres!$E$144) -> 200000 | F110: =MIN(F108,NA_total*Appels_base*Paramètres!$F$144) -> 200000 | G110: =MIN(G108,NA_total*Appels_base*Paramètres!$G$144) -> 200000 | H110: =MIN(H108,NA_total*Appels_base*Paramètres!$H$144) -> 200000 | I110: =MIN(I108,NA_total*Appels_base*Paramètres!$I$144) -> 0 | J110: =MIN(J108,NA_total*Appels_base*Paramètres!$J$144) -> 0 | K110: Rythme normal × multiplicateur ; MAPIF II 60 %, MSIG 3 40 % du non-appelé
B111: Distributions des fonds fermés | C111: =(C102*Paramètres!$D$79+C103*Paramètres!$D$80)/2*Paramètres!$C$139 -> 58800 | D111: =(D102*Paramètres!$D$79+D103*Paramètres!$D$80)/2*Paramètres!$D$139 -> 50187.829 | E111: =(E102*Paramètres!$D$79+E103*Paramètres!$D$80)/2*Paramètres!$E$139 -> 64354.561 | F111: =(F102*Paramètres!$D$79+F103*Paramètres!$D$80)/2*Paramètres!$F$139 -> 87455.223 | G111: =(G102*Paramètres!$D$79+G103*Paramètres!$D$80)/2*Paramètres!$G$139 -> 114728.33 | H111: =(H102*Paramètres!$D$79+H103*Paramètres!$D$80)/2*Paramètres!$H$139 -> 125877.28 | I111: =(I102*Paramètres!$D$79+I103*Paramètres!$D$80)/2*Paramètres!$I$139 -> 136597.67 | J111: =(J102*Paramètres!$D$79+J103*Paramètres!$D$80)/2*Paramètres!$J$139 -> 141720.09 | K111: Valeur × taux annuel / 2 × multiplicateur
...

Sheet LST Reverse
B2: LST - TESTS INVERSÉS : TAUX DE RACHAT PERSISTANT, AVEC ET SANS PLAFONNEMENT
B3: Moteur compact en % de l'actif net de départ (actif net supposé constant, effet marché neutralisé) : un même taux de rachat demandé à chaque date, collecte nulle, flux de ressources du profil choisi dans l'onglet Paramètres (par défaut le régime normal, pour isoler l'effet des rachats ; 3 pour cumuler avec les flux S3). Cascade identique au moteur principal : poche liquide, rachats evergreen pour reconstituer la poche d'exécution, cession secondaire décotée au-delà. Avec plafonnement : suspension après le nombre maximal de reports. L'écart entre les deux points de rupture mesure la valeur du plafonnement.
B5: A. RESSOURCES PAR DATE EN % DE L'ACTIF NET (profil de flux choisi, hors rachats et hors collecte)
B6: Flux | C6: Date 1 | D6: Date 2 | E6: Date 3 | F6: Date 4 | G6: Date 5 | H6: Date 6 | I6: Date 7 | J6: Date 8 | O6: Source
B7: Capacité de rachat des fonds evergreen | C7: =(Paramètres!$D$70*Paramètres!$F$70+Paramètres!$D$71*Paramètres!$F$71)*2*(1-CHOOSE(Reverse_flux,Paramètres!$C$148,Paramètres!$C$149,Paramètres!$C$150,Paramètres!$C$151)) -> 0.0343 | D7: =(Paramètres!$D$70*Paramètres!$F$70+Paramètres!$D$71*Paramètres!$F$71)*2*(1-CHOOSE(Reverse_flux,Paramètres!$D$148,Paramètres!$D$149,Paramètres!$D$150,Paramètres!$D$151)) -> 0.0343 | E7: =(Paramètres!$D$70*Paramètres!$F$70+Paramètres!$D$71*Paramètres!$F$71)*2*(1-CHOOSE(Reverse_flux,Paramètres!$E$148,Paramètres!$E$149,Paramètres!$E$150,Paramètres!$E$151)) -> 0.0343 | F7: =(Paramètres!$D$70*Paramètres!$F$70+Paramètres!$D$71*Paramètres!$F$71)*2*(1-CHOOSE(Reverse_flux,Paramètres!$F$148,Paramètres!$F$149,Paramètres!$F$150,Paramètres!$F$151)) -> 0.0343 | G7: =(Paramètres!$D$70*Paramètres!$F$70+Paramètres!$D$71*Paramètres!$F$71)*2*(1-CHOOSE(Reverse_flux,Paramètres!$G$148,Paramètres!$G$149,Paramètres!$G$150,Paramètres!$G$151)) -> 0.0343 | H7: =(Paramètres!$D$70*Paramètres!$F$70+Paramètres!$D$71*Paramètres!$F$71)*2*(1-CHOOSE(Reverse_flux,Paramètres!$H$148,Paramètres!$H$149,Paramètres!$H$150,Paramètres!$H$151)) -> 0.0343 | I7: =(Paramètres!$D$70*Paramètres!$F$70+Paramètres!$D$71*Paramètres!$F$71)*2*(1-CHOOSE(Reverse_flux,Paramètres!$I$148,Paramètres!$I$149,Paramètres!$I$150,Paramètres!$I$151)) -> 0.0343 | J7: =(Paramètres!$D$70*Paramètres!$F$70+Paramètres!$D$71*Paramètres!$F$71)*2*(1-CHOOSE(Reverse_flux,Paramètres!$J$148,Paramètres!$J$149,Paramètres!$J$150,Paramètres!$J$151)) -> 0.0343 | O7: Gates trimestriels × 2, part des pairs déduite
B8: Distributions des fonds cibles | C8: =((Paramètres!$D$68*Paramètres!$D$79+Paramètres!$D$69*Paramètres!$D$80)+(Paramètres!$D$70*Paramètres!$D$81+Paramètres!$D$71*Paramètres!$D$82))/2*CHOOSE(Reverse_flux,Paramètres!$C$138,Paramètres!$C$139,Paramètres!$C$140,Paramètres!$C$141) -> 0.019075 | D8: =((Paramètres!$D$68*Paramètres!$D$79+Paramètres!$D$69*Paramètres!$D$80)+(Paramètres!$D$70*Paramètres!$D$81+Paramètres!$D$71*Paramètres!$D$82))/2*CHOOSE(Reverse_flux,Paramètres!$D$138,Paramètres!$D$139,Paramètres!$D$140,Paramètres!$D$141) -> 0.019075 | E8: =((Paramètres!$D$68*Paramètres!$D$79+Paramètres!$D$69*Paramètres!$D$80)+(Paramètres!$D$70*Paramètres!$D$81+Paramètres!$D$71*Paramètres!$D$82))/2*CHOOSE(Reverse_flux,Paramètres!$E$138,Paramètres!$E$139,Paramètres!$E$140,Paramètres!$E$141) -> 0.019075 | F8: =((Paramètres!$D$68*Paramètres!$D$79+Paramètres!$D$69*Paramètres!$D$80)+(Paramètres!$D$70*Paramètres!$D$81+Paramètres!$D$71*Paramètres!$D$82))/2*CHOOSE(Reverse_flux,Paramètres!$F$138,Paramètres!$F$139,Paramètres!$F$140,Paramètres!$F$141) -> 0.019075 | G8: =((Paramètres!$D$68*Paramètres!$D$79+Paramètres!$D$69*Paramètres!$D$80)+(Paramètres!$D$70*Paramètres!$D$81+Paramètres!$D$71*Paramètres!$D$82))/2*CHOOSE(Reverse_flux,Paramètres!$G$138,Paramètres!$G$139,Paramètres!$G$140,Paramètres!$G$141) -> 0.019075 | H8: =((Paramètres!$D$68*Paramètres!$D$79+Paramètres!$D$69*Paramètres!$D$80)+(Paramètres!$D$70*Paramètres!$D$81+Paramètres!$D$71*Paramètres!$D$82))/2*CHOOSE(Reverse_flux,Paramètres!$H$138,Paramètres!$H$139,Paramètres!$H$140,Paramètres!$H$141) -> 0.019075 | I8: =((Paramètres!$D$68*Paramètres!$D$79+Paramètres!$D$69*Paramètres!$D$80)+(Paramètres!$D$70*Paramètres!$D$81+Paramètres!$D$71*Paramètres!$D$82))/2*CHOOSE(Reverse_flux,Paramètres!$I$138,Paramètres!$I$139,Paramètres!$I$140,Paramètres!$I$141) -> 0.019075 | J8: =((Paramètres!$D$68*Paramètres!$D$79+Paramètres!$D$69*Paramètres!$D$80)+(Paramètres!$D$70*Paramètres!$D$81+Paramètres!$D$71*Paramètres!$D$82))/2*CHOOSE(Reverse_flux,Paramètres!$J$138,Paramètres!$J$139,Paramètres!$J$140,Paramètres!$J$141) -> 0.019075 | O8: Multiplicateur S3
B9: Appels des fonds fermés | C9: =MIN(NA_total/AN_depart,NA_total/AN_depart*Appels_base*CHOOSE(Reverse_flux,Paramètres!$C$143,Paramètres!$C$144,Paramètres!$C$145,Paramètres!$C$146)) -> 0.025 | D9: =MIN(MAX(0,NA_total/AN_depart-SUM($C$9:C$9)),NA_total/AN_depart*Appels_base*CHOOSE(Reverse_flux,Paramètres!$D$143,Paramètres!$D$144,Paramètres!$D$145,Paramètres!$D$146)) -> 0.025 | E9: =MIN(MAX(0,NA_total/AN_depart-SUM($C$9:D$9)),NA_total/AN_depart*Appels_base*CHOOSE(Reverse_flux,Paramètres!$E$143,Paramètres!$E$144,Paramètres!$E$145,Paramètres!$E$146)) -> 0.025 | F9: =MIN(MAX(0,NA_total/AN_depart-SUM($C$9:E$9)),NA_total/AN_depart*Appels_base*CHOOSE(Reverse_flux,Paramètres!$F$143,Paramètres!$F$144,Paramètres!$F$145,Paramètres!$F$146)) -> 0.025 | G9: =MIN(MAX(0,NA_total/AN_depart-SUM($C$9:F$9)),NA_total/AN_depart*Appels_base*CHOOSE(Reverse_flux,Paramètres!$G$143,Paramètres!$G$144,Paramètres!$G$145,Paramètres!$G$146)) -> 0.025 | H9: =MIN(MAX(0,NA_total/AN_depart-SUM($C$9:G$9)),NA_total/AN_depart*Appels_base*CHOOSE(Reverse_flux,Paramètres!$H$143,Paramètres!$H$144,Paramètres!$H$145,Paramètres!$H$146)) -> 0.025 | I9: =MIN(MAX(0,NA_total/AN_depart-SUM($C$9:H$9)),NA_total/AN_depart*Appels_base*CHOOSE(Reverse_flux,Paramètres!$I$143,Paramètres!$I$144,Paramètres!$I$145,Paramètres!$I$146)) -> 0 | J9: =MIN(MAX(0,NA_total/AN_depart-SUM($C$9:I$9)),NA_total/AN_depart*Appels_base*CHOOSE(Reverse_flux,Paramètres!$J$143,Paramètres!$J$144,Paramètres!$J$145,Paramètres!$J$146)) -> 0 | O9: Jusqu'à épuisement du non-appelé
B10: Frais du Fonds | C10: =Frais_an/2 -> 0.0162995 | D10: =Frais_an/2 -> 0.0162995 | E10: =Frais_an/2 -> 0.0162995 | F10: =Frais_an/2 -> 0.0162995 | G10: =Frais_an/2 -> 0.0162995 | H10: =Frais_an/2 -> 0.0162995 | I10: =Frais_an/2 -> 0.0162995 | J10: =Frais_an/2 -> 0.0162995
B11: Ressources nettes hors rachats | C11: =C8-C9-C10 -> -0.0222245 | D11: =D8-D9-D10 -> -0.0222245 | E11: =E8-E9-E10 -> -0.0222245 | F11: =F8-F9-F10 -> -0.0222245 | G11: =G8-G9-G10 -> -0.0222245 | H11: =H8-H9-H10 -> -0.0222245 | I11: =I8-I9-I10 -> 0.0027755 | J11: =J8-J9-J10 -> 0.0027755 | O11: Négatif : les appels dépassent les distributions
B13: B. AVEC PLAFONNEMENT (gate 5 % par date, reports automatiques, suspension après le nombre maximal de reports)
B14: Taux par date et variable | C14: Date 1 | D14: Date 2 | E14: Date 3 | F14: Date 4 | G14: Date 5 | H14: Date 6 | I14: Date 7 | J14: Date 8 | L14: File à la date 8 | M14: Poche min | N14: Cessions à la date 4 | O14: Cessions à la date 8 | P14: Verdict
B15: 0.025 | L15: =J18 -> 0 | M15: =MIN(C22:J22) -> 0.048153 | N15: =F23 -> 0 | O15: =J23 -> 0 | P15: =IF(AND($B$15>Gate+0.0001,Reports_max<8,Suspension_auto=1),"Rouge : suspension à la date "&(Reports_max+1),IF(N15>0.0001,"Rouge : cessions décotées",IF(M15<S_poche_rouge,"Rouge : poche sous 5 %",IF(OR(M15<S_poche_orange,$B$15>Gate+0.0001),"Orange","Vert")))) -> Rouge : poche sous 5 %
B16: Demande totale (nouvelle + reportée) | C16: =$B$15 -> 0.025 | D16: =$B$15+C18 -> 0.025 | E16: =$B$15+D18 -> 0.025 | F16: =$B$15+E18 -> 0.025 | G16: =$B$15+F18 -> 0.025 | H16: =$B$15+G18 -> 0.025 | I16: =$B$15+H18 -> 0.025 | J16: =$B$15+I18 -> 0.025
B17: Exécuté | C17: =IF(AND($B$15>Gate+0.0001,1>Reports_max,Suspension_auto=1),0,MIN(C16,Gate)) -> 0.025 | D17: =IF(AND($B$15>Gate+0.0001,2>Reports_max,Suspension_auto=1),0,MIN(D16,Gate)) -> 0.025 | E17: =IF(AND($B$15>Gate+0.0001,3>Reports_max,Suspension_auto=1),0,MIN(E16,Gate)) -> 0.025 | F17: =IF(AND($B$15>Gate+0.0001,4>Reports_max,Suspension_auto=1),0,MIN(F16,Gate)) -> 0.025 | G17: =IF(AND($B$15>Gate+0.0001,5>Reports_max,Suspension_auto=1),0,MIN(G16,Gate)) -> 0.025 | H17: =IF(AND($B$15>Gate+0.0001,6>Reports_max,Suspension_auto=1),0,MIN(H16,Gate)) -> 0.025 | I17: =IF(AND($B$15>Gate+0.0001,7>Reports_max,Suspension_auto=1),0,MIN(I16,Gate)) -> 0.025 | J17: =IF(AND($B$15>Gate+0.0001,8>Reports_max,Suspension_auto=1),0,MIN(J16,Gate)) -> 0.025
B18: File reportée | C18: =C16-C17 -> 0 | D18: =D16-D17 -> 0 | E18: =E16-E17 -> 0 | F18: =F16-F17 -> 0 | G18: =G16-G17 -> 0 | H18: =H16-H17 -> 0 | I18: =I16-I17 -> 0 | J18: =J16-J17 -> 0
B19: Poche liquide avant appel aux fonds cibles | C19: =W_cash+W_HY-C17+C11 -> 0.1127755 | D19: =C22-D17+D11 -> 0.065551 | E19: =D22-E17+E11 -> 0.0526265 | F19: =E22-F17+F11 -> 0.039702 | G19: =F22-G17+G11 -> 0.0267775 | H19: =G22-H17+H11 -> 0.013853 | I19: =H22-I17+I11 -> 0.0259285 | J19: =I22-J17+J11 -> 0.038004
B20: Rachats obtenus des fonds evergreen | C20: =MIN(C7,MAX(0,Poche_min_exec-C19)) -> 0 | D20: =MIN(D7,MAX(0,Poche_min_exec-D19)) -> 0.0343 | E20: =MIN(E7,MAX(0,Poche_min_exec-E19)) -> 0.0343 | F20: =MIN(F7,MAX(0,Poche_min_exec-F19)) -> 0.0343 | G20: =MIN(G7,MAX(0,Poche_min_exec-G19)) -> 0.0343 | H20: =MIN(H7,MAX(0,Poche_min_exec-H19)) -> 0.0343 | I20: =MIN(I7,MAX(0,Poche_min_exec-I19)) -> 0.0343 | J20: =MIN(J7,MAX(0,Poche_min_exec-J19)) -> 0.0343
B21: Cession secondaire (valeur cédée) | C21: =IF(Cession_autorisee=1,MAX(0,Cash_min-(C19+C20))/(1-CHOOSE(Reverse_flux,Paramètres!$J$79,Paramètres!$J$79,Paramètres!$K$79,Paramètres!$L$79)),0) -> 0 | D21: =IF(Cession_autorisee=1,MAX(0,Cash_min-(D19+D20))/(1-CHOOSE(Reverse_flux,Paramètres!$J$79,Paramètres!$J$79,Paramètres!$K$79,Paramètres!$L$79)),0) -> 0 | E21: =IF(Cession_autorisee=1,MAX(0,Cash_min-(E19+E20))/(1-CHOOSE(Reverse_flux,Paramètres!$J$79,Paramètres!$J$79,Paramètres!$K$79,Paramètres!$L$79)),0) -> 0 | F21: =IF(Cession_autorisee=1,MAX(0,Cash_min-(F19+F20))/(1-CHOOSE(Reverse_flux,Paramètres!$J$79,Paramètres!$J$79,Paramètres!$K$79,Paramètres!$L$79)),0) -> 0 | G21: =IF(Cession_autorisee=1,MAX(0,Cash_min-(G19+G20))/(1-CHOOSE(Reverse_flux,Paramètres!$J$79,Paramètres!$J$79,Paramètres!$K$79,Paramètres!$L$79)),0) -> 0 | H21: =IF(Cession_autorisee=1,MAX(0,Cash_min-(H19+H20))/(1-CHOOSE(Reverse_flux,Paramètres!$J$79,Paramètres!$J$79,Paramètres!$K$79,Paramètres!$L$79)),0) -> 0 | I21: =IF(Cession_autorisee=1,MAX(0,Cash_min-(I19+I20))/(1-CHOOSE(Reverse_flux,Paramètres!$J$79,Paramètres!$J$79,Paramètres!$K$79,Paramètres!$L$79)),0) -> 0 | J21: =IF(Cession_autorisee=1,MAX(0,Cash_min-(J19+J20))/(1-CHOOSE(Reverse_flux,Paramètres!$J$79,Paramètres!$J$79,Paramètres!$K$79,Paramètres!$L$79)),0) -> 0
B22: Poche liquide de fin | C22: =C19+C20+C21*(1-CHOOSE(Reverse_flux,Paramètres!$J$79,Paramètres!$J$79,Paramètres!$K$79,Paramètres!$L$79)) -> 0.1127755 | D22: =D19+D20+D21*(1-CHOOSE(Reverse_flux,Paramètres!$J$79,Paramètres!$J$79,Paramètres!$K$79,Paramètres!$L$79)) -> 0.099851 | E22: =E19+E20+E21*(1-CHOOSE(Reverse_flux,Paramètres!$J$79,Paramètres!$J$79,Paramètres!$K$79,Paramètres!$L$79)) -> 0.0869265 | F22: =F19+F20+F21*(1-CHOOSE(Reverse_flux,Paramètres!$J$79,Paramètres!$J$79,Paramètres!$K$79,Paramètres!$L$79)) -> 0.074002 | G22: =G19+G20+G21*(1-CHOOSE(Reverse_flux,Paramètres!$J$79,Paramètres!$J$79,Paramètres!$K$79,Paramètres!$L$79)) -> 0.0610775 | H22: =H19+H20+H21*(1-CHOOSE(Reverse_flux,Paramètres!$J$79,Paramètres!$J$79,Paramètres!$K$79,Paramètres!$L$79)) -> 0.048153 | I22: =I19+I20+I21*(1-CHOOSE(Reverse_flux,Paramètres!$J$79,Paramètres!$J$79,Paramètres!$K$79,Paramètres!$L$79)) -> 0.0602285 | J22: =J19+J20+J21*(1-CHOOSE(Reverse_flux,Paramètres!$J$79,Paramètres!$J$79,Paramètres!$K$79,Paramètres!$L$79)) -> 0.072304
B23: Cessions cumulées | C23: =SUM($C$21:C21) -> 0 | D23: =SUM($C$21:D21) -> 0 | E23: =SUM($C$21:E21) -> 0 | F23: =SUM($C$21:F21) -> 0 | G23: =SUM($C$21:G21) -> 0 | H23: =SUM($C$21:H21) -> 0 | I23: =SUM($C$21:I21) -> 0 | J23: =SUM($C$21:J21) -> 0
B24: 0.05 | L24: =J27 -> 0 | M24: =MIN(C31:J31) -> 0.01 | N24: =F32 -> 0.027968824 | O24: =J32 -> 0.14761353 | P24: =IF(AND($B$24>Gate+0.0001,Reports_max<8,Suspension_auto=1),"Rouge : suspension à la date "&(Reports_max+1),IF(N24>0.0001,"Rouge : cessions décotées",IF(M24<S_poche_rouge,"Rouge : poche sous 5 %",IF(OR(M24<S_poche_orange,$B$24>Gate+0.0001),"Orange","Vert")))) -> Rouge : cessions décotées
B25: Demande totale (nouvelle + reportée) | C25: =$B$24 -> 0.05 | D25: =$B$24+C27 -> 0.05 | E25: =$B$24+D27 -> 0.05 | F25: =$B$24+E27 -> 0.05 | G25: =$B$24+F27 -> 0.05 | H25: =$B$24+G27 -> 0.05 | I25: =$B$24+H27 -> 0.05 | J25: =$B$24+I27 -> 0.05
B26: Exécuté | C26: =IF(AND($B$24>Gate+0.0001,1>Reports_max,Suspension_auto=1),0,MIN(C25,Gate)) -> 0.05 | D26: =IF(AND($B$24>Gate+0.0001,2>Reports_max,Suspension_auto=1),0,MIN(D25,Gate)) -> 0.05 | E26: =IF(AND($B$24>Gate+0.0001,3>Reports_max,Suspension_auto=1),0,MIN(E25,Gate)) -> 0.05 | F26: =IF(AND($B$24>Gate+0.0001,4>Reports_max,Suspension_auto=1),0,MIN(F25,Gate)) -> 0.05 | G26: =IF(AND($B$24>Gate+0.0001,5>Reports_max,Suspension_auto=1),0,MIN(G25,Gate)) -> 0.05 | H26: =IF(AND($B$24>Gate+0.0001,6>Reports_max,Suspension_auto=1),0,MIN(H25,Gate)) -> 0.05 | I26: =IF(AND($B$24>Gate+0.0001,7>Reports_max,Suspension_auto=1),0,MIN(I25,Gate)) -> 0.05 | J26: =IF(AND($B$24>Gate+0.0001,8>Reports_max,Suspension_auto=1),0,MIN(J25,Gate)) -> 0.05
B27: File reportée | C27: =C25-C26 -> 0 | D27: =D25-D26 -> 0 | E27: =E25-E26 -> 0 | F27: =F25-F26 -> 0 | G27: =G25-G26 -> 0 | H27: =H25-H26 -> 0 | I27: =I25-I26 -> 0 | J27: =J25-J26 -> 0
B28: Poche liquide avant appel aux fonds cibles | C28: =W_cash+W_HY-C26+C11 -> 0.0877755 | D28: =C31-D26+D11 -> 0.0277755 | E28: =D31-E26+E11 -> -0.010149 | F28: =E31-F26+F11 -> -0.0480735 | G28: =F31-G26+G11 -> -0.0622245 | H28: =G31-H26+H11 -> -0.0622245 | I28: =H31-I26+I11 -> -0.0372245 | J28: =I31-J26+J11 -> -0.0372245
B29: Rachats obtenus des fonds evergreen | C29: =MIN(C7,MAX(0,Poche_min_exec-C28)) -> 0.0122245 | D29: =MIN(D7,MAX(0,Poche_min_exec-D28)) -> 0.0343 | E29: =MIN(E7,MAX(0,Poche_min_exec-E28)) -> 0.0343 | F29: =MIN(F7,MAX(0,Poche_min_exec-F28)) -> 0.0343 | G29: =MIN(G7,MAX(0,Poche_min_exec-G28)) -> 0.0343 | H29: =MIN(H7,MAX(0,Poche_min_exec-H28)) -> 0.0343 | I29: =MIN(I7,MAX(0,Poche_min_exec-I28)) -> 0.0343 | J29: =MIN(J7,MAX(0,Poche_min_exec-J28)) -> 0.0343
B30: Cession secondaire (valeur cédée) | C30: =IF(Cession_autorisee=1,MAX(0,Cash_min-(C28+C29))/(1-CHOOSE(Reverse_flux,Paramètres!$J$79,Paramètres!$J$79,Paramètres!$K$79,Paramètres!$L$79)),0) -> 0 | D30: =IF(Cession_autorisee=1,MAX(0,Cash_min-(D28+D29))/(1-CHOOSE(Reverse_flux,Paramètres!$J$79,Paramètres!$J$79,Paramètres!$K$79,Paramètres!$L$79)),0) -> 0 | E30: =IF(Cession_autorisee=1,MAX(0,Cash_min-(E28+E29))/(1-CHOOSE(Reverse_flux,Paramètres!$J$79,Paramètres!$J$79,Paramètres!$K$79,Paramètres!$L$79)),0) -> 0 | F30: =IF(Cession_autorisee=1,MAX(0,Cash_min-(F28+F29))/(1-CHOOSE(Reverse_flux,Paramètres!$J$79,Paramètres!$J$79,Paramètres!$K$79,Paramètres!$L$79)),0) -> 0.027968824 | G30: =IF(Cession_autorisee=1,MAX(0,Cash_min-(G28+G29))/(1-CHOOSE(Reverse_flux,Paramètres!$J$79,Paramètres!$J$79,Paramètres!$K$79,Paramètres!$L$79)),0) -> 0.044617059 | H30: =IF(Cession_autorisee=1,MAX(0,Cash_min-(H28+H29))/(1-CHOOSE(Reverse_flux,Paramètres!$J$79,Paramètres!$J$79,Paramètres!$K$79,Paramètres!$L$79)),0) -> 0.044617059 | I30: =IF(Cession_autorisee=1,MAX(0,Cash_min-(I28+I29))/(1-CHOOSE(Reverse_flux,Paramètres!$J$79,Paramètres!$J$79,Paramètres!$K$79,Paramètres!$L$79)),0) -> 0.015205294 | J30: =IF(Cession_autorisee=1,MAX(0,Cash_min-(J28+J29))/(1-CHOOSE(Reverse_flux,Paramètres!$J$79,Paramètres!$J$79,Paramètres!$K$79,Paramètres!$L$79)),0) -> 0.015205294
B31: Poche liquide de fin | C31: =C28+C29+C30*(1-CHOOSE(Reverse_flux,Paramètres!$J$79,Paramètres!$J$79,Paramètres!$K$79,Paramètres!$L$79)) -> 0.1 | D31: =D28+D29+D30*(1-CHOOSE(Reverse_flux,Paramètres!$J$79,Paramètres!$J$79,Paramètres!$K$79,Paramètres!$L$79)) -> 0.0620755 | E31: =E28+E29+E30*(1-CHOOSE(Reverse_flux,Paramètres!$J$79,Paramètres!$J$79,Paramètres!$K$79,Paramètres!$L$79)) -> 0.024151 | F31: =F28+F29+F30*(1-CHOOSE(Reverse_flux,Paramètres!$J$79,Paramètres!$J$79,Paramètres!$K$79,Paramètres!$L$79)) -> 0.01 | G31: =G28+G29+G30*(1-CHOOSE(Reverse_flux,Paramètres!$J$79,Paramètres!$J$79,Paramètres!$K$79,Paramètres!$L$79)) -> 0.01 | H31: =H28+H29+H30*(1-CHOOSE(Reverse_flux,Paramètres!$J$79,Paramètres!$J$79,Paramètres!$K$79,Paramètres!$L$79)) -> 0.01 | I31: =I28+I29+I30*(1-CHOOSE(Reverse_flux,Paramètres!$J$79,Paramètres!$J$79,Paramètres!$K$79,Paramètres!$L$79)) -> 0.01 | J31: =J28+J29+J30*(1-CHOOSE(Reverse_flux,Paramètres!$J$79,Paramètres!$J$79,Paramètres!$K$79,Paramètres!$L$79)) -> 0.01
B32: Cessions cumulées | C32: =SUM($C$30:C30) -> 0 | D32: =SUM($C$30:D30) -> 0 | E32: =SUM($C$30:E30) -> 0 | F32: =SUM($C$30:F30) -> 0.027968824 | G32: =SUM($C$30:G30) -> 0.072585882 | H32: =SUM($C$30:H30) -> 0.11720294 | I32: =SUM($C$30:I30) -> 0.13240824 | J32: =SUM($C$30:J30) -> 0.14761353
B33: 0.075 | L33: =J36 -> 0.4 | M33: =MIN(C40:J40) -> 0.01 | N33: =F41 -> 0.027968824 | O33: =J41 -> 0.027968824 | P33: =IF(AND($B$33>Gate+0.0001,Reports_max<8,Suspension_auto=1),"Rouge : suspension à la date "&(Reports_max+1),IF(N33>0.0001,"Rouge : cessions décotées",IF(M33<S_poche_rouge,"Rouge : poche sous 5 %",IF(OR(M33<S_poche_orange,$B$33>Gate+0.0001),"Orange","Vert")))) -> Rouge : suspension à la date 5
B34: Demande totale (nouvelle + reportée) | C34: =$B$33 -> 0.075 | D34: =$B$33+C36 -> 0.1 | E34: =$B$33+D36 -> 0.125 | F34: =$B$33+E36 -> 0.15 | G34: =$B$33+F36 -> 0.175 | H34: =$B$33+G36 -> 0.25 | I34: =$B$33+H36 -> 0.325 | J34: =$B$33+I36 -> 0.4
B35: Exécuté | C35: =IF(AND($B$33>Gate+0.0001,1>Reports_max,Suspension_auto=1),0,MIN(C34,Gate)) -> 0.05 | D35: =IF(AND($B$33>Gate+0.0001,2>Reports_max,Suspension_auto=1),0,MIN(D34,Gate)) -> 0.05 | E35: =IF(AND($B$33>Gate+0.0001,3>Reports_max,Suspension_auto=1),0,MIN(E34,Gate)) -> 0.05 | F35: =IF(AND($B$33>Gate+0.0001,4>Reports_max,Suspension_auto=1),0,MIN(F34,Gate)) -> 0.05 | G35: =IF(AND($B$33>Gate+0.0001,5>Reports_max,Suspension_auto=1),0,MIN(G34,Gate)) -> 0 | H35: =IF(AND($B$33>Gate+0.0001,6>Reports_max,Suspension_auto=1),0,MIN(H34,Gate)) -> 0 | I35: =IF(AND($B$33>Gate+0.0001,7>Reports_max,Suspension_auto=1),0,MIN(I34,Gate)) -> 0 | J35: =IF(AND($B$33>Gate+0.0001,8>Reports_max,Suspension_auto=1),0,MIN(J34,Gate)) -> 0
B36: File reportée | C36: =C34-C35 -> 0.025 | D36: =D34-D35 -> 0.05 | E36: =E34-E35 -> 0.075 | F36: =F34-F35 -> 0.1 | G36: =G34-G35 -> 0.175 | H36: =H34-H35 -> 0.25 | I36: =I34-I35 -> 0.325 | J36: =J34-J35 -> 0.4
B37: Poche liquide avant appel aux fonds cibles | C37: =W_cash+W_HY-C35+C11 -> 0.0877755 | D37: =C40-D35+D11 -> 0.0277755 | E37: =D40-E35+E11 -> -0.010149 | F37: =E40-F35+F11 -> -0.0480735 | G37: =F40-G35+G11 -> -0.0122245 | H37: =G40-H35+H11 -> -0.000149 | I37: =H40-I35+I11 -> 0.0369265 | J37: =I40-J35+J11 -> 0.074002
B38: Rachats obtenus des fonds evergreen | C38: =MIN(C7,MAX(0,Poche_min_exec-C37)) -> 0.0122245 | D38: =MIN(D7,MAX(0,Poche_min_exec-D37)) -> 0.0343 | E38: =MIN(E7,MAX(0,Poche_min_exec-E37)) -> 0.0343 | F38: =MIN(F7,MAX(0,Poche_min_exec-F37)) -> 0.0343 | G38: =MIN(G7,MAX(0,Poche_min_exec-G37)) -> 0.0343 | H38: =MIN(H7,MAX(0,Poche_min_exec-H37)) -> 0.0343 | I38: =MIN(I7,MAX(0,Poche_min_exec-I37)) -> 0.0343 | J38: =MIN(J7,MAX(0,Poche_min_exec-J37)) -> 0.025998
B39: Cession secondaire (valeur cédée) | C39: =IF(Cession_autorisee=1,MAX(0,Cash_min-(C37+C38))/(1-CHOOSE(Reverse_flux,Paramètres!$J$79,Paramètres!$J$79,Paramètres!$K$79,Paramètres!$L$79)),0) -> 0 | D39: =IF(Cession_autorisee=1,MAX(0,Cash_min-(D37+D38))/(1-CHOOSE(Reverse_flux,Paramètres!$J$79,Paramètres!$J$79,Paramètres!$K$79,Paramètres!$L$79)),0) -> 0 | E39: =IF(Cession_autorisee=1,MAX(0,Cash_min-(E37+E38))/(1-CHOOSE(Reverse_flux,Paramètres!$J$79,Paramètres!$J$79,Paramètres!$K$79,Paramètres!$L$79)),0) -> 0 | F39: =IF(Cession_autorisee=1,MAX(0,Cash_min-(F37+F38))/(1-CHOOSE(Reverse_flux,Paramètres!$J$79,Paramètres!$J$79,Paramètres!$K$79,Paramètres!$L$79)),0) -> 0.027968824 | G39: =IF(Cession_autorisee=1,MAX(0,Cash_min-(G37+G38))/(1-CHOOSE(Reverse_flux,Paramètres!$J$79,Paramètres!$J$79,Paramètres!$K$79,Paramètres!$L$79)),0) -> 0 | H39: =IF(Cession_autorisee=1,MAX(0,Cash_min-(H37+H38))/(1-CHOOSE(Reverse_flux,Paramètres!$J$79,Paramètres!$J$79,Paramètres!$K$79,Paramètres!$L$79)),0) -> 0 | I39: =IF(Cession_autorisee=1,MAX(0,Cash_min-(I37+I38))/(1-CHOOSE(Reverse_flux,Paramètres!$J$79,Paramètres!$J$79,Paramètres!$K$79,Paramètres!$L$79)),0) -> 0 | J39: =IF(Cession_autorisee=1,MAX(0,Cash_min-(J37+J38))/(1-CHOOSE(Reverse_flux,Paramètres!$J$79,Paramètres!$J$79,Paramètres!$K$79,Paramètres!$L$79)),0) -> 0
B40: Poche liquide de fin | C40: =C37+C38+C39*(1-CHOOSE(Reverse_flux,Paramètres!$J$79,Paramètres!$J$79,Paramètres!$K$79,Paramètres!$L$79)) -> 0.1 | D40: =D37+D38+D39*(1-CHOOSE(Reverse_flux,Paramètres!$J$79,Paramètres!$J$79,Paramètres!$K$79,Paramètres!$L$79)) -> 0.0620755 | E40: =E37+E38+E39*(1-CHOOSE(Reverse_flux,Paramètres!$J$79,Paramètres!$J$79,Paramètres!$K$79,Paramètres!$L$79)) -> 0.024151 | F40: =F37+F38+F39*(1-CHOOSE(Reverse_flux,Paramètres!$J$79,Paramètres!$J$79,Paramètres!$K$79,Paramètres!$L$79)) -> 0.01 | G40: =G37+G38+G39*(1-CHOOSE(Reverse_flux,Paramètres!$J$79,Paramètres!$J$79,Paramètres!$K$79,Paramètres!$L$79)) -> 0.0220755 | H40: =H37+H38+H39*(1-CHOOSE(Reverse_flux,Paramètres!$J$79,Paramètres!$J$79,Paramètres!$K$79,Paramètres!$L$79)) -> 0.034151 | I40: =I37+I38+I39*(1-CHOOSE(Reverse_flux,Paramètres!$J$79,Paramètres!$J$79,Paramètres!$K$79,Paramètres!$L$79)) -> 0.0712265 | J40: =J37+J38+J39*(1-CHOOSE(Reverse_flux,Paramètres!$J$79,Paramètres!$J$79,Paramètres!$K$79,Paramètres!$L$79)) -> 0.1
B41: Cessions cumulées | C41: =SUM($C$39:C39) -> 0 | D41: =SUM($C$39:D39) -> 0 | E41: =SUM($C$39:E39) -> 0 | F41: =SUM($C$39:F39) -> 0.027968824 | G41: =SUM($C$39:G39) -> 0.027968824 | H41: =SUM($C$39:H39) -> 0.027968824 | I41: =SUM($C$39:I39) -> 0.027968824 | J41: =SUM($C$39:J39) -> 0.027968824
B42: 0.1 | L42: =J45 -> 0.6 | M42: =MIN(C49:J49) -> 0.01 | N42: =F50 -> 0.027968824 | O42: =J50 -> 0.027968824 | P42: =IF(AND($B$42>Gate+0.0001,Reports_max<8,Suspension_auto=1),"Rouge : suspension à la date "&(Reports_max+1),IF(N42>0.0001,"Rouge : cessions décotées",IF(M42<S_poche_rouge,"Rouge : poche sous 5 %",IF(OR(M42<S_poche_orange,$B$42>Gate+0.0001),"Orange","Vert")))) -> Rouge : suspension à la date 5
B43: Demande totale (nouvelle + reportée) | C43: =$B$42 -> 0.1 | D43: =$B$42+C45 -> 0.15 | E43: =$B$42+D45 -> 0.2 | F43: =$B$42+E45 -> 0.25 | G43: =$B$42+F45 -> 0.3 | H43: =$B$42+G45 -> 0.4 | I43: =$B$42+H45 -> 0.5 | J43: =$B$42+I45 -> 0.6
B44: Exécuté | C44: =IF(AND($B$42>Gate+0.0001,1>Reports_max,Suspension_auto=1),0,MIN(C43,Gate)) -> 0.05 | D44: =IF(AND($B$42>Gate+0.0001,2>Reports_max,Suspension_auto=1),0,MIN(D43,Gate)) -> 0.05 | E44: =IF(AND($B$42>Gate+0.0001,3>Reports_max,Suspension_auto=1),0,MIN(E43,Gate)) -> 0.05 | F44: =IF(AND($B$42>Gate+0.0001,4>Reports_max,Suspension_auto=1),0,MIN(F43,Gate)) -> 0.05 | G44: =IF(AND($B$42>Gate+0.0001,5>Reports_max,Suspension_auto=1),0,MIN(G43,Gate)) -> 0 | H44: =IF(AND($B$42>Gate+0.0001,6>Reports_max,Suspension_auto=1),0,MIN(H43,Gate)) -> 0 | I44: =IF(AND($B$42>Gate+0.0001,7>Reports_max,Suspension_auto=1),0,MIN(I43,Gate)) -> 0 | J44: =IF(AND($B$42>Gate+0.0001,8>Reports_max,Suspension_auto=1),0,MIN(J43,Gate)) -> 0
B45: File reportée | C45: =C43-C44 -> 0.05 | D45: =D43-D44 -> 0.1 | E45: =E43-E44 -> 0.15 | F45: =F43-F44 -> 0.2 | G45: =G43-G44 -> 0.3 | H45: =H43-H44 -> 0.4 | I45: =I43-I44 -> 0.5 | J45: =J43-J44 -> 0.6
B46: Poche liquide avant appel aux fonds cibles | C46: =W_cash+W_HY-C44+C11 -> 0.0877755 | D46: =C49-D44+D11 -> 0.0277755 | E46: =D49-E44+E11 -> -0.010149 | F46: =E49-F44+F11 -> -0.0480735 | G46: =F49-G44+G11 -> -0.0122245 | H46: =G49-H44+H11 -> -0.000149 | I46: =H49-I44+I11 -> 0.0369265 | J46: =I49-J44+J11 -> 0.074002
B47: Rachats obtenus des fonds evergreen | C47: =MIN(C7,MAX(0,Poche_min_exec-C46)) -> 0.0122245 | D47: =MIN(D7,MAX(0,Poche_min_exec-D46)) -> 0.0343 | E47: =MIN(E7,MAX(0,Poche_min_exec-E46)) -> 0.0343 | F47: =MIN(F7,MAX(0,Poche_min_exec-F46)) -> 0.0343 | G47: =MIN(G7,MAX(0,Poche_min_exec-G46)) -> 0.0343 | H47: =MIN(H7,MAX(0,Poche_min_exec-H46)) -> 0.0343 | I47: =MIN(I7,MAX(0,Poche_min_exec-I46)) -> 0.0343 | J47: =MIN(J7,MAX(0,Poche_min_exec-J46)) -> 0.025998
B48: Cession secondaire (valeur cédée) | C48: =IF(Cession_autorisee=1,MAX(0,Cash_min-(C46+C47))/(1-CHOOSE(Reverse_flux,Paramètres!$J$79,Paramètres!$J$79,Paramètres!$K$79,Paramètres!$L$79)),0) -> 0 | D48: =IF(Cession_autorisee=1,MAX(0,Cash_min-(D46+D47))/(1-CHOOSE(Reverse_flux,Paramètres!$J$79,Paramètres!$J$79,Paramètres!$K$79,Paramètres!$L$79)),0) -> 0 | E48: =IF(Cession_autorisee=1,MAX(0,Cash_min-(E46+E47))/(1-CHOOSE(Reverse_flux,Paramètres!$J$79,Paramètres!$J$79,Paramètres!$K$79,Paramètres!$L$79)),0) -> 0 | F48: =IF(Cession_autorisee=1,MAX(0,Cash_min-(F46+F47))/(1-CHOOSE(Reverse_flux,Paramètres!$J$79,Paramètres!$J$79,Paramètres!$K$79,Paramètres!$L$79)),0) -> 0.027968824 | G48: =IF(Cession_autorisee=1,MAX(0,Cash_min-(G46+G47))/(1-CHOOSE(Reverse_flux,Paramètres!$J$79,Paramètres!$J$79,Paramètres!$K$79,Paramètres!$L$79)),0) -> 0 | H48: =IF(Cession_autorisee=1,MAX(0,Cash_min-(H46+H47))/(1-CHOOSE(Reverse_flux,Paramètres!$J$79,Paramètres!$J$79,Paramètres!$K$79,Paramètres!$L$79)),0) -> 0 | I48: =IF(Cession_autorisee=1,MAX(0,Cash_min-(I46+I47))/(1-CHOOSE(Reverse_flux,Paramètres!$J$79,Paramètres!$J$79,Paramètres!$K$79,Paramètres!$L$79)),0) -> 0 | J48: =IF(Cession_autorisee=1,MAX(0,Cash_min-(J46+J47))/(1-CHOOSE(Reverse_flux,Paramètres!$J$79,Paramètres!$J$79,Paramètres!$K$79,Paramètres!$L$79)),0) -> 0
B49: Poche liquide de fin | C49: =C46+C47+C48*(1-CHOOSE(Reverse_flux,Paramètres!$J$79,Paramètres!$J$79,Paramètres!$K$79,Paramètres!$L$79)) -> 0.1 | D49: =D46+D47+D48*(1-CHOOSE(Reverse_flux,Paramètres!$J$79,Paramètres!$J$79,Paramètres!$K$79,Paramètres!$L$79)) -> 0.0620755 | E49: =E46+E47+E48*(1-CHOOSE(Reverse_flux,Paramètres!$J$79,Paramètres!$J$79,Paramètres!$K$79,Paramètres!$L$79)) -> 0.024151 | F49: =F46+F47+F48*(1-CHOOSE(Reverse_flux,Paramètres!$J$79,Paramètres!$J$79,Paramètres!$K$79,Paramètres!$L$79)) -> 0.01 | G49: =G46+G47+G48*(1-CHOOSE(Reverse_flux,Paramètres!$J$79,Paramètres!$J$79,Paramètres!$K$79,Paramètres!$L$79)) -> 0.0220755 | H49: =H46+H47+H48*(1-CHOOSE(Reverse_flux,Paramètres!$J$79,Paramètres!$J$79,Paramètres!$K$79,Paramètres!$L$79)) -> 0.034151 | I49: =I46+I47+I48*(1-CHOOSE(Reverse_flux,Paramètres!$J$79,Paramètres!$J$79,Paramètres!$K$79,Paramètres!$L$79)) -> 0.0712265 | J49: =J46+J47+J48*(1-CHOOSE(Reverse_flux,Paramètres!$J$79,Paramètres!$J$79,Paramètres!$K$79,Paramètres!$L$79)) -> 0.1
B50: Cessions cumulées | C50: =SUM($C$48:C48) -> 0 | D50: =SUM($C$48:D48) -> 0 | E50: =SUM($C$48:E48) -> 0 | F50: =SUM($C$48:F48) -> 0.027968824 | G50: =SUM($C$48:G48) -> 0.027968824 | H50: =SUM($C$48:H48) -> 0.027968824 | I50: =SUM($C$48:I48) -> 0.027968824 | J50: =SUM($C$48:J48) -> 0.027968824
B51: 0.125 | L51: =J54 -> 0.8 | M51: =MIN(C58:J58) -> 0.01 | N51: =F59 -> 0.027968824 | O51: =J59 -> 0.027968824 | P51: =IF(AND($B$51>Gate+0.0001,Reports_max<8,Suspension_auto=1),"Rouge : suspension à la date "&(Reports_max+1),IF(N51>0.0001,"Rouge : cessions décotées",IF(M51<S_poche_rouge,"Rouge : poche sous 5 %",IF(OR(M51<S_poche_orange,$B$51>Gate+0.0001),"Orange","Vert")))) -> Rouge : suspension à la date 5
B52: Demande totale (nouvelle + reportée) | C52: =$B$51 -> 0.125 | D52: =$B$51+C54 -> 0.2 | E52: =$B$51+D54 -> 0.275 | F52: =$B$51+E54 -> 0.35 | G52: =$B$51+F54 -> 0.425 | H52: =$B$51+G54 -> 0.55 | I52: =$B$51+H54 -> 0.675 | J52: =$B$51+I54 -> 0.8
B53: Exécuté | C53: =IF(AND($B$51>Gate+0.0001,1>Reports_max,Suspension_auto=1),0,MIN(C52,Gate)) -> 0.05 | D53: =IF(AND($B$51>Gate+0.0001,2>Reports_max,Suspension_auto=1),0,MIN(D52,Gate)) -> 0.05 | E53: =IF(AND($B$51>Gate+0.0001,3>Reports_max,Suspension_auto=1),0,MIN(E52,Gate)) -> 0.05 | F53: =IF(AND($B$51>Gate+0.0001,4>Reports_max,Suspension_auto=1),0,MIN(F52,Gate)) -> 0.05 | G53: =IF(AND($B$51>Gate+0.0001,5>Reports_max,Suspension_auto=1),0,MIN(G52,Gate)) -> 0 | H53: =IF(AND($B$51>Gate+0.0001,6>Reports_max,Suspension_auto=1),0,MIN(H52,Gate)) -> 0 | I53: =IF(AND($B$51>Gate+0.0001,7>Reports_max,Suspension_auto=1),0,MIN(I52,Gate)) -> 0 | J53: =IF(AND($B$51>Gate+0.0001,8>Reports_max,Suspension_auto=1),0,MIN(J52,Gate)) -> 0
B54: File reportée | C54: =C52-C53 -> 0.075 | D54: =D52-D53 -> 0.15 | E54: =E52-E53 -> 0.225 | F54: =F52-F53 -> 0.3 | G54: =G52-G53 -> 0.425 | H54: =H52-H53 -> 0.55 | I54: =I52-I53 -> 0.675 | J54: =J52-J53 -> 0.8
B55: Poche liquide avant appel aux fonds cibles | C55: =W_cash+W_HY-C53+C11 -> 0.0877755 | D55: =C58-D53+D11 -> 0.0277755 | E55: =D58-E53+E11 -> -0.010149 | F55: =E58-F53+F11 -> -0.0480735 | G55: =F58-G53+G11 -> -0.0122245 | H55: =G58-H53+H11 -> -0.000149 | I55: =H58-I53+I11 -> 0.0369265 | J55: =I58-J53+J11 -> 0.074002
B56: Rachats obtenus des fonds evergreen | C56: =MIN(C7,MAX(0,Poche_min_exec-C55)) -> 0.0122245 | D56: =MIN(D7,MAX(0,Poche_min_exec-D55)) -> 0.0343 | E56: =MIN(E7,MAX(0,Poche_min_exec-E55)) -> 0.0343 | F56: =MIN(F7,MAX(0,Poche_min_exec-F55)) -> 0.0343 | G56: =MIN(G7,MAX(0,Poche_min_exec-G55)) -> 0.0343 | H56: =MIN(H7,MAX(0,Poche_min_exec-H55)) -> 0.0343 | I56: =MIN(I7,MAX(0,Poche_min_exec-I55)) -> 0.0343 | J56: =MIN(J7,MAX(0,Poche_min_exec-J55)) -> 0.025998
B57: Cession secondaire (valeur cédée) | C57: =IF(Cession_autorisee=1,MAX(0,Cash_min-(C55+C56))/(1-CHOOSE(Reverse_flux,Paramètres!$J$79,Paramètres!$J$79,Paramètres!$K$79,Paramètres!$L$79)),0) -> 0 | D57: =IF(Cession_autorisee=1,MAX(0,Cash_min-(D55+D56))/(1-CHOOSE(Reverse_flux,Paramètres!$J$79,Paramètres!$J$79,Paramètres!$K$79,Paramètres!$L$79)),0) -> 0 | E57: =IF(Cession_autorisee=1,MAX(0,Cash_min-(E55+E56))/(1-CHOOSE(Reverse_flux,Paramètres!$J$79,Paramètres!$J$79,Paramètres!$K$79,Paramètres!$L$79)),0) -> 0 | F57: =IF(Cession_autorisee=1,MAX(0,Cash_min-(F55+F56))/(1-CHOOSE(Reverse_flux,Paramètres!$J$79,Paramètres!$J$79,Paramètres!$K$79,Paramètres!$L$79)),0) -> 0.027968824 | G57: =IF(Cession_autorisee=1,MAX(0,Cash_min-(G55+G56))/(1-CHOOSE(Reverse_flux,Paramètres!$J$79,Paramètres!$J$79,Paramètres!$K$79,Paramètres!$L$79)),0) -> 0 | H57: =IF(Cession_autorisee=1,MAX(0,Cash_min-(H55+H56))/(1-CHOOSE(Reverse_flux,Paramètres!$J$79,Paramètres!$J$79,Paramètres!$K$79,Paramètres!$L$79)),0) -> 0 | I57: =IF(Cession_autorisee=1,MAX(0,Cash_min-(I55+I56))/(1-CHOOSE(Reverse_flux,Paramètres!$J$79,Paramètres!$J$79,Paramètres!$K$79,Paramètres!$L$79)),0) -> 0 | J57: =IF(Cession_autorisee=1,MAX(0,Cash_min-(J55+J56))/(1-CHOOSE(Reverse_flux,Paramètres!$J$79,Paramètres!$J$79,Paramètres!$K$79,Paramètres!$L$79)),0) -> 0
B58: Poche liquide de fin | C58: =C55+C56+C57*(1-CHOOSE(Reverse_flux,Paramètres!$J$79,Paramètres!$J$79,Paramètres!$K$79,Paramètres!$L$79)) -> 0.1 | D58: =D55+D56+D57*(1-CHOOSE(Reverse_flux,Paramètres!$J$79,Paramètres!$J$79,Paramètres!$K$79,Paramètres!$L$79)) -> 0.0620755 | E58: =E55+E56+E57*(1-CHOOSE(Reverse_flux,Paramètres!$J$79,Paramètres!$J$79,Paramètres!$K$79,Paramètres!$L$79)) -> 0.024151 | F58: =F55+F56+F57*(1-CHOOSE(Reverse_flux,Paramètres!$J$79,Paramètres!$J$79,Paramètres!$K$79,Paramètres!$L$79)) -> 0.01 | G58: =G55+G56+G57*(1-CHOOSE(Reverse_flux,Paramètres!$J$79,Paramètres!$J$79,Paramètres!$K$79,Paramètres!$L$79)) -> 0.0220755 | H58: =H55+H56+H57*(1-CHOOSE(Reverse_flux,Paramètres!$J$79,Paramètres!$J$79,Paramètres!$K$79,Paramètres!$L$79)) -> 0.034151 | I58: =I55+I56+I57*(1-CHOOSE(Reverse_flux,Paramètres!$J$79,Paramètres!$J$79,Paramètres!$K$79,Paramètres!$L$79)) -> 0.0712265 | J58: =J55+J56+J57*(1-CHOOSE(Reverse_flux,Paramètres!$J$79,Paramètres!$J$79,Paramètres!$K$79,Paramètres!$L$79)) -> 0.1
B59: Cessions cumulées | C59: =SUM($C$57:C57) -> 0 | D59: =SUM($C$57:D57) -> 0 | E59: =SUM($C$57:E57) -> 0 | F59: =SUM($C$57:F57) -> 0.027968824 | G59: =SUM($C$57:G57) -> 0.027968824 | H59: =SUM($C$57:H57) -> 0.027968824 | I59: =SUM($C$57:I57) -> 0.027968824 | J59: =SUM($C$57:J57) -> 0.027968824
B60: 0.15 | L60: =J63 -> 1 | M60: =MIN(C67:J67) -> 0.01 | N60: =F68 -> 0.027968824 | O60: =J68 -> 0.027968824 | P60: =IF(AND($B$60>Gate+0.0001,Reports_max<8,Suspension_auto=1),"Rouge : suspension à la date "&(Reports_max+1),IF(N60>0.0001,"Rouge : cessions décotées",IF(M60<S_poche_rouge,"Rouge : poche sous 5 %",IF(OR(M60<S_poche_orange,$B$60>Gate+0.0001),"Orange","Vert")))) -> Rouge : suspension à la date 5
B61: Demande totale (nouvelle + reportée) | C61: =$B$60 -> 0.15 | D61: =$B$60+C63 -> 0.25 | E61: =$B$60+D63 -> 0.35 | F61: =$B$60+E63 -> 0.45 | G61: =$B$60+F63 -> 0.55 | H61: =$B$60+G63 -> 0.7 | I61: =$B$60+H63 -> 0.85 | J61: =$B$60+I63 -> 1
B62: Exécuté | C62: =IF(AND($B$60>Gate+0.0001,1>Reports_max,Suspension_auto=1),0,MIN(C61,Gate)) -> 0.05 | D62: =IF(AND($B$60>Gate+0.0001,2>Reports_max,Suspension_auto=1),0,MIN(D61,Gate)) -> 0.05 | E62: =IF(AND($B$60>Gate+0.0001,3>Reports_max,Suspension_auto=1),0,MIN(E61,Gate)) -> 0.05 | F62: =IF(AND($B$60>Gate+0.0001,4>Reports_max,Suspension_auto=1),0,MIN(F61,Gate)) -> 0.05 | G62: =IF(AND($B$60>Gate+0.0001,5>Reports_max,Suspension_auto=1),0,MIN(G61,Gate)) -> 0 | H62: =IF(AND($B$60>Gate+0.0001,6>Reports_max,Suspension_auto=1),0,MIN(H61,Gate)) -> 0 | I62: =IF(AND($B$60>Gate+0.0001,7>Reports_max,Suspension_auto=1),0,MIN(I61,Gate)) -> 0 | J62: =IF(AND($B$60>Gate+0.0001,8>Reports_max,Suspension_auto=1),0,MIN(J61,Gate)) -> 0
B63: File reportée | C63: =C61-C62 -> 0.1 | D63: =D61-D62 -> 0.2 | E63: =E61-E62 -> 0.3 | F63: =F61-F62 -> 0.4 | G63: =G61-G62 -> 0.55 | H63: =H61-H62 -> 0.7 | I63: =I61-I62 -> 0.85 | J63: =J61-J62 -> 1
B64: Poche liquide avant appel aux fonds cibles | C64: =W_cash+W_HY-C62+C11 -> 0.0877755 | D64: =C67-D62+D11 -> 0.0277755 | E64: =D67-E62+E11 -> -0.010149 | F64: =E67-F62+F11 -> -0.0480735 | G64: =F67-G62+G11 -> -0.0122245 | H64: =G67-H62+H11 -> -0.000149 | I64: =H67-I62+I11 -> 0.0369265 | J64: =I67-J62+J11 -> 0.074002
B65: Rachats obtenus des fonds evergreen | C65: =MIN(C7,MAX(0,Poche_min_exec-C64)) -> 0.0122245 | D65: =MIN(D7,MAX(0,Poche_min_exec-D64)) -> 0.0343 | E65: =MIN(E7,MAX(0,Poche_min_exec-E64)) -> 0.0343 | F65: =MIN(F7,MAX(0,Poche_min_exec-F64)) -> 0.0343 | G65: =MIN(G7,MAX(0,Poche_min_exec-G64)) -> 0.0343 | H65: =MIN(H7,MAX(0,Poche_min_exec-H64)) -> 0.0343 | I65: =MIN(I7,MAX(0,Poche_min_exec-I64)) -> 0.0343 | J65: =MIN(J7,MAX(0,Poche_min_exec-J64)) -> 0.025998
B66: Cession secondaire (valeur cédée) | C66: =IF(Cession_autorisee=1,MAX(0,Cash_min-(C64+C65))/(1-CHOOSE(Reverse_flux,Paramètres!$J$79,Paramètres!$J$79,Paramètres!$K$79,Paramètres!$L$79)),0) -> 0 | D66: =IF(Cession_autorisee=1,MAX(0,Cash_min-(D64+D65))/(1-CHOOSE(Reverse_flux,Paramètres!$J$79,Paramètres!$J$79,Paramètres!$K$79,Paramètres!$L$79)),0) -> 0 | E66: =IF(Cession_autorisee=1,MAX(0,Cash_min-(E64+E65))/(1-CHOOSE(Reverse_flux,Paramètres!$J$79,Paramètres!$J$79,Paramètres!$K$79,Paramètres!$L$79)),0) -> 0 | F66: =IF(Cession_autorisee=1,MAX(0,Cash_min-(F64+F65))/(1-CHOOSE(Reverse_flux,Paramètres!$J$79,Paramètres!$J$79,Paramètres!$K$79,Paramètres!$L$79)),0) -> 0.027968824 | G66: =IF(Cession_autorisee=1,MAX(0,Cash_min-(G64+G65))/(1-CHOOSE(Reverse_flux,Paramètres!$J$79,Paramètres!$J$79,Paramètres!$K$79,Paramètres!$L$79)),0) -> 0 | H66: =IF(Cession_autorisee=1,MAX(0,Cash_min-(H64+H65))/(1-CHOOSE(Reverse_flux,Paramètres!$J$79,Paramètres!$J$79,Paramètres!$K$79,Paramètres!$L$79)),0) -> 0 | I66: =IF(Cession_autorisee=1,MAX(0,Cash_min-(I64+I65))/(1-CHOOSE(Reverse_flux,Paramètres!$J$79,Paramètres!$J$79,Paramètres!$K$79,Paramètres!$L$79)),0) -> 0 | J66: =IF(Cession_autorisee=1,MAX(0,Cash_min-(J64+J65))/(1-CHOOSE(Reverse_flux,Paramètres!$J$79,Paramètres!$J$79,Paramètres!$K$79,Paramètres!$L$79)),0) -> 0
B67: Poche liquide de fin | C67: =C64+C65+C66*(1-CHOOSE(Reverse_flux,Paramètres!$J$79,Paramètres!$J$79,Paramètres!$K$79,Paramètres!$L$79)) -> 0.1 | D67: =D64+D65+D66*(1-CHOOSE(Reverse_flux,Paramètres!$J$79,Paramètres!$J$79,Paramètres!$K$79,Paramètres!$L$79)) -> 0.0620755 | E67: =E64+E65+E66*(1-CHOOSE(Reverse_flux,Paramètres!$J$79,Paramètres!$J$79,Paramètres!$K$79,Paramètres!$L$79)) -> 0.024151 | F67: =F64+F65+F66*(1-CHOOSE(Reverse_flux,Paramètres!$J$79,Paramètres!$J$79,Paramètres!$K$79,Paramètres!$L$79)) -> 0.01 | G67: =G64+G65+G66*(1-CHOOSE(Reverse_flux,Paramètres!$J$79,Paramètres!$J$79,Paramètres!$K$79,Paramètres!$L$79)) -> 0.0220755 | H67: =H64+H65+H66*(1-CHOOSE(Reverse_flux,Paramètres!$J$79,Paramètres!$J$79,Paramètres!$K$79,Paramètres!$L$79)) -> 0.034151 | I67: =I64+I65+I66*(1-CHOOSE(Reverse_flux,Paramètres!$J$79,Paramètres!$J$79,Paramètres!$K$79,Paramètres!$L$79)) -> 0.0712265 | J67: =J64+J65+J66*(1-CHOOSE(Reverse_flux,Paramètres!$J$79,Paramètres!$J$79,Paramètres!$K$79,Paramètres!$L$79)) -> 0.1
B68: Cessions cumulées | C68: =SUM($C$66:C66) -> 0 | D68: =SUM($C$66:D66) -> 0 | E68: =SUM($C$66:E66) -> 0 | F68: =SUM($C$66:F66) -> 0.027968824 | G68: =SUM($C$66:G66) -> 0.027968824 | H68: =SUM($C$66:H66) -> 0.027968824 | I68: =SUM($C$66:I66) -> 0.027968824 | J68: =SUM($C$66:J66) -> 0.027968824
B69: 0.2 | L69: =J72 -> 1.4 | M69: =MIN(C76:J76) -> 0.01 | N69: =F77 -> 0.027968824 | O69: =J77 -> 0.027968824 | P69: =IF(AND($B$69>Gate+0.0001,Reports_max<8,Suspension_auto=1),"Rouge : suspension à la date "&(Reports_max+1),IF(N69>0.0001,"Rouge : cessions décotées",IF(M69<S_poche_rouge,"Rouge : poche sous 5 %",IF(OR(M69<S_poche_orange,$B$69>Gate+0.0001),"Orange","Vert")))) -> Rouge : suspension à la date 5
B70: Demande totale (nouvelle + reportée) | C70: =$B$69 -> 0.2 | D70: =$B$69+C72 -> 0.35 | E70: =$B$69+D72 -> 0.5 | F70: =$B$69+E72 -> 0.65 | G70: =$B$69+F72 -> 0.8 | H70: =$B$69+G72 -> 1 | I70: =$B$69+H72 -> 1.2 | J70: =$B$69+I72 -> 1.4
B71: Exécuté | C71: =IF(AND($B$69>Gate+0.0001,1>Reports_max,Suspension_auto=1),0,MIN(C70,Gate)) -> 0.05 | D71: =IF(AND($B$69>Gate+0.0001,2>Reports_max,Suspension_auto=1),0,MIN(D70,Gate)) -> 0.05 | E71: =IF(AND($B$69>Gate+0.0001,3>Reports_max,Suspension_auto=1),0,MIN(E70,Gate)) -> 0.05 | F71: =IF(AND($B$69>Gate+0.0001,4>Reports_max,Suspension_auto=1),0,MIN(F70,Gate)) -> 0.05 | G71: =IF(AND($B$69>Gate+0.0001,5>Reports_max,Suspension_auto=1),0,MIN(G70,Gate)) -> 0 | H71: =IF(AND($B$69>Gate+0.0001,6>Reports_max,Suspension_auto=1),0,MIN(H70,Gate)) -> 0 | I71: =IF(AND($B$69>Gate+0.0001,7>Reports_max,Suspension_auto=1),0,MIN(I70,Gate)) -> 0 | J71: =IF(AND($B$69>Gate+0.0001,8>Reports_max,Suspension_auto=1),0,MIN(J70,Gate)) -> 0
B72: File reportée | C72: =C70-C71 -> 0.15 | D72: =D70-D71 -> 0.3 | E72: =E70-E71 -> 0.45 | F72: =F70-F71 -> 0.6 | G72: =G70-G71 -> 0.8 | H72: =H70-H71 -> 1 | I72: =I70-I71 -> 1.2 | J72: =J70-J71 -> 1.4
B73: Poche liquide avant appel aux fonds cibles | C73: =W_cash+W_HY-C71+C11 -> 0.0877755 | D73: =C76-D71+D11 -> 0.0277755 | E73: =D76-E71+E11 -> -0.010149 | F73: =E76-F71+F11 -> -0.0480735 | G73: =F76-G71+G11 -> -0.0122245 | H73: =G76-H71+H11 -> -0.000149 | I73: =H76-I71+I11 -> 0.0369265 | J73: =I76-J71+J11 -> 0.074002
B74: Rachats obtenus des fonds evergreen | C74: =MIN(C7,MAX(0,Poche_min_exec-C73)) -> 0.0122245 | D74: =MIN(D7,MAX(0,Poche_min_exec-D73)) -> 0.0343 | E74: =MIN(E7,MAX(0,Poche_min_exec-E73)) -> 0.0343 | F74: =MIN(F7,MAX(0,Poche_min_exec-F73)) -> 0.0343 | G74: =MIN(G7,MAX(0,Poche_min_exec-G73)) -> 0.0343 | H74: =MIN(H7,MAX(0,Poche_min_exec-H73)) -> 0.0343 | I74: =MIN(I7,MAX(0,Poche_min_exec-I73)) -> 0.0343 | J74: =MIN(J7,MAX(0,Poche_min_exec-J73)) -> 0.025998
B75: Cession secondaire (valeur cédée) | C75: =IF(Cession_autorisee=1,MAX(0,Cash_min-(C73+C74))/(1-CHOOSE(Reverse_flux,Paramètres!$J$79,Paramètres!$J$79,Paramètres!$K$79,Paramètres!$L$79)),0) -> 0 | D75: =IF(Cession_autorisee=1,MAX(0,Cash_min-(D73+D74))/(1-CHOOSE(Reverse_flux,Paramètres!$J$79,Paramètres!$J$79,Paramètres!$K$79,Paramètres!$L$79)),0) -> 0 | E75: =IF(Cession_autorisee=1,MAX(0,Cash_min-(E73+E74))/(1-CHOOSE(Reverse_flux,Paramètres!$J$79,Paramètres!$J$79,Paramètres!$K$79,Paramètres!$L$79)),0) -> 0 | F75: =IF(Cession_autorisee=1,MAX(0,Cash_min-(F73+F74))/(1-CHOOSE(Reverse_flux,Paramètres!$J$79,Paramètres!$J$79,Paramètres!$K$79,Paramètres!$L$79)),0) -> 0.027968824 | G75: =IF(Cession_autorisee=1,MAX(0,Cash_min-(G73+G74))/(1-CHOOSE(Reverse_flux,Paramètres!$J$79,Paramètres!$J$79,Paramètres!$K$79,Paramètres!$L$79)),0) -> 0 | H75: =IF(Cession_autorisee=1,MAX(0,Cash_min-(H73+H74))/(1-CHOOSE(Reverse_flux,Paramètres!$J$79,Paramètres!$J$79,Paramètres!$K$79,Paramètres!$L$79)),0) -> 0 | I75: =IF(Cession_autorisee=1,MAX(0,Cash_min-(I73+I74))/(1-CHOOSE(Reverse_flux,Paramètres!$J$79,Paramètres!$J$79,Paramètres!$K$79,Paramètres!$L$79)),0) -> 0 | J75: =IF(Cession_autorisee=1,MAX(0,Cash_min-(J73+J74))/(1-CHOOSE(Reverse_flux,Paramètres!$J$79,Paramètres!$J$79,Paramètres!$K$79,Paramètres!$L$79)),0) -> 0
B76: Poche liquide de fin | C76: =C73+C74+C75*(1-CHOOSE(Reverse_flux,Paramètres!$J$79,Paramètres!$J$79,Paramètres!$K$79,Paramètres!$L$79)) -> 0.1 | D76: =D73+D74+D75*(1-CHOOSE(Reverse_flux,Paramètres!$J$79,Paramètres!$J$79,Paramètres!$K$79,Paramètres!$L$79)) -> 0.0620755 | E76: =E73+E74+E75*(1-CHOOSE(Reverse_flux,Paramètres!$J$79,Paramètres!$J$79,Paramètres!$K$79,Paramètres!$L$79)) -> 0.024151 | F76: =F73+F74+F75*(1-CHOOSE(Reverse_flux,Paramètres!$J$79,Paramètres!$J$79,Paramètres!$K$79,Paramètres!$L$79)) -> 0.01 | G76: =G73+G74+G75*(1-CHOOSE(Reverse_flux,Paramètres!$J$79,Paramètres!$J$79,Paramètres!$K$79,Paramètres!$L$79)) -> 0.0220755 | H76: =H73+H74+H75*(1-CHOOSE(Reverse_flux,Paramètres!$J$79,Paramètres!$J$79,Paramètres!$K$79,Paramètres!$L$79)) -> 0.034151 | I76: =I73+I74+I75*(1-CHOOSE(Reverse_flux,Paramètres!$J$79,Paramètres!$J$79,Paramètres!$K$79,Paramètres!$L$79)) -> 0.0712265 | J76: =J73+J74+J75*(1-CHOOSE(Reverse_flux,Paramètres!$J$79,Paramètres!$J$79,Paramètres!$K$79,Paramètres!$L$79)) -> 0.1
B77: Cessions cumulées | C77: =SUM($C$75:C75) -> 0 | D77: =SUM($C$75:D75) -> 0 | E77: =SUM($C$75:E75) -> 0 | F77: =SUM($C$75:F75) -> 0.027968824 | G77: =SUM($C$75:G75) -> 0.027968824 | H77: =SUM($C$75:H75) -> 0.027968824 | I77: =SUM($C$75:I75) -> 0.027968824 | J77: =SUM($C$75:J75) -> 0.027968824
B78: 0.25 | L78: =J81 -> 1.8 | M78: =MIN(C85:J85) -> 0.01 | N78: =F86 -> 0.027968824 | O78: =J86 -> 0.027968824 | P78: =IF(AND($B$78>Gate+0.0001,Reports_max<8,Suspension_auto=1),"Rouge : suspension à la date "&(Reports_max+1),IF(N78>0.0001,"Rouge : cessions décotées",IF(M78<S_poche_rouge,"Rouge : poche sous 5 %",IF(OR(M78<S_poche_orange,$B$78>Gate+0.0001),"Orange","Vert")))) -> Rouge : suspension à la date 5
B79: Demande totale (nouvelle + reportée) | C79: =$B$78 -> 0.25 | D79: =$B$78+C81 -> 0.45 | E79: =$B$78+D81 -> 0.65 | F79: =$B$78+E81 -> 0.85 | G79: =$B$78+F81 -> 1.05 | H79: =$B$78+G81 -> 1.3 | I79: =$B$78+H81 -> 1.55 | J79: =$B$78+I81 -> 1.8
B80: Exécuté | C80: =IF(AND($B$78>Gate+0.0001,1>Reports_max,Suspension_auto=1),0,MIN(C79,Gate)) -> 0.05 | D80: =IF(AND($B$78>Gate+0.0001,2>Reports_max,Suspension_auto=1),0,MIN(D79,Gate)) -> 0.05 | E80: =IF(AND($B$78>Gate+0.0001,3>Reports_max,Suspension_auto=1),0,MIN(E79,Gate)) -> 0.05 | F80: =IF(AND($B$78>Gate+0.0001,4>Reports_max,Suspension_auto=1),0,MIN(F79,Gate)) -> 0.05 | G80: =IF(AND($B$78>Gate+0.0001,5>Reports_max,Suspension_auto=1),0,MIN(G79,Gate)) -> 0 | H80: =IF(AND($B$78>Gate+0.0001,6>Reports_max,Suspension_auto=1),0,MIN(H79,Gate)) -> 0 | I80: =IF(AND($B$78>Gate+0.0001,7>Reports_max,Suspension_auto=1),0,MIN(I79,Gate)) -> 0 | J80: =IF(AND($B$78>Gate+0.0001,8>Reports_max,Suspension_auto=1),0,MIN(J79,Gate)) -> 0
B81: File reportée | C81: =C79-C80 -> 0.2 | D81: =D79-D80 -> 0.4 | E81: =E79-E80 -> 0.6 | F81: =F79-F80 -> 0.8 | G81: =G79-G80 -> 1.05 | H81: =H79-H80 -> 1.3 | I81: =I79-I80 -> 1.55 | J81: =J79-J80 -> 1.8
B82: Poche liquide avant appel aux fonds cibles | C82: =W_cash+W_HY-C80+C11 -> 0.0877755 | D82: =C85-D80+D11 -> 0.0277755 | E82: =D85-E80+E11 -> -0.010149 | F82: =E85-F80+F11 -> -0.0480735 | G82: =F85-G80+G11 -> -0.0122245 | H82: =G85-H80+H11 -> -0.000149 | I82: =H85-I80+I11 -> 0.0369265 | J82: =I85-J80+J11 -> 0.074002
B83: Rachats obtenus des fonds evergreen | C83: =MIN(C7,MAX(0,Poche_min_exec-C82)) -> 0.0122245 | D83: =MIN(D7,MAX(0,Poche_min_exec-D82)) -> 0.0343 | E83: =MIN(E7,MAX(0,Poche_min_exec-E82)) -> 0.0343 | F83: =MIN(F7,MAX(0,Poche_min_exec-F82)) -> 0.0343 | G83: =MIN(G7,MAX(0,Poche_min_exec-G82)) -> 0.0343 | H83: =MIN(H7,MAX(0,Poche_min_exec-H82)) -> 0.0343 | I83: =MIN(I7,MAX(0,Poche_min_exec-I82)) -> 0.0343 | J83: =MIN(J7,MAX(0,Poche_min_exec-J82)) -> 0.025998
B84: Cession secondaire (valeur cédée) | C84: =IF(Cession_autorisee=1,MAX(0,Cash_min-(C82+C83))/(1-CHOOSE(Reverse_flux,Paramètres!$J$79,Paramètres!$J$79,Paramètres!$K$79,Paramètres!$L$79)),0) -> 0 | D84: =IF(Cession_autorisee=1,MAX(0,Cash_min-(D82+D83))/(1-CHOOSE(Reverse_flux,Paramètres!$J$79,Paramètres!$J$79,Paramètres!$K$79,Paramètres!$L$79)),0) -> 0 | E84: =IF(Cession_autorisee=1,MAX(0,Cash_min-(E82+E83))/(1-CHOOSE(Reverse_flux,Paramètres!$J$79,Paramètres!$J$79,Paramètres!$K$79,Paramètres!$L$79)),0) -> 0 | F84: =IF(Cession_autorisee=1,MAX(0,Cash_min-(F82+F83))/(1-CHOOSE(Reverse_flux,Paramètres!$J$79,Paramètres!$J$79,Paramètres!$K$79,Paramètres!$L$79)),0) -> 0.027968824 | G84: =IF(Cession_autorisee=1,MAX(0,Cash_min-(G82+G83))/(1-CHOOSE(Reverse_flux,Paramètres!$J$79,Paramètres!$J$79,Paramètres!$K$79,Paramètres!$L$79)),0) -> 0 | H84: =IF(Cession_autorisee=1,MAX(0,Cash_min-(H82+H83))/(1-CHOOSE(Reverse_flux,Paramètres!$J$79,Paramètres!$J$79,Paramètres!$K$79,Paramètres!$L$79)),0) -> 0 | I84: =IF(Cession_autorisee=1,MAX(0,Cash_min-(I82+I83))/(1-CHOOSE(Reverse_flux,Paramètres!$J$79,Paramètres!$J$79,Paramètres!$K$79,Paramètres!$L$79)),0) -> 0 | J84: =IF(Cession_autorisee=1,MAX(0,Cash_min-(J82+J83))/(1-CHOOSE(Reverse_flux,Paramètres!$J$79,Paramètres!$J$79,Paramètres!$K$79,Paramètres!$L$79)),0) -> 0
B85: Poche liquide de fin | C85: =C82+C83+C84*(1-CHOOSE(Reverse_flux,Paramètres!$J$79,Paramètres!$J$79,Paramètres!$K$79,Paramètres!$L$79)) -> 0.1 | D85: =D82+D83+D84*(1-CHOOSE(Reverse_flux,Paramètres!$J$79,Paramètres!$J$79,Paramètres!$K$79,Paramètres!$L$79)) -> 0.0620755 | E85: =E82+E83+E84*(1-CHOOSE(Reverse_flux,Paramètres!$J$79,Paramètres!$J$79,Paramètres!$K$79,Paramètres!$L$79)) -> 0.024151 | F85: =F82+F83+F84*(1-CHOOSE(Reverse_flux,Paramètres!$J$79,Paramètres!$J$79,Paramètres!$K$79,Paramètres!$L$79)) -> 0.01 | G85: =G82+G83+G84*(1-CHOOSE(Reverse_flux,Paramètres!$J$79,Paramètres!$J$79,Paramètres!$K$79,Paramètres!$L$79)) -> 0.0220755 | H85: =H82+H83+H84*(1-CHOOSE(Reverse_flux,Paramètres!$J$79,Paramètres!$J$79,Paramètres!$K$79,Paramètres!$L$79)) -> 0.034151 | I85: =I82+I83+I84*(1-CHOOSE(Reverse_flux,Paramètres!$J$79,Paramètres!$J$79,Paramètres!$K$79,Paramètres!$L$79)) -> 0.0712265 | J85: =J82+J83+J84*(1-CHOOSE(Reverse_flux,Paramètres!$J$79,Paramètres!$J$79,Paramètres!$K$79,Paramètres!$L$79)) -> 0.1
B86: Cessions cumulées | C86: =SUM($C$84:C84) -> 0 | D86: =SUM($C$84:D84) -> 0 | E86: =SUM($C$84:E84) -> 0 | F86: =SUM($C$84:F84) -> 0.027968824 | G86: =SUM($C$84:G84) -> 0.027968824 | H86: =SUM($C$84:H84) -> 0.027968824 | I86: =SUM($C$84:I84) -> 0.027968824 | J86: =SUM($C$84:J84) -> 0.027968824
B87: 0.3 | L87: =J90 -> 2.2 | M87: =MIN(C94:J94) -> 0.01 | N87: =F95 -> 0.027968824 | O87: =J95 -> 0.027968824 | P87: =IF(AND($B$87>Gate+0.0001,Reports_max<8,Suspension_auto=1),"Rouge : suspension à la date "&(Reports_max+1),IF(N87>0.0001,"Rouge : cessions décotées",IF(M87<S_poche_rouge,"Rouge : poche sous 5 %",IF(OR(M87<S_poche_orange,$B$87>Gate+0.0001),"Orange","Vert")))) -> Rouge : suspension à la date 5
B88: Demande totale (nouvelle + reportée) | C88: =$B$87 -> 0.3 | D88: =$B$87+C90 -> 0.55 | E88: =$B$87+D90 -> 0.8 | F88: =$B$87+E90 -> 1.05 | G88: =$B$87+F90 -> 1.3 | H88: =$B$87+G90 -> 1.6 | I88: =$B$87+H90 -> 1.9 | J88: =$B$87+I90 -> 2.2
B89: Exécuté | C89: =IF(AND($B$87>Gate+0.0001,1>Reports_max,Suspension_auto=1),0,MIN(C88,Gate)) -> 0.05 | D89: =IF(AND($B$87>Gate+0.0001,2>Reports_max,Suspension_auto=1),0,MIN(D88,Gate)) -> 0.05 | E89: =IF(AND($B$87>Gate+0.0001,3>Reports_max,Suspension_auto=1),0,MIN(E88,Gate)) -> 0.05 | F89: =IF(AND($B$87>Gate+0.0001,4>Reports_max,Suspension_auto=1),0,MIN(F88,Gate)) -> 0.05 | G89: =IF(AND($B$87>Gate+0.0001,5>Reports_max,Suspension_auto=1),0,MIN(G88,Gate)) -> 0 | H89: =IF(AND($B$87>Gate+0.0001,6>Reports_max,Suspension_auto=1),0,MIN(H88,Gate)) -> 0 | I89: =IF(AND($B$87>Gate+0.0001,7>Reports_max,Suspension_auto=1),0,MIN(I88,Gate)) -> 0 | J89: =IF(AND($B$87>Gate+0.0001,8>Reports_max,Suspension_auto=1),0,MIN(J88,Gate)) -> 0
B90: File reportée | C90: =C88-C89 -> 0.25 | D90: =D88-D89 -> 0.5 | E90: =E88-E89 -> 0.75 | F90: =F88-F89 -> 1 | G90: =G88-G89 -> 1.3 | H90: =H88-H89 -> 1.6 | I90: =I88-I89 -> 1.9 | J90: =J88-J89 -> 2.2
B91: Poche liquide avant appel aux fonds cibles | C91: =W_cash+W_HY-C89+C11 -> 0.0877755 | D91: =C94-D89+D11 -> 0.0277755 | E91: =D94-E89+E11 -> -0.010149 | F91: =E94-F89+F11 -> -0.0480735 | G91: =F94-G89+G11 -> -0.0122245 | H91: =G94-H89+H11 -> -0.000149 | I91: =H94-I89+I11 -> 0.0369265 | J91: =I94-J89+J11 -> 0.074002
B92: Rachats obtenus des fonds evergreen | C92: =MIN(C7,MAX(0,Poche_min_exec-C91)) -> 0.0122245 | D92: =MIN(D7,MAX(0,Poche_min_exec-D91)) -> 0.0343 | E92: =MIN(E7,MAX(0,Poche_min_exec-E91)) -> 0.0343 | F92: =MIN(F7,MAX(0,Poche_min_exec-F91)) -> 0.0343 | G92: =MIN(G7,MAX(0,Poche_min_exec-G91)) -> 0.0343 | H92: =MIN(H7,MAX(0,Poche_min_exec-H91)) -> 0.0343 | I92: =MIN(I7,MAX(0,Poche_min_exec-I91)) -> 0.0343 | J92: =MIN(J7,MAX(0,Poche_min_exec-J91)) -> 0.025998
B93: Cession secondaire (valeur cédée) | C93: =IF(Cession_autorisee=1,MAX(0,Cash_min-(C91+C92))/(1-CHOOSE(Reverse_flux,Paramètres!$J$79,Paramètres!$J$79,Paramètres!$K$79,Paramètres!$L$79)),0) -> 0 | D93: =IF(Cession_autorisee=1,MAX(0,Cash_min-(D91+D92))/(1-CHOOSE(Reverse_flux,Paramètres!$J$79,Paramètres!$J$79,Paramètres!$K$79,Paramètres!$L$79)),0) -> 0 | E93: =IF(Cession_autorisee=1,MAX(0,Cash_min-(E91+E92))/(1-CHOOSE(Reverse_flux,Paramètres!$J$79,Paramètres!$J$79,Paramètres!$K$79,Paramètres!$L$79)),0) -> 0 | F93: =IF(Cession_autorisee=1,MAX(0,Cash_min-(F91+F92))/(1-CHOOSE(Reverse_flux,Paramètres!$J$79,Paramètres!$J$79,Paramètres!$K$79,Paramètres!$L$79)),0) -> 0.027968824 | G93: =IF(Cession_autorisee=1,MAX(0,Cash_min-(G91+G92))/(1-CHOOSE(Reverse_flux,Paramètres!$J$79,Paramètres!$J$79,Paramètres!$K$79,Paramètres!$L$79)),0) -> 0 | H93: =IF(Cession_autorisee=1,MAX(0,Cash_min-(H91+H92))/(1-CHOOSE(Reverse_flux,Paramètres!$J$79,Paramètres!$J$79,Paramètres!$K$79,Paramètres!$L$79)),0) -> 0 | I93: =IF(Cession_autorisee=1,MAX(0,Cash_min-(I91+I92))/(1-CHOOSE(Reverse_flux,Paramètres!$J$79,Paramètres!$J$79,Paramètres!$K$79,Paramètres!$L$79)),0) -> 0 | J93: =IF(Cession_autorisee=1,MAX(0,Cash_min-(J91+J92))/(1-CHOOSE(Reverse_flux,Paramètres!$J$79,Paramètres!$J$79,Paramètres!$K$79,Paramètres!$L$79)),0) -> 0
B94: Poche liquide de fin | C94: =C91+C92+C93*(1-CHOOSE(Reverse_flux,Paramètres!$J$79,Paramètres!$J$79,Paramètres!$K$79,Paramètres!$L$79)) -> 0.1 | D94: =D91+D92+D93*(1-CHOOSE(Reverse_flux,Paramètres!$J$79,Paramètres!$J$79,Paramètres!$K$79,Paramètres!$L$79)) -> 0.0620755 | E94: =E91+E92+E93*(1-CHOOSE(Reverse_flux,Paramètres!$J$79,Paramètres!$J$79,Paramètres!$K$79,Paramètres!$L$79)) -> 0.024151 | F94: =F91+F92+F93*(1-CHOOSE(Reverse_flux,Paramètres!$J$79,Paramètres!$J$79,Paramètres!$K$79,Paramètres!$L$79)) -> 0.01 | G94: =G91+G92+G93*(1-CHOOSE(Reverse_flux,Paramètres!$J$79,Paramètres!$J$79,Paramètres!$K$79,Paramètres!$L$79)) -> 0.0220755 | H94: =H91+H92+H93*(1-CHOOSE(Reverse_flux,Paramètres!$J$79,Paramètres!$J$79,Paramètres!$K$79,Paramètres!$L$79)) -> 0.034151 | I94: =I91+I92+I93*(1-CHOOSE(Reverse_flux,Paramètres!$J$79,Paramètres!$J$79,Paramètres!$K$79,Paramètres!$L$79)) -> 0.0712265 | J94: =J91+J92+J93*(1-CHOOSE(Reverse_flux,Paramètres!$J$79,Paramètres!$J$79,Paramètres!$K$79,Paramètres!$L$79)) -> 0.1
B95: Cessions cumulées | C95: =SUM($C$93:C93) -> 0 | D95: =SUM($C$93:D93) -> 0 | E95: =SUM($C$93:E93) -> 0 | F95: =SUM($C$93:F93) -> 0.027968824 | G95: =SUM($C$93:G93) -> 0.027968824 | H95: =SUM($C$93:H93) -> 0.027968824 | I95: =SUM($C$93:I93) -> 0.027968824 | J95: =SUM($C$93:J93) -> 0.027968824
B96: Point de rupture : premier taux imposant des cessions décotées dans les quatre premières dates | C96: {=MIN(IF(N15:N87>0.0001,B15:B87,9))} -> 0.05 | P96: Avec le gate, la file absorbe l'excès de demande ; la cession n'intervient qu'à cause des appels et des frais
B97: Premier taux conduisant à la suspension | C97: {=MIN(IF(B15:B87>Gate+0.0001,B15:B87,9))} -> 0.075 | P97: Par construction : premier taux supérieur au plafond
B99: C. SANS PLAFONNEMENT (gate levé par la Société de Gestion : toutes les demandes sont honorées)
B100: Taux par date et variable | C100: Date 1 | D100: Date 2 | E100: Date 3 | F100: Date 4 | G100: Date 5 | H100: Date 6 | I100: Date 7 | J100: Date 8 | L100: File à la date 8 | M100: Poche min | N100: Cessions à la date 4 | O100: Cessions à la date 8 | P100: Verdict
B101: 0.025 | L101: =J104 -> 0 | M101: =MIN(C108:J108) -> 0.048153 | N101: =F109 -> 0 | O101: =J109 -> 0 | P101: =IF(O101>(Paramètres!$D$68+Paramètres!$D$69),"Rouge : cession impossible",IF(N101>0.0001,"Rouge : cessions décotées",IF(M101<S_poche_rouge,"Rouge : poche sous 5 %",IF(M101<S_poche_orange,"Orange","Vert")))) -> Rouge : poche sous 5 %
B102: Demande totale (nouvelle + reportée) | C102: =$B$101 -> 0.025 | D102: =$B$101+C104 -> 0.025 | E102: =$B$101+D104 -> 0.025 | F102: =$B$101+E104 -> 0.025 | G102: =$B$101+F104 -> 0.025 | H102: =$B$101+G104 -> 0.025 | I102: =$B$101+H104 -> 0.025 | J102: =$B$101+I104 -> 0.025
B103: Exécuté | C103: =C102 -> 0.025 | D103: =D102 -> 0.025 | E103: =E102 -> 0.025 | F103: =F102 -> 0.025 | G103: =G102 -> 0.025 | H103: =H102 -> 0.025 | I103: =I102 -> 0.025 | J103: =J102 -> 0.025
B104: File reportée | C104: =C102-C103 -> 0 | D104: =D102-D103 -> 0 | E104: =E102-E103 -> 0 | F104: =F102-F103 -> 0 | G104: =G102-G103 -> 0 | H104: =H102-H103 -> 0 | I104: =I102-I103 -> 0 | J104: =J102-J103 -> 0
...

Sheet Concentration
B2: CONCENTRATION DES PORTEURS ET CHOC DU PREMIER PORTEUR
B3: Registre non constitué : répartition hypothétique à remplacer par le registre réel (cellules cyan). Les ratios alimentent la question 118 du reporting Annex IV et le choc « porteur 1 » des scénarios S3 et S4.
B5: Rang | C5: Porteur (anonymisé) | D5: Part de l'AN | E5: Encours (EUR) | F5: Cumul | G5: Alerte | H5: Commentaire
B6: 1 | C6: POR-001 | D6: =Top1 -> 0.15 | E6: =D6*AN_depart -> 1200000 | F6: =SUM(D6:D6) -> 0.15 | G6: =IF(D6>0.2,"Rouge : > 20 %",IF(D6>0.1,"Orange : 10 à 20 %","Vert")) -> Orange : 10 à 20 % | H6: Hypothèse : premier porteur = paramètre Top1
B7: 2 | C7: POR-002 | D7: 0.08 | E7: =D7*AN_depart -> 640000 | F7: =SUM(D6:D7) -> 0.23 | G7: =IF(D7>0.2,"Rouge : > 20 %",IF(D7>0.1,"Orange : 10 à 20 %","Vert")) -> Vert | H7: Hypothèse
B8: 3 | C8: POR-003 | D8: 0.05 | E8: =D8*AN_depart -> 400000 | F8: =SUM(D6:D8) -> 0.28 | G8: =IF(D8>0.2,"Rouge : > 20 %",IF(D8>0.1,"Orange : 10 à 20 %","Vert")) -> Vert | H8: Hypothèse
B9: 4 | C9: POR-004 | D9: 0.04 | E9: =D9*AN_depart -> 320000 | F9: =SUM(D6:D9) -> 0.32 | G9: =IF(D9>0.2,"Rouge : > 20 %",IF(D9>0.1,"Orange : 10 à 20 %","Vert")) -> Vert | H9: Hypothèse
B10: 5 | C10: POR-005 | D10: 0.03 | E10: =D10*AN_depart -> 240000 | F10: =SUM(D6:D10) -> 0.35 | G10: =IF(D10>0.2,"Rouge : > 20 %",IF(D10>0.1,"Orange : 10 à 20 %","Vert")) -> Vert | H10: Hypothèse
B11: 6 | C11: POR-006 | D11: 0.03 | E11: =D11*AN_depart -> 240000 | F11: =SUM(D6:D11) -> 0.38 | G11: =IF(D11>0.2,"Rouge : > 20 %",IF(D11>0.1,"Orange : 10 à 20 %","Vert")) -> Vert | H11: Hypothèse
B12: 7 | C12: POR-007 | D12: 0.02 | E12: =D12*AN_depart -> 160000 | F12: =SUM(D6:D12) -> 0.4 | G12: =IF(D12>0.2,"Rouge : > 20 %",IF(D12>0.1,"Orange : 10 à 20 %","Vert")) -> Vert | H12: Hypothèse
B13: 8 | C13: POR-008 | D13: 0.02 | E13: =D13*AN_depart -> 160000 | F13: =SUM(D6:D13) -> 0.42 | G13: =IF(D13>0.2,"Rouge : > 20 %",IF(D13>0.1,"Orange : 10 à 20 %","Vert")) -> Vert | H13: Hypothèse
B14: 9 | C14: POR-009 | D14: 0.02 | E14: =D14*AN_depart -> 160000 | F14: =SUM(D6:D14) -> 0.44 | G14: =IF(D14>0.2,"Rouge : > 20 %",IF(D14>0.1,"Orange : 10 à 20 %","Vert")) -> Vert | H14: Hypothèse
B15: 10 | C15: POR-010 | D15: 0.02 | E15: =D15*AN_depart -> 160000 | F15: =SUM(D6:D15) -> 0.46 | G15: =IF(D15>0.2,"Rouge : > 20 %",IF(D15>0.1,"Orange : 10 à 20 %","Vert")) -> Vert | H15: Hypothèse
C16: Autres porteurs | D16: =1-SUM(D6:D15) -> 0.54 | E16: =D16*AN_depart -> 4320000 | F16: 1
B18: RATIOS ET CHOC
B19: Mesure | D19: Valeur | G19: Lecture
B20: Part du premier porteur | D20: =D6 -> 0.15 | G20: Vert ≤ 10 % ; Orange 10 à 20 % ; Rouge > 20 %
B21: Part des trois premiers | D21: =SUM(D6:D8) -> 0.28
B22: Part des cinq premiers | D22: =SUM(D6:D10) -> 0.35 | G22: Alimente le scénario de concentration du rapport de risque
B23: Part des dix premiers | D23: =SUM(D6:D15) -> 0.46
B24: Indice de Herfindahl (dix premiers et solde) | D24: =SUMPRODUCT(D6:D16,D6:D16)*10000 -> 3280 | G24: > 2 500 : concentré
B25: Dates de rachat consommées par la sortie intégrale du premier porteur | D25: =D6/Gate -> 3 | G25: Part / plafond par date
B26: Verdict du choc porteur 1 | D26: =IF(D25<=2,"Vert : absorbé en deux dates",IF(D25<=Reports_max,"Orange : cascade sur plusieurs dates","Rouge : dépasse le nombre maximal de reports")) -> Orange : cascade sur plusieurs dates | G26: Au-delà du nombre maximal de reports, la suspension devient probable

Sheet MST Données
B2: MST - SÉRIES MENSUELLES DES PROXIES COTÉS ET STATISTIQUES
B3: Rendements mensuels simples des composites équipondérés du classeur des cours (devise locale, dividendes réinvestis ; Brookfield exclu) et variation du cours EUR/USD. Valeurs importées ; statistiques en formules. Source : Yahoo Finance, extraction du 06/10/2026.
B5: Mois | C5: C1 Infrastructure cotée | D5: C2 Dette d'infra cotée | E5: C3 Direct lending coté | F5: C4 Crédit HY coté | G5: EUR/USD (variation) | I5: Statistique | J5: C1 Infra | K5: C2 Dette infra | L5: C3 Direct lending | M5: C4 Crédit HY | N5: EUR/USD | O5: C1 : 6 mois glissants | P5: C2 : 6 mois glissants | Q5: C3 : 6 mois glissants | R5: C4 : 6 mois glissants | S5: USD : 6 mois glissants
B6: 40878 | C6: 0.0075224562 | D6: 0.037779797 | E6: 0.016713464 | F6: 0.02319144 | G6: -0.027622288 | I6: Nombre de mois | J6: =COUNT(C6:C183) -> 178 | K6: =COUNT(D6:D183) -> 178 | L6: =COUNT(E6:E183) -> 178 | M6: =COUNT(F6:F183) -> 178 | N6: =COUNT(G6:G183) -> 178
B7: 40909 | C7: 0.0081933733 | D7: 0.033613409 | E7: 0.025889734 | F7: 0.035302817 | G7: 0.014164464 | I7: Rendement mensuel moyen | J7: =AVERAGE(C6:C183) -> 0.0051673792 | K7: =AVERAGE(D6:D183) -> -0.0001155246 | L7: =AVERAGE(E6:E183) -> 0.0092944077 | M7: =AVERAGE(F6:F183) -> 0.0036896528 | N7: =AVERAGE(G6:G183) -> -0.00068212523
B8: 40940 | C8: 0.018797481 | D8: -0.017421846 | E8: 0.051735529 | F8: 0.0080792749 | G8: 0.025756494 | I8: Écart-type mensuel | J8: =STDEV(C6:C183) -> 0.024101148 | K8: =STDEV(D6:D183) -> 0.028803613 | L8: =STDEV(E6:E183) -> 0.052708725 | M8: =STDEV(F6:F183) -> 0.015838184 | N8: =STDEV(G6:G183) -> 0.021133075
B9: 40969 | C9: 0.018286741 | D9: -0.0011816416 | E9: 0.0033720488 | F9: 0.0040840081 | G9: -0.009862054 | I9: Volatilité annualisée | J9: =STDEV(C6:C183)*SQRT(12) -> 0.083488827 | K9: =STDEV(D6:D183)*SQRT(12) -> 0.099778644 | L9: =STDEV(E6:E183)*SQRT(12) -> 0.18258838 | M9: =STDEV(F6:F183)*SQRT(12) -> 0.05486508 | N9: =STDEV(G6:G183)*SQRT(12) -> 0.073207118
B10: 41000 | C10: -0.0019274187 | D10: -0.0023671009 | E10: -0.018960586 | F10: 0.0022346371 | G10: -0.0077595911 | I10: Écart-type semestriel (σ × √6) | J10: =STDEV(C6:C183)*SQRT(6) -> 0.059035515 | K10: =STDEV(D6:D183)*SQRT(6) -> 0.070554156 | L10: =STDEV(E6:E183)*SQRT(6) -> 0.12910948 | M10: =STDEV(F6:F183)*SQRT(6) -> 0.03879547 | N10: =STDEV(G6:G183)*SQRT(6) -> 0.051765249
B11: 41030 | C11: -0.0076288914 | D11: -0.011516861 | E11: -0.059226897 | F11: -0.023110648 | G11: -0.065462131 | I11: Rendement semestriel moyen (× 6) | J11: =AVERAGE(C6:C183)*6 -> 0.031004275 | K11: =AVERAGE(D6:D183)*6 -> -0.00069314762 | L11: =AVERAGE(E6:E183)*6 -> 0.055766446 | M11: =AVERAGE(F6:F183)*6 -> 0.022137917 | N11: =AVERAGE(G6:G183)*6 -> -0.0040927514 | O11: {=PRODUCT(1+C6:C11)-1} -> 0.043741042 | P11: {=PRODUCT(1+D6:D11)-1} -> 0.038142558 | Q11: {=PRODUCT(1+E6:E11)-1} -> 0.015872375 | R11: {=PRODUCT(1+F6:F11)-1} -> 0.049793342 | S11: {=PRODUCT(1+G6:G11)-1} -> -0.071253525
B12: 41061 | C12: 0.020447276 | D12: 0.0036014312 | E12: 0.083468035 | F12: 0.031705694 | G12: 0.02345555 | I12: Pire mois | J12: =MIN(C6:C183) -> -0.097793532 | K12: =MIN(D6:D183) -> -0.10509586 | L12: =MIN(E6:E183) -> -0.36824491 | M12: =MIN(F6:F183) -> -0.09642604 | N12: =MIN(G6:G183) -> -0.071870511 | O12: {=PRODUCT(1+C7:C12)-1} -> 0.057130485 | P12: {=PRODUCT(1+D7:D12)-1} -> 0.0039522452 | Q12: {=PRODUCT(1+E7:E12)-1} -> 0.082571722 | R12: {=PRODUCT(1+F7:F12)-1} -> 0.058528957 | S12: {=PRODUCT(1+G7:G12)-1} -> -0.022467584
B13: 41091 | C13: 0.019229556 | D13: 0.021530897 | E13: 0.041979474 | F13: 0.012775353 | G13: -0.032021604 | I13: Autocorrélation d'ordre 1 | J13: =CORREL(C7:C183,C6:C182) -> -0.11677899 | K13: =CORREL(D7:D183,D6:D182) -> -0.070372234 | L13: =CORREL(E7:E183,E6:E182) -> -0.078823934 | M13: =CORREL(F7:F183,F6:F182) -> -0.092810082 | N13: =CORREL(G7:G183,G6:G182) -> 0.030552298 | O13: {=PRODUCT(1+C8:C13)-1} -> 0.068702358 | P13: {=PRODUCT(1+D8:D13)-1} -> -0.00778354 | Q13: {=PRODUCT(1+E8:E13)-1} -> 0.099550445 | R13: {=PRODUCT(1+F8:F13)-1} -> 0.035496109 | S13: {=PRODUCT(1+G8:G13)-1} -> -0.066985391
B14: 41122 | C14: 0.029389136 | D14: -0.0011709574 | E14: 0.038484656 | F14: 0.0024986246 | G14: 0.020517918 | I14: Asymétrie | J14: =SKEW(C6:C183) -> -0.64008658 | K14: =SKEW(D6:D183) -> -0.79004716 | L14: =SKEW(E6:E183) -> -1.5979071 | M14: =SKEW(F6:F183) -> -1.3782532 | N14: =SKEW(G6:G183) -> -0.17528851 | O14: {=PRODUCT(1+C9:C14)-1} -> 0.079812837 | P14: {=PRODUCT(1+D9:D14)-1} -> 0.0086267565 | Q14: {=PRODUCT(1+E9:E14)-1} -> 0.08569715 | R14: {=PRODUCT(1+F9:F14)-1} -> 0.029763681 | S14: {=PRODUCT(1+G9:G14)-1} -> -0.07175033
B15: 41153 | C15: -0.0066601276 | D15: 0 | E15: 0.01721207 | F15: 0.009165555 | G15: 0.026704862 | I15: Aplatissement (excès) | J15: =KURT(C6:C183) -> 2.8593869 | K15: =KURT(D6:D183) -> 1.4614587 | L15: =KURT(E6:E183) -> 15.782201 | M15: =KURT(F6:F183) -> 9.760566 | N15: =KURT(G6:G183) -> 0.37873304 | O15: {=PRODUCT(1+C10:C15)-1} -> 0.053358649 | P15: {=PRODUCT(1+D10:D15)-1} -> 0.0098200018 | Q15: {=PRODUCT(1+E10:E15)-1} -> 0.10067272 | R15: {=PRODUCT(1+F10:F15)-1} -> 0.034975189 | S15: {=PRODUCT(1+G10:G15)-1} -> -0.037469019
B16: 41183 | C16: 0.017782586 | D16: 0.038687256 | E16: 0.017503218 | F16: 0.011034743 | G16: 0.0091516554 | I16: Pire semestre glissant observé | J16: =MIN(O11:O183) -> -0.11310915 | K16: =MIN(P11:P183) -> -0.20189842 | L16: =MIN(Q11:Q183) -> -0.40676308 | M16: =MIN(R11:R183) -> -0.11594613 | N16: =MIN(S11:S183) -> -0.15736547 | O16: {=PRODUCT(1+C11:C16)-1} -> 0.074160447 | P16: {=PRODUCT(1+D11:D16)-1} -> 0.05137588 | Q16: {=PRODUCT(1+E11:E16)-1} -> 0.14158312 | R16: {=PRODUCT(1+F11:F16)-1} -> 0.044062773 | S16: {=PRODUCT(1+G11:G16)-1} -> -0.021064125
B17: 41214 | C17: -0.0036313669 | D17: -0.029013703 | E17: 0.017201918 | F17: 0.0059917843 | G17: 0.00084321793 | I17: Percentile 5 % des semestres glissants | J17: =PERCENTILE(O11:O183,0.05) -> -0.05954118 | K17: =PERCENTILE(P11:P183,0.05) -> -0.11813281 | L17: =PERCENTILE(Q11:Q183,0.05) -> -0.11033748 | M17: =PERCENTILE(R11:R183,0.05) -> -0.046908864 | N17: =PERCENTILE(S11:S183,0.05) -> -0.087776519 | O17: {=PRODUCT(1+C12:C17)-1} -> 0.07848744 | P17: {=PRODUCT(1+D12:D17)-1} -> 0.032765793 | Q17: {=PRODUCT(1+E12:E17)-1} -> 0.23432583 | R17: {=PRODUCT(1+F12:F17)-1} -> 0.075166363 | S17: {=PRODUCT(1+G12:G17)-1} -> 0.048391258
B18: 41244 | C18: 0.014954726 | D18: 0.0034886047 | E18: 0.011305996 | F18: 0.016784859 | G18: 0.019590206 | I18: Percentile 1 % des semestres glissants | J18: =PERCENTILE(O11:O183,0.01) -> -0.10707399 | K18: =PERCENTILE(P11:P183,0.01) -> -0.17555125 | L18: =PERCENTILE(Q11:Q183,0.01) -> -0.24500913 | M18: =PERCENTILE(R11:R183,0.01) -> -0.089793355 | N18: =PERCENTILE(S11:S183,0.01) -> -0.14684273 | O18: {=PRODUCT(1+C13:C18)-1} -> 0.072682489 | P18: {=PRODUCT(1+D13:D18)-1} -> 0.032649688 | Q18: {=PRODUCT(1+E13:E18)-1} -> 0.15211624 | R18: {=PRODUCT(1+F13:F18)-1} -> 0.059616988 | S18: {=PRODUCT(1+G13:G18)-1} -> 0.044431738
B19: 41275 | C19: 0.0037518709 | D19: 0.01042843 | E19: 0.023429093 | F19: 0.00011120911 | G19: 0.025752716 | O19: {=PRODUCT(1+C14:C19)-1} -> 0.056393085 | P19: {=PRODUCT(1+D14:D19)-1} -> 0.021426376 | Q19: {=PRODUCT(1+E14:E19)-1} -> 0.13160509 | R19: {=PRODUCT(1+F14:F19)-1} -> 0.046367117 | S19: {=PRODUCT(1+G14:G19)-1} -> 0.10676922
B20: 41306 | C20: 0.0088697859 | D20: 0.02522944 | E20: 0.034058809 | F20: 0.0065815432 | G20: -0.030760118 | I20: MATRICE DE CORRÉLATION DES RENDEMENTS MENSUELS | O20: {=PRODUCT(1+C15:C20)-1} -> 0.035335451 | P20: {=PRODUCT(1+D15:D20)-1} -> 0.048424051 | Q20: {=PRODUCT(1+E15:E20)-1} -> 0.12678238 | R20: {=PRODUCT(1+F15:F20)-1} -> 0.050628701 | S20: {=PRODUCT(1+G15:G20)-1} -> 0.051157305
B21: 41334 | C21: 0.0031451985 | D21: 0.022371454 | E21: -0.0021367214 | F21: 0.0069032333 | G21: -0.026089674 | J21: C1 | K21: C2 | L21: C3 | M21: C4 | N21: USD | O21: {=PRODUCT(1+C16:C21)-1} -> 0.045555318 | P21: {=PRODUCT(1+D16:D21)-1} -> 0.071878822 | Q21: {=PRODUCT(1+E16:E21)-1} -> 0.1053494 | R21: {=PRODUCT(1+F16:F21)-1} -> 0.048273428 | S21: {=PRODUCT(1+G16:G21)-1} -> -0.0028946074
B22: 41365 | C22: 0.039188477 | D22: -0.017505714 | E22: 0.014680689 | F22: 0.016830708 | G22: 0.022485627 | I22: C1 | J22: =CORREL(C6:C183,C6:C183) -> 1 | K22: =CORREL(C6:C183,D6:D183) -> 0.56714271 | L22: =CORREL(C6:C183,E6:E183) -> 0.47009699 | M22: =CORREL(C6:C183,F6:F183) -> 0.57925357 | N22: =CORREL(C6:C183,G6:G183) -> 0.2051897 | O22: {=PRODUCT(1+C17:C22)-1} -> 0.067545323 | P22: {=PRODUCT(1+D17:D22)-1} -> 0.013890188 | Q22: {=PRODUCT(1+E17:E22)-1} -> 0.10228319 | R22: {=PRODUCT(1+F17:F22)-1} -> 0.054282871 | S22: {=PRODUCT(1+G17:G22)-1} -> 0.010280196
B23: 41395 | C23: -0.0043495637 | D23: -0.048668347 | E23: -0.046594298 | F23: -0.010911084 | G23: -0.003965371 | I23: C2 | J23: =CORREL(D6:D183,C6:C183) -> 0.56714271 | K23: =CORREL(D6:D183,D6:D183) -> 1 | L23: =CORREL(D6:D183,E6:E183) -> 0.31784804 | M23: =CORREL(D6:D183,F6:F183) -> 0.37433052 | N23: =CORREL(D6:D183,G6:G183) -> 0.1294642 | O23: {=PRODUCT(1+C18:C23)-1} -> 0.066775821 | P23: {=PRODUCT(1+D18:D23)-1} -> -0.0066329142 | Q23: {=PRODUCT(1+E18:E23)-1} -> 0.033150904 | R23: {=PRODUCT(1+F18:F23)-1} -> 0.036568607 | S23: {=PRODUCT(1+G18:G23)-1} -> 0.0054262666
B24: 41426 | C24: -0.00061951873 | D24: 0.016393527 | E24: 0.011782852 | F24: -0.01526715 | G24: -0.0023682963 | I24: C3 | J24: =CORREL(E6:E183,C6:C183) -> 0.47009699 | K24: =CORREL(E6:E183,D6:D183) -> 0.31784804 | L24: =CORREL(E6:E183,E6:E183) -> 1 | M24: =CORREL(E6:E183,F6:F183) -> 0.76710855 | N24: =CORREL(E6:E183,G6:G183) -> 0.060276079 | O24: {=PRODUCT(1+C19:C24)-1} -> 0.050406393 | P24: {=PRODUCT(1+D19:D24)-1} -> 0.0061418444 | Q24: {=PRODUCT(1+E19:E24)-1} -> 0.033638061 | R24: {=PRODUCT(1+F19:F24)-1} -> 0.0038929567 | S24: {=PRODUCT(1+G19:G24)-1} -> -0.016227193
B25: 41456 | C25: 0.010837024 | D25: 0.013824853 | E25: 0.03566155 | F25: 0.020731455 | G25: 0.019353381 | I25: C4 | J25: =CORREL(F6:F183,C6:C183) -> 0.57925357 | K25: =CORREL(F6:F183,D6:D183) -> 0.37433052 | L25: =CORREL(F6:F183,E6:E183) -> 0.76710855 | M25: =CORREL(F6:F183,F6:F183) -> 1 | N25: =CORREL(F6:F183,G6:G183) -> 0.28574389 | O25: {=PRODUCT(1+C20:C25)-1} -> 0.057820865 | P25: {=PRODUCT(1+D20:D25)-1} -> 0.0095238587 | Q25: {=PRODUCT(1+E20:E25)-1} -> 0.045992541 | R25: {=PRODUCT(1+F20:F25)-1} -> 0.024591174 | S25: {=PRODUCT(1+G20:G25)-1} -> -0.022364629
B26: 41487 | C26: -0.0041499863 | D26: 0.0068182364 | E26: -0.021050456 | F26: -0.0064282109 | G26: -0.0030812249 | I26: USD | J26: =CORREL(G6:G183,C6:C183) -> 0.2051897 | K26: =CORREL(G6:G183,D6:D183) -> 0.1294642 | L26: =CORREL(G6:G183,E6:E183) -> 0.060276079 | M26: =CORREL(G6:G183,F6:F183) -> 0.28574389 | N26: =CORREL(G6:G183,G6:G183) -> 1 | O26: {=PRODUCT(1+C21:C26)-1} -> 0.044169364 | P26: {=PRODUCT(1+D21:D26)-1} -> -0.0086053017 | Q26: {=PRODUCT(1+E21:E26)-1} -> -0.0097527221 | R26: {=PRODUCT(1+F21:F26)-1} -> 0.011348651 | S26: {=PRODUCT(1+G21:G26)-1} -> 0.0055540166
B27: 41518 | C27: -0.011216256 | D27: -0.013544056 | E27: 0.021662205 | F27: 0.0082312617 | G27: 0.020526711 | O27: {=PRODUCT(1+C22:C27)-1} -> 0.02922059 | P27: {=PRODUCT(1+D22:D27)-1} -> -0.043432611 | Q27: {=PRODUCT(1+E22:E27)-1} -> 0.013864564 | R27: {=PRODUCT(1+F22:F27)-1} -> 0.012682543 | S27: {=PRODUCT(1+G22:G27)-1} -> 0.053685032
B28: 41548 | C28: 0.018620367 | D28: 0.013730016 | E28: 0.010226424 | F28: 0.017258223 | G28: 0.016935446 | I28: LISSAGE DES VL PRIVÉES (Geltner) - entrées du classeur DIC v2.3 | O28: {=PRODUCT(1+C23:C28)-1} -> 0.0088497685 | P28: {=PRODUCT(1+D23:D28)-1} -> -0.013021155 | Q28: {=PRODUCT(1+E23:E28)-1} -> 0.0094138809 | R28: {=PRODUCT(1+F23:F28)-1} -> 0.013108314 | S28: {=PRODUCT(1+G23:G28)-1} -> 0.047965497
B29: 41579 | C29: -0.022146043 | D29: -0.019980583 | E29: 0.05414637 | F29: 0.0048477274 | G29: -0.0094750635 | I29: Autocorrélation d'ordre 1 des rendements trimestriels Preqin Infrastructure | J29: 0.1169 | O29: {=PRODUCT(1+C24:C29)-1} -> -0.0091826388 | P29: {=PRODUCT(1+D24:D29)-1} -> 0.016741564 | Q29: {=PRODUCT(1+E24:E29)-1} -> 0.1160726 | R29: {=PRODUCT(1+F24:F29)-1} -> 0.029249818 | S29: {=PRODUCT(1+G24:G29)-1} -> 0.042168542
B30: 41609 | C30: 0.020679211 | D30: 0.039170444 | E30: -0.0099713461 | F30: 0.0061965707 | G30: 0.015895361 | I30: Volatilité annualisée brute (Preqin Infrastructure) | J30: 0.0297 | O30: {=PRODUCT(1+C25:C30)-1} -> 0.011933595 | P30: {=PRODUCT(1+D25:D30)-1} -> 0.03952628 | Q30: {=PRODUCT(1+E25:E30)-1} -> 0.092076081 | R30: {=PRODUCT(1+F25:F30)-1} -> 0.051683853 | S30: {=PRODUCT(1+G25:G30)-1} -> 0.061247536
B31: 41640 | C31: -0.0013602363 | D31: -0.035311994 | E31: -0.0045480877 | F31: 0.0024459671 | G31: -0.018195873 | I31: Volatilité annualisée désmoothée (Preqin Infrastructure) | J31: 0.0334 | O31: {=PRODUCT(1+C26:C31)-1} -> -0.00027689735 | P31: {=PRODUCT(1+D26:D31)-1} -> -0.010856233 | Q31: {=PRODUCT(1+E26:E31)-1} -> 0.049676144 | R31: {=PRODUCT(1+F26:F31)-1} -> 0.032843881 | S31: {=PRODUCT(1+G26:G31)-1} -> 0.022155055
B32: 41671 | C32: 0.023745238 | D32: 0.018390838 | E32: 0.017424125 | F32: 0.013277804 | G32: 0.010965963 | I32: Autocorrélation mensuelle après interpolation (variante ordre 2, infra) | J32: 0.7126 | O32: {=PRODUCT(1+C27:C32)-1} -> 0.027726818 | P32: {=PRODUCT(1+D27:D32)-1} -> 0.00051321419 | Q32: {=PRODUCT(1+E27:E32)-1} -> 0.090930415 | R32: {=PRODUCT(1+F27:F32)-1} -> 0.053328799 | S32: {=PRODUCT(1+G27:G32)-1} -> 0.036557837
B33: 41699 | C33: 0.0081602121 | D33: -0.0045144548 | E33: -0.0096044805 | F33: 0.0013887891 | G33: 0.003259253 | I33: VEV proxy privé désmoothé (DIC) | J33: 0.0502 | O33: {=PRODUCT(1+C28:C33)-1} -> 0.047866425 | P33: {=PRODUCT(1+D28:D33)-1} -> 0.00967149 | Q33: {=PRODUCT(1+E28:E33)-1} -> 0.057543863 | R33: {=PRODUCT(1+F28:F33)-1} -> 0.046180267 | S33: {=PRODUCT(1+G28:G33)-1} -> 0.01901913
B34: 41730 | C34: -0.0013375981 | D34: 0.027382162 | E34: -0.02623023 | F34: 0.0041364729 | G34: 0.00447568 | I34: VEV contrôle coté retenue (DIC) | J34: 0.1088 | O34: {=PRODUCT(1+C29:C34)-1} -> 0.027335438 | P34: {=PRODUCT(1+D29:D34)-1} -> 0.023268978 | Q34: {=PRODUCT(1+E29:E34)-1} -> 0.019379636 | R34: {=PRODUCT(1+F29:F34)-1} -> 0.032685448 | S34: {=PRODUCT(1+G29:G34)-1} -> 0.0065338346
B35: 41760 | C35: 0.016161825 | D35: 0.024282466 | E35: 0.0020381947 | F35: 0.0070858913 | G35: -0.012966531 | I35: Rapport de lissage 1 / (1 - AR1) | J35: =1/(1-G_ar1) -> 1.1323746 | O35: {=PRODUCT(1+C30:C35)-1} -> 0.067581766 | P35: {=PRODUCT(1+D30:D35)-1} -> 0.069485414 | Q35: {=PRODUCT(1+E30:E35)-1} -> -0.031009963 | R35: {=PRODUCT(1+F30:F35)-1} -> 0.034985616 | S35: {=PRODUCT(1+G30:G35)-1} -> 0.0029859377
B36: 41791 | C36: 0.017691898 | D36: -0.012930841 | E36: 0.059606265 | F36: 0.0054512824 | G36: 0.00072314735 | I36: Transmission implicite des chocs cotés = VEV privée / VEV cotée | J36: =VEV_priv/VEV_cote -> 0.46139706 | O36: {=PRODUCT(1+C31:C36)-1} -> 0.064457179 | P36: {=PRODUCT(1+D31:D36)-1} -> 0.015864217 | Q36: {=PRODUCT(1+E31:E36)-1} -> 0.037089088 | R36: {=PRODUCT(1+F31:F36)-1} -> 0.034219004 | S36: {=PRODUCT(1+G31:G36)-1} -> -0.011993476
B37: 41821 | C37: 0.0091554238 | D37: -0.0042025325 | E37: -0.04980177 | F37: -0.011854498 | G37: -0.018205147 | I37: Volatilité du composite coté C1 / volatilité désmoothée Preqin | J37: ='MST Données'!$J$9/G_vol_desm -> 2.4996655 | O37: {=PRODUCT(1+C32:C37)-1} -> 0.075665895 | P37: {=PRODUCT(1+D32:D37)-1} -> 0.048624019 | Q37: {=PRODUCT(1+E32:E37)-1} -> -0.010057439 | R37: {=PRODUCT(1+F32:F37)-1} -> 0.019465278 | S37: {=PRODUCT(1+G32:G37)-1} -> -0.012002809
B38: 41852 | C38: 0.028471941 | D38: 0.024123321 | E38: 0.02716562 | F38: 0.013063459 | G38: -0.019517946 | I38: Lecture : les VL d'expertise lissent les chocs ; la transmission retenue dans l'onglet Paramètres (0,5 par défaut) est cohérente avec le rapport VEV privée / VEV cotée. Une transmission de 1 reviendrait à valoriser les fonds cibles comme des actifs cotés. | O38: {=PRODUCT(1+C33:C38)-1} -> 0.080632319 | P38: {=PRODUCT(1+D33:D38)-1} -> 0.054526684 | Q38: {=PRODUCT(1+E33:E38)-1} -> -0.00057907013 | R38: {=PRODUCT(1+F33:F38)-1} -> 0.019249624 | S38: {=PRODUCT(1+G33:G38)-1} -> -0.041794135
B39: 41883 | C39: -0.0019375728 | D39: 0.010706549 | E39: -0.041462942 | F39: -0.014814407 | G39: -0.033783046 | O39: {=PRODUCT(1+C34:C39)-1} -> 0.06980865 | P39: {=PRODUCT(1+D34:D39)-1} -> 0.070650429 | Q39: {=PRODUCT(1+E34:E39)-1} -> -0.032727856 | R39: {=PRODUCT(1+F34:F39)-1} -> 0.0027574263 | S39: {=PRODUCT(1+G34:G39)-1} -> -0.077172974
B40: 41913 | C40: 0.020073418 | D40: -0.03373828 | E40: 0.00034341599 | F40: 0.0075102046 | G40: -0.0061049158 | O40: {=PRODUCT(1+C35:C40)-1} -> 0.09274502 | P40: {=PRODUCT(1+D35:D40)-1} -> 0.0069558957 | Q40: {=PRODUCT(1+E35:E40)-1} -> -0.0063315258 | R40: {=PRODUCT(1+F35:F40)-1} -> 0.0061265246 | S40: {=PRODUCT(1+G35:G40)-1} -> -0.086893528
B41: 41944 | C41: 0.00034898704 | D41: 0.035087992 | E41: 0.015157344 | F41: -0.00022976317 | G41: -0.013905587 | O41: {=PRODUCT(1+C36:C41)-1} -> 0.075740445 | P41: {=PRODUCT(1+D36:D41)-1} -> 0.017578637 | Q41: {=PRODUCT(1+E36:E41)-1} -> 0.006678043 | R41: {=PRODUCT(1+F36:F41)-1} -> -0.0011821608 | S41: {=PRODUCT(1+G36:G41)-1} -> -0.08776225
B42: 41974 | C42: 0.0055384333 | D42: 0.036016926 | E42: -0.041689658 | F42: -0.0065875955 | G42: -0.022183551 | O42: {=PRODUCT(1+C37:C42)-1} -> 0.062893754 | P42: {=PRODUCT(1+D37:D42)-1} -> 0.068039338 | Q42: {=PRODUCT(1+E37:E42)-1} -> -0.089558063 | R42: {=PRODUCT(1+F37:F42)-1} -> -0.013141613 | S42: {=PRODUCT(1+G37:G42)-1} -> -0.1086435
B43: 42005 | C43: 0.016393843 | D43: -0.022340895 | E43: 0.027177 | F43: 0.0045236133 | G43: -0.071870511 | O43: {=PRODUCT(1+C38:C43)-1} -> 0.070517624 | P43: {=PRODUCT(1+D38:D43)-1} -> 0.048585095 | Q43: {=PRODUCT(1+E38:E43)-1} -> -0.015800085 | R43: {=PRODUCT(1+F38:F43)-1} -> 0.0032151658 | S43: {=PRODUCT(1+G38:G43)-1} -> -0.15736547
B44: 42036 | C44: 0.015397001 | D44: -0.025104571 | E44: 0.046905105 | F44: 0.017509998 | G44: -0.0079728394 | O44: {=PRODUCT(1+C39:C44)-1} -> 0.056908159 | P44: {=PRODUCT(1+D39:D44)-1} -> -0.001818633 | Q44: {=PRODUCT(1+E39:E44)-1} -> 0.0031137082 | R44: {=PRODUCT(1+F39:F44)-1} -> 0.0076184785 | S44: {=PRODUCT(1+G39:G44)-1} -> -0.1474435
B45: 42064 | C45: 0.012688198 | D45: 0.0085835918 | E45: 0.0093524209 | F45: -0.0045124374 | G45: -0.032837396 | O45: {=PRODUCT(1+C40:C45)-1} -> 0.072396264 | P45: {=PRODUCT(1+D40:D45)-1} -> -0.0039152818 | Q45: {=PRODUCT(1+E40:E45)-1} -> 0.056292233 | R45: {=PRODUCT(1+F40:F45)-1} -> 0.018155027 | S45: {=PRODUCT(1+G40:G45)-1} -> -0.1466091
B46: 42095 | C46: 0.0040694847 | D46: -0.021121189 | E46: 0.00080366296 | F46: 0.0057748413 | G46: 0.02622985 | O46: {=PRODUCT(1+C41:C46)-1} -> 0.055571437 | P46: {=PRODUCT(1+D41:D46)-1} -> 0.0090912275 | Q46: {=PRODUCT(1+E41:E46)-1} -> 0.056778222 | R46: {=PRODUCT(1+F41:F46)-1} -> 0.016401328 | S46: {=PRODUCT(1+G41:G46)-1} -> -0.11884541
B47: 42125 | C47: 0.007361784 | D47: 0.01825248 | E47: -0.013858768 | F47: 0.0029741193 | G47: -0.013853898 | O47: {=PRODUCT(1+C42:C47)-1} -> 0.062971363 | P47: {=PRODUCT(1+D42:D47)-1} -> -0.0073214521 | Q47: {=PRODUCT(1+E42:E47)-1} -> 0.026572466 | R47: {=PRODUCT(1+F42:F47)-1} -> 0.019658507 | S47: {=PRODUCT(1+G42:G47)-1} -> -0.11879922
B48: 42156 | C48: 0.00035706862 | D48: -0.018192321 | E48: -0.0092847998 | F48: -0.016879879 | G48: 0.023961074 | O48: {=PRODUCT(1+C43:C48)-1} -> 0.057494057 | P48: {=PRODUCT(1+D43:D48)-1} -> -0.059263033 | Q48: {=PRODUCT(1+E43:E48)-1} -> 0.061285578 | R48: {=PRODUCT(1+F43:F48)-1} -> 0.0090942994 | S48: {=PRODUCT(1+G43:G48)-1} -> -0.07721403
B49: 42186 | C49: -0.021715629 | D49: -0.0012920974 | E49: -0.025516808 | F49: 0.0013552986 | G49: -0.025280559 | O49: {=PRODUCT(1+C44:C49)-1} -> 0.017843541 | P49: {=PRODUCT(1+D44:D49)-1} -> -0.039009161 | Q49: {=PRODUCT(1+E44:E49)-1} -> 0.006842013 | R49: {=PRODUCT(1+F44:F49)-1} -> 0.0059115685 | S49: {=PRODUCT(1+G44:G49)-1} -> -0.030892311
B50: 42217 | C50: -0.01807334 | D50: 0.0091594883 | E50: -0.0061227835 | F50: -0.011781777 | G50: 0.025119373 | O50: {=PRODUCT(1+C45:C50)-1} -> -0.015707445 | P50: {=PRODUCT(1+D45:D50)-1} -> -0.0052337978 | Q50: {=PRODUCT(1+E45:E50)-1} -> -0.044156597 | R50: {=PRODUCT(1+F45:F50)-1} -> -0.023046314 | S50: {=PRODUCT(1+G45:G50)-1} -> 0.00143535
... B183: 46266 | C183: -0.02374441 | D183: -0.007079198 | E183: -0.035289364 | F183: -0.014839086 | G183: -0.021411453 | O183: {=PRODUCT(1+C178:C183)-1} -> 0.024375874 | P183: {=PRODUCT(1+D178:D183)-1} -> 0.12691424 | Q183: {=PRODUCT(1+E178:E183)-1} -> 0.090318127 | R183: {=PRODUCT(1+F178:F183)-1} -> 0.018117403 | S183: {=PRODUCT(1+G178:G183)-1} -> -0.010399499

Sheet MST Scénarios
B2: MST - CHOCS DE MARCHÉ PAR SCÉNARIO ET PAR SEMESTRE, RENDEMENT DES LIGNES ET TRAJECTOIRE DE VL
B3: Chocs des facteurs cotés = profil en σ (Paramètres H) × écart-type semestriel du facteur (MST Données). Rendement d'une ligne = dérive (TRI cible / 2) + transmission × choc du proxy (part immédiate et part retardée d'un semestre) + effet dollar + courbe en J. Trajectoire de VL hors flux de passif (effet marché pur), reprise par le moteur LST.
B5: S1 - BASE Rachats courants, collecte normale, marchés stables
B6: Semestre | C6: 1 | D6: 2 | E6: 3 | F6: 4 | G6: 5 | H6: 6 | I6: 7 | J6: 8 | K6: Lecture
B7: Date de fin de semestre | C7: =EDATE(Date_depart,0) -> 47118 | D7: =EDATE(Date_depart,6) -> 47299 | E7: =EDATE(Date_depart,12) -> 47483 | F7: =EDATE(Date_depart,18) -> 47664 | G7: =EDATE(Date_depart,24) -> 47848 | H7: =EDATE(Date_depart,30) -> 48029 | I7: =EDATE(Date_depart,36) -> 48213 | J7: =EDATE(Date_depart,42) -> 48395
B8: Profil de choc (σ) | C8: =Paramètres!$C$161 -> -0.5 | D8: =Paramètres!$D$161 -> 0 | E8: =Paramètres!$E$161 -> 0 | F8: =Paramètres!$F$161 -> 0 | G8: =Paramètres!$G$161 -> 0 | H8: =Paramètres!$H$161 -> 0 | I8: =Paramètres!$I$161 -> 0 | J8: =Paramètres!$J$161 -> 0 | K8: Paramètres H
B9: Choc C1 Infrastructure cotée | C9: =Paramètres!$C$161*'MST Données'!$J$10 -> -0.029517758 | D9: =Paramètres!$D$161*'MST Données'!$J$10 -> 0 | E9: =Paramètres!$E$161*'MST Données'!$J$10 -> 0 | F9: =Paramètres!$F$161*'MST Données'!$J$10 -> 0 | G9: =Paramètres!$G$161*'MST Données'!$J$10 -> 0 | H9: =Paramètres!$H$161*'MST Données'!$J$10 -> 0 | I9: =Paramètres!$I$161*'MST Données'!$J$10 -> 0 | J9: =Paramètres!$J$161*'MST Données'!$J$10 -> 0 | K9: σ semestriel du facteur × profil
B10: Choc C3 Direct lending coté | C10: =Paramètres!$C$161*'MST Données'!$L$10 -> -0.064554741 | D10: =Paramètres!$D$161*'MST Données'!$L$10 -> 0 | E10: =Paramètres!$E$161*'MST Données'!$L$10 -> 0 | F10: =Paramètres!$F$161*'MST Données'!$L$10 -> 0 | G10: =Paramètres!$G$161*'MST Données'!$L$10 -> 0 | H10: =Paramètres!$H$161*'MST Données'!$L$10 -> 0 | I10: =Paramètres!$I$161*'MST Données'!$L$10 -> 0 | J10: =Paramètres!$J$161*'MST Données'!$L$10 -> 0 | K10: σ semestriel du facteur × profil
B11: Choc C4 Crédit HY coté | C11: =Paramètres!$C$161*'MST Données'!$M$10 -> -0.019397735 | D11: =Paramètres!$D$161*'MST Données'!$M$10 -> 0 | E11: =Paramètres!$E$161*'MST Données'!$M$10 -> 0 | F11: =Paramètres!$F$161*'MST Données'!$M$10 -> 0 | G11: =Paramètres!$G$161*'MST Données'!$M$10 -> 0 | H11: =Paramètres!$H$161*'MST Données'!$M$10 -> 0 | I11: =Paramètres!$I$161*'MST Données'!$M$10 -> 0 | J11: =Paramètres!$J$161*'MST Données'!$M$10 -> 0 | K11: σ semestriel du facteur × profil
B12: Choc dollar (EUR/USD) | C12: =Paramètres!$C$166 -> 0 | D12: =Paramètres!$D$166 -> 0 | E12: =Paramètres!$E$166 -> 0 | F12: =Paramètres!$F$166 -> 0 | G12: =Paramètres!$G$166 -> 0 | H12: =Paramètres!$H$166 -> 0 | I12: =Paramètres!$I$166 -> 0 | J12: =Paramètres!$J$166 -> 0 | K12: Paramètres H, en %
B13: Choc proxy Ares (60 % C1, 20 % C3, 20 % C4) | C13: =0.6*C9+0.2*C10+0.2*C11 -> -0.03450115 | D13: =0.6*D9+0.2*D10+0.2*D11 -> 0 | E13: =0.6*E9+0.2*E10+0.2*E11 -> 0 | F13: =0.6*F9+0.2*F10+0.2*F11 -> 0 | G13: =0.6*G9+0.2*G10+0.2*G11 -> 0 | H13: =0.6*H9+0.2*H10+0.2*H11 -> 0 | I13: =0.6*I9+0.2*I10+0.2*I11 -> 0 | J13: =0.6*J9+0.2*J10+0.2*J11 -> 0 | K13: Mix de la documentation Ares
B15: Rendement semestriel de la ligne | C15: 1 | D15: 2 | E15: 3 | F15: 4 | G15: 5 | H15: 6 | I15: 7 | J15: 8 | K15: Composition
B16: MAPIF II | C16: =Paramètres!$C$79/2+Paramètres!$F$79*((1-Paramètres!$G$79)*C9)+Paramètres!$H$79*C12+IF(AND(C9<0,"S1"<>"S1",1<=2),Paramètres!$I$79,0) -> 0.060120561 | D16: =Paramètres!$C$79/2+Paramètres!$F$79*((1-Paramètres!$G$79)*D9+Paramètres!$G$79*C9)+Paramètres!$H$79*D12+IF(AND(D9<0,"S1"<>"S1",2<=2),Paramètres!$I$79,0) -> 0.060120561 | E16: =Paramètres!$C$79/2+Paramètres!$F$79*((1-Paramètres!$G$79)*E9+Paramètres!$G$79*D9)+Paramètres!$H$79*E12+IF(AND(E9<0,"S1"<>"S1",3<=2),Paramètres!$I$79,0) -> 0.0675 | F16: =Paramètres!$C$79/2+Paramètres!$F$79*((1-Paramètres!$G$79)*F9+Paramètres!$G$79*E9)+Paramètres!$H$79*F12+IF(AND(F9<0,"S1"<>"S1",4<=2),Paramètres!$I$79,0) -> 0.0675 | G16: =Paramètres!$C$79/2+Paramètres!$F$79*((1-Paramètres!$G$79)*G9+Paramètres!$G$79*F9)+Paramètres!$H$79*G12+IF(AND(G9<0,"S1"<>"S1",5<=2),Paramètres!$I$79,0) -> 0.0675 | H16: =Paramètres!$C$79/2+Paramètres!$F$79*((1-Paramètres!$G$79)*H9+Paramètres!$G$79*G9)+Paramètres!$H$79*H12+IF(AND(H9<0,"S1"<>"S1",6<=2),Paramètres!$I$79,0) -> 0.0675 | I16: =Paramètres!$C$79/2+Paramètres!$F$79*((1-Paramètres!$G$79)*I9+Paramètres!$G$79*H9)+Paramètres!$H$79*I12+IF(AND(I9<0,"S1"<>"S1",7<=2),Paramètres!$I$79,0) -> 0.0675 | J16: =Paramètres!$C$79/2+Paramètres!$F$79*((1-Paramètres!$G$79)*J9+Paramètres!$G$79*I9)+Paramètres!$H$79*J12+IF(AND(J9<0,"S1"<>"S1",8<=2),Paramètres!$I$79,0) -> 0.0675 | K16: Dérive + transmission × choc C1 (retard d'un semestre) + dollar + courbe en J
B17: MSIG 3 | C17: =Paramètres!$C$80/2+Paramètres!$F$80*((1-Paramètres!$G$80)*C10)+Paramètres!$H$80*C12+IF(AND(C10<0,"S1"<>"S1",1<=2),Paramètres!$I$80,0) -> 0.038861315 | D17: =Paramètres!$C$80/2+Paramètres!$F$80*((1-Paramètres!$G$80)*D10+Paramètres!$G$80*C10)+Paramètres!$H$80*D12+IF(AND(D10<0,"S1"<>"S1",2<=2),Paramètres!$I$80,0) -> 0.038861315 | E17: =Paramètres!$C$80/2+Paramètres!$F$80*((1-Paramètres!$G$80)*E10+Paramètres!$G$80*D10)+Paramètres!$H$80*E12+IF(AND(E10<0,"S1"<>"S1",3<=2),Paramètres!$I$80,0) -> 0.055 | F17: =Paramètres!$C$80/2+Paramètres!$F$80*((1-Paramètres!$G$80)*F10+Paramètres!$G$80*E10)+Paramètres!$H$80*F12+IF(AND(F10<0,"S1"<>"S1",4<=2),Paramètres!$I$80,0) -> 0.055 | G17: =Paramètres!$C$80/2+Paramètres!$F$80*((1-Paramètres!$G$80)*G10+Paramètres!$G$80*F10)+Paramètres!$H$80*G12+IF(AND(G10<0,"S1"<>"S1",5<=2),Paramètres!$I$80,0) -> 0.055 | H17: =Paramètres!$C$80/2+Paramètres!$F$80*((1-Paramètres!$G$80)*H10+Paramètres!$G$80*G10)+Paramètres!$H$80*H12+IF(AND(H10<0,"S1"<>"S1",6<=2),Paramètres!$I$80,0) -> 0.055 | I17: =Paramètres!$C$80/2+Paramètres!$F$80*((1-Paramètres!$G$80)*I10+Paramètres!$G$80*H10)+Paramètres!$H$80*I12+IF(AND(I10<0,"S1"<>"S1",7<=2),Paramètres!$I$80,0) -> 0.055 | J17: =Paramètres!$C$80/2+Paramètres!$F$80*((1-Paramètres!$G$80)*J10+Paramètres!$G$80*I10)+Paramètres!$H$80*J12+IF(AND(J10<0,"S1"<>"S1",8<=2),Paramètres!$I$80,0) -> 0.055 | K17: Dérive + transmission × choc C3 (retard d'un semestre) + dollar + courbe en J
B18: PG NGI | C18: =Paramètres!$C$81/2+Paramètres!$F$81*((1-Paramètres!$G$81)*C9)+Paramètres!$H$81*C12+IF(AND(C9<0,"S1"<>"S1",1<=2),Paramètres!$I$81,0) -> 0.050120561 | D18: =Paramètres!$C$81/2+Paramètres!$F$81*((1-Paramètres!$G$81)*D9+Paramètres!$G$81*C9)+Paramètres!$H$81*D12+IF(AND(D9<0,"S1"<>"S1",2<=2),Paramètres!$I$81,0) -> 0.050120561 | E18: =Paramètres!$C$81/2+Paramètres!$F$81*((1-Paramètres!$G$81)*E9+Paramètres!$G$81*D9)+Paramètres!$H$81*E12+IF(AND(E9<0,"S1"<>"S1",3<=2),Paramètres!$I$81,0) -> 0.0575 | F18: =Paramètres!$C$81/2+Paramètres!$F$81*((1-Paramètres!$G$81)*F9+Paramètres!$G$81*E9)+Paramètres!$H$81*F12+IF(AND(F9<0,"S1"<>"S1",4<=2),Paramètres!$I$81,0) -> 0.0575 | G18: =Paramètres!$C$81/2+Paramètres!$F$81*((1-Paramètres!$G$81)*G9+Paramètres!$G$81*F9)+Paramètres!$H$81*G12+IF(AND(G9<0,"S1"<>"S1",5<=2),Paramètres!$I$81,0) -> 0.0575 | H18: =Paramètres!$C$81/2+Paramètres!$F$81*((1-Paramètres!$G$81)*H9+Paramètres!$G$81*G9)+Paramètres!$H$81*H12+IF(AND(H9<0,"S1"<>"S1",6<=2),Paramètres!$I$81,0) -> 0.0575 | I18: =Paramètres!$C$81/2+Paramètres!$F$81*((1-Paramètres!$G$81)*I9+Paramètres!$G$81*H9)+Paramètres!$H$81*I12+IF(AND(I9<0,"S1"<>"S1",7<=2),Paramètres!$I$81,0) -> 0.0575 | J18: =Paramètres!$C$81/2+Paramètres!$F$81*((1-Paramètres!$G$81)*J9+Paramètres!$G$81*I9)+Paramètres!$H$81*J12+IF(AND(J9<0,"S1"<>"S1",8<=2),Paramètres!$I$81,0) -> 0.0575 | K18: Dérive + transmission × choc C1 (retard d'un semestre) + dollar + courbe en J
B19: Ares AGI | C19: =Paramètres!$C$82/2+Paramètres!$F$82*((1-Paramètres!$G$82)*C13)+Paramètres!$H$82*C12+IF(AND(C13<0,"S1"<>"S1",1<=2),Paramètres!$I$82,0) -> 0.038874713 | D19: =Paramètres!$C$82/2+Paramètres!$F$82*((1-Paramètres!$G$82)*D13+Paramètres!$G$82*C13)+Paramètres!$H$82*D12+IF(AND(D13<0,"S1"<>"S1",2<=2),Paramètres!$I$82,0) -> 0.038874713 | E19: =Paramètres!$C$82/2+Paramètres!$F$82*((1-Paramètres!$G$82)*E13+Paramètres!$G$82*D13)+Paramètres!$H$82*E12+IF(AND(E13<0,"S1"<>"S1",3<=2),Paramètres!$I$82,0) -> 0.0475 | F19: =Paramètres!$C$82/2+Paramètres!$F$82*((1-Paramètres!$G$82)*F13+Paramètres!$G$82*E13)+Paramètres!$H$82*F12+IF(AND(F13<0,"S1"<>"S1",4<=2),Paramètres!$I$82,0) -> 0.0475 | G19: =Paramètres!$C$82/2+Paramètres!$F$82*((1-Paramètres!$G$82)*G13+Paramètres!$G$82*F13)+Paramètres!$H$82*G12+IF(AND(G13<0,"S1"<>"S1",5<=2),Paramètres!$I$82,0) -> 0.0475 | H19: =Paramètres!$C$82/2+Paramètres!$F$82*((1-Paramètres!$G$82)*H13+Paramètres!$G$82*G13)+Paramètres!$H$82*H12+IF(AND(H13<0,"S1"<>"S1",6<=2),Paramètres!$I$82,0) -> 0.0475 | I19: =Paramètres!$C$82/2+Paramètres!$F$82*((1-Paramètres!$G$82)*I13+Paramètres!$G$82*H13)+Paramètres!$H$82*I12+IF(AND(I13<0,"S1"<>"S1",7<=2),Paramètres!$I$82,0) -> 0.0475 | J19: =Paramètres!$C$82/2+Paramètres!$F$82*((1-Paramètres!$G$82)*J13+Paramètres!$G$82*I13)+Paramètres!$H$82*J12+IF(AND(J13<0,"S1"<>"S1",8<=2),Paramètres!$I$82,0) -> 0.0475 | K19: Dérive + transmission × choc ARES (retard d'un semestre) + dollar + courbe en J
B20: Fonds HY UCITS | C20: =Paramètres!$C$83/2+Paramètres!$F$83*((1-Paramètres!$G$83)*C11)+Paramètres!$H$83*C12+IF(AND(C11<0,"S1"<>"S1",1<=2),Paramètres!$I$83,0) -> 0.010602265 | D20: =Paramètres!$C$83/2+Paramètres!$F$83*((1-Paramètres!$G$83)*D11+Paramètres!$G$83*C11)+Paramètres!$H$83*D12+IF(AND(D11<0,"S1"<>"S1",2<=2),Paramètres!$I$83,0) -> 0.03 | E20: =Paramètres!$C$83/2+Paramètres!$F$83*((1-Paramètres!$G$83)*E11+Paramètres!$G$83*D11)+Paramètres!$H$83*E12+IF(AND(E11<0,"S1"<>"S1",3<=2),Paramètres!$I$83,0) -> 0.03 | F20: =Paramètres!$C$83/2+Paramètres!$F$83*((1-Paramètres!$G$83)*F11+Paramètres!$G$83*E11)+Paramètres!$H$83*F12+IF(AND(F11<0,"S1"<>"S1",4<=2),Paramètres!$I$83,0) -> 0.03 | G20: =Paramètres!$C$83/2+Paramètres!$F$83*((1-Paramètres!$G$83)*G11+Paramètres!$G$83*F11)+Paramètres!$H$83*G12+IF(AND(G11<0,"S1"<>"S1",5<=2),Paramètres!$I$83,0) -> 0.03 | H20: =Paramètres!$C$83/2+Paramètres!$F$83*((1-Paramètres!$G$83)*H11+Paramètres!$G$83*G11)+Paramètres!$H$83*H12+IF(AND(H11<0,"S1"<>"S1",6<=2),Paramètres!$I$83,0) -> 0.03 | I20: =Paramètres!$C$83/2+Paramètres!$F$83*((1-Paramètres!$G$83)*I11+Paramètres!$G$83*H11)+Paramètres!$H$83*I12+IF(AND(I11<0,"S1"<>"S1",7<=2),Paramètres!$I$83,0) -> 0.03 | J20: =Paramètres!$C$83/2+Paramètres!$F$83*((1-Paramètres!$G$83)*J11+Paramètres!$G$83*I11)+Paramètres!$H$83*J12+IF(AND(J11<0,"S1"<>"S1",8<=2),Paramètres!$I$83,0) -> 0.03 | K20: Dérive + transmission × choc C4 (retard d'un semestre) + dollar + courbe en J
B21: Trésorerie | C21: =Paramètres!$C$84/2 -> 0.0125 | D21: =Paramètres!$C$84/2 -> 0.0125 | E21: =Paramètres!$C$84/2 -> 0.0125 | F21: =Paramètres!$C$84/2 -> 0.0125 | G21: =Paramètres!$C$84/2 -> 0.0125 | H21: =Paramètres!$C$84/2 -> 0.0125 | I21: =Paramètres!$C$84/2 -> 0.0125 | J21: =Paramètres!$C$84/2 -> 0.0125 | K21: Taux monétaire / 2
B23: Rendement du portefeuille (poids de départ) | C23: =Paramètres!$D$68*C16+Paramètres!$D$69*C17+Paramètres!$D$70*C18+Paramètres!$D$71*C19+Paramètres!$D$72*C20+Paramètres!$D$73*C21 -> 0.044637287 | D23: =Paramètres!$D$68*D16+Paramètres!$D$69*D17+Paramètres!$D$70*D18+Paramètres!$D$71*D19+Paramètres!$D$72*D20+Paramètres!$D$73*D21 -> 0.046771038 | E23: =Paramètres!$D$68*E16+Paramètres!$D$69*E17+Paramètres!$D$70*E18+Paramètres!$D$71*E19+Paramètres!$D$72*E20+Paramètres!$D$73*E21 -> 0.053275 | F23: =Paramètres!$D$68*F16+Paramètres!$D$69*F17+Paramètres!$D$70*F18+Paramètres!$D$71*F19+Paramètres!$D$72*F20+Paramètres!$D$73*F21 -> 0.053275 | G23: =Paramètres!$D$68*G16+Paramètres!$D$69*G17+Paramètres!$D$70*G18+Paramètres!$D$71*G19+Paramètres!$D$72*G20+Paramètres!$D$73*G21 -> 0.053275 | H23: =Paramètres!$D$68*H16+Paramètres!$D$69*H17+Paramètres!$D$70*H18+Paramètres!$D$71*H19+Paramètres!$D$72*H20+Paramètres!$D$73*H21 -> 0.053275 | I23: =Paramètres!$D$68*I16+Paramètres!$D$69*I17+Paramètres!$D$70*I18+Paramètres!$D$71*I19+Paramètres!$D$72*I20+Paramètres!$D$73*I21 -> 0.053275 | J23: =Paramètres!$D$68*J16+Paramètres!$D$69*J17+Paramètres!$D$70*J18+Paramètres!$D$71*J19+Paramètres!$D$72*J20+Paramètres!$D$73*J21 -> 0.053275 | K23: Σ poids × rendement de ligne
B24: Indice de VL hors flux (base 100) | C24: =100*(1+C23) -> 104.46373 | D24: =C24*(1+D23) -> 109.34961 | E24: =D24*(1+E23) -> 115.17521 | F24: =E24*(1+F23) -> 121.31117 | G24: =F24*(1+G23) -> 127.77402 | H24: =G24*(1+H23) -> 134.58118 | I24: =H24*(1+I23) -> 141.75099 | J24: =I24*(1+J23) -> 149.30277 | K24: Effet marché seul
B25: Écart au départ | C25: =C24/100-1 -> 0.044637287 | D25: =D24/100-1 -> 0.093496058 | E25: =E24/100-1 -> 0.15175206 | F25: =F24/100-1 -> 0.21311165 | G25: =G24/100-1 -> 0.27774017 | H25: =H24/100-1 -> 0.34581178 | I25: =I24/100-1 -> 0.4175099 | J25: =J24/100-1 -> 0.49302774
B26: Pire écart cumulé (creux) | C26: =MIN(C25:J25) -> 0.044637287 | K26: Mesure retenue pour le verdict MST
B27: Semestre de retour au-dessus du niveau de départ | C27: =IFERROR(MATCH(TRUE(),INDEX(C25:J25>=0,0),0),"au-delà de 8") -> 1 | K27: Premier semestre où l'indice repasse 100
B28: Verdict MST | C28: =IF(-C26>S_mst_rouge,"Rouge",IF(-C26>S_mst_orange,"Orange","Vert")) -> Vert | K28: Vert ≤ 10 % ; Orange 10 à 25 % ; Rouge > 25 %
B30: S2 - PLAUSIBLE Correction de marché à 1,5 écart-type, rachats de 7,5 % sur deux dates, collecte divisée par deux
B31: Semestre | C31: 1 | D31: 2 | E31: 3 | F31: 4 | G31: 5 | H31: 6 | I31: 7 | J31: 8 | K31: Lecture
B32: Date de fin de semestre | C32: =EDATE(Date_depart,0) -> 47118 | D32: =EDATE(Date_depart,6) -> 47299 | E32: =EDATE(Date_depart,12) -> 47483 | F32: =EDATE(Date_depart,18) -> 47664 | G32: =EDATE(Date_depart,24) -> 47848 | H32: =EDATE(Date_depart,30) -> 48029 | I32: =EDATE(Date_depart,36) -> 48213 | J32: =EDATE(Date_depart,42) -> 48395
B33: Profil de choc (σ) | C33: =Paramètres!$C$162 -> -1.5 | D33: =Paramètres!$D$162 -> 0 | E33: =Paramètres!$E$162 -> 0.5 | F33: =Paramètres!$F$162 -> 0.5 | G33: =Paramètres!$G$162 -> 0 | H33: =Paramètres!$H$162 -> 0 | I33: =Paramètres!$I$162 -> 0 | J33: =Paramètres!$J$162 -> 0 | K33: Paramètres H
B34: Choc C1 Infrastructure cotée | C34: =Paramètres!$C$162*'MST Données'!$J$10 -> -0.088553273 | D34: =Paramètres!$D$162*'MST Données'!$J$10 -> 0 | E34: =Paramètres!$E$162*'MST Données'!$J$10 -> 0.029517758 | F34: =Paramètres!$F$162*'MST Données'!$J$10 -> 0.029517758 | G34: =Paramètres!$G$162*'MST Données'!$J$10 -> 0 | H34: =Paramètres!$H$162*'MST Données'!$J$10 -> 0 | I34: =Paramètres!$I$162*'MST Données'!$J$10 -> 0 | J34: =Paramètres!$J$162*'MST Données'!$J$10 -> 0 | K34: σ semestriel du facteur × profil
B35: Choc C3 Direct lending coté | C35: =Paramètres!$C$162*'MST Données'!$L$10 -> -0.19366422 | D35: =Paramètres!$D$162*'MST Données'!$L$10 -> 0 | E35: =Paramètres!$E$162*'MST Données'!$L$10 -> 0.064554741 | F35: =Paramètres!$F$162*'MST Données'!$L$10 -> 0.064554741 | G35: =Paramètres!$G$162*'MST Données'!$L$10 -> 0 | H35: =Paramètres!$H$162*'MST Données'!$L$10 -> 0 | I35: =Paramètres!$I$162*'MST Données'!$L$10 -> 0 | J35: =Paramètres!$J$162*'MST Données'!$L$10 -> 0 | K35: σ semestriel du facteur × profil
B36: Choc C4 Crédit HY coté | C36: =Paramètres!$C$162*'MST Données'!$M$10 -> -0.058193206 | D36: =Paramètres!$D$162*'MST Données'!$M$10 -> 0 | E36: =Paramètres!$E$162*'MST Données'!$M$10 -> 0.019397735 | F36: =Paramètres!$F$162*'MST Données'!$M$10 -> 0.019397735 | G36: =Paramètres!$G$162*'MST Données'!$M$10 -> 0 | H36: =Paramètres!$H$162*'MST Données'!$M$10 -> 0 | I36: =Paramètres!$I$162*'MST Données'!$M$10 -> 0 | J36: =Paramètres!$J$162*'MST Données'!$M$10 -> 0 | K36: σ semestriel du facteur × profil
B37: Choc dollar (EUR/USD) | C37: =Paramètres!$C$167 -> -0.05 | D37: =Paramètres!$D$167 -> 0 | E37: =Paramètres!$E$167 -> 0 | F37: =Paramètres!$F$167 -> 0 | G37: =Paramètres!$G$167 -> 0 | H37: =Paramètres!$H$167 -> 0 | I37: =Paramètres!$I$167 -> 0 | J37: =Paramètres!$J$167 -> 0 | K37: Paramètres H, en %
B38: Choc proxy Ares (60 % C1, 20 % C3, 20 % C4) | C38: =0.6*C34+0.2*C35+0.2*C36 -> -0.10350345 | D38: =0.6*D34+0.2*D35+0.2*D36 -> 0 | E38: =0.6*E34+0.2*E35+0.2*E36 -> 0.03450115 | F38: =0.6*F34+0.2*F35+0.2*F36 -> 0.03450115 | G38: =0.6*G34+0.2*G35+0.2*G36 -> 0 | H38: =0.6*H34+0.2*H35+0.2*H36 -> 0 | I38: =0.6*I34+0.2*I35+0.2*I36 -> 0 | J38: =0.6*J34+0.2*J35+0.2*J36 -> 0 | K38: Mix de la documentation Ares
B40: Rendement semestriel de la ligne | C40: 1 | D40: 2 | E40: 3 | F40: 4 | G40: 5 | H40: 6 | I40: 7 | J40: 8 | K40: Composition
B41: MAPIF II | C41: =Paramètres!$C$79/2+Paramètres!$F$79*((1-Paramètres!$G$79)*C34)+Paramètres!$H$79*C37+IF(AND(C34<0,"S2"<>"S1",1<=2),Paramètres!$I$79,0) -> -0.054638318 | D41: =Paramètres!$C$79/2+Paramètres!$F$79*((1-Paramètres!$G$79)*D34+Paramètres!$G$79*C34)+Paramètres!$H$79*D37+IF(AND(D34<0,"S2"<>"S1",2<=2),Paramètres!$I$79,0) -> 0.045361682 | E41: =Paramètres!$C$79/2+Paramètres!$F$79*((1-Paramètres!$G$79)*E34+Paramètres!$G$79*D34)+Paramètres!$H$79*E37+IF(AND(E34<0,"S2"<>"S1",3<=2),Paramètres!$I$79,0) -> 0.074879439 | F41: =Paramètres!$C$79/2+Paramètres!$F$79*((1-Paramètres!$G$79)*F34+Paramètres!$G$79*E34)+Paramètres!$H$79*F37+IF(AND(F34<0,"S2"<>"S1",4<=2),Paramètres!$I$79,0) -> 0.082258879 | G41: =Paramètres!$C$79/2+Paramètres!$F$79*((1-Paramètres!$G$79)*G34+Paramètres!$G$79*F34)+Paramètres!$H$79*G37+IF(AND(G34<0,"S2"<>"S1",5<=2),Paramètres!$I$79,0) -> 0.074879439 | H41: =Paramètres!$C$79/2+Paramètres!$F$79*((1-Paramètres!$G$79)*H34+Paramètres!$G$79*G34)+Paramètres!$H$79*H37+IF(AND(H34<0,"S2"<>"S1",6<=2),Paramètres!$I$79,0) -> 0.0675 | I41: =Paramètres!$C$79/2+Paramètres!$F$79*((1-Paramètres!$G$79)*I34+Paramètres!$G$79*H34)+Paramètres!$H$79*I37+IF(AND(I34<0,"S2"<>"S1",7<=2),Paramètres!$I$79,0) -> 0.0675 | J41: =Paramètres!$C$79/2+Paramètres!$F$79*((1-Paramètres!$G$79)*J34+Paramètres!$G$79*I34)+Paramètres!$H$79*J37+IF(AND(J34<0,"S2"<>"S1",8<=2),Paramètres!$I$79,0) -> 0.0675 | K41: Dérive + transmission × choc C1 (retard d'un semestre) + dollar + courbe en J
B42: MSIG 3 | C42: =Paramètres!$C$80/2+Paramètres!$F$80*((1-Paramètres!$G$80)*C35)+Paramètres!$H$80*C37+IF(AND(C35<0,"S2"<>"S1",1<=2),Paramètres!$I$80,0) -> -0.043416055 | D42: =Paramètres!$C$80/2+Paramètres!$F$80*((1-Paramètres!$G$80)*D35+Paramètres!$G$80*C35)+Paramètres!$H$80*D37+IF(AND(D35<0,"S2"<>"S1",2<=2),Paramètres!$I$80,0) -> 0.0065839445 | E42: =Paramètres!$C$80/2+Paramètres!$F$80*((1-Paramètres!$G$80)*E35+Paramètres!$G$80*D35)+Paramètres!$H$80*E37+IF(AND(E35<0,"S2"<>"S1",3<=2),Paramètres!$I$80,0) -> 0.071138685 | F42: =Paramètres!$C$80/2+Paramètres!$F$80*((1-Paramètres!$G$80)*F35+Paramètres!$G$80*E35)+Paramètres!$H$80*F37+IF(AND(F35<0,"S2"<>"S1",4<=2),Paramètres!$I$80,0) -> 0.08727737 | G42: =Paramètres!$C$80/2+Paramètres!$F$80*((1-Paramètres!$G$80)*G35+Paramètres!$G$80*F35)+Paramètres!$H$80*G37+IF(AND(G35<0,"S2"<>"S1",5<=2),Paramètres!$I$80,0) -> 0.071138685 | H42: =Paramètres!$C$80/2+Paramètres!$F$80*((1-Paramètres!$G$80)*H35+Paramètres!$G$80*G35)+Paramètres!$H$80*H37+IF(AND(H35<0,"S2"<>"S1",6<=2),Paramètres!$I$80,0) -> 0.055 | I42: =Paramètres!$C$80/2+Paramètres!$F$80*((1-Paramètres!$G$80)*I35+Paramètres!$G$80*H35)+Paramètres!$H$80*I37+IF(AND(I35<0,"S2"<>"S1",7<=2),Paramètres!$I$80,0) -> 0.055 | J42: =Paramètres!$C$80/2+Paramètres!$F$80*((1-Paramètres!$G$80)*J35+Paramètres!$G$80*I35)+Paramètres!$H$80*J37+IF(AND(J35<0,"S2"<>"S1",8<=2),Paramètres!$I$80,0) -> 0.055 | K42: Dérive + transmission × choc C3 (retard d'un semestre) + dollar + courbe en J
B43: PG NGI | C43: =Paramètres!$C$81/2+Paramètres!$F$81*((1-Paramètres!$G$81)*C34)+Paramètres!$H$81*C37+IF(AND(C34<0,"S2"<>"S1",1<=2),Paramètres!$I$81,0) -> 0.035361682 | D43: =Paramètres!$C$81/2+Paramètres!$F$81*((1-Paramètres!$G$81)*D34+Paramètres!$G$81*C34)+Paramètres!$H$81*D37+IF(AND(D34<0,"S2"<>"S1",2<=2),Paramètres!$I$81,0) -> 0.035361682 | E43: =Paramètres!$C$81/2+Paramètres!$F$81*((1-Paramètres!$G$81)*E34+Paramètres!$G$81*D34)+Paramètres!$H$81*E37+IF(AND(E34<0,"S2"<>"S1",3<=2),Paramètres!$I$81,0) -> 0.064879439 | F43: =Paramètres!$C$81/2+Paramètres!$F$81*((1-Paramètres!$G$81)*F34+Paramètres!$G$81*E34)+Paramètres!$H$81*F37+IF(AND(F34<0,"S2"<>"S1",4<=2),Paramètres!$I$81,0) -> 0.072258879 | G43: =Paramètres!$C$81/2+Paramètres!$F$81*((1-Paramètres!$G$81)*G34+Paramètres!$G$81*F34)+Paramètres!$H$81*G37+IF(AND(G34<0,"S2"<>"S1",5<=2),Paramètres!$I$81,0) -> 0.064879439 | H43: =Paramètres!$C$81/2+Paramètres!$F$81*((1-Paramètres!$G$81)*H34+Paramètres!$G$81*G34)+Paramètres!$H$81*H37+IF(AND(H34<0,"S2"<>"S1",6<=2),Paramètres!$I$81,0) -> 0.0575 | I43: =Paramètres!$C$81/2+Paramètres!$F$81*((1-Paramètres!$G$81)*I34+Paramètres!$G$81*H34)+Paramètres!$H$81*I37+IF(AND(I34<0,"S2"<>"S1",7<=2),Paramètres!$I$81,0) -> 0.0575 | J43: =Paramètres!$C$81/2+Paramètres!$F$81*((1-Paramètres!$G$81)*J34+Paramètres!$G$81*I34)+Paramètres!$H$81*J37+IF(AND(J34<0,"S2"<>"S1",8<=2),Paramètres!$I$81,0) -> 0.0575 | K43: Dérive + transmission × choc C1 (retard d'un semestre) + dollar + courbe en J
B44: Ares AGI | C44: =Paramètres!$C$82/2+Paramètres!$F$82*((1-Paramètres!$G$82)*C38)+Paramètres!$H$82*C37+IF(AND(C38<0,"S2"<>"S1",1<=2),Paramètres!$I$82,0) -> -0.0083758623 | D44: =Paramètres!$C$82/2+Paramètres!$F$82*((1-Paramètres!$G$82)*D38+Paramètres!$G$82*C38)+Paramètres!$H$82*D37+IF(AND(D38<0,"S2"<>"S1",2<=2),Paramètres!$I$82,0) -> 0.021624138 | E44: =Paramètres!$C$82/2+Paramètres!$F$82*((1-Paramètres!$G$82)*E38+Paramètres!$G$82*D38)+Paramètres!$H$82*E37+IF(AND(E38<0,"S2"<>"S1",3<=2),Paramètres!$I$82,0) -> 0.056125287 | F44: =Paramètres!$C$82/2+Paramètres!$F$82*((1-Paramètres!$G$82)*F38+Paramètres!$G$82*E38)+Paramètres!$H$82*F37+IF(AND(F38<0,"S2"<>"S1",4<=2),Paramètres!$I$82,0) -> 0.064750575 | G44: =Paramètres!$C$82/2+Paramètres!$F$82*((1-Paramètres!$G$82)*G38+Paramètres!$G$82*F38)+Paramètres!$H$82*G37+IF(AND(G38<0,"S2"<>"S1",5<=2),Paramètres!$I$82,0) -> 0.056125287 | H44: =Paramètres!$C$82/2+Paramètres!$F$82*((1-Paramètres!$G$82)*H38+Paramètres!$G$82*G38)+Paramètres!$H$82*H37+IF(AND(H38<0,"S2"<>"S1",6<=2),Paramètres!$I$82,0) -> 0.0475 | I44: =Paramètres!$C$82/2+Paramètres!$F$82*((1-Paramètres!$G$82)*I38+Paramètres!$G$82*H38)+Paramètres!$H$82*I37+IF(AND(I38<0,"S2"<>"S1",7<=2),Paramètres!$I$82,0) -> 0.0475 | J44: =Paramètres!$C$82/2+Paramètres!$F$82*((1-Paramètres!$G$82)*J38+Paramètres!$G$82*I38)+Paramètres!$H$82*J37+IF(AND(J38<0,"S2"<>"S1",8<=2),Paramètres!$I$82,0) -> 0.0475 | K44: Dérive + transmission × choc ARES (retard d'un semestre) + dollar + courbe en J
B45: Fonds HY UCITS | C45: =Paramètres!$C$83/2+Paramètres!$F$83*((1-Paramètres!$G$83)*C36)+Paramètres!$H$83*C37+IF(AND(C36<0,"S2"<>"S1",1<=2),Paramètres!$I$83,0) -> -0.028193206 | D45: =Paramètres!$C$83/2+Paramètres!$F$83*((1-Paramètres!$G$83)*D36+Paramètres!$G$83*C36)+Paramètres!$H$83*D37+IF(AND(D36<0,"S2"<>"S1",2<=2),Paramètres!$I$83,0) -> 0.03 | E45: =Paramètres!$C$83/2+Paramètres!$F$83*((1-Paramètres!$G$83)*E36+Paramètres!$G$83*D36)+Paramètres!$H$83*E37+IF(AND(E36<0,"S2"<>"S1",3<=2),Paramètres!$I$83,0) -> 0.049397735 | F45: =Paramètres!$C$83/2+Paramètres!$F$83*((1-Paramètres!$G$83)*F36+Paramètres!$G$83*E36)+Paramètres!$H$83*F37+IF(AND(F36<0,"S2"<>"S1",4<=2),Paramètres!$I$83,0) -> 0.049397735 | G45: =Paramètres!$C$83/2+Paramètres!$F$83*((1-Paramètres!$G$83)*G36+Paramètres!$G$83*F36)+Paramètres!$H$83*G37+IF(AND(G36<0,"S2"<>"S1",5<=2),Paramètres!$I$83,0) -> 0.03 | H45: =Paramètres!$C$83/2+Paramètres!$F$83*((1-Paramètres!$G$83)*H36+Paramètres!$G$83*G36)+Paramètres!$H$83*H37+IF(AND(H36<0,"S2"<>"S1",6<=2),Paramètres!$I$83,0) -> 0.03 | I45: =Paramètres!$C$83/2+Paramètres!$F$83*((1-Paramètres!$G$83)*I36+Paramètres!$G$83*H36)+Paramètres!$H$83*I37+IF(AND(I36<0,"S2"<>"S1",7<=2),Paramètres!$I$83,0) -> 0.03 | J45: =Paramètres!$C$83/2+Paramètres!$F$83*((1-Paramètres!$G$83)*J36+Paramètres!$G$83*I36)+Paramètres!$H$83*J37+IF(AND(J36<0,"S2"<>"S1",8<=2),Paramètres!$I$83,0) -> 0.03 | K45: Dérive + transmission × choc C4 (retard d'un semestre) + dollar + courbe en J
B46: Trésorerie | C46: =Paramètres!$C$84/2 -> 0.0125 | D46: =Paramètres!$C$84/2 -> 0.0125 | E46: =Paramètres!$C$84/2 -> 0.0125 | F46: =Paramètres!$C$84/2 -> 0.0125 | G46: =Paramètres!$C$84/2 -> 0.0125 | H46: =Paramètres!$C$84/2 -> 0.0125 | I46: =Paramètres!$C$84/2 -> 0.0125 | J46: =Paramètres!$C$84/2 -> 0.0125 | K46: Taux monétaire / 2
B48: Rendement du portefeuille (poids de départ) | C48: =Paramètres!$D$68*C41+Paramètres!$D$69*C42+Paramètres!$D$70*C43+Paramètres!$D$71*C44+Paramètres!$D$72*C45+Paramètres!$D$73*C46 -> -0.014988138 | D48: =Paramètres!$D$68*D41+Paramètres!$D$69*D42+Paramètres!$D$70*D43+Paramètres!$D$71*D44+Paramètres!$D$72*D45+Paramètres!$D$73*D46 -> 0.033763114 | E48: =Paramètres!$D$68*E41+Paramètres!$D$69*E42+Paramètres!$D$70*E43+Paramètres!$D$71*E44+Paramètres!$D$72*E45+Paramètres!$D$73*E46 -> 0.061912713 | F48: =Paramètres!$D$68*F41+Paramètres!$D$69*F42+Paramètres!$D$70*F43+Paramètres!$D$71*F44+Paramètres!$D$72*F45+Paramètres!$D$73*F46 -> 0.068416675 | G48: =Paramètres!$D$68*G41+Paramètres!$D$69*G42+Paramètres!$D$70*G43+Paramètres!$D$71*G44+Paramètres!$D$72*G45+Paramètres!$D$73*G46 -> 0.059778962 | H48: =Paramètres!$D$68*H41+Paramètres!$D$69*H42+Paramètres!$D$70*H43+Paramètres!$D$71*H44+Paramètres!$D$72*H45+Paramètres!$D$73*H46 -> 0.053275 | I48: =Paramètres!$D$68*I41+Paramètres!$D$69*I42+Paramètres!$D$70*I43+Paramètres!$D$71*I44+Paramètres!$D$72*I45+Paramètres!$D$73*I46 -> 0.053275 | J48: =Paramètres!$D$68*J41+Paramètres!$D$69*J42+Paramètres!$D$70*J43+Paramètres!$D$71*J44+Paramètres!$D$72*J45+Paramètres!$D$73*J46 -> 0.053275 | K48: Σ poids × rendement de ligne
B49: Indice de VL hors flux (base 100) | C49: =100*(1+C48) -> 98.501186 | D49: =C49*(1+D48) -> 101.82689 | E49: =D49*(1+E48) -> 108.13127 | F49: =E49*(1+F48) -> 115.52925 | G49: =F49*(1+G48) -> 122.43547 | H49: =G49*(1+H48) -> 128.95822 | I49: =H49*(1+I48) -> 135.82847 | J49: =I49*(1+J48) -> 143.06473 | K49: Effet marché seul
B50: Écart au départ | C50: =C49/100-1 -> -0.014988138 | D50: =D49/100-1 -> 0.01826893 | E50: =E49/100-1 -> 0.081312722 | F50: =F49/100-1 -> 0.15529254 | G50: =G49/100-1 -> 0.22435473 | H50: =H49/100-1 -> 0.28958223 | I50: =I49/100-1 -> 0.35828472 | J50: =J49/100-1 -> 0.43064734
B51: Pire écart cumulé (creux) | C51: =MIN(C50:J50) -> -0.014988138 | K51: Mesure retenue pour le verdict MST
B52: Semestre de retour au-dessus du niveau de départ | C52: =IFERROR(MATCH(TRUE(),INDEX(C50:J50>=0,0),0),"au-delà de 8") -> 2 | K52: Premier semestre où l'indice repasse 100
B53: Verdict MST | C53: =IF(-C51>S_mst_rouge,"Rouge",IF(-C51>S_mst_orange,"Orange","Vert")) -> Vert | K53: Vert ≤ 10 % ; Orange 10 à 25 % ; Rouge > 25 %
B55: S3 - SÉVÈRE Réplique 2008 : pire semestre historique des proxies, rachats de 15 % sur deux dates, collecte nulle, sortie du premier porteur
B56: Semestre | C56: 1 | D56: 2 | E56: 3 | F56: 4 | G56: 5 | H56: 6 | I56: 7 | J56: 8 | K56: Lecture
B57: Date de fin de semestre | C57: =EDATE(Date_depart,0) -> 47118 | D57: =EDATE(Date_depart,6) -> 47299 | E57: =EDATE(Date_depart,12) -> 47483 | F57: =EDATE(Date_depart,18) -> 47664 | G57: =EDATE(Date_depart,24) -> 47848 | H57: =EDATE(Date_depart,30) -> 48029 | I57: =EDATE(Date_depart,36) -> 48213 | J57: =EDATE(Date_depart,42) -> 48395
B58: Profil de choc (σ) | C58: =Paramètres!$C$163 -> -2.5 | D58: =Paramètres!$D$163 -> -1 | E58: =Paramètres!$E$163 -> 0 | F58: =Paramètres!$F$163 -> 0.75 | G58: =Paramètres!$G$163 -> 0.75 | H58: =Paramètres!$H$163 -> 0.5 | I58: =Paramètres!$I$163 -> 0 | J58: =Paramètres!$J$163 -> 0 | K58: Paramètres H
B59: Choc C1 Infrastructure cotée | C59: =Paramètres!$C$163*'MST Données'!$J$10 -> -0.14758879 | D59: =Paramètres!$D$163*'MST Données'!$J$10 -> -0.059035515 | E59: =Paramètres!$E$163*'MST Données'!$J$10 -> 0 | F59: =Paramètres!$F$163*'MST Données'!$J$10 -> 0.044276637 | G59: =Paramètres!$G$163*'MST Données'!$J$10 -> 0.044276637 | H59: =Paramètres!$H$163*'MST Données'!$J$10 -> 0.029517758 | I59: =Paramètres!$I$163*'MST Données'!$J$10 -> 0 | J59: =Paramètres!$J$163*'MST Données'!$J$10 -> 0 | K59: σ semestriel du facteur × profil
B60: Choc C3 Direct lending coté | C60: =Paramètres!$C$163*'MST Données'!$L$10 -> -0.3227737 | D60: =Paramètres!$D$163*'MST Données'!$L$10 -> -0.12910948 | E60: =Paramètres!$E$163*'MST Données'!$L$10 -> 0 | F60: =Paramètres!$F$163*'MST Données'!$L$10 -> 0.096832111 | G60: =Paramètres!$G$163*'MST Données'!$L$10 -> 0.096832111 | H60: =Paramètres!$H$163*'MST Données'!$L$10 -> 0.064554741 | I60: =Paramètres!$I$163*'MST Données'!$L$10 -> 0 | J60: =Paramètres!$J$163*'MST Données'!$L$10 -> 0 | K60: σ semestriel du facteur × profil
B61: Choc C4 Crédit HY coté | C61: =Paramètres!$C$163*'MST Données'!$M$10 -> -0.096988676 | D61: =Paramètres!$D$163*'MST Données'!$M$10 -> -0.03879547 | E61: =Paramètres!$E$163*'MST Données'!$M$10 -> 0 | F61: =Paramètres!$F$163*'MST Données'!$M$10 -> 0.029096603 | G61: =Paramètres!$G$163*'MST Données'!$M$10 -> 0.029096603 | H61: =Paramètres!$H$163*'MST Données'!$M$10 -> 0.019397735 | I61: =Paramètres!$I$163*'MST Données'!$M$10 -> 0 | J61: =Paramètres!$J$163*'MST Données'!$M$10 -> 0 | K61: σ semestriel du facteur × profil
B62: Choc dollar (EUR/USD) | C62: =Paramètres!$C$168 -> -0.15 | D62: =Paramètres!$D$168 -> 0 | E62: =Paramètres!$E$168 -> 0 | F62: =Paramètres!$F$168 -> 0.05 | G62: =Paramètres!$G$168 -> 0 | H62: =Paramètres!$H$168 -> 0 | I62: =Paramètres!$I$168 -> 0 | J62: =Paramètres!$J$168 -> 0 | K62: Paramètres H, en %
B63: Choc proxy Ares (60 % C1, 20 % C3, 20 % C4) | C63: =0.6*C59+0.2*C60+0.2*C61 -> -0.17250575 | D63: =0.6*D59+0.2*D60+0.2*D61 -> -0.0690023 | E63: =0.6*E59+0.2*E60+0.2*E61 -> 0 | F63: =0.6*F59+0.2*F60+0.2*F61 -> 0.051751725 | G63: =0.6*G59+0.2*G60+0.2*G61 -> 0.051751725 | H63: =0.6*H59+0.2*H60+0.2*H61 -> 0.03450115 | I63: =0.6*I59+0.2*I60+0.2*I61 -> 0 | J63: =0.6*J59+0.2*J60+0.2*J61 -> 0 | K63: Mix de la documentation Ares
B65: Rendement semestriel de la ligne | C65: 1 | D65: 2 | E65: 3 | F65: 4 | G65: 5 | H65: 6 | I65: 7 | J65: 8 | K65: Composition
B66: MAPIF II | C66: =Paramètres!$C$79/2+Paramètres!$F$79*((1-Paramètres!$G$79)*C59)+Paramètres!$H$79*C62+IF(AND(C59<0,"S3"<>"S1",1<=2),Paramètres!$I$79,0) -> -0.1693972 | D66: =Paramètres!$C$79/2+Paramètres!$F$79*((1-Paramètres!$G$79)*D59+Paramètres!$G$79*C59)+Paramètres!$H$79*D62+IF(AND(D59<0,"S3"<>"S1",2<=2),Paramètres!$I$79,0) -> -0.034156076 | E66: =Paramètres!$C$79/2+Paramètres!$F$79*((1-Paramètres!$G$79)*E59+Paramètres!$G$79*D59)+Paramètres!$H$79*E62+IF(AND(E59<0,"S3"<>"S1",3<=2),Paramètres!$I$79,0) -> 0.052741121 | F66: =Paramètres!$C$79/2+Paramètres!$F$79*((1-Paramètres!$G$79)*F59+Paramètres!$G$79*E59)+Paramètres!$H$79*F62+IF(AND(F59<0,"S3"<>"S1",4<=2),Paramètres!$I$79,0) -> 0.12856916 | G66: =Paramètres!$C$79/2+Paramètres!$F$79*((1-Paramètres!$G$79)*G59+Paramètres!$G$79*F59)+Paramètres!$H$79*G62+IF(AND(G59<0,"S3"<>"S1",5<=2),Paramètres!$I$79,0) -> 0.089638318 | H66: =Paramètres!$C$79/2+Paramètres!$F$79*((1-Paramètres!$G$79)*H59+Paramètres!$G$79*G59)+Paramètres!$H$79*H62+IF(AND(H59<0,"S3"<>"S1",6<=2),Paramètres!$I$79,0) -> 0.085948599 | I66: =Paramètres!$C$79/2+Paramètres!$F$79*((1-Paramètres!$G$79)*I59+Paramètres!$G$79*H59)+Paramètres!$H$79*I62+IF(AND(I59<0,"S3"<>"S1",7<=2),Paramètres!$I$79,0) -> 0.074879439 | J66: =Paramètres!$C$79/2+Paramètres!$F$79*((1-Paramètres!$G$79)*J59+Paramètres!$G$79*I59)+Paramètres!$H$79*J62+IF(AND(J59<0,"S3"<>"S1",8<=2),Paramètres!$I$79,0) -> 0.0675 | K66: Dérive + transmission × choc C1 (retard d'un semestre) + dollar + courbe en J
B67: MSIG 3 | C67: =Paramètres!$C$80/2+Paramètres!$F$80*((1-Paramètres!$G$80)*C60)+Paramètres!$H$80*C62+IF(AND(C60<0,"S3"<>"S1",1<=2),Paramètres!$I$80,0) -> -0.17569343 | D67: =Paramètres!$C$80/2+Paramètres!$F$80*((1-Paramètres!$G$80)*D60+Paramètres!$G$80*C60)+Paramètres!$H$80*D62+IF(AND(D60<0,"S3"<>"S1",2<=2),Paramètres!$I$80,0) -> -0.057970796 | E67: =Paramètres!$C$80/2+Paramètres!$F$80*((1-Paramètres!$G$80)*E60+Paramètres!$G$80*D60)+Paramètres!$H$80*E62+IF(AND(E60<0,"S3"<>"S1",3<=2),Paramètres!$I$80,0) -> 0.02272263 | F67: =Paramètres!$C$80/2+Paramètres!$F$80*((1-Paramètres!$G$80)*F60+Paramètres!$G$80*E60)+Paramètres!$H$80*F62+IF(AND(F60<0,"S3"<>"S1",4<=2),Paramètres!$I$80,0) -> 0.12920803 | G67: =Paramètres!$C$80/2+Paramètres!$F$80*((1-Paramètres!$G$80)*G60+Paramètres!$G$80*F60)+Paramètres!$H$80*G62+IF(AND(G60<0,"S3"<>"S1",5<=2),Paramètres!$I$80,0) -> 0.10341606 | H67: =Paramètres!$C$80/2+Paramètres!$F$80*((1-Paramètres!$G$80)*H60+Paramètres!$G$80*G60)+Paramètres!$H$80*H62+IF(AND(H60<0,"S3"<>"S1",6<=2),Paramètres!$I$80,0) -> 0.095346713 | I67: =Paramètres!$C$80/2+Paramètres!$F$80*((1-Paramètres!$G$80)*I60+Paramètres!$G$80*H60)+Paramètres!$H$80*I62+IF(AND(I60<0,"S3"<>"S1",7<=2),Paramètres!$I$80,0) -> 0.071138685 | J67: =Paramètres!$C$80/2+Paramètres!$F$80*((1-Paramètres!$G$80)*J60+Paramètres!$G$80*I60)+Paramètres!$H$80*J62+IF(AND(J60<0,"S3"<>"S1",8<=2),Paramètres!$I$80,0) -> 0.055 | K67: Dérive + transmission × choc C3 (retard d'un semestre) + dollar + courbe en J
