Workbook
Name Taux_Constitution: '01_Input'!$F$20
Name Distrib_Global_Classe_Selectionnee: '01_Input'!$F$30
Name ActifNet_Prev_An1: '01_Input'!$F$19
Name Distrib_SousDistrib_Classe_Selectionnee: '01_Input'!$F$31
Name AUM_Max: '01_Input'!$F$12
Name Classes_DistribGlobal: '02_Classes_de_Parts'!$D$7:$D$18
Name Classes_Distribuante: '02_Classes_de_Parts'!$F$7:$F$18
Name AUM_Min: '01_Input'!$F$11
Name Cout_Marginal_Investisseur: '01_Input'!$F$18
Name Nb_KYC_Gratuites_Par_Tranche: '01_Input'!$F$24
Name Seuil_Bareme_T2: '01_Input'!$F$43
Name Nb_Investisseurs: '01_Input'!$F$17
Name Conseil_Taux_T1: '01_Input'!$F$46
Name Majoration_Valorisation: '01_Input'!$F$38
Name Classes_Nom: '02_Classes_de_Parts'!$C$7:$C$18
Name Nb_Categories_Parts: '01_Input'!$F$37
Name Seuil_Bareme_T1: '01_Input'!$F$42
Name Plancher_Constitution: '01_Input'!$F$21
Name Nom_Fonds: '01_Input'!$F$8
Name Frequence_VL: '01_Input'!$F$35
Name Cout_Par_KYC_Supplementaire: '01_Input'!$F$26
Name Jours_Feries_FR: Jours_Feries_FR!$A$2:$A$452
Name AUM_Ladder: '01_Input'!$AS$7:$AS$156
Name Conseil_Taux_T2: '01_Input'!$F$47
Name Nb_Distributions_Par_An: '01_Input'!$F$22
Name Conseil_Taux_T3: '01_Input'!$F$48
Name Cout_Par_Distribution_CAC: '01_Input'!$F$23
Name AUM_Pas: '01_Input'!$F$13
Name Classe_Selectionnee_Distribue: '01_Input'!$F$32
Name Gestion_Taux_T2: '01_Input'!$E$47
Name Classes_DistribSousDistrib: '02_Classes_de_Parts'!$E$7:$E$18
Name Gestion_Taux_T1: '01_Input'!$E$46
Name Gestion_Taux_T3: '01_Input'!$E$48
Name Nb_Lignes_Valorisation: '01_Input'!$F$36
Name Classe_Selectionnee: '01_Input'!$F$29
Name Taille_Tranche_KYC: '01_Input'!$F$25

Sheet 00_Demarrage_Rapide
B1: 00_DÉMARRAGE RAPIDE — Comment utiliser ce classeur en 5 étapes
B2: Pour la méthode de calcul détaillée, les sources documentaires et les hypothèses retenues poste par poste : onglet 06_Documentation. Cet onglet-ci ne couvre que l'essentiel pour démarrer sans se tromper.
B4: 1. Renommez le fonds
C5: 01_Input, §1 "FONDS TESTÉ" — une seule cellule (lime) à remplir.
B7: 2. Fixez l'échelle d'AUM à tester
C8: 01_Input, §2 "ÉCHELLE D'AUM" — AUM minimum, maximum et pas. 04_Recap calculera chaque poste de frais pour tous les paliers de cette échelle, automatiquement.
B10: 3. Remplissez les paramètres et le tableau de frais
C11: 01_Input, §3 à §4 : renseignez les paramètres auxiliaires (§3), les 2 seuils et les 6 taux du tableau "Barèmes de Commissions" (§3D, pour Commission de Gestion et Commission de Conseil), puis une ligne par poste de frais (§4 — "Actif" = Oui/Non). Ne remplissez QUE les cases lime : les cases grises sont verrouillées (barèmes standard Fundcraft ou valeurs pilotées depuis un autre paramètre) et les cases rouges signalent une incohérence à corriger (voir légende en tête de 01_Input).
B13: 4. Vérifiez le résultat
C14: 04_Recap se met à jour automatiquement, ligne par ligne, palier d'AUM par palier d'AUM — aucune saisie supplémentaire n'y est nécessaire.
B16: 5. Réglez le prévisionnel de trésorerie
C17: 05_Tresorerie, §1 : date de lancement du fonds. §2 : AUM mensuel réel/prévisionnel. §3 et suivants : fréquence de facturation par poste (pré-remplie, modifiable). Le prorata du 1er mois et les jours fériés français sont gérés automatiquement.
B19: RAPPEL — CODE COULEUR (identique sur tout le classeur)
B20: lime | C20: cellule à saisir — propre à ce fonds.
B21: gris | C21: cellule verrouillée — barème standard Fundcraft, ou valeur pilotée depuis un autre paramètre. Ne pas modifier.
B22: rouge | C22: incohérence détectée (ex. AUM min ≥ AUM max) — à corriger avant de continuer.

Sheet 01_Input
B1: 01_INPUT — Seule zone de saisie manuelle du classeur
B2: Renseignez ici l'échelle d'AUM à tester et la liste des frais/provisions du fonds. L'onglet 04_Recap se met à jour automatiquement, ligne par ligne, sans aucune autre saisie. L'onglet 02_Classes_de_Parts est optionnel : à utiliser seulement si le fonds a des frais différenciés par classe (§3B et colonne "Mode de calcul" ci-dessous).
B4: Légende : | C4: cellule à saisir | E4: barème standard — ne pas modifier
C5: incohérence détectée — à corriger
AR6: Palier | AS6: AUM (Actif Net)
B7: 1. FONDS TESTÉ | AR7: 1 | AS7: =F11 -> 5000000
B8: Nom du fonds | F8: AF CVC | AR8: 2 | AS8: =IF(AS7="","",IF(AS7+$F$13>$F$12,"",AS7+$F$13)) -> 10000000
AR9: 3 | AS9: =IF(AS8="","",IF(AS8+$F$13>$F$12,"",AS8+$F$13)) -> 15000000
B10: 2. ÉCHELLE D'AUM (axe du Récap — Actif Net du fonds) | AR10: 4 | AS10: =IF(AS9="","",IF(AS9+$F$13>$F$12,"",AS9+$F$13)) -> 20000000
B11: AUM minimum testé (€) | F11: 5000000 | AR11: 5 | AS11: =IF(AS10="","",IF(AS10+$F$13>$F$12,"",AS10+$F$13)) -> 25000000
B12: AUM maximum testé (€) | F12: 50000000 | AR12: 6 | AS12: =IF(AS11="","",IF(AS11+$F$13>$F$12,"",AS11+$F$13)) -> 30000000
B13: Pas / incrément (€) | F13: 5000000 | AR13: 7 | AS13: =IF(AS12="","",IF(AS12+$F$13>$F$12,"",AS12+$F$13)) -> 35000000
B14: Nombre de paliers utilisés / disponibles | F14: =COUNT(AS7:AS156)&" / 150" -> 10 / 150 | AR14: 8 | AS14: =IF(AS13="","",IF(AS13+$F$13>$F$12,"",AS13+$F$13)) -> 40000000
AR15: 9 | AS15: =IF(AS14="","",IF(AS14+$F$13>$F$12,"",AS14+$F$13)) -> 45000000
B16: 3. PARAMÈTRES AUXILIAIRES — utilisés par certaines lignes de frais (formules ci-dessous) | AR16: 10 | AS16: =IF(AS15="","",IF(AS15+$F$13>$F$12,"",AS15+$F$13)) -> 50000000
B17: Nombre d'investisseurs (hypothèse fixe) | F17: 60 | AR17: 11 | AS17: =IF(AS16="","",IF(AS16+$F$13>$F$12,"",AS16+$F$13))
B18: Coût marginal par investisseur, €/an (Tenue du Passif) | F18: 15 | AR18: 12 | AS18: =IF(AS17="","",IF(AS17+$F$13>$F$12,"",AS17+$F$13))
B19: Actif Net prévisionnel au 1er anniversaire, € (Frais de Constitution) | F19: 0 | AR19: 13 | AS19: =IF(AS18="","",IF(AS18+$F$13>$F$12,"",AS18+$F$13))
B20: Taux des Frais de Constitution (%) | F20: 0.01 | AR20: 14 | AS20: =IF(AS19="","",IF(AS19+$F$13>$F$12,"",AS19+$F$13))
B21: Plancher des Frais de Constitution (€) | F21: 60000 | AR21: 15 | AS21: =IF(AS20="","",IF(AS20+$F$13>$F$12,"",AS20+$F$13))
B22: Nombre de distributions par an (Commissaire aux Comptes) | F22: 0 | AR22: 16 | AS22: =IF(AS21="","",IF(AS21+$F$13>$F$12,"",AS21+$F$13))
B23: Coût moyen par distribution, € (Commissaire aux Comptes) | F23: 1600 | AR23: 17 | AS23: =IF(AS22="","",IF(AS22+$F$13>$F$12,"",AS22+$F$13))
B24: Nombre de diligences KYC incluses par tranche (Frais KYC) | F24: 100 | AR24: 18 | AS24: =IF(AS23="","",IF(AS23+$F$13>$F$12,"",AS23+$F$13))
B25: Taille de la tranche d'AUM pour le renouvellement du forfait KYC, € (Frais KYC) | F25: 100000000 | AR25: 19 | AS25: =IF(AS24="","",IF(AS24+$F$13>$F$12,"",AS24+$F$13))
B26: Coût par diligence KYC supplémentaire, € (Frais KYC) | F26: 10 | AR26: 20 | AS26: =IF(AS25="","",IF(AS25+$F$13>$F$12,"",AS25+$F$13))
AR27: 21 | AS27: =IF(AS26="","",IF(AS26+$F$13>$F$12,"",AS26+$F$13))
B28: 3B. CLASSE DE PARTS SÉLECTIONNÉE (optionnel — voir 02_Classes_de_Parts) | AR28: 22 | AS28: =IF(AS27="","",IF(AS27+$F$13>$F$12,"",AS27+$F$13))
B29: Classe de parts sélectionnée pour le calcul de 04_Recap | F29: A | AR29: 23 | AS29: =IF(AS28="","",IF(AS28+$F$13>$F$12,"",AS28+$F$13))
B30: → Taux Distributeur Global de cette classe (calculé) | F30: {=IFERROR(INDEX(Classes_DistribGlobal,MATCH($F$29,Classes_Nom,0)),0)} -> 0.001 | AR30: 24 | AS30: =IF(AS29="","",IF(AS29+$F$13>$F$12,"",AS29+$F$13))
B31: → Taux Sous-distributeurs de cette classe (calculé) | F31: {=IFERROR(INDEX(Classes_DistribSousDistrib,MATCH($F$29,Classes_Nom,0)),0)} -> 0.009 | AR31: 25 | AS31: =IF(AS30="","",IF(AS30+$F$13>$F$12,"",AS30+$F$13))
B32: → Cette classe distribue-t-elle ? (calculé) | F32: {=IFERROR(INDEX(Classes_Distribuante,MATCH($F$29,Classes_Nom,0)),"Non")} -> Non | AR32: 26 | AS32: =IF(AS31="","",IF(AS31+$F$13>$F$12,"",AS31+$F$13))
AR33: 27 | AS33: =IF(AS32="","",IF(AS32+$F$13>$F$12,"",AS32+$F$13))
B34: 3C. PARAMÈTRES VALORISATION (CIC) — utilisés par la ligne "Valorisation (CIC)" | AR34: 28 | AS34: =IF(AS33="","",IF(AS33+$F$13>$F$12,"",AS33+$F$13))
B35: Fréquence de la VL (Mensuelle / Bi-mensuelle) | F35: Mensuelle | AR35: 29 | AS35: =IF(AS34="","",IF(AS34+$F$13>$F$12,"",AS34+$F$13))
B36: Nombre de lignes du portefeuille (valorisation) | F36: 2 | AR36: 30 | AS36: =IF(AS35="","",IF(AS35+$F$13>$F$12,"",AS35+$F$13))
B37: → Nombre de catégories de parts du fonds (déduit de 02_Classes_de_Parts) | F37: =COUNTIF(Classes_Nom,"<>") -> 2 | AR37: 31 | AS37: =IF(AS36="","",IF(AS36+$F$13>$F$12,"",AS36+$F$13))
B38: → Majoration applicable (calculée) | F38: =IF(F37>=5,0.15,IF(F37>=3,0.1,0)) -> 0 | AR38: 32 | AS38: =IF(AS37="","",IF(AS37+$F$13>$F$12,"",AS37+$F$13))
AR39: 33 | AS39: =IF(AS38="","",IF(AS38+$F$13>$F$12,"",AS38+$F$13))
B40: 3D. BARÈMES DE COMMISSIONS (Commission de Gestion + Commission de Conseil) | AR40: 34 | AS40: =IF(AS39="","",IF(AS39+$F$13>$F$12,"",AS39+$F$13))
B41: UN SEUL TABLEAU pour saisir les 2 commissions calculées par barème (Commission de Gestion, Commission de Conseil) : les 2 seuils et les 6 taux ci-dessous se répercutent automatiquement dans le tableau large du §4 (cases grisées, non éditables — à titre de contrôle visuel seulement) ainsi que dans 04_Recap et 05_Tresorerie. Décision du 14/09/2026 suite à un retour utilisateur : éviter d'avoir à modifier le tableau large (source d'erreur) — ne changez les taux ou les seuils de ces 2 commissions qu'ICI. | AR41: 35 | AS41: =IF(AS40="","",IF(AS40+$F$13>$F$12,"",AS40+$F$13))
B42: Seuil tranche 1 → 2, € d'Actif Net (commun aux 2 commissions) | F42: 100000000 | AR42: 36 | AS42: =IF(AS41="","",IF(AS41+$F$13>$F$12,"",AS41+$F$13))
B43: Seuil tranche 2 → 3, € d'Actif Net (commun aux 2 commissions) | F43: 500000000 | AR43: 37 | AS43: =IF(AS42="","",IF(AS42+$F$13>$F$12,"",AS42+$F$13))
AR44: 38 | AS44: =IF(AS43="","",IF(AS43+$F$13>$F$12,"",AS43+$F$13))
B45: Tranche (Actif Net du fonds) | E45: Commission de Gestion (taux) | F45: Commission de Conseil (taux) | AR45: 39 | AS45: =IF(AS44="","",IF(AS44+$F$13>$F$12,"",AS44+$F$13))
B46: ="Tranche 1 : 0 € → "&TEXT(F42,"#,##0")&" €" -> Tranche 1 : 0 € → 100,000,000 € | E46: 0.0018 | F46: 0.0045 | AR46: 40 | AS46: =IF(AS45="","",IF(AS45+$F$13>$F$12,"",AS45+$F$13))
B47: ="Tranche 2 : "&TEXT(F42,"#,##0")&" € → "&TEXT(F43,"#,##0")&" €" -> Tranche 2 : 100,000,000 € → 500,000,000 € | E47: 0.0014 | F47: 0.0035 | AR47: 41 | AS47: =IF(AS46="","",IF(AS46+$F$13>$F$12,"",AS46+$F$13))
B48: ="Tranche 3 : au-delà de "&TEXT(F43,"#,##0")&" €" -> Tranche 3 : au-delà de 500,000,000 € | E48: 0.0009 | F48: 0.0025 | AR48: 42 | AS48: =IF(AS47="","",IF(AS47+$F$13>$F$12,"",AS47+$F$13))
AR49: 43 | AS49: =IF(AS48="","",IF(AS48+$F$13>$F$12,"",AS48+$F$13))
B50: 4. FRAIS & PROVISIONS DU FONDS | AR50: 44 | AS50: =IF(AS49="","",IF(AS49+$F$13>$F$12,"",AS49+$F$13))
B51: Une ligne par frais/provision (jusqu'à 5 tranches Forfait/Taux/Palier). Basculez "Actif" sur Non plutôt que de supprimer une ligne. Détail des sources, de la méthode de calcul et du mode d'emploi complet : onglet 06_Documentation. | AR51: 45 | AS51: =IF(AS50="","",IF(AS50+$F$13>$F$12,"",AS50+$F$13))
B52: # | C52: Actif ? | D52: Nom du poste | E52: Bénéficiaire (à qui ça revient) | F52: Récurrent ? | G52: Mode de calcul | H52: Plancher annuel (€) | I52: Plafond annuel (€) | J52: T1 Borne inf. | K52: T1 Borne sup. | L52: T1 Nature | M52: T1 Valeur | N52: T2 Borne inf. | O52: T2 Borne sup. | P52: T2 Nature | Q52: T2 Valeur | R52: T3 Borne inf. | S52: T3 Borne sup. | T52: T3 Nature | U52: T3 Valeur | V52: T4 Borne inf. | W52: T4 Borne sup. | X52: T4 Nature | Y52: T4 Valeur | Z52: T5 Borne inf. | AA52: T5 Borne sup. | AB52: T5 Nature | AC52: T5 Valeur | AD52: Commentaire / Source | AR52: 46 | AS52: =IF(AS51="","",IF(AS51+$F$13>$F$12,"",AS51+$F$13))
B53: 1 | C53: Oui | D53: Commission de Gestion | F53: Oui | G53: Barème (Forfait/Taux/Palier) | H53: 60000 | I53: 999999999999 | J53: 0 | K53: =Seuil_Bareme_T1 -> 100000000 | L53: Taux | M53: =Gestion_Taux_T1 -> 0.0018 | N53: =Seuil_Bareme_T1 -> 100000000 | O53: =Seuil_Bareme_T2 -> 500000000 | P53: Taux | Q53: =Gestion_Taux_T2 -> 0.0014 | R53: =Seuil_Bareme_T2 -> 500000000 | S53: 999999999999 | T53: Taux | U53: =Gestion_Taux_T3 -> 0.0009 | V53: 0 | W53: 0 | X53: Taux | Y53: 0 | Z53: 0 | AA53: 0 | AB53: Taux | AC53: 0 | AR53: 47 | AS53: =IF(AS52="","",IF(AS52+$F$13>$F$12,"",AS52+$F$13))
B54: 2 | C54: Oui | D54: Commission de Conseil | F54: Oui | G54: Barème (Forfait/Taux/Palier) | H54: 0 | I54: 999999999999 | J54: 0 | K54: =Seuil_Bareme_T1 -> 100000000 | L54: Taux | M54: =Conseil_Taux_T1 -> 0.0045 | N54: =Seuil_Bareme_T1 -> 100000000 | O54: =Seuil_Bareme_T2 -> 500000000 | P54: Taux | Q54: =Conseil_Taux_T2 -> 0.0035 | R54: =Seuil_Bareme_T2 -> 500000000 | S54: 999999999999 | T54: Taux | U54: =Conseil_Taux_T3 -> 0.0025 | V54: 0 | W54: 0 | X54: Taux | Y54: 0 | Z54: 0 | AA54: 0 | AB54: Taux | AC54: 0 | AR54: 48 | AS54: =IF(AS53="","",IF(AS53+$F$13>$F$12,"",AS53+$F$13))
B55: 3 | C55: Oui | D55: Distribution — Distributeur Global | F55: Oui | G55: Taux Classe sélectionnée | H55: 0 | I55: 999999999999 | J55: 0 | K55: 999999999999 | L55: Taux | M55: =Distrib_Global_Classe_Selectionnee -> 0.001 | N55: 0 | O55: 0 | P55: Taux | Q55: 0 | R55: 0 | S55: 0 | T55: Taux | U55: 0 | V55: 0 | W55: 0 | X55: Taux | Y55: 0 | Z55: 0 | AA55: 0 | AB55: Taux | AC55: 0 | AR55: 49 | AS55: =IF(AS54="","",IF(AS54+$F$13>$F$12,"",AS54+$F$13))
B56: 4 | C56: Oui | D56: Distribution — Sous-distributeurs | F56: Oui | G56: Taux Classe sélectionnée | H56: 0 | I56: 999999999999 | J56: 0 | K56: 999999999999 | L56: Taux | M56: =Distrib_SousDistrib_Classe_Selectionnee -> 0.009 | N56: 0 | O56: 0 | P56: Taux | Q56: 0 | R56: 0 | S56: 0 | T56: Taux | U56: 0 | V56: 0 | W56: 0 | X56: Taux | Y56: 0 | Z56: 0 | AA56: 0 | AB56: Taux | AC56: 0 | AR56: 50 | AS56: =IF(AS55="","",IF(AS55+$F$13>$F$12,"",AS55+$F$13))
B57: 5 | C57: Oui | D57: Commission Dépositaire (BFCM) | E57: Dépositaire (BFCM) | F57: Oui | G57: Barème (Forfait/Taux/Palier) | H57: 12000 | I57: 50000 | J57: 0 | K57: 999999999999 | L57: Taux | M57: 0.0003 | N57: 0 | O57: 0 | P57: Taux | Q57: 0 | R57: 0 | S57: 0 | T57: Taux | U57: 0 | V57: 0 | W57: 0 | X57: Taux | Y57: 0 | Z57: 0 | AA57: 0 | AB57: Taux | AC57: 0 | AD57: Annexe 11 "Conditions financières" de la Convention Dépositaire – Société de Gestion BFCM / Fundcraft France SAS, applicable au 01/06/2026 (assiette : Actif Net Comptable). Taux de 0,030%, montant MINIMUM annuel de 12.000€/OPC, montant MAXIMUM annuel PLAFONNÉ à 50.000€/OPC. Remplace la précédente ventilation en 4 lignes (Garde/Contrôle/Teneur de registre/Distribution) : non retrouvée telle quelle dans la grille tarifaire réelle — probable reprise erronée d'un autre document. Un forfait spécifique de liquidation existe séparément (voir ligne dédiée, à activer le cas échéant en désactivant celle-ci). | AR57: 51 | AS57: =IF(AS56="","",IF(AS56+$F$13>$F$12,"",AS56+$F$13))
B58: 6 | C58: Oui | D58: Commissaire aux Comptes | E58: CAC | F58: Oui | G58: Barème (Forfait/Taux/Palier) | H58: 0 | I58: 999999999999 | J58: 0 | K58: 999999999999 | L58: Forfait | M58: 5500 | N58: 0 | O58: 0 | P58: Taux | Q58: 0 | R58: 0 | S58: 0 | T58: Taux | U58: 0 | V58: 0 | W58: 0 | X58: Taux | Y58: 0 | Z58: 0 | AA58: 0 | AB58: Taux | AC58: 0 | AD58: Lettre de mission Aplitec du 01/07/2026 (associé signataire Maxime Gallet, chef de mission Antony Aplogan), spécifique au FIPS AirFund Conviction Value Capital : honoraires de 5.500€ HT/an, correspondant à 2 interventions semestrielles (contrôle des situations semestrielles + comptes annuels). Ce montant est calculé par le CAC en fonction de la taille visée DE CE FONDS (objectif de collecte 30M€, hard cap 70-100M€) — CE N'EST PAS un tarif fixe applicable à tous les fonds Fundcraft (contrairement au coût par distribution ci-dessous, lui issu d'une pratique tarifaire générique du même CAC) : cellule volontairement laissée éditable (lime), reprise ici à 5.500€ par défaut (valeur AirFund) à confirmer/ajuster avec le CAC pour chaque nouveau fonds — et remise à blanc dans le modèle vierge. Hors forfait, facturés en sus par le CAC : TVA, frais de déplacement, et cotisation H2A (~100€ HT/an) — non modélisés séparément ici, montants mineurs au vu de la matérialité de ce poste. | AR58: 52 | AS58: =IF(AS57="","",IF(AS57+$F$13>$F$12,"",AS57+$F$13))
B59: 7 | C59: Oui | D59: CAC — Frais par Distribution | F59: Oui | G59: Barème (Forfait/Taux/Palier) | H59: 0 | I59: 999999999999 | J59: 0 | K59: 999999999999 | L59: Forfait | M59: =IF(Classe_Selectionnee_Distribue="Oui",Nb_Distributions_Par_An*Cout_Par_Distribution_CAC,0) -> 0 | N59: 0 | O59: 0 | P59: Taux | Q59: 0 | R59: 0 | S59: 0 | T59: Taux | U59: 0 | V59: 0 | W59: 0 | X59: Taux | Y59: 0 | Z59: 0 | AA59: 0 | AB59: Taux | AC59: 0 | AR59: 53 | AS59: =IF(AS58="","",IF(AS58+$F$13>$F$12,"",AS58+$F$13))
B60: 8 | C60: Oui | D60: Reporting — Rapport Annuel (CIC) | E60: CIC Administration de Fonds | F60: Oui | G60: Barème (Forfait/Taux/Palier) | H60: 0 | I60: 999999999999 | J60: 0 | K60: 999999999999 | L60: Forfait | M60: 800 | N60: 0 | O60: 0 | P60: Taux | Q60: 0 | R60: 0 | S60: 0 | T60: Taux | U60: 0 | V60: 0 | W60: 0 | X60: Taux | Y60: 0 | Z60: 0 | AA60: 0 | AB60: Taux | AC60: 0 | AD60: Annexe Tarifaire du "CONTRAT DE DELEGATION DE VALORISATION ENTRE FUNDCRAFT FRANCE SAS ET CIC" signé le 24/06/2026, section II.B.1 "Rapport annuel" : commission forfaitaire de 800€HT par an et par FIA. ⚠ Précédemment classée par erreur sous "Valorisation" — c'est une prestation de reporting. | AR60: 54 | AS60: =IF(AS59="","",IF(AS59+$F$13>$F$12,"",AS59+$F$13))
B61: 9 | C61: Oui | D61: Valorisation (CIC) | E61: Valorisateur (CIC / SOC Asset Servicing) | F61: Oui | G61: Barème (Forfait/Taux/Palier) | H61: 0 | I61: 999999999999 | J61: 0 | K61: 40000000 | L61: Palier | M61: =IF(Frequence_VL="Mensuelle",12000,17000)*(1+Majoration_Valorisation) -> 12000 | N61: 40000000 | O61: 80000000 | P61: Palier | Q61: =IF(Frequence_VL="Mensuelle",14000,20000)*(1+Majoration_Valorisation) -> 14000 | R61: 80000000 | S61: 120000000 | T61: Palier | U61: =IF(Frequence_VL="Mensuelle",16000,22000)*(1+Majoration_Valorisation) -> 16000 | V61: 120000000 | W61: 999999999999 | X61: Palier | Y61: =IF(Frequence_VL="Mensuelle",18000,24000)*(1+Majoration_Valorisation) -> 18000 | Z61: 0 | AA61: 999999999999 | AB61: Forfait | AC61: =IF(Nb_Lignes_Valorisation<=10,0,ROUNDUP((Nb_Lignes_Valorisation-10)/10,0)*500) -> 0 | AD61: Annexe Tarifaire du "CONTRAT DE DELEGATION DE VALORISATION ENTRE FUNDCRAFT FRANCE SAS ET CIC" signé le 24/06/2026, section I.B. 4 tranches "Palier" exclusives par Actif Net (0-40M/40-80M/80-120M/>120M€), montant selon la fréquence de VL choisie en §3C, majoré de +10% (3-4 catégories de parts) ou +15% (5 et plus, cas d'Openstone avec 9 classes), + supplément de 500€ par tranche de 10 lignes de portefeuille au-delà de 10 (tranche Forfait séparée, toujours active). ⚠ Remplace le précédent forfait de 12.000€ (recopié par erreur du Dépositaire). Le barème "Période de liquidation de l'OPC" (14.000€/12.000€) n'est pas modélisé ici (dépend du statut du fonds, pas de l'AUM) : à activer manuellement le cas échéant. | AR61: 55 | AS61: =IF(AS60="","",IF(AS60+$F$13>$F$12,"",AS60+$F$13))
B62: 10 | C62: Non | D62: Reporting AIFM (part refacturée au fonds) | E62: Prestataire reporting | F62: Oui | G62: Barème (Forfait/Taux/Palier) | H62: 0 | I62: 999999999999 | J62: 0 | K62: 999999999999 | L62: Forfait | M62: 500 | N62: 0 | O62: 0 | P62: Taux | Q62: 0 | R62: 0 | S62: 0 | T62: Taux | U62: 0 | V62: 0 | W62: 0 | X62: Taux | Y62: 0 | Z62: 0 | AA62: 0 | AB62: Taux | AC62: 0 | AD62: Annexe Tarifaire du "CONTRAT DE DELEGATION DE VALORISATION ENTRE FUNDCRAFT FRANCE SAS ET CIC" signé le 24/06/2026, section II.B.3 "AIFM – Reporting périodique complet ou push de données" : 3.000€HT à la mise en place (mutualisé, absorbé par la SGP, non modélisé ici) + 500€HT par reporting annuel et par FIA (modélisé ici). Ce même document précise explicitement "Non retenu par la société de gestion" pour cette prestation — désactivée (Actif = Non) le 14/09/2026 en conséquence, à la demande d'Apolline. Ne réactiver que si Fundcraft souscrit effectivement cette option auprès de CIC pour ce fonds. | AR62: 56 | AS62: =IF(AS61="","",IF(AS61+$F$13>$F$12,"",AS61+$F$13))
B63: 11 | C63: Oui | D63: Tenue du Passif | E63: Teneur de registre / Transfer Agent | F63: Oui | G63: Barème (Forfait/Taux/Palier) | H63: 0 | I63: 999999999999 | J63: 0 | K63: 999999999999 | L63: Forfait | M63: 1000 | N63: 0 | O63: 999999999999 | P63: Forfait | Q63: =Cout_Marginal_Investisseur*Nb_Investisseurs -> 900 | R63: 0 | S63: 0 | T63: Taux | U63: 0 | V63: 0 | W63: 0 | X63: Taux | Y63: 0 | Z63: 0 | AA63: 0 | AB63: Taux | AC63: 0 | AD63: Annexe 11 de la Convention Dépositaire BFCM (applicable au 01/06/2026) : forfait fixe de 1.000€/OPC + montant annuel par porteur (15€ ci-dessous, paramètre §3). Confirmé conforme à la grille tarifaire réelle. | AR63: 57 | AS63: =IF(AS62="","",IF(AS62+$F$13>$F$12,"",AS62+$F$13))
B64: 12 | C64: Oui | D64: Finologee | E64: Finologee | F64: Oui | G64: Barème (Forfait/Taux/Palier) | H64: 0 | I64: 999999999999 | J64: 0 | K64: 999999999999 | L64: Forfait | M64: 1392 | N64: 0 | O64: 0 | P64: Taux | Q64: 0 | R64: 0 | S64: 0 | T64: Taux | U64: 0 | V64: 0 | W64: 0 | X64: Taux | Y64: 0 | Z64: 0 | AA64: 0 | AB64: Taux | AC64: 0 | AD64: 116€HT par OPC et par mois, soit 1.392€HT/an (116 x 12) — forfait fixe indépendant de l'Actif Net du fonds. Facturé et payé mensuellement (virement automatique le 10 de chaque mois, par fonds) — fréquence "Mensuel" pré-réglée dans 05_Tresorerie §3 en conséquence. SANS PRORATA sur le mois de lancement (confirmé par Apolline, 14/09/2026 : "un mois entamé est dû en totalité") — contrairement aux autres postes mensuels, dont le tout premier mois est proratisé en jours ouvrés (05_Tresorerie §1/§5) : le virement Finologee est un forfait mensuel fixe, pas un service facturé au prorata du temps réellement presté. Poste TOUJOURS présent, sur tous les fonds Fundcraft (confirmé par Apolline, 14/09/2026) : traité comme les autres plaquettes tarifaires prestataires (Dépositaire BFCM, Valorisation/Reporting CIC) — verrouillé (gris), pas une donnée propre au fonds testé. ⚠ Confiance MOYENNE sur le montant : information communiquée directement par Apolline en conversation, non retrouvée à ce jour dans une convention Finologee signée dans les pièces disponibles pour AirFund — à sourcer avec le contrat Finologee dès qu'il est disponible et à corriger ici si le montant réel diffère. | AR64: 58 | AS64: =IF(AS63="","",IF(AS63+$F$13>$F$12,"",AS63+$F$13))
B65: 13 | C65: Oui | D65: Frais KYC (au-delà du forfait inclus) | F65: Oui | G65: Frais KYC (paliers de 100M€) | H65: 0 | I65: 999999999999 | J65: 0 | K65: 0 | L65: Taux | M65: 0 | N65: 0 | O65: 0 | P65: Taux | Q65: 0 | R65: 0 | S65: 0 | T65: Taux | U65: 0 | V65: 0 | W65: 0 | X65: Taux | Y65: 0 | Z65: 0 | AA65: 0 | AB65: Taux | AC65: 0 | AR65: 59 | AS65: =IF(AS64="","",IF(AS64+$F$13>$F$12,"",AS64+$F$13))
B66: 14 | C66: Non | D66: Frais de Constitution (hors barème — actif par défaut, voir 05_Tresorerie) | F66: Non | G66: Barème (Forfait/Taux/Palier) | H66: =Plancher_Constitution -> 60000 | I66: 999999999999 | J66: 0 | K66: 999999999999 | L66: Forfait | M66: =MAX(Plancher_Constitution,Taux_Constitution*ActifNet_Prev_An1) -> 60000 | N66: 0 | O66: 0 | P66: Taux | Q66: 0 | R66: 0 | S66: 0 | T66: Taux | U66: 0 | V66: 0 | W66: 0 | X66: Taux | Y66: 0 | Z66: 0 | AA66: 0 | AB66: Taux | AC66: 0 | AR66: 60 | AS66: =IF(AS65="","",IF(AS65+$F$13>$F$12,"",AS65+$F$13))
B67: 15 | C67: Non | D67: Dépositaire — Forfait liquidation (ANC<5M€) | E67: Dépositaire (BFCM) | F67: Oui | G67: Barème (Forfait/Taux/Palier) | H67: 0 | I67: 999999999999 | J67: 0 | K67: 999999999999 | L67: Forfait | M67: 7000 | N67: 0 | O67: 0 | P67: Taux | Q67: 0 | R67: 0 | S67: 0 | T67: Taux | U67: 0 | V67: 0 | W67: 0 | X67: Taux | Y67: 0 | Z67: 0 | AA67: 0 | AB67: Taux | AC67: 0 | AD67: Annexe 11 de la Convention Dépositaire BFCM : forfait spécifique de 7.000€ pour les OPC en liquidation dont l'ANC est inférieur à 5M€. À activer (et à désactiver "Commission Dépositaire (BFCM)" en parallèle) uniquement lorsque le fonds est effectivement en phase de liquidation. | AR67: 61 | AS67: =IF(AS66="","",IF(AS66+$F$13>$F$12,"",AS66+$F$13))
B68: 16 | C68: Non | D68: Dépositaire — Admission Euroclear (par ISIN) | E68: Dépositaire (BFCM) | F68: Non | G68: Barème (Forfait/Taux/Palier) | H68: 0 | I68: 999999999999 | J68: 0 | K68: 999999999999 | L68: Forfait | M68: 1000 | N68: 0 | O68: 0 | P68: Taux | Q68: 0 | R68: 0 | S68: 0 | T68: Taux | U68: 0 | V68: 0 | W68: 0 | X68: Taux | Y68: 0 | Z68: 0 | AA68: 0 | AB68: Taux | AC68: 0 | AD68: Annexe 11 de la Convention Dépositaire BFCM : 1.000€ par code ISIN admis à l'admission Euroclear France. Frais ponctuel (à l'acte), à activer l'année d'admission d'une nouvelle classe/ligne. | AR68: 62 | AS68: =IF(AS67="","",IF(AS67+$F$13>$F$12,"",AS67+$F$13))
B69: 17 | C69: Non | D69: Reporting — Solvabilité II (optionnel) | E69: Prestataire reporting | F69: Oui | G69: Barème (Forfait/Taux/Palier) | H69: 0 | I69: 999999999999 | J69: 0 | K69: 999999999999 | L69: Forfait | M69: 500 | N69: 0 | O69: 0 | P69: Taux | Q69: 0 | R69: 0 | S69: 0 | T69: Taux | U69: 0 | V69: 0 | W69: 0 | X69: Taux | Y69: 0 | Z69: 0 | AA69: 0 | AB69: Taux | AC69: 0 | AD69: Annexe Tarifaire du "CONTRAT DE DELEGATION DE VALORISATION ENTRE FUNDCRAFT FRANCE SAS ET CIC" signé le 24/06/2026, section II.B.2 : fourniture de données d'inventaires transparisés sur demande (investisseurs assurantiels). Commission forfaitaire de 3.000€ à la mise en place (mutualisée, non modélisée ici, cf. Reporting AIFM) + 500€ par reporting, modélisé ici. Ce même document précise "Non retenu par la société de gestion" — cohérent avec Actif = Non par défaut. À activer seulement si le fonds compte des investisseurs assujettis à Solvabilité II ET que Fundcraft souscrit effectivement cette option. | AR69: 63 | AS69: =IF(AS68="","",IF(AS68+$F$13>$F$12,"",AS68+$F$13))
B70: 18 | C70: Non | F70: Oui | G70: Barème (Forfait/Taux/Palier) | H70: 0 | I70: 999999999999 | J70: 0 | K70: 0 | L70: Taux | M70: 0 | N70: 0 | O70: 0 | P70: Taux | Q70: 0 | R70: 0 | S70: 0 | T70: Taux | U70: 0 | V70: 0 | W70: 0 | X70: Taux | Y70: 0 | Z70: 0 | AA70: 0 | AB70: Taux | AC70: 0 | AR70: 64 | AS70: =IF(AS69="","",IF(AS69+$F$13>$F$12,"",AS69+$F$13))
B71: 19 | C71: Non | F71: Oui | G71: Barème (Forfait/Taux/Palier) | H71: 0 | I71: 999999999999 | J71: 0 | K71: 0 | L71: Taux | M71: 0 | N71: 0 | O71: 0 | P71: Taux | Q71: 0 | R71: 0 | S71: 0 | T71: Taux | U71: 0 | V71: 0 | W71: 0 | X71: Taux | Y71: 0 | Z71: 0 | AA71: 0 | AB71: Taux | AC71: 0 | AR71: 65 | AS71: =IF(AS70="","",IF(AS70+$F$13>$F$12,"",AS70+$F$13))
B72: 20 | C72: Non | F72: Oui | G72: Barème (Forfait/Taux/Palier) | H72: 0 | I72: 999999999999 | J72: 0 | K72: 0 | L72: Taux | M72: 0 | N72: 0 | O72: 0 | P72: Taux | Q72: 0 | R72: 0 | S72: 0 | T72: Taux | U72: 0 | V72: 0 | W72: 0 | X72: Taux | Y72: 0 | Z72: 0 | AA72: 0 | AB72: Taux | AC72: 0 | AR72: 66 | AS72: =IF(AS71="","",IF(AS71+$F$13>$F$12,"",AS71+$F$13))
AR73: 67 | AS73: =IF(AS72="","",IF(AS72+$F$13>$F$12,"",AS72+$F$13))
AR74: 68 | AS74: =IF(AS73="","",IF(AS73+$F$13>$F$12,"",AS73+$F$13))
B75: Lignes libres : ajoutez un poste en renseignant une ligne "Actif = Non" existante (jusqu'à 20 postes disponibles), désactivez-en un en repassant "Actif" à Non plutôt qu'en effaçant la ligne. | AR75: 69 | AS75: =IF(AS74="","",IF(AS74+$F$13>$F$12,"",AS74+$F$13))
AR76: 70 | AS76: =IF(AS75="","",IF(AS75+$F$13>$F$12,"",AS75+$F$13))
AR77: 71 | AS77: =IF(AS76="","",IF(AS76+$F$13>$F$12,"",AS76+$F$13))
AR78: 72 | AS78: =IF(AS77="","",IF(AS77+$F$13>$F$12,"",AS77+$F$13))
AR79: 73 | AS79: =IF(AS78="","",IF(AS78+$F$13>$F$12,"",AS78+$F$13))
AR80: 74 | AS80: =IF(AS79="","",IF(AS79+$F$13>$F$12,"",AS79+$F$13))
AR81: 75 | AS81: =IF(AS80="","",IF(AS80+$F$13>$F$12,"",AS80+$F$13))
AR82: 76 | AS82: =IF(AS81="","",IF(AS81+$F$13>$F$12,"",AS81+$F$13))
AR83: 77 | AS83: =IF(AS82="","",IF(AS82+$F$13>$F$12,"",AS82+$F$13))
AR84: 78 | AS84: =IF(AS83="","",IF(AS83+$F$13>$F$12,"",AS83+$F$13))
AR85: 79 | AS85: =IF(AS84="","",IF(AS84+$F$13>$F$12,"",AS84+$F$13))
AR86: 80 | AS86: =IF(AS85="","",IF(AS85+$F$13>$F$12,"",AS85+$F$13))
AR87: 81 | AS87: =IF(AS86="","",IF(AS86+$F$13>$F$12,"",AS86+$F$13))
... AR156: 150 | AS156: =IF(AS155="","",IF(AS155+$F$13>$F$12,"",AS155+$F$13))

Sheet 02_Classes_de_Parts
B1: 02_CLASSES DE PARTS — Optionnel — uniquement pour un fonds à frais différenciés par classe
B2: N'est utilisé par 01_Input / 04_Recap QUE pour les postes de frais dont le "Mode de calcul" (colonne du tableau de frais en 01_Input) est "Taux Classe sélectionnée" — ex. les 2 lignes de Commission de Distribution (Distributeur Global / Sous-distributeurs), qui varient par classe de parts. Si votre fonds n'a pas ce mécanisme, laissez cet onglet inutilisé et gardez tous les postes de 01_Input en mode "Barème". Sert aussi à déduire automatiquement le nombre de catégories de parts du fonds (01_Input §3C).
B4: Dans 01_Input, vous choisissez UNE classe — celle sur laquelle 04_Recap calcule le détail. Un poste en mode "Taux Classe sélectionnée" = Taux de cette classe x AUM. Détail de la méthode et des sources : onglet 06_Documentation.
C6: Nom de la classe | D6: Taux Distributeur Global | E6: Taux Sous- distributeurs | F6: Distribuante ? | G6: Commentaire / Source
C7: A | D7: 0.001 | E7: 0.009 | F7: Non
C8: B | D8: 0.001 | E8: 0 | F8: Non
D9: 0 | E9: 0 | F9: Non
D10: 0 | E10: 0 | F10: Non
D11: 0 | E11: 0 | F11: Non
D12: 0 | E12: 0 | F12: Non
D13: 0 | E13: 0 | F13: Non
D14: 0 | E14: 0 | F14: Non
D15: 0 | E15: 0 | F15: Non
D16: 0 | E16: 0 | F16: Non
D17: 0 | E17: 0 | F17: Non
D18: 0 | E18: 0 | F18: Non
B21: Lignes libres : ajoutez une classe en renseignant une ligne vide (jusqu'à 12 classes disponibles). Une ligne dont le nom est vide est ignorée par le sélecteur de 01_Input.

Sheet 03_Detail_Depositaire_Valo
B1: 03_DÉTAIL DÉPOSITAIRE / VALORISATION — Zéro saisie manuelle — décompose pas à pas 2 postes de 01_Input dont le calcul n'est pas un simple taux
B2: "Commission Dépositaire (BFCM)" (taux + plancher + PLAFOND) et "Valorisation (CIC)" (barème par tranche d'actif, fréquence de VL, majoration par nombre de catégories de parts, supplément lignes de portefeuille) sont les 2 postes les moins immédiats à lire directement dans le tableau de 01_Input. Cet onglet réexplique chaque paramètre, puis reconstitue le calcul complet sur toute l'échelle d'AUM testée — les lignes "Écart vs 04_Recap" prouvent que ce détail correspond exactement (doit toujours afficher 0).
B5: Zéro saisie manuelle : reconstitue pas à pas le calcul des 2 postes les moins immédiats à lire en 01_Input (Dépositaire, Valorisation). Détail de la méthode et des sources : onglet 06_Documentation.
B7: PARAMÈTRES ACTIFS (repris de 01_Input — rien à saisir ici)
B8: Commission Dépositaire (BFCM)
B9: Taux appliqué | C9: ='01_Input'!$M$57 -> 0.0003
B10: Plancher annuel | C10: ='01_Input'!$H$57 -> 12000
B11: Plafond annuel | C11: ='01_Input'!$I$57 -> 50000
B13: Valorisation (CIC)
B14: Fréquence de VL retenue | C14: =Frequence_VL -> Mensuelle
B15: Nombre de lignes du portefeuille | C15: =Nb_Lignes_Valorisation -> 2
B16: Nombre de catégories de parts | C16: =Nb_Categories_Parts -> 2
B17: Majoration applicable | C17: =Majoration_Valorisation -> 0
B20: DÉTAIL DU CALCUL SUR L'ÉCHELLE D'AUM TESTÉE (01_Input §2)
B21: Étape de calcul | E21: {=INDEX(AUM_Ladder,1)} -> 5000000 | F21: {=INDEX(AUM_Ladder,2)} -> 10000000 | G21: {=INDEX(AUM_Ladder,3)} -> 15000000 | H21: {=INDEX(AUM_Ladder,4)} -> 20000000 | I21: {=INDEX(AUM_Ladder,5)} -> 25000000 | J21: {=INDEX(AUM_Ladder,6)} -> 30000000 | K21: {=INDEX(AUM_Ladder,7)} -> 35000000 | L21: {=INDEX(AUM_Ladder,8)} -> 40000000 | M21: {=INDEX(AUM_Ladder,9)} -> 45000000 | N21: {=INDEX(AUM_Ladder,10)} -> 50000000 | O21: {=INDEX(AUM_Ladder,11)} | P21: {=INDEX(AUM_Ladder,12)} | Q21: {=INDEX(AUM_Ladder,13)} | R21: {=INDEX(AUM_Ladder,14)} | S21: {=INDEX(AUM_Ladder,15)} | T21: {=INDEX(AUM_Ladder,16)} | U21: {=INDEX(AUM_Ladder,17)} | V21: {=INDEX(AUM_Ladder,18)} | W21: {=INDEX(AUM_Ladder,19)} | X21: {=INDEX(AUM_Ladder,20)} | Y21: {=INDEX(AUM_Ladder,21)} | Z21: {=INDEX(AUM_Ladder,22)} | AA21: {=INDEX(AUM_Ladder,23)} | AB21: {=INDEX(AUM_Ladder,24)} | AC21: {=INDEX(AUM_Ladder,25)} | AD21: {=INDEX(AUM_Ladder,26)} | AE21: {=INDEX(AUM_Ladder,27)} | AF21: {=INDEX(AUM_Ladder,28)} | AG21: {=INDEX(AUM_Ladder,29)} | AH21: {=INDEX(AUM_Ladder,30)} | AI21: {=INDEX(AUM_Ladder,31)} | AJ21: {=INDEX(AUM_Ladder,32)} | AK21: {=INDEX(AUM_Ladder,33)} | AL21: {=INDEX(AUM_Ladder,34)} | AM21: {=INDEX(AUM_Ladder,35)} | AN21: {=INDEX(AUM_Ladder,36)} | AO21: {=INDEX(AUM_Ladder,37)} | AP21: {=INDEX(AUM_Ladder,38)} | AQ21: {=INDEX(AUM_Ladder,39)} | AR21: {=INDEX(AUM_Ladder,40)} | AS21: {=INDEX(AUM_Ladder,41)} | AT21: {=INDEX(AUM_Ladder,42)} | AU21: {=INDEX(AUM_Ladder,43)} | AV21: {=INDEX(AUM_Ladder,44)} | AW21: {=INDEX(AUM_Ladder,45)} | AX21: {=INDEX(AUM_Ladder,46)} | AY21: {=INDEX(AUM_Ladder,47)} | AZ21: {=INDEX(AUM_Ladder,48)} | BA21: {=INDEX(AUM_Ladder,49)} | BB21: {=INDEX(AUM_Ladder,50)} | BC21: {=INDEX(AUM_Ladder,51)} | BD21: {=INDEX(AUM_Ladder,52)} | BE21: {=INDEX(AUM_Ladder,53)} | BF21: {=INDEX(AUM_Ladder,54)} | BG21: {=INDEX(AUM_Ladder,55)} | BH21: {=INDEX(AUM_Ladder,56)} | BI21: {=INDEX(AUM_Ladder,57)} | BJ21: {=INDEX(AUM_Ladder,58)} | BK21: {=INDEX(AUM_Ladder,59)} | BL21: {=INDEX(AUM_Ladder,60)} | BM21: {=INDEX(AUM_Ladder,61)} | BN21: {=INDEX(AUM_Ladder,62)} | BO21: {=INDEX(AUM_Ladder,63)} | BP21: {=INDEX(AUM_Ladder,64)} | BQ21: {=INDEX(AUM_Ladder,65)} | BR21: {=INDEX(AUM_Ladder,66)} | BS21: {=INDEX(AUM_Ladder,67)} | BT21: {=INDEX(AUM_Ladder,68)} | BU21: {=INDEX(AUM_Ladder,69)} | BV21: {=INDEX(AUM_Ladder,70)} | BW21: {=INDEX(AUM_Ladder,71)} | BX21: {=INDEX(AUM_Ladder,72)} | BY21: {=INDEX(AUM_Ladder,73)} | BZ21: {=INDEX(AUM_Ladder,74)} | CA21: {=INDEX(AUM_Ladder,75)} | CB21: {=INDEX(AUM_Ladder,76)} | CC21: {=INDEX(AUM_Ladder,77)} | CD21: {=INDEX(AUM_Ladder,78)} | CE21: {=INDEX(AUM_Ladder,79)} | CF21: {=INDEX(AUM_Ladder,80)} | CG21: {=INDEX(AUM_Ladder,81)} | CH21: {=INDEX(AUM_Ladder,82)} | CI21: {=INDEX(AUM_Ladder,83)} | CJ21: {=INDEX(AUM_Ladder,84)} | CK21: {=INDEX(AUM_Ladder,85)} | CL21: {=INDEX(AUM_Ladder,86)} | CM21: {=INDEX(AUM_Ladder,87)} | CN21: {=INDEX(AUM_Ladder,88)} | CO21: {=INDEX(AUM_Ladder,89)} | CP21: {=INDEX(AUM_Ladder,90)} | CQ21: {=INDEX(AUM_Ladder,91)} | CR21: {=INDEX(AUM_Ladder,92)} | CS21: {=INDEX(AUM_Ladder,93)} | CT21: {=INDEX(AUM_Ladder,94)} | CU21: {=INDEX(AUM_Ladder,95)} | CV21: {=INDEX(AUM_Ladder,96)} | CW21: {=INDEX(AUM_Ladder,97)} | CX21: {=INDEX(AUM_Ladder,98)} | CY21: {=INDEX(AUM_Ladder,99)} | CZ21: {=INDEX(AUM_Ladder,100)} | DA21: {=INDEX(AUM_Ladder,101)} | DB21: {=INDEX(AUM_Ladder,102)} | DC21: {=INDEX(AUM_Ladder,103)} | DD21: {=INDEX(AUM_Ladder,104)} | DE21: {=INDEX(AUM_Ladder,105)} | DF21: {=INDEX(AUM_Ladder,106)} | DG21: {=INDEX(AUM_Ladder,107)} | DH21: {=INDEX(AUM_Ladder,108)} | DI21: {=INDEX(AUM_Ladder,109)} | DJ21: {=INDEX(AUM_Ladder,110)} | DK21: {=INDEX(AUM_Ladder,111)} | DL21: {=INDEX(AUM_Ladder,112)} | DM21: {=INDEX(AUM_Ladder,113)} | DN21: {=INDEX(AUM_Ladder,114)} | DO21: {=INDEX(AUM_Ladder,115)} | DP21: {=INDEX(AUM_Ladder,116)} | DQ21: {=INDEX(AUM_Ladder,117)} | DR21: {=INDEX(AUM_Ladder,118)} | DS21: {=INDEX(AUM_Ladder,119)} | DT21: {=INDEX(AUM_Ladder,120)} | DU21: {=INDEX(AUM_Ladder,121)} | DV21: {=INDEX(AUM_Ladder,122)} | DW21: {=INDEX(AUM_Ladder,123)} | DX21: {=INDEX(AUM_Ladder,124)} | DY21: {=INDEX(AUM_Ladder,125)} | DZ21: {=INDEX(AUM_Ladder,126)} | EA21: {=INDEX(AUM_Ladder,127)} | EB21: {=INDEX(AUM_Ladder,128)} | EC21: {=INDEX(AUM_Ladder,129)} | ED21: {=INDEX(AUM_Ladder,130)} | EE21: {=INDEX(AUM_Ladder,131)} | EF21: {=INDEX(AUM_Ladder,132)} | EG21: {=INDEX(AUM_Ladder,133)} | EH21: {=INDEX(AUM_Ladder,134)} | EI21: {=INDEX(AUM_Ladder,135)} | EJ21: {=INDEX(AUM_Ladder,136)} | EK21: {=INDEX(AUM_Ladder,137)} | EL21: {=INDEX(AUM_Ladder,138)} | EM21: {=INDEX(AUM_Ladder,139)} | EN21: {=INDEX(AUM_Ladder,140)} | EO21: {=INDEX(AUM_Ladder,141)} | EP21: {=INDEX(AUM_Ladder,142)} | EQ21: {=INDEX(AUM_Ladder,143)} | ER21: {=INDEX(AUM_Ladder,144)} | ES21: {=INDEX(AUM_Ladder,145)} | ET21: {=INDEX(AUM_Ladder,146)} | EU21: {=INDEX(AUM_Ladder,147)} | EV21: {=INDEX(AUM_Ladder,148)} | EW21: {=INDEX(AUM_Ladder,149)} | EX21: {=INDEX(AUM_Ladder,150)}
B22: — COMMISSION DÉPOSITAIRE (BFCM) —
B23: Taux appliqué (%) | E23: ='01_Input'!$M$57 -> 0.0003 | F23: ='01_Input'!$M$57 -> 0.0003 | G23: ='01_Input'!$M$57 -> 0.0003 | H23: ='01_Input'!$M$57 -> 0.0003 | I23: ='01_Input'!$M$57 -> 0.0003 | J23: ='01_Input'!$M$57 -> 0.0003 | K23: ='01_Input'!$M$57 -> 0.0003 | L23: ='01_Input'!$M$57 -> 0.0003 | ... EX23: ='01_Input'!$M$57 -> 0.0003
B24: Montant théorique = Taux x AUM (€) | E24: =E$21*E23 -> 1500 | F24: =F$21*F23 -> 3000 | G24: =G$21*G23 -> 4500 | H24: =H$21*H23 -> 6000 | I24: =I$21*I23 -> 7500 | J24: =J$21*J23 -> 9000 | K24: =K$21*K23 -> 10500 | L24: =L$21*L23 -> 12000 | ... EX24: =EX$21*EX23 -> 0
B25: Plancher annuel (€) | E25: ='01_Input'!$H$57 -> 12000 | F25: ='01_Input'!$H$57 -> 12000 | G25: ='01_Input'!$H$57 -> 12000 | H25: ='01_Input'!$H$57 -> 12000 | I25: ='01_Input'!$H$57 -> 12000 | J25: ='01_Input'!$H$57 -> 12000 | K25: ='01_Input'!$H$57 -> 12000 | L25: ='01_Input'!$H$57 -> 12000 | ... EX25: ='01_Input'!$H$57 -> 12000
B26: Plafond annuel (€) | E26: ='01_Input'!$I$57 -> 50000 | F26: ='01_Input'!$I$57 -> 50000 | G26: ='01_Input'!$I$57 -> 50000 | H26: ='01_Input'!$I$57 -> 50000 | I26: ='01_Input'!$I$57 -> 50000 | J26: ='01_Input'!$I$57 -> 50000 | K26: ='01_Input'!$I$57 -> 50000 | L26: ='01_Input'!$I$57 -> 50000 | ... EX26: ='01_Input'!$I$57 -> 50000
B27: Mécanisme retenu | E27: =IF(E24<E25,"Plancher (min.)",IF(E24>E26,"Plafond (max.)","Barème (plein)")) -> Plancher (min.) | F27: =IF(F24<F25,"Plancher (min.)",IF(F24>F26,"Plafond (max.)","Barème (plein)")) -> Plancher (min.) | G27: =IF(G24<G25,"Plancher (min.)",IF(G24>G26,"Plafond (max.)","Barème (plein)")) -> Plancher (min.) | H27: =IF(H24<H25,"Plancher (min.)",IF(H24>H26,"Plafond (max.)","Barème (plein)")) -> Plancher (min.) | I27: =IF(I24<I25,"Plancher (min.)",IF(I24>I26,"Plafond (max.)","Barème (plein)")) -> Plancher (min.) | J27: =IF(J24<J25,"Plancher (min.)",IF(J24>J26,"Plafond (max.)","Barème (plein)")) -> Plancher (min.) | K27: =IF(K24<K25,"Plancher (min.)",IF(K24>K26,"Plafond (max.)","Barème (plein)")) -> Plancher (min.) | L27: =IF(L24<L25,"Plancher (min.)",IF(L24>L26,"Plafond (max.)","Barème (plein)")) -> Barème (plein) | ... EX27: =IF(EX24<EX25,"Plancher (min.)",IF(EX24>EX26,"Plafond (max.)","Barème (plein)")) -> Plancher (min.)
B28: → Commission Dépositaire retenue (€) | E28: =MIN(E26,MAX(E25,E24)) -> 12000 | F28: =MIN(F26,MAX(F25,F24)) -> 12000 | G28: =MIN(G26,MAX(G25,G24)) -> 12000 | H28: =MIN(H26,MAX(H25,H24)) -> 12000 | I28: =MIN(I26,MAX(I25,I24)) -> 12000 | J28: =MIN(J26,MAX(J25,J24)) -> 12000 | K28: =MIN(K26,MAX(K25,K24)) -> 12000 | L28: =MIN(L26,MAX(L25,L24)) -> 12000 | ... EX28: =MIN(EX26,MAX(EX25,EX24)) -> 12000
B29: Écart vs 04_Recap (doit être 0) | E29: =ROUND(E28-'04_Recap'!E25,2) -> 0 | F29: =ROUND(F28-'04_Recap'!F25,2) -> 0 | G29: =ROUND(G28-'04_Recap'!G25,2) -> 0 | H29: =ROUND(H28-'04_Recap'!H25,2) -> 0 | I29: =ROUND(I28-'04_Recap'!I25,2) -> 0 | J29: =ROUND(J28-'04_Recap'!J25,2) -> 0 | K29: =ROUND(K28-'04_Recap'!K25,2) -> 0 | L29: =ROUND(L28-'04_Recap'!L25,2) -> 0 | ... EX29: =ROUND(EX28-'04_Recap'!EX25,2) -> -38000
B31: — VALORISATION (CIC) —
B32: Fréquence de VL retenue | E32: =Frequence_VL -> Mensuelle | F32: =Frequence_VL -> Mensuelle | G32: =Frequence_VL -> Mensuelle | H32: =Frequence_VL -> Mensuelle | I32: =Frequence_VL -> Mensuelle | J32: =Frequence_VL -> Mensuelle | K32: =Frequence_VL -> Mensuelle | L32: =Frequence_VL -> Mensuelle | ... EX32: =Frequence_VL -> Mensuelle
B33: Tranche d'actif atteinte | E33: =IF(E$21<'01_Input'!$K$61,"0 - "&TEXT('01_Input'!$K$61/1000000,"0")&"M€",IF(E$21<'01_Input'!$O$61,TEXT('01_Input'!$K$61/1000000,"0")&" - "&TEXT('01_Input'!$O$61/1000000,"0")&"M€",IF(E$21<'01_Input'!$S$61,TEXT('01_Input'!$O$61/1000000,"0")&" - "&TEXT('01_Input'!$S$61/1000000,"0")&"M€","> "&TEXT('01_Input'!$S$61/1000000,"0")&"M€"))) -> 0 - 40M€ | F33: =IF(F$21<'01_Input'!$K$61,"0 - "&TEXT('01_Input'!$K$61/1000000,"0")&"M€",IF(F$21<'01_Input'!$O$61,TEXT('01_Input'!$K$61/1000000,"0")&" - "&TEXT('01_Input'!$O$61/1000000,"0")&"M€",IF(F$21<'01_Input'!$S$61,TEXT('01_Input'!$O$61/1000000,"0")&" - "&TEXT('01_Input'!$S$61/1000000,"0")&"M€","> "&TEXT('01_Input'!$S$61/1000000,"0")&"M€"))) -> 0 - 40M€ | G33: =IF(G$21<'01_Input'!$K$61,"0 - "&TEXT('01_Input'!$K$61/1000000,"0")&"M€",IF(G$21<'01_Input'!$O$61,TEXT('01_Input'!$K$61/1000000,"0")&" - "&TEXT('01_Input'!$O$61/1000000,"0")&"M€",IF(G$21<'01_Input'!$S$61,TEXT('01_Input'!$O$61/1000000,"0")&" - "&TEXT('01_Input'!$S$61/1000000,"0")&"M€","> "&TEXT('01_Input'!$S$61/1000000,"0")&"M€"))) -> 0 - 40M€ | H33: =IF(H$21<'01_Input'!$K$61,"0 - "&TEXT('01_Input'!$K$61/1000000,"0")&"M€",IF(H$21<'01_Input'!$O$61,TEXT('01_Input'!$K$61/1000000,"0")&" - "&TEXT('01_Input'!$O$61/1000000,"0")&"M€",IF(H$21<'01_Input'!$S$61,TEXT('01_Input'!$O$61/1000000,"0")&" - "&TEXT('01_Input'!$S$61/1000000,"0")&"M€","> "&TEXT('01_Input'!$S$61/1000000,"0")&"M€"))) -> 0 - 40M€ | I33: =IF(I$21<'01_Input'!$K$61,"0 - "&TEXT('01_Input'!$K$61/1000000,"0")&"M€",IF(I$21<'01_Input'!$O$61,TEXT('01_Input'!$K$61/1000000,"0")&" - "&TEXT('01_Input'!$O$61/1000000,"0")&"M€",IF(I$21<'01_Input'!$S$61,TEXT('01_Input'!$O$61/1000000,"0")&" - "&TEXT('01_Input'!$S$61/1000000,"0")&"M€","> "&TEXT('01_Input'!$S$61/1000000,"0")&"M€"))) -> 0 - 40M€ | J33: =IF(J$21<'01_Input'!$K$61,"0 - "&TEXT('01_Input'!$K$61/1000000,"0")&"M€",IF(J$21<'01_Input'!$O$61,TEXT('01_Input'!$K$61/1000000,"0")&" - "&TEXT('01_Input'!$O$61/1000000,"0")&"M€",IF(J$21<'01_Input'!$S$61,TEXT('01_Input'!$O$61/1000000,"0")&" - "&TEXT('01_Input'!$S$61/1000000,"0")&"M€","> "&TEXT('01_Input'!$S$61/1000000,"0")&"M€"))) -> 0 - 40M€ | K33: =IF(K$21<'01_Input'!$K$61,"0 - "&TEXT('01_Input'!$K$61/1000000,"0")&"M€",IF(K$21<'01_Input'!$O$61,TEXT('01_Input'!$K$61/1000000,"0")&" - "&TEXT('01_Input'!$O$61/1000000,"0")&"M€",IF(K$21<'01_Input'!$S$61,TEXT('01_Input'!$O$61/1000000,"0")&" - "&TEXT('01_Input'!$S$61/1000000,"0")&"M€","> "&TEXT('01_Input'!$S$61/1000000,"0")&"M€"))) -> 0 - 40M€ | L33: =IF(L$21<'01_Input'!$K$61,"0 - "&TEXT('01_Input'!$K$61/1000000,"0")&"M€",IF(L$21<'01_Input'!$O$61,TEXT('01_Input'!$K$61/1000000,"0")&" - "&TEXT('01_Input'!$O$61/1000000,"0")&"M€",IF(L$21<'01_Input'!$S$61,TEXT('01_Input'!$O$61/1000000,"0")&" - "&TEXT('01_Input'!$S$61/1000000,"0")&"M€","> "&TEXT('01_Input'!$S$61/1000000,"0")&"M€"))) -> 40 - 80M€ | ... EX33: =IF(EX$21<'01_Input'!$K$61,"0 - "&TEXT('01_Input'!$K$61/1000000,"0")&"M€",IF(EX$21<'01_Input'!$O$61,TEXT('01_Input'!$K$61/1000000,"0")&" - "&TEXT('01_Input'!$O$61/1000000,"0")&"M€",IF(EX$21<'01_Input'!$S$61,TEXT('01_Input'!$O$61/1000000,"0")&" - "&TEXT('01_Input'!$S$61/1000000,"0")&"M€","> "&TEXT('01_Input'!$S$61/1000000,"0")&"M€"))) -> > 120M€
B34: Montant de la tranche (majoration incluse) (€) | E34: =IF(E$21<'01_Input'!$K$61,'01_Input'!$M$61,IF(E$21<'01_Input'!$O$61,'01_Input'!$Q$61,IF(E$21<'01_Input'!$S$61,'01_Input'!$U$61,'01_Input'!$Y$61))) -> 12000 | F34: =IF(F$21<'01_Input'!$K$61,'01_Input'!$M$61,IF(F$21<'01_Input'!$O$61,'01_Input'!$Q$61,IF(F$21<'01_Input'!$S$61,'01_Input'!$U$61,'01_Input'!$Y$61))) -> 12000 | G34: =IF(G$21<'01_Input'!$K$61,'01_Input'!$M$61,IF(G$21<'01_Input'!$O$61,'01_Input'!$Q$61,IF(G$21<'01_Input'!$S$61,'01_Input'!$U$61,'01_Input'!$Y$61))) -> 12000 | H34: =IF(H$21<'01_Input'!$K$61,'01_Input'!$M$61,IF(H$21<'01_Input'!$O$61,'01_Input'!$Q$61,IF(H$21<'01_Input'!$S$61,'01_Input'!$U$61,'01_Input'!$Y$61))) -> 12000 | I34: =IF(I$21<'01_Input'!$K$61,'01_Input'!$M$61,IF(I$21<'01_Input'!$O$61,'01_Input'!$Q$61,IF(I$21<'01_Input'!$S$61,'01_Input'!$U$61,'01_Input'!$Y$61))) -> 12000 | J34: =IF(J$21<'01_Input'!$K$61,'01_Input'!$M$61,IF(J$21<'01_Input'!$O$61,'01_Input'!$Q$61,IF(J$21<'01_Input'!$S$61,'01_Input'!$U$61,'01_Input'!$Y$61))) -> 12000 | K34: =IF(K$21<'01_Input'!$K$61,'01_Input'!$M$61,IF(K$21<'01_Input'!$O$61,'01_Input'!$Q$61,IF(K$21<'01_Input'!$S$61,'01_Input'!$U$61,'01_Input'!$Y$61))) -> 12000 | L34: =IF(L$21<'01_Input'!$K$61,'01_Input'!$M$61,IF(L$21<'01_Input'!$O$61,'01_Input'!$Q$61,IF(L$21<'01_Input'!$S$61,'01_Input'!$U$61,'01_Input'!$Y$61))) -> 14000 | ... EX34: =IF(EX$21<'01_Input'!$K$61,'01_Input'!$M$61,IF(EX$21<'01_Input'!$O$61,'01_Input'!$Q$61,IF(EX$21<'01_Input'!$S$61,'01_Input'!$U$61,'01_Input'!$Y$61))) -> 18000
B35: Majoration appliquée (%) | E35: =Majoration_Valorisation -> 0 | F35: =Majoration_Valorisation -> 0 | G35: =Majoration_Valorisation -> 0 | H35: =Majoration_Valorisation -> 0 | I35: =Majoration_Valorisation -> 0 | J35: =Majoration_Valorisation -> 0 | K35: =Majoration_Valorisation -> 0 | L35: =Majoration_Valorisation -> 0 | ... EX35: =Majoration_Valorisation -> 0
B36: Nombre de lignes du portefeuille | E36: =Nb_Lignes_Valorisation -> 2 | F36: =Nb_Lignes_Valorisation -> 2 | G36: =Nb_Lignes_Valorisation -> 2 | H36: =Nb_Lignes_Valorisation -> 2 | I36: =Nb_Lignes_Valorisation -> 2 | J36: =Nb_Lignes_Valorisation -> 2 | K36: =Nb_Lignes_Valorisation -> 2 | L36: =Nb_Lignes_Valorisation -> 2 | ... EX36: =Nb_Lignes_Valorisation -> 2
B37: Supplément lignes (€) | E37: ='01_Input'!$AC$61 -> 0 | F37: ='01_Input'!$AC$61 -> 0 | G37: ='01_Input'!$AC$61 -> 0 | H37: ='01_Input'!$AC$61 -> 0 | I37: ='01_Input'!$AC$61 -> 0 | J37: ='01_Input'!$AC$61 -> 0 | K37: ='01_Input'!$AC$61 -> 0 | L37: ='01_Input'!$AC$61 -> 0 | ... EX37: ='01_Input'!$AC$61 -> 0
B38: → Valorisation (CIC) retenue (€) | E38: =E34+E37 -> 12000 | F38: =F34+F37 -> 12000 | G38: =G34+G37 -> 12000 | H38: =H34+H37 -> 12000 | I38: =I34+I37 -> 12000 | J38: =J34+J37 -> 12000 | K38: =K34+K37 -> 12000 | L38: =L34+L37 -> 14000 | ... EX38: =EX34+EX37 -> 18000
B39: Écart vs 04_Recap (doit être 0) | E39: =ROUND(E38-'04_Recap'!E29,2) -> 0 | F39: =ROUND(F38-'04_Recap'!F29,2) -> 0 | G39: =ROUND(G38-'04_Recap'!G29,2) -> 0 | H39: =ROUND(H38-'04_Recap'!H29,2) -> 0 | I39: =ROUND(I38-'04_Recap'!I29,2) -> 0 | J39: =ROUND(J38-'04_Recap'!J29,2) -> 0 | K39: =ROUND(K38-'04_Recap'!K29,2) -> 0 | L39: =ROUND(L38-'04_Recap'!L29,2) -> 0 | ... EX39: =ROUND(EX38-'04_Recap'!EX29,2) -> 18000

Sheet 04_Recap
B1: 04_RÉCAP — Zéro saisie manuelle — tout provient de 01_Input (et 02_Classes_de_Parts si utilisé)
B2: Une ligne par frais/provision, une colonne par niveau d'Actif Net (repris de l'échelle définie en 01_Input) — pour lire d'un coup d'œil comment chaque poste évolue avec la taille du fonds. Les postes en mode "Résiduel vs Gestion" ou "Taux Classe sélectionnée" (01_Input) reflètent la classe de parts choisie en 01_Input §3B. Détail pas-à-pas des postes Dépositaire et Valorisation : voir 03_Detail_Depositaire_Valo.
B4: Fonds testé : | C4: =Nom_Fonds -> AF CVC
B5: Classe testée (si applicable) : | C5: =Classe_Selectionnee -> A
B20: Poste de frais | C20: Bénéficiaire | D20: Actif ? | E20: {=INDEX(AUM_Ladder,1)} -> 5000000 | F20: {=INDEX(AUM_Ladder,2)} -> 10000000 | G20: {=INDEX(AUM_Ladder,3)} -> 15000000 | H20: {=INDEX(AUM_Ladder,4)} -> 20000000 | I20: {=INDEX(AUM_Ladder,5)} -> 25000000 | J20: {=INDEX(AUM_Ladder,6)} -> 30000000 | K20: {=INDEX(AUM_Ladder,7)} -> 35000000 | L20: {=INDEX(AUM_Ladder,8)} -> 40000000 | M20: {=INDEX(AUM_Ladder,9)} -> 45000000 | N20: {=INDEX(AUM_Ladder,10)} -> 50000000 | O20: {=INDEX(AUM_Ladder,11)} | P20: {=INDEX(AUM_Ladder,12)} | Q20: {=INDEX(AUM_Ladder,13)} | R20: {=INDEX(AUM_Ladder,14)} | S20: {=INDEX(AUM_Ladder,15)} | T20: {=INDEX(AUM_Ladder,16)} | U20: {=INDEX(AUM_Ladder,17)} | V20: {=INDEX(AUM_Ladder,18)} | W20: {=INDEX(AUM_Ladder,19)} | X20: {=INDEX(AUM_Ladder,20)} | Y20: {=INDEX(AUM_Ladder,21)} | Z20: {=INDEX(AUM_Ladder,22)} | AA20: {=INDEX(AUM_Ladder,23)} | AB20: {=INDEX(AUM_Ladder,24)} | AC20: {=INDEX(AUM_Ladder,25)} | AD20: {=INDEX(AUM_Ladder,26)} | AE20: {=INDEX(AUM_Ladder,27)} | AF20: {=INDEX(AUM_Ladder,28)} | AG20: {=INDEX(AUM_Ladder,29)} | AH20: {=INDEX(AUM_Ladder,30)} | AI20: {=INDEX(AUM_Ladder,31)} | AJ20: {=INDEX(AUM_Ladder,32)} | AK20: {=INDEX(AUM_Ladder,33)} | AL20: {=INDEX(AUM_Ladder,34)} | AM20: {=INDEX(AUM_Ladder,35)} | AN20: {=INDEX(AUM_Ladder,36)} | AO20: {=INDEX(AUM_Ladder,37)} | AP20: {=INDEX(AUM_Ladder,38)} | AQ20: {=INDEX(AUM_Ladder,39)} | AR20: {=INDEX(AUM_Ladder,40)} | AS20: {=INDEX(AUM_Ladder,41)} | AT20: {=INDEX(AUM_Ladder,42)} | AU20: {=INDEX(AUM_Ladder,43)} | AV20: {=INDEX(AUM_Ladder,44)} | AW20: {=INDEX(AUM_Ladder,45)} | AX20: {=INDEX(AUM_Ladder,46)} | AY20: {=INDEX(AUM_Ladder,47)} | AZ20: {=INDEX(AUM_Ladder,48)} | BA20: {=INDEX(AUM_Ladder,49)} | BB20: {=INDEX(AUM_Ladder,50)} | BC20: {=INDEX(AUM_Ladder,51)} | BD20: {=INDEX(AUM_Ladder,52)} | BE20: {=INDEX(AUM_Ladder,53)} | BF20: {=INDEX(AUM_Ladder,54)} | BG20: {=INDEX(AUM_Ladder,55)} | BH20: {=INDEX(AUM_Ladder,56)} | BI20: {=INDEX(AUM_Ladder,57)} | BJ20: {=INDEX(AUM_Ladder,58)} | BK20: {=INDEX(AUM_Ladder,59)} | BL20: {=INDEX(AUM_Ladder,60)} | BM20: {=INDEX(AUM_Ladder,61)} | BN20: {=INDEX(AUM_Ladder,62)} | BO20: {=INDEX(AUM_Ladder,63)} | BP20: {=INDEX(AUM_Ladder,64)} | BQ20: {=INDEX(AUM_Ladder,65)} | BR20: {=INDEX(AUM_Ladder,66)} | BS20: {=INDEX(AUM_Ladder,67)} | BT20: {=INDEX(AUM_Ladder,68)} | BU20: {=INDEX(AUM_Ladder,69)} | BV20: {=INDEX(AUM_Ladder,70)} | BW20: {=INDEX(AUM_Ladder,71)} | BX20: {=INDEX(AUM_Ladder,72)} | BY20: {=INDEX(AUM_Ladder,73)} | BZ20: {=INDEX(AUM_Ladder,74)} | CA20: {=INDEX(AUM_Ladder,75)} | CB20: {=INDEX(AUM_Ladder,76)} | CC20: {=INDEX(AUM_Ladder,77)} | CD20: {=INDEX(AUM_Ladder,78)} | CE20: {=INDEX(AUM_Ladder,79)} | CF20: {=INDEX(AUM_Ladder,80)} | CG20: {=INDEX(AUM_Ladder,81)} | CH20: {=INDEX(AUM_Ladder,82)} | CI20: {=INDEX(AUM_Ladder,83)} | CJ20: {=INDEX(AUM_Ladder,84)} | CK20: {=INDEX(AUM_Ladder,85)} | CL20: {=INDEX(AUM_Ladder,86)} | CM20: {=INDEX(AUM_Ladder,87)} | CN20: {=INDEX(AUM_Ladder,88)} | CO20: {=INDEX(AUM_Ladder,89)} | CP20: {=INDEX(AUM_Ladder,90)} | CQ20: {=INDEX(AUM_Ladder,91)} | CR20: {=INDEX(AUM_Ladder,92)} | CS20: {=INDEX(AUM_Ladder,93)} | CT20: {=INDEX(AUM_Ladder,94)} | CU20: {=INDEX(AUM_Ladder,95)} | CV20: {=INDEX(AUM_Ladder,96)} | CW20: {=INDEX(AUM_Ladder,97)} | CX20: {=INDEX(AUM_Ladder,98)} | CY20: {=INDEX(AUM_Ladder,99)} | CZ20: {=INDEX(AUM_Ladder,100)} | DA20: {=INDEX(AUM_Ladder,101)} | DB20: {=INDEX(AUM_Ladder,102)} | DC20: {=INDEX(AUM_Ladder,103)} | DD20: {=INDEX(AUM_Ladder,104)} | DE20: {=INDEX(AUM_Ladder,105)} | DF20: {=INDEX(AUM_Ladder,106)} | DG20: {=INDEX(AUM_Ladder,107)} | DH20: {=INDEX(AUM_Ladder,108)} | DI20: {=INDEX(AUM_Ladder,109)} | DJ20: {=INDEX(AUM_Ladder,110)} | DK20: {=INDEX(AUM_Ladder,111)} | DL20: {=INDEX(AUM_Ladder,112)} | DM20: {=INDEX(AUM_Ladder,113)} | DN20: {=INDEX(AUM_Ladder,114)} | DO20: {=INDEX(AUM_Ladder,115)} | DP20: {=INDEX(AUM_Ladder,116)} | DQ20: {=INDEX(AUM_Ladder,117)} | DR20: {=INDEX(AUM_Ladder,118)} | DS20: {=INDEX(AUM_Ladder,119)} | DT20: {=INDEX(AUM_Ladder,120)} | DU20: {=INDEX(AUM_Ladder,121)} | DV20: {=INDEX(AUM_Ladder,122)} | DW20: {=INDEX(AUM_Ladder,123)} | DX20: {=INDEX(AUM_Ladder,124)} | DY20: {=INDEX(AUM_Ladder,125)} | DZ20: {=INDEX(AUM_Ladder,126)} | EA20: {=INDEX(AUM_Ladder,127)} | EB20: {=INDEX(AUM_Ladder,128)} | EC20: {=INDEX(AUM_Ladder,129)} | ED20: {=INDEX(AUM_Ladder,130)} | EE20: {=INDEX(AUM_Ladder,131)} | EF20: {=INDEX(AUM_Ladder,132)} | EG20: {=INDEX(AUM_Ladder,133)} | EH20: {=INDEX(AUM_Ladder,134)} | EI20: {=INDEX(AUM_Ladder,135)} | EJ20: {=INDEX(AUM_Ladder,136)} | EK20: {=INDEX(AUM_Ladder,137)} | EL20: {=INDEX(AUM_Ladder,138)} | EM20: {=INDEX(AUM_Ladder,139)} | EN20: {=INDEX(AUM_Ladder,140)} | EO20: {=INDEX(AUM_Ladder,141)} | EP20: {=INDEX(AUM_Ladder,142)} | EQ20: {=INDEX(AUM_Ladder,143)} | ER20: {=INDEX(AUM_Ladder,144)} | ES20: {=INDEX(AUM_Ladder,145)} | ET20: {=INDEX(AUM_Ladder,146)} | EU20: {=INDEX(AUM_Ladder,147)} | EV20: {=INDEX(AUM_Ladder,148)} | EW20: {=INDEX(AUM_Ladder,149)} | EX20: {=INDEX(AUM_Ladder,150)}
B21: =IF('01_Input'!D53="","(inactif)",'01_Input'!D53) -> Commission de Gestion | C21: =IF('01_Input'!E53="","",'01_Input'!E53) | D21: ='01_Input'!C53 -> Oui | E21: =IF('01_Input'!$C$53="Non",0,MIN('01_Input'!$I$53,MAX('01_Input'!$H$53,IF('01_Input'!$G$53="Résiduel vs Gestion",0,IF('01_Input'!$G$53="Taux Classe sélectionnée",Distrib_Global_Classe_Selectionnee*E$20,IF('01_Input'!$G$53="Frais KYC (paliers de 100M€)",MAX(0,Nb_Investisseurs-Nb_KYC_Gratuites_Par_Tranche*(FLOOR(E$20/Taille_Tranche_KYC,1)+1))*Cout_Par_KYC_Supplementaire,(IF('01_Input'!$L$53="Forfait",IF(E$20>='01_Input'!$J$53,'01_Input'!$M$53,0),IF('01_Input'!$L$53="Palier",IF(AND(E$20>='01_Input'!$J$53,E$20<'01_Input'!$K$53),'01_Input'!$M$53,0),MAX(MIN(E$20,'01_Input'!$K$53)-'01_Input'!$J$53,0)*'01_Input'!$M$53))+IF('01_Input'!$P$53="Forfait",IF(E$20>='01_Input'!$N$53,'01_Input'!$Q$53,0),IF('01_Input'!$P$53="Palier",IF(AND(E$20>='01_Input'!$N$53,E$20<'01_Input'!$O$53),'01_Input'!$Q$53,0),MAX(MIN(E$20,'01_Input'!$O$53)-'01_Input'!$N$53,0)*'01_Input'!$Q$53))+IF('01_Input'!$T$53="Forfait",IF(E$20>='01_Input'!$R$53,'01_Input'!$U$53,0),IF('01_Input'!$T$53="Palier",IF(AND(E$20>='01_Input'!$R$53,E$20<'01_Input'!$S$53),'01_Input'!$U$53,0),MAX(MIN(E$20,'01_Input'!$S$53)-'01_Input'!$R$53,0)*'01_Input'!$U$53))+IF('01_Input'!$X$53="Forfait",IF(E$20>='01_Input'!$V$53,'01_Input'!$Y$53,0),IF('01_Input'!$X$53="Palier",IF(AND(E$20>='01_Input'!$V$53,E$20<'01_Input'!$W$53),'01_Input'!$Y$53,0),MAX(MIN(E$20,'01_Input'!$W$53)-'01_Input'!$V$53,0)*'01_Input'!$Y$53))+IF('01_Input'!$AB$53="Forfait",IF(E$20>='01_Input'!$Z$53,'01_Input'!$AC$53,0),IF('01_Input'!$AB$53="Palier",IF(AND(E$20>='01_Input'!$Z$53,E$20<'01_Input'!$AA$53),'01_Input'!$AC$53,0),MAX(MIN(E$20,'01_Input'!$AA$53)-'01_Input'!$Z$53,0)*'01_Input'!$AC$53))))))))) -> 60000 | F21: =IF('01_Input'!$C$53="Non",0,MIN('01_Input'!$I$53,MAX('01_Input'!$H$53,IF('01_Input'!$G$53="Résiduel vs Gestion",0,IF('01_Input'!$G$53="Taux Classe sélectionnée",Distrib_Global_Classe_Selectionnee*F$20,IF('01_Input'!$G$53="Frais KYC (paliers de 100M€)",MAX(0,Nb_Investisseurs-Nb_KYC_Gratuites_Par_Tranche*(FLOOR(F$20/Taille_Tranche_KYC,1)+1))*Cout_Par_KYC_Supplementaire,(IF('01_Input'!$L$53="Forfait",IF(F$20>='01_Input'!$J$53,'01_Input'!$M$53,0),IF('01_Input'!$L$53="Palier",IF(AND(F$20>='01_Input'!$J$53,F$20<'01_Input'!$K$53),'01_Input'!$M$53,0),MAX(MIN(F$20,'01_Input'!$K$53)-'01_Input'!$J$53,0)*'01_Input'!$M$53))+IF('01_Input'!$P$53="Forfait",IF(F$20>='01_Input'!$N$53,'01_Input'!$Q$53,0),IF('01_Input'!$P$53="Palier",IF(AND(F$20>='01_Input'!$N$53,F$20<'01_Input'!$O$53),'01_Input'!$Q$53,0),MAX(MIN(F$20,'01_Input'!$O$53)-'01_Input'!$N$53,0)*'01_Input'!$Q$53))+IF('01_Input'!$T$53="Forfait",IF(F$20>='01_Input'!$R$53,'01_Input'!$U$53,0),IF('01_Input'!$T$53="Palier",IF(AND(F$20>='01_Input'!$R$53,F$20<'01_Input'!$S$53),'01_Input'!$U$53,0),MAX(MIN(F$20,'01_Input'!$S$53)-'01_Input'!$R$53,0)*'01_Input'!$U$53))+IF('01_Input'!$X$53="Forfait",IF(F$20>='01_Input'!$V$53,'01_Input'!$Y$53,0),IF('01_Input'!$X$53="Palier",IF(AND(F$20>='01_Input'!$V$53,F$20<'01_Input'!$W$53),'01_Input'!$Y$53,0),MAX(MIN(F$20,'01_Input'!$W$53)-'01_Input'!$V$53,0)*'01_Input'!$Y$53))+IF('01_Input'!$AB$53="Forfait",IF(F$20>='01_Input'!$Z$53,'01_Input'!$AC$53,0),IF('01_Input'!$AB$53="Palier",IF(AND(F$20>='01_Input'!$Z$53,F$20<'01_Input'!$AA$53),'01_Input'!$AC$53,0),MAX(MIN(F$20,'01_Input'!$AA$53)-'01_Input'!$Z$53,0)*'01_Input'!$AC$53))))))))) -> 60000 | G21: =IF('01_Input'!$C$53="Non",0,MIN('01_Input'!$I$53,MAX('01_Input'!$H$53,IF('01_Input'!$G$53="Résiduel vs Gestion",0,IF('01_Input'!$G$53="Taux Classe sélectionnée",Distrib_Global_Classe_Selectionnee*G$20,IF('01_Input'!$G$53="Frais KYC (paliers de 100M€)",MAX(0,Nb_Investisseurs-Nb_KYC_Gratuites_Par_Tranche*(FLOOR(G$20/Taille_Tranche_KYC,1)+1))*Cout_Par_KYC_Supplementaire,(IF('01_Input'!$L$53="Forfait",IF(G$20>='01_Input'!$J$53,'01_Input'!$M$53,0),IF('01_Input'!$L$53="Palier",IF(AND(G$20>='01_Input'!$J$53,G$20<'01_Input'!$K$53),'01_Input'!$M$53,0),MAX(MIN(G$20,'01_Input'!$K$53)-'01_Input'!$J$53,0)*'01_Input'!$M$53))+IF('01_Input'!$P$53="Forfait",IF(G$20>='01_Input'!$N$53,'01_Input'!$Q$53,0),IF('01_Input'!$P$53="Palier",IF(AND(G$20>='01_Input'!$N$53,G$20<'01_Input'!$O$53),'01_Input'!$Q$53,0),MAX(MIN(G$20,'01_Input'!$O$53)-'01_Input'!$N$53,0)*'01_Input'!$Q$53))+IF('01_Input'!$T$53="Forfait",IF(G$20>='01_Input'!$R$53,'01_Input'!$U$53,0),IF('01_Input'!$T$53="Palier",IF(AND(G$20>='01_Input'!$R$53,G$20<'01_Input'!$S$53),'01_Input'!$U$53,0),MAX(MIN(G$20,'01_Input'!$S$53)-'01_Input'!$R$53,0)*'01_Input'!$U$53))+IF('01_Input'!$X$53="Forfait",IF(G$20>='01_Input'!$V$53,'01_Input'!$Y$53,0),IF('01_Input'!$X$53="Palier",IF(AND(G$20>='01_Input'!$V$53,G$20<'01_Input'!$W$53),'01_Input'!$Y$53,0),MAX(MIN(G$20,'01_Input'!$W$53)-'01_Input'!$V$53,0)*'01_Input'!$Y$53))+IF('01_Input'!$AB$53="Forfait",IF(G$20>='01_Input'!$Z$53,'01_Input'!$AC$53,0),IF('01_Input'!$AB$53="Palier",IF(AND(G$20>='01_Input'!$Z$53,G$20<'01_Input'!$AA$53),'01_Input'!$AC$53,0),MAX(MIN(G$20,'01_Input'!$AA$53)-'01_Input'!$Z$53,0)*'01_Input'!$AC$53))))))))) -> 60000 | H21: =IF('01_Input'!$C$53="Non",0,MIN('01_Input'!$I$53,MAX('01_Input'!$H$53,IF('01_Input'!$G$53="Résiduel vs Gestion",0,IF('01_Input'!$G$53="Taux Classe sélectionnée",Distrib_Global_Classe_Selectionnee*H$20,IF('01_Input'!$G$53="Frais KYC (paliers de 100M€)",MAX(0,Nb_Investisseurs-Nb_KYC_Gratuites_Par_Tranche*(FLOOR(H$20/Taille_Tranche_KYC,1)+1))*Cout_Par_KYC_Supplementaire,(IF('01_Input'!$L$53="Forfait",IF(H$20>='01_Input'!$J$53,'01_Input'!$M$53,0),IF('01_Input'!$L$53="Palier",IF(AND(H$20>='01_Input'!$J$53,H$20<'01_Input'!$K$53),'01_Input'!$M$53,0),MAX(MIN(H$20,'01_Input'!$K$53)-'01_Input'!$J$53,0)*'01_Input'!$M$53))+IF('01_Input'!$P$53="Forfait",IF(H$20>='01_Input'!$N$53,'01_Input'!$Q$53,0),IF('01_Input'!$P$53="Palier",IF(AND(H$20>='01_Input'!$N$53,H$20<'01_Input'!$O$53),'01_Input'!$Q$53,0),MAX(MIN(H$20,'01_Input'!$O$53)-'01_Input'!$N$53,0)*'01_Input'!$Q$53))+IF('01_Input'!$T$53="Forfait",IF(H$20>='01_Input'!$R$53,'01_Input'!$U$53,0),IF('01_Input'!$T$53="Palier",IF(AND(H$20>='01_Input'!$R$53,H$20<'01_Input'!$S$53),'01_Input'!$U$53,0),MAX(MIN(H$20,'01_Input'!$S$53)-'01_Input'!$R$53,0)*'01_Input'!$U$53))+IF('01_Input'!$X$53="Forfait",IF(H$20>='01_Input'!$V$53,'01_Input'!$Y$53,0),IF('01_Input'!$X$53="Palier",IF(AND(H$20>='01_Input'!$V$53,H$20<'01_Input'!$W$53),'01_Input'!$Y$53,0),MAX(MIN(H$20,'01_Input'!$W$53)-'01_Input'!$V$53,0)*'01_Input'!$Y$53))+IF('01_Input'!$AB$53="Forfait",IF(H$20>='01_Input'!$Z$53,'01_Input'!$AC$53,0),IF('01_Input'!$AB$53="Palier",IF(AND(H$20>='01_Input'!$Z$53,H$20<'01_Input'!$AA$53),'01_Input'!$AC$53,0),MAX(MIN(H$20,'01_Input'!$AA$53)-'01_Input'!$Z$53,0)*'01_Input'!$AC$53))))))))) -> 60000 | I21: =IF('01_Input'!$C$53="Non",0,MIN('01_Input'!$I$53,MAX('01_Input'!$H$53,IF('01_Input'!$G$53="Résiduel vs Gestion",0,IF('01_Input'!$G$53="Taux Classe sélectionnée",Distrib_Global_Classe_Selectionnee*I$20,IF('01_Input'!$G$53="Frais KYC (paliers de 100M€)",MAX(0,Nb_Investisseurs-Nb_KYC_Gratuites_Par_Tranche*(FLOOR(I$20/Taille_Tranche_KYC,1)+1))*Cout_Par_KYC_Supplementaire,(IF('01_Input'!$L$53="Forfait",IF(I$20>='01_Input'!$J$53,'01_Input'!$M$53,0),IF('01_Input'!$L$53="Palier",IF(AND(I$20>='01_Input'!$J$53,I$20<'01_Input'!$K$53),'01_Input'!$M$53,0),MAX(MIN(I$20,'01_Input'!$K$53)-'01_Input'!$J$53,0)*'01_Input'!$M$53))+IF('01_Input'!$P$53="Forfait",IF(I$20>='01_Input'!$N$53,'01_Input'!$Q$53,0),IF('01_Input'!$P$53="Palier",IF(AND(I$20>='01_Input'!$N$53,I$20<'01_Input'!$O$53),'01_Input'!$Q$53,0),MAX(MIN(I$20,'01_Input'!$O$53)-'01_Input'!$N$53,0)*'01_Input'!$Q$53))+IF('01_Input'!$T$53="Forfait",IF(I$20>='01_Input'!$R$53,'01_Input'!$U$53,0),IF('01_Input'!$T$53="Palier",IF(AND(I$20>='01_Input'!$R$53,I$20<'01_Input'!$S$53),'01_Input'!$U$53,0),MAX(MIN(I$20,'01_Input'!$S$53)-'01_Input'!$R$53,0)*'01_Input'!$U$53))+IF('01_Input'!$X$53="Forfait",IF(I$20>='01_Input'!$V$53,'01_Input'!$Y$53,0),IF('01_Input'!$X$53="Palier",IF(AND(I$20>='01_Input'!$V$53,I$20<'01_Input'!$W$53),'01_Input'!$Y$53,0),MAX(MIN(I$20,'01_Input'!$W$53)-'01_Input'!$V$53,0)*'01_Input'!$Y$53))+IF('01_Input'!$AB$53="Forfait",IF(I$20>='01_Input'!$Z$53,'01_Input'!$AC$53,0),IF('01_Input'!$AB$53="Palier",IF(AND(I$20>='01_Input'!$Z$53,I$20<'01_Input'!$AA$53),'01_Input'!$AC$53,0),MAX(MIN(I$20,'01_Input'!$AA$53)-'01_Input'!$Z$53,0)*'01_Input'!$AC$53))))))))) -> 60000 | J21: =IF('01_Input'!$C$53="Non",0,MIN('01_Input'!$I$53,MAX('01_Input'!$H$53,IF('01_Input'!$G$53="Résiduel vs Gestion",0,IF('01_Input'!$G$53="Taux Classe sélectionnée",Distrib_Global_Classe_Selectionnee*J$20,IF('01_Input'!$G$53="Frais KYC (paliers de 100M€)",MAX(0,Nb_Investisseurs-Nb_KYC_Gratuites_Par_Tranche*(FLOOR(J$20/Taille_Tranche_KYC,1)+1))*Cout_Par_KYC_Supplementaire,(IF('01_Input'!$L$53="Forfait",IF(J$20>='01_Input'!$J$53,'01_Input'!$M$53,0),IF('01_Input'!$L$53="Palier",IF(AND(J$20>='01_Input'!$J$53,J$20<'01_Input'!$K$53),'01_Input'!$M$53,0),MAX(MIN(J$20,'01_Input'!$K$53)-'01_Input'!$J$53,0)*'01_Input'!$M$53))+IF('01_Input'!$P$53="Forfait",IF(J$20>='01_Input'!$N$53,'01_Input'!$Q$53,0),IF('01_Input'!$P$53="Palier",IF(AND(J$20>='01_Input'!$N$53,J$20<'01_Input'!$O$53),'01_Input'!$Q$53,0),MAX(MIN(J$20,'01_Input'!$O$53)-'01_Input'!$N$53,0)*'01_Input'!$Q$53))+IF('01_Input'!$T$53="Forfait",IF(J$20>='01_Input'!$R$53,'01_Input'!$U$53,0),IF('01_Input'!$T$53="Palier",IF(AND(J$20>='01_Input'!$R$53,J$20<'01_Input'!$S$53),'01_Input'!$U$53,0),MAX(MIN(J$20,'01_Input'!$S$53)-'01_Input'!$R$53,0)*'01_Input'!$U$53))+IF('01_Input'!$X$53="Forfait",IF(J$20>='01_Input'!$V$53,'01_Input'!$Y$53,0),IF('01_Input'!$X$53="Palier",IF(AND(J$20>='01_Input'!$V$53,J$20<'01_Input'!$W$53),'01_Input'!$Y$53,0),MAX(MIN(J$20,'01_Input'!$W$53)-'01_Input'!$V$53,0)*'01_Input'!$Y$53))+IF('01_Input'!$AB$53="Forfait",IF(J$20>='01_Input'!$Z$53,'01_Input'!$AC$53,0),IF('01_Input'!$AB$53="Palier",IF(AND(J$20>='01_Input'!$Z$53,J$20<'01_Input'!$AA$53),'01_Input'!$AC$53,0),MAX(MIN(J$20,'01_Input'!$AA$53)-'01_Input'!$Z$53,0)*'01_Input'!$AC$53))))))))) -> 60000 | K21: =IF('01_Input'!$C$53="Non",0,MIN('01_Input'!$I$53,MAX('01_Input'!$H$53,IF('01_Input'!$G$53="Résiduel vs Gestion",0,IF('01_Input'!$G$53="Taux Classe sélectionnée",Distrib_Global_Classe_Selectionnee*K$20,IF('01_Input'!$G$53="Frais KYC (paliers de 100M€)",MAX(0,Nb_Investisseurs-Nb_KYC_Gratuites_Par_Tranche*(FLOOR(K$20/Taille_Tranche_KYC,1)+1))*Cout_Par_KYC_Supplementaire,(IF('01_Input'!$L$53="Forfait",IF(K$20>='01_Input'!$J$53,'01_Input'!$M$53,0),IF('01_Input'!$L$53="Palier",IF(AND(K$20>='01_Input'!$J$53,K$20<'01_Input'!$K$53),'01_Input'!$M$53,0),MAX(MIN(K$20,'01_Input'!$K$53)-'01_Input'!$J$53,0)*'01_Input'!$M$53))+IF('01_Input'!$P$53="Forfait",IF(K$20>='01_Input'!$N$53,'01_Input'!$Q$53,0),IF('01_Input'!$P$53="Palier",IF(AND(K$20>='01_Input'!$N$53,K$20<'01_Input'!$O$53),'01_Input'!$Q$53,0),MAX(MIN(K$20,'01_Input'!$O$53)-'01_Input'!$N$53,0)*'01_Input'!$Q$53))+IF('01_Input'!$T$53="Forfait",IF(K$20>='01_Input'!$R$53,'01_Input'!$U$53,0),IF('01_Input'!$T$53="Palier",IF(AND(K$20>='01_Input'!$R$53,K$20<'01_Input'!$S$53),'01_Input'!$U$53,0),MAX(MIN(K$20,'01_Input'!$S$53)-'01_Input'!$R$53,0)*'01_Input'!$U$53))+IF('01_Input'!$X$53="Forfait",IF(K$20>='01_Input'!$V$53,'01_Input'!$Y$53,0),IF('01_Input'!$X$53="Palier",IF(AND(K$20>='01_Input'!$V$53,K$20<'01_Input'!$W$53),'01_Input'!$Y$53,0),MAX(MIN(K$20,'01_Input'!$W$53)-'01_Input'!$V$53,0)*'01_Input'!$Y$53))+IF('01_Input'!$AB$53="Forfait",IF(K$20>='01_Input'!$Z$53,'01_Input'!$AC$53,0),IF('01_Input'!$AB$53="Palier",IF(AND(K$20>='01_Input'!$Z$53,K$20<'01_Input'!$AA$53),'01_Input'!$AC$53,0),MAX(MIN(K$20,'01_Input'!$AA$53)-'01_Input'!$Z$53,0)*'01_Input'!$AC$53))))))))) -> 63000 | L21: =IF('01_Input'!$C$53="Non",0,MIN('01_Input'!$I$53,MAX('01_Input'!$H$53,IF('01_Input'!$G$53="Résiduel vs Gestion",0,IF('01_Input'!$G$53="Taux Classe sélectionnée",Distrib_Global_Classe_Selectionnee*L$20,IF('01_Input'!$G$53="Frais KYC (paliers de 100M€)",MAX(0,Nb_Investisseurs-Nb_KYC_Gratuites_Par_Tranche*(FLOOR(L$20/Taille_Tranche_KYC,1)+1))*Cout_Par_KYC_Supplementaire,(IF('01_Input'!$L$53="Forfait",IF(L$20>='01_Input'!$J$53,'01_Input'!$M$53,0),IF('01_Input'!$L$53="Palier",IF(AND(L$20>='01_Input'!$J$53,L$20<'01_Input'!$K$53),'01_Input'!$M$53,0),MAX(MIN(L$20,'01_Input'!$K$53)-'01_Input'!$J$53,0)*'01_Input'!$M$53))+IF('01_Input'!$P$53="Forfait",IF(L$20>='01_Input'!$N$53,'01_Input'!$Q$53,0),IF('01_Input'!$P$53="Palier",IF(AND(L$20>='01_Input'!$N$53,L$20<'01_Input'!$O$53),'01_Input'!$Q$53,0),MAX(MIN(L$20,'01_Input'!$O$53)-'01_Input'!$N$53,0)*'01_Input'!$Q$53))+IF('01_Input'!$T$53="Forfait",IF(L$20>='01_Input'!$R$53,'01_Input'!$U$53,0),IF('01_Input'!$T$53="Palier",IF(AND(L$20>='01_Input'!$R$53,L$20<'01_Input'!$S$53),'01_Input'!$U$53,0),MAX(MIN(L$20,'01_Input'!$S$53)-'01_Input'!$R$53,0)*'01_Input'!$U$53))+IF('01_Input'!$X$53="Forfait",IF(L$20>='01_Input'!$V$53,'01_Input'!$Y$53,0),IF('01_Input'!$X$53="Palier",IF(AND(L$20>='01_Input'!$V$53,L$20<'01_Input'!$W$53),'01_Input'!$Y$53,0),MAX(MIN(L$20,'01_Input'!$W$53)-'01_Input'!$V$53,0)*'01_Input'!$Y$53))+IF('01_Input'!$AB$53="Forfait",IF(L$20>='01_Input'!$Z$53,'01_Input'!$AC$53,0),IF('01_Input'!$AB$53="Palier",IF(AND(L$20>='01_Input'!$Z$53,L$20<'01_Input'!$AA$53),'01_Input'!$AC$53,0),MAX(MIN(L$20,'01_Input'!$AA$53)-'01_Input'!$Z$53,0)*'01_Input'!$AC$53))))))))) -> 72000 | ... EX21: =IF('01_Input'!$C$53="Non",0,MIN('01_Input'!$I$53,MAX('01_Input'!$H$53,IF('01_Input'!$G$53="Résiduel vs Gestion",0,IF('01_Input'!$G$53="Taux Classe sélectionnée",Distrib_Global_Classe_Selectionnee*EX$20,IF('01_Input'!$G$53="Frais KYC (paliers de 100M€)",MAX(0,Nb_Investisseurs-Nb_KYC_Gratuites_Par_Tranche*(FLOOR(EX$20/Taille_Tranche_KYC,1)+1))*Cout_Par_KYC_Supplementaire,(IF('01_Input'!$L$53="Forfait",IF(EX$20>='01_Input'!$J$53,'01_Input'!$M$53,0),IF('01_Input'!$L$53="Palier",IF(AND(EX$20>='01_Input'!$J$53,EX$20<'01_Input'!$K$53),'01_Input'!$M$53,0),MAX(MIN(EX$20,'01_Input'!$K$53)-'01_Input'!$J$53,0)*'01_Input'!$M$53))+IF('01_Input'!$P$53="Forfait",IF(EX$20>='01_Input'!$N$53,'01_Input'!$Q$53,0),IF('01_Input'!$P$53="Palier",IF(AND(EX$20>='01_Input'!$N$53,EX$20<'01_Input'!$O$53),'01_Input'!$Q$53,0),MAX(MIN(EX$20,'01_Input'!$O$53)-'01_Input'!$N$53,0)*'01_Input'!$Q$53))+IF('01_Input'!$T$53="Forfait",IF(EX$20>='01_Input'!$R$53,'01_Input'!$U$53,0),IF('01_Input'!$T$53="Palier",IF(AND(EX$20>='01_Input'!$R$53,EX$20<'01_Input'!$S$53),'01_Input'!$U$53,0),MAX(MIN(EX$20,'01_Input'!$S$53)-'01_Input'!$R$53,0)*'01_Input'!$U$53))+IF('01_Input'!$X$53="Forfait",IF(EX$20>='01_Input'!$V$53,'01_Input'!$Y$53,0),IF('01_Input'!$X$53="Palier",IF(AND(EX$20>='01_Input'!$V$53,EX$20<'01_Input'!$W$53),'01_Input'!$Y$53,0),MAX(MIN(EX$20,'01_Input'!$W$53)-'01_Input'!$V$53,0)*'01_Input'!$Y$53))+IF('01_Input'!$AB$53="Forfait",IF(EX$20>='01_Input'!$Z$53,'01_Input'!$AC$53,0),IF('01_Input'!$AB$53="Palier",IF(AND(EX$20>='01_Input'!$Z$53,EX$20<'01_Input'!$AA$53),'01_Input'!$AC$53,0),MAX(MIN(EX$20,'01_Input'!$AA$53)-'01_Input'!$Z$53,0)*'01_Input'!$AC$53))))))))) -> 900290000
B22: =IF('01_Input'!D54="","(inactif)",'01_Input'!D54) -> Commission de Conseil | C22: =IF('01_Input'!E54="","",'01_Input'!E54) | D22: ='01_Input'!C54 -> Oui | E22: =IF('01_Input'!$C$54="Non",0,MIN('01_Input'!$I$54,MAX('01_Input'!$H$54,IF('01_Input'!$G$54="Résiduel vs Gestion",0,IF('01_Input'!$G$54="Taux Classe sélectionnée",Distrib_Global_Classe_Selectionnee*E$20,IF('01_Input'!$G$54="Frais KYC (paliers de 100M€)",MAX(0,Nb_Investisseurs-Nb_KYC_Gratuites_Par_Tranche*(FLOOR(E$20/Taille_Tranche_KYC,1)+1))*Cout_Par_KYC_Supplementaire,(IF('01_Input'!$L$54="Forfait",IF(E$20>='01_Input'!$J$54,'01_Input'!$M$54,0),IF('01_Input'!$L$54="Palier",IF(AND(E$20>='01_Input'!$J$54,E$20<'01_Input'!$K$54),'01_Input'!$M$54,0),MAX(MIN(E$20,'01_Input'!$K$54)-'01_Input'!$J$54,0)*'01_Input'!$M$54))+IF('01_Input'!$P$54="Forfait",IF(E$20>='01_Input'!$N$54,'01_Input'!$Q$54,0),IF('01_Input'!$P$54="Palier",IF(AND(E$20>='01_Input'!$N$54,E$20<'01_Input'!$O$54),'01_Input'!$Q$54,0),MAX(MIN(E$20,'01_Input'!$O$54)-'01_Input'!$N$54,0)*'01_Input'!$Q$54))+IF('01_Input'!$T$54="Forfait",IF(E$20>='01_Input'!$R$54,'01_Input'!$U$54,0),IF('01_Input'!$T$54="Palier",IF(AND(E$20>='01_Input'!$R$54,E$20<'01_Input'!$S$54),'01_Input'!$U$54,0),MAX(MIN(E$20,'01_Input'!$S$54)-'01_Input'!$R$54,0)*'01_Input'!$U$54))+IF('01_Input'!$X$54="Forfait",IF(E$20>='01_Input'!$V$54,'01_Input'!$Y$54,0),IF('01_Input'!$X$54="Palier",IF(AND(E$20>='01_Input'!$V$54,E$20<'01_Input'!$W$54),'01_Input'!$Y$54,0),MAX(MIN(E$20,'01_Input'!$W$54)-'01_Input'!$V$54,0)*'01_Input'!$Y$54))+IF('01_Input'!$AB$54="Forfait",IF(E$20>='01_Input'!$Z$54,'01_Input'!$AC$54,0),IF('01_Input'!$AB$54="Palier",IF(AND(E$20>='01_Input'!$Z$54,E$20<'01_Input'!$AA$54),'01_Input'!$AC$54,0),MAX(MIN(E$20,'01_Input'!$AA$54)-'01_Input'!$Z$54,0)*'01_Input'!$AC$54))))))))) -> 22500 | F22: =IF('01_Input'!$C$54="Non",0,MIN('01_Input'!$I$54,MAX('01_Input'!$H$54,IF('01_Input'!$G$54="Résiduel vs Gestion",0,IF('01_Input'!$G$54="Taux Classe sélectionnée",Distrib_Global_Classe_Selectionnee*F$20,IF('01_Input'!$G$54="Frais KYC (paliers de 100M€)",MAX(0,Nb_Investisseurs-Nb_KYC_Gratuites_Par_Tranche*(FLOOR(F$20/Taille_Tranche_KYC,1)+1))*Cout_Par_KYC_Supplementaire,(IF('01_Input'!$L$54="Forfait",IF(F$20>='01_Input'!$J$54,'01_Input'!$M$54,0),IF('01_Input'!$L$54="Palier",IF(AND(F$20>='01_Input'!$J$54,F$20<'01_Input'!$K$54),'01_Input'!$M$54,0),MAX(MIN(F$20,'01_Input'!$K$54)-'01_Input'!$J$54,0)*'01_Input'!$M$54))+IF('01_Input'!$P$54="Forfait",IF(F$20>='01_Input'!$N$54,'01_Input'!$Q$54,0),IF('01_Input'!$P$54="Palier",IF(AND(F$20>='01_Input'!$N$54,F$20<'01_Input'!$O$54),'01_Input'!$Q$54,0),MAX(MIN(F$20,'01_Input'!$O$54)-'01_Input'!$N$54,0)*'01_Input'!$Q$54))+IF('01_Input'!$T$54="Forfait",IF(F$20>='01_Input'!$R$54,'01_Input'!$U$54,0),IF('01_Input'!$T$54="Palier",IF(AND(F$20>='01_Input'!$R$54,F$20<'01_Input'!$S$54),'01_Input'!$U$54,0),MAX(MIN(F$20,'01_Input'!$S$54)-'01_Input'!$R$54,0)*'01_Input'!$U$54))+IF('01_Input'!$X$54="Forfait",IF(F$20>='01_Input'!$V$54,'01_Input'!$Y$54,0),IF('01_Input'!$X$54="Palier",IF(AND(F$20>='01_Input'!$V$54,F$20<'01_Input'!$W$54),'01_Input'!$Y$54,0),MAX(MIN(F$20,'01_Input'!$W$54)-'01_Input'!$V$54,0)*'01_Input'!$Y$54))+IF('01_Input'!$AB$54="Forfait",IF(F$20>='01_Input'!$Z$54,'01_Input'!$AC$54,0),IF('01_Input'!$AB$54="Palier",IF(AND(F$20>='01_Input'!$Z$54,F$20<'01_Input'!$AA$54),'01_Input'!$AC$54,0),MAX(MIN(F$20,'01_Input'!$AA$54)-'01_Input'!$Z$54,0)*'01_Input'!$AC$54))))))))) -> 45000 | G22: =IF('01_Input'!$C$54="Non",0,MIN('01_Input'!$I$54,MAX('01_Input'!$H$54,IF('01_Input'!$G$54="Résiduel vs Gestion",0,IF('01_Input'!$G$54="Taux Classe sélectionnée",Distrib_Global_Classe_Selectionnee*G$20,IF('01_Input'!$G$54="Frais KYC (paliers de 100M€)",MAX(0,Nb_Investisseurs-Nb_KYC_Gratuites_Par_Tranche*(FLOOR(G$20/Taille_Tranche_KYC,1)+1))*Cout_Par_KYC_Supplementaire,(IF('01_Input'!$L$54="Forfait",IF(G$20>='01_Input'!$J$54,'01_Input'!$M$54,0),IF('01_Input'!$L$54="Palier",IF(AND(G$20>='01_Input'!$J$54,G$20<'01_Input'!$K$54),'01_Input'!$M$54,0),MAX(MIN(G$20,'01_Input'!$K$54)-'01_Input'!$J$54,0)*'01_Input'!$M$54))+IF('01_Input'!$P$54="Forfait",IF(G$20>='01_Input'!$N$54,'01_Input'!$Q$54,0),IF('01_Input'!$P$54="Palier",IF(AND(G$20>='01_Input'!$N$54,G$20<'01_Input'!$O$54),'01_Input'!$Q$54,0),MAX(MIN(G$20,'01_Input'!$O$54)-'01_Input'!$N$54,0)*'01_Input'!$Q$54))+IF('01_Input'!$T$54="Forfait",IF(G$20>='01_Input'!$R$54,'01_Input'!$U$54,0),IF('01_Input'!$T$54="Palier",IF(AND(G$20>='01_Input'!$R$54,G$20<'01_Input'!$S$54),'01_Input'!$U$54,0),MAX(MIN(G$20,'01_Input'!$S$54)-'01_Input'!$R$54,0)*'01_Input'!$U$54))+IF('01_Input'!$X$54="Forfait",IF(G$20>='01_Input'!$V$54,'01_Input'!$Y$54,0),IF('01_Input'!$X$54="Palier",IF(AND(G$20>='01_Input'!$V$54,G$20<'01_Input'!$W$54),'01_Input'!$Y$54,0),MAX(MIN(G$20,'01_Input'!$W$54)-'01_Input'!$V$54,0)*'01_Input'!$Y$54))+IF('01_Input'!$AB$54="Forfait",IF(G$20>='01_Input'!$Z$54,'01_Input'!$AC$54,0),IF('01_Input'!$AB$54="Palier",IF(AND(G$20>='01_Input'!$Z$54,G$20<'01_Input'!$AA$54),'01_Input'!$AC$54,0),MAX(MIN(G$20,'01_Input'!$AA$54)-'01_Input'!$Z$54,0)*'01_Input'!$AC$54))))))))) -> 67500 | H22: =IF('01_Input'!$C$54="Non",0,MIN('01_Input'!$I$54,MAX('01_Input'!$H$54,IF('01_Input'!$G$54="Résiduel vs Gestion",0,IF('01_Input'!$G$54="Taux Classe sélectionnée",Distrib_Global_Classe_Selectionnee*H$20,IF('01_Input'!$G$54="Frais KYC (paliers de 100M€)",MAX(0,Nb_Investisseurs-Nb_KYC_Gratuites_Par_Tranche*(FLOOR(H$20/Taille_Tranche_KYC,1)+1))*Cout_Par_KYC_Supplementaire,(IF('01_Input'!$L$54="Forfait",IF(H$20>='01_Input'!$J$54,'01_Input'!$M$54,0),IF('01_Input'!$L$54="Palier",IF(AND(H$20>='01_Input'!$J$54,H$20<'01_Input'!$K$54),'01_Input'!$M$54,0),MAX(MIN(H$20,'01_Input'!$K$54)-'01_Input'!$J$54,0)*'01_Input'!$M$54))+IF('01_Input'!$P$54="Forfait",IF(H$20>='01_Input'!$N$54,'01_Input'!$Q$54,0),IF('01_Input'!$P$54="Palier",IF(AND(H$20>='01_Input'!$N$54,H$20<'01_Input'!$O$54),'01_Input'!$Q$54,0),MAX(MIN(H$20,'01_Input'!$O$54)-'01_Input'!$N$54,0)*'01_Input'!$Q$54))+IF('01_Input'!$T$54="Forfait",IF(H$20>='01_Input'!$R$54,'01_Input'!$U$54,0),IF('01_Input'!$T$54="Palier",IF(AND(H$20>='01_Input'!$R$54,H$20<'01_Input'!$S$54),'01_Input'!$U$54,0),MAX(MIN(H$20,'01_Input'!$S$54)-'01_Input'!$R$54,0)*'01_Input'!$U$54))+IF('01_Input'!$X$54="Forfait",IF(H$20>='01_Input'!$V$54,'01_Input'!$Y$54,0),IF('01_Input'!$X$54="Palier",IF(AND(H$20>='01_Input'!$V$54,H$20<'01_Input'!$W$54),'01_Input'!$Y$54,0),MAX(MIN(H$20,'01_Input'!$W$54)-'01_Input'!$V$54,0)*'01_Input'!$Y$54))+IF('01_Input'!$AB$54="Forfait",IF(H$20>='01_Input'!$Z$54,'01_Input'!$AC$54,0),IF('01_Input'!$AB$54="Palier",IF(AND(H$20>='01_Input'!$Z$54,H$20<'01_Input'!$AA$54),'01_Input'!$AC$54,0),MAX(MIN(H$20,'01_Input'!$AA$54)-'01_Input'!$Z$54,0)*'01_Input'!$AC$54))))))))) -> 90000 | I22: =IF('01_Input'!$C$54="Non",0,MIN('01_Input'!$I$54,MAX('01_Input'!$H$54,IF('01_Input'!$G$54="Résiduel vs Gestion",0,IF('01_Input'!$G$54="Taux Classe sélectionnée",Distrib_Global_Classe_Selectionnee*I$20,IF('01_Input'!$G$54="Frais KYC (paliers de 100M€)",MAX(0,Nb_Investisseurs-Nb_KYC_Gratuites_Par_Tranche*(FLOOR(I$20/Taille_Tranche_KYC,1)+1))*Cout_Par_KYC_Supplementaire,(IF('01_Input'!$L$54="Forfait",IF(I$20>='01_Input'!$J$54,'01_Input'!$M$54,0),IF('01_Input'!$L$54="Palier",IF(AND(I$20>='01_Input'!$J$54,I$20<'01_Input'!$K$54),'01_Input'!$M$54,0),MAX(MIN(I$20,'01_Input'!$K$54)-'01_Input'!$J$54,0)*'01_Input'!$M$54))+IF('01_Input'!$P$54="Forfait",IF(I$20>='01_Input'!$N$54,'01_Input'!$Q$54,0),IF('01_Input'!$P$54="Palier",IF(AND(I$20>='01_Input'!$N$54,I$20<'01_Input'!$O$54),'01_Input'!$Q$54,0),MAX(MIN(I$20,'01_Input'!$O$54)-'01_Input'!$N$54,0)*'01_Input'!$Q$54))+IF('01_Input'!$T$54="Forfait",IF(I$20>='01_Input'!$R$54,'01_Input'!$U$54,0),IF('01_Input'!$T$54="Palier",IF(AND(I$20>='01_Input'!$R$54,I$20<'01_Input'!$S$54),'01_Input'!$U$54,0),MAX(MIN(I$20,'01_Input'!$S$54)-'01_Input'!$R$54,0)*'01_Input'!$U$54))+IF('01_Input'!$X$54="Forfait",IF(I$20>='01_Input'!$V$54,'01_Input'!$Y$54,0),IF('01_Input'!$X$54="Palier",IF(AND(I$20>='01_Input'!$V$54,I$20<'01_Input'!$W$54),'01_Input'!$Y$54,0),MAX(MIN(I$20,'01_Input'!$W$54)-'01_Input'!$V$54,0)*'01_Input'!$Y$54))+IF('01_Input'!$AB$54="Forfait",IF(I$20>='01_Input'!$Z$54,'01_Input'!$AC$54,0),IF('01_Input'!$AB$54="Palier",IF(AND(I$20>='01_Input'!$Z$54,I$20<'01_Input'!$AA$54),'01_Input'!$AC$54,0),MAX(MIN(I$20,'01_Input'!$AA$54)-'01_Input'!$Z$54,0)*'01_Input'!$AC$54))))))))) -> 112500 | J22: =IF('01_Input'!$C$54="Non",0,MIN('01_Input'!$I$54,MAX('01_Input'!$H$54,IF('01_Input'!$G$54="Résiduel vs Gestion",0,IF('01_Input'!$G$54="Taux Classe sélectionnée",Distrib_Global_Classe_Selectionnee*J$20,IF('01_Input'!$G$54="Frais KYC (paliers de 100M€)",MAX(0,Nb_Investisseurs-Nb_KYC_Gratuites_Par_Tranche*(FLOOR(J$20/Taille_Tranche_KYC,1)+1))*Cout_Par_KYC_Supplementaire,(IF('01_Input'!$L$54="Forfait",IF(J$20>='01_Input'!$J$54,'01_Input'!$M$54,0),IF('01_Input'!$L$54="Palier",IF(AND(J$20>='01_Input'!$J$54,J$20<'01_Input'!$K$54),'01_Input'!$M$54,0),MAX(MIN(J$20,'01_Input'!$K$54)-'01_Input'!$J$54,0)*'01_Input'!$M$54))+IF('01_Input'!$P$54="Forfait",IF(J$20>='01_Input'!$N$54,'01_Input'!$Q$54,0),IF('01_Input'!$P$54="Palier",IF(AND(J$20>='01_Input'!$N$54,J$20<'01_Input'!$O$54),'01_Input'!$Q$54,0),MAX(MIN(J$20,'01_Input'!$O$54)-'01_Input'!$N$54,0)*'01_Input'!$Q$54))+IF('01_Input'!$T$54="Forfait",IF(J$20>='01_Input'!$R$54,'01_Input'!$U$54,0),IF('01_Input'!$T$54="Palier",IF(AND(J$20>='01_Input'!$R$54,J$20<'01_Input'!$S$54),'01_Input'!$U$54,0),MAX(MIN(J$20,'01_Input'!$S$54)-'01_Input'!$R$54,0)*'01_Input'!$U$54))+IF('01_Input'!$X$54="Forfait",IF(J$20>='01_Input'!$V$54,'01_Input'!$Y$54,0),IF('01_Input'!$X$54="Palier",IF(AND(J$20>='01_Input'!$V$54,J$20<'01_Input'!$W$54),'01_Input'!$Y$54,0),MAX(MIN(J$20,'01_Input'!$W$54)-'01_Input'!$V$54,0)*'01_Input'!$Y$54))+IF('01_Input'!$AB$54="Forfait",IF(J$20>='01_Input'!$Z$54,'01_Input'!$AC$54,0),IF('01_Input'!$AB$54="Palier",IF(AND(J$20>='01_Input'!$Z$54,J$20<'01_Input'!$AA$54),'01_Input'!$AC$54,0),MAX(MIN(J$20,'01_Input'!$AA$54)-'01_Input'!$Z$54,0)*'01_Input'!$AC$54))))))))) -> 135000 | K22: =IF('01_Input'!$C$54="Non",0,MIN('01_Input'!$I$54,MAX('01_Input'!$H$54,IF('01_Input'!$G$54="Résiduel vs Gestion",0,IF('01_Input'!$G$54="Taux Classe sélectionnée",Distrib_Global_Classe_Selectionnee*K$20,IF('01_Input'!$G$54="Frais KYC (paliers de 100M€)",MAX(0,Nb_Investisseurs-Nb_KYC_Gratuites_Par_Tranche*(FLOOR(K$20/Taille_Tranche_KYC,1)+1))*Cout_Par_KYC_Supplementaire,(IF('01_Input'!$L$54="Forfait",IF(K$20>='01_Input'!$J$54,'01_Input'!$M$54,0),IF('01_Input'!$L$54="Palier",IF(AND(K$20>='01_Input'!$J$54,K$20<'01_Input'!$K$54),'01_Input'!$M$54,0),MAX(MIN(K$20,'01_Input'!$K$54)-'01_Input'!$J$54,0)*'01_Input'!$M$54))+IF('01_Input'!$P$54="Forfait",IF(K$20>='01_Input'!$N$54,'01_Input'!$Q$54,0),IF('01_Input'!$P$54="Palier",IF(AND(K$20>='01_Input'!$N$54,K$20<'01_Input'!$O$54),'01_Input'!$Q$54,0),MAX(MIN(K$20,'01_Input'!$O$54)-'01_Input'!$N$54,0)*'01_Input'!$Q$54))+IF('01_Input'!$T$54="Forfait",IF(K$20>='01_Input'!$R$54,'01_Input'!$U$54,0),IF('01_Input'!$T$54="Palier",IF(AND(K$20>='01_Input'!$R$54,K$20<'01_Input'!$S$54),'01_Input'!$U$54,0),MAX(MIN(K$20,'01_Input'!$S$54)-'01_Input'!$R$54,0)*'01_Input'!$U$54))+IF('01_Input'!$X$54="Forfait",IF(K$20>='01_Input'!$V$54,'01_Input'!$Y$54,0),IF('01_Input'!$X$54="Palier",IF(AND(K$20>='01_Input'!$V$54,K$20<'01_Input'!$W$54),'01_Input'!$Y$54,0),MAX(MIN(K$20,'01_Input'!$W$54)-'01_Input'!$V$54,0)*'01_Input'!$Y$54))+IF('01_Input'!$AB$54="Forfait",IF(K$20>='01_Input'!$Z$54,'01_Input'!$AC$54,0),IF('01_Input'!$AB$54="Palier",IF(AND(K$20>='01_Input'!$Z$54,K$20<'01_Input'!$AA$54),'01_Input'!$AC$54,0),MAX(MIN(K$20,'01_Input'!$AA$54)-'01_Input'!$Z$54,0)*'01_Input'!$AC$54))))))))) -> 157500 | L22: =IF('01_Input'!$C$54="Non",0,MIN('01_Input'!$I$54,MAX('01_Input'!$H$54,IF('01_Input'!$G$54="Résiduel vs Gestion",0,IF('01_Input'!$G$54="Taux Classe sélectionnée",Distrib_Global_Classe_Selectionnee*L$20,IF('01_Input'!$G$54="Frais KYC (paliers de 100M€)",MAX(0,Nb_Investisseurs-Nb_KYC_Gratuites_Par_Tranche*(FLOOR(L$20/Taille_Tranche_KYC,1)+1))*Cout_Par_KYC_Supplementaire,(IF('01_Input'!$L$54="Forfait",IF(L$20>='01_Input'!$J$54,'01_Input'!$M$54,0),IF('01_Input'!$L$54="Palier",IF(AND(L$20>='01_Input'!$J$54,L$20<'01_Input'!$K$54),'01_Input'!$M$54,0),MAX(MIN(L$20,'01_Input'!$K$54)-'01_Input'!$J$54,0)*'01_Input'!$M$54))+IF('01_Input'!$P$54="Forfait",IF(L$20>='01_Input'!$N$54,'01_Input'!$Q$54,0),IF('01_Input'!$P$54="Palier",IF(AND(L$20>='01_Input'!$N$54,L$20<'01_Input'!$O$54),'01_Input'!$Q$54,0),MAX(MIN(L$20,'01_Input'!$O$54)-'01_Input'!$N$54,0)*'01_Input'!$Q$54))+IF('01_Input'!$T$54="Forfait",IF(L$20>='01_Input'!$R$54,'01_Input'!$U$54,0),IF('01_Input'!$T$54="Palier",IF(AND(L$20>='01_Input'!$R$54,L$20<'01_Input'!$S$54),'01_Input'!$U$54,0),MAX(MIN(L$20,'01_Input'!$S$54)-'01_Input'!$R$54,0)*'01_Input'!$U$54))+IF('01_Input'!$X$54="Forfait",IF(L$20>='01_Input'!$V$54,'01_Input'!$Y$54,0),IF('01_Input'!$X$54="Palier",IF(AND(L$20>='01_Input'!$V$54,L$20<'01_Input'!$W$54),'01_Input'!$Y$54,0),MAX(MIN(L$20,'01_Input'!$W$54)-'01_Input'!$V$54,0)*'01_Input'!$Y$54))+IF('01_Input'!$AB$54="Forfait",IF(L$20>='01_Input'!$Z$54,'01_Input'!$AC$54,0),IF('01_Input'!$AB$54="Palier",IF(AND(L$20>='01_Input'!$Z$54,L$20<'01_Input'!$AA$54),'01_Input'!$AC$54,0),MAX(MIN(L$20,'01_Input'!$AA$54)-'01_Input'!$Z$54,0)*'01_Input'!$AC$54))))))))) -> 180000 | ... EX22: =IF('01_Input'!$C$54="Non",0,MIN('01_Input'!$I$54,MAX('01_Input'!$H$54,IF('01_Input'!$G$54="Résiduel vs Gestion",0,IF('01_Input'!$G$54="Taux Classe sélectionnée",Distrib_Global_Classe_Selectionnee*EX$20,IF('01_Input'!$G$54="Frais KYC (paliers de 100M€)",MAX(0,Nb_Investisseurs-Nb_KYC_Gratuites_Par_Tranche*(FLOOR(EX$20/Taille_Tranche_KYC,1)+1))*Cout_Par_KYC_Supplementaire,(IF('01_Input'!$L$54="Forfait",IF(EX$20>='01_Input'!$J$54,'01_Input'!$M$54,0),IF('01_Input'!$L$54="Palier",IF(AND(EX$20>='01_Input'!$J$54,EX$20<'01_Input'!$K$54),'01_Input'!$M$54,0),MAX(MIN(EX$20,'01_Input'!$K$54)-'01_Input'!$J$54,0)*'01_Input'!$M$54))+IF('01_Input'!$P$54="Forfait",IF(EX$20>='01_Input'!$N$54,'01_Input'!$Q$54,0),IF('01_Input'!$P$54="Palier",IF(AND(EX$20>='01_Input'!$N$54,EX$20<'01_Input'!$O$54),'01_Input'!$Q$54,0),MAX(MIN(EX$20,'01_Input'!$O$54)-'01_Input'!$N$54,0)*'01_Input'!$Q$54))+IF('01_Input'!$T$54="Forfait",IF(EX$20>='01_Input'!$R$54,'01_Input'!$U$54,0),IF('01_Input'!$T$54="Palier",IF(AND(EX$20>='01_Input'!$R$54,EX$20<'01_Input'!$S$54),'01_Input'!$U$54,0),MAX(MIN(EX$20,'01_Input'!$S$54)-'01_Input'!$R$54,0)*'01_Input'!$U$54))+IF('01_Input'!$X$54="Forfait",IF(EX$20>='01_Input'!$V$54,'01_Input'!$Y$54,0),IF('01_Input'!$X$54="Palier",IF(AND(EX$20>='01_Input'!$V$54,EX$20<'01_Input'!$W$54),'01_Input'!$Y$54,0),MAX(MIN(EX$20,'01_Input'!$W$54)-'01_Input'!$V$54,0)*'01_Input'!$Y$54))+IF('01_Input'!$AB$54="Forfait",IF(EX$20>='01_Input'!$Z$54,'01_Input'!$AC$54,0),IF('01_Input'!$AB$54="Palier",IF(AND(EX$20>='01_Input'!$Z$54,EX$20<'01_Input'!$AA$54),'01_Input'!$AC$54,0),MAX(MIN(EX$20,'01_Input'!$AA$54)-'01_Input'!$Z$54,0)*'01_Input'!$AC$54))))))))) -> 2500600000
B23: =IF('01_Input'!D55="","(inactif)",'01_Input'!D55) -> Distribution — Distributeur Global | C23: =IF('01_Input'!E55="","",'01_Input'!E55) | D23: ='01_Input'!C55 -> Oui | E23: =IF('01_Input'!$C$55="Non",0,MIN('01_Input'!$I$55,MAX('01_Input'!$H$55,IF('01_Input'!$G$55="Résiduel vs Gestion",0,IF('01_Input'!$G$55="Taux Classe sélectionnée",Distrib_Global_Classe_Selectionnee*E$20,IF('01_Input'!$G$55="Frais KYC (paliers de 100M€)",MAX(0,Nb_Investisseurs-Nb_KYC_Gratuites_Par_Tranche*(FLOOR(E$20/Taille_Tranche_KYC,1)+1))*Cout_Par_KYC_Supplementaire,(IF('01_Input'!$L$55="Forfait",IF(E$20>='01_Input'!$J$55,'01_Input'!$M$55,0),IF('01_Input'!$L$55="Palier",IF(AND(E$20>='01_Input'!$J$55,E$20<'01_Input'!$K$55),'01_Input'!$M$55,0),MAX(MIN(E$20,'01_Input'!$K$55)-'01_Input'!$J$55,0)*'01_Input'!$M$55))+IF('01_Input'!$P$55="Forfait",IF(E$20>='01_Input'!$N$55,'01_Input'!$Q$55,0),IF('01_Input'!$P$55="Palier",IF(AND(E$20>='01_Input'!$N$55,E$20<'01_Input'!$O$55),'01_Input'!$Q$55,0),MAX(MIN(E$20,'01_Input'!$O$55)-'01_Input'!$N$55,0)*'01_Input'!$Q$55))+IF('01_Input'!$T$55="Forfait",IF(E$20>='01_Input'!$R$55,'01_Input'!$U$55,0),IF('01_Input'!$T$55="Palier",IF(AND(E$20>='01_Input'!$R$55,E$20<'01_Input'!$S$55),'01_Input'!$U$55,0),MAX(MIN(E$20,'01_Input'!$S$55)-'01_Input'!$R$55,0)*'01_Input'!$U$55))+IF('01_Input'!$X$55="Forfait",IF(E$20>='01_Input'!$V$55,'01_Input'!$Y$55,0),IF('01_Input'!$X$55="Palier",IF(AND(E$20>='01_Input'!$V$55,E$20<'01_Input'!$W$55),'01_Input'!$Y$55,0),MAX(MIN(E$20,'01_Input'!$W$55)-'01_Input'!$V$55,0)*'01_Input'!$Y$55))+IF('01_Input'!$AB$55="Forfait",IF(E$20>='01_Input'!$Z$55,'01_Input'!$AC$55,0),IF('01_Input'!$AB$55="Palier",IF(AND(E$20>='01_Input'!$Z$55,E$20<'01_Input'!$AA$55),'01_Input'!$AC$55,0),MAX(MIN(E$20,'01_Input'!$AA$55)-'01_Input'!$Z$55,0)*'01_Input'!$AC$55))))))))) -> 5000 | F23: =IF('01_Input'!$C$55="Non",0,MIN('01_Input'!$I$55,MAX('01_Input'!$H$55,IF('01_Input'!$G$55="Résiduel vs Gestion",0,IF('01_Input'!$G$55="Taux Classe sélectionnée",Distrib_Global_Classe_Selectionnee*F$20,IF('01_Input'!$G$55="Frais KYC (paliers de 100M€)",MAX(0,Nb_Investisseurs-Nb_KYC_Gratuites_Par_Tranche*(FLOOR(F$20/Taille_Tranche_KYC,1)+1))*Cout_Par_KYC_Supplementaire,(IF('01_Input'!$L$55="Forfait",IF(F$20>='01_Input'!$J$55,'01_Input'!$M$55,0),IF('01_Input'!$L$55="Palier",IF(AND(F$20>='01_Input'!$J$55,F$20<'01_Input'!$K$55),'01_Input'!$M$55,0),MAX(MIN(F$20,'01_Input'!$K$55)-'01_Input'!$J$55,0)*'01_Input'!$M$55))+IF('01_Input'!$P$55="Forfait",IF(F$20>='01_Input'!$N$55,'01_Input'!$Q$55,0),IF('01_Input'!$P$55="Palier",IF(AND(F$20>='01_Input'!$N$55,F$20<'01_Input'!$O$55),'01_Input'!$Q$55,0),MAX(MIN(F$20,'01_Input'!$O$55)-'01_Input'!$N$55,0)*'01_Input'!$Q$55))+IF('01_Input'!$T$55="Forfait",IF(F$20>='01_Input'!$R$55,'01_Input'!$U$55,0),IF('01_Input'!$T$55="Palier",IF(AND(F$20>='01_Input'!$R$55,F$20<'01_Input'!$S$55),'01_Input'!$U$55,0),MAX(MIN(F$20,'01_Input'!$S$55)-'01_Input'!$R$55,0)*'01_Input'!$U$55))+IF('01_Input'!$X$55="Forfait",IF(F$20>='01_Input'!$V$55,'01_Input'!$Y$55,0),IF('01_Input'!$X$55="Palier",IF(AND(F$20>='01_Input'!$V$55,F$20<'01_Input'!$W$55),'01_Input'!$Y$55,0),MAX(MIN(F$20,'01_Input'!$W$55)-'01_Input'!$V$55,0)*'01_Input'!$Y$55))+IF('01_Input'!$AB$55="Forfait",IF(F$20>='01_Input'!$Z$55,'01_Input'!$AC$55,0),IF('01_Input'!$AB$55="Palier",IF(AND(F$20>='01_Input'!$Z$55,F$20<'01_Input'!$AA$55),'01_Input'!$AC$55,0),MAX(MIN(F$20,'01_Input'!$AA$55)-'01_Input'!$Z$55,0)*'01_Input'!$AC$55))))))))) -> 10000 | G23: =IF('01_Input'!$C$55="Non",0,MIN('01_Input'!$I$55,MAX('01_Input'!$H$55,IF('01_Input'!$G$55="Résiduel vs Gestion",0,IF('01_Input'!$G$55="Taux Classe sélectionnée",Distrib_Global_Classe_Selectionnee*G$20,IF('01_Input'!$G$55="Frais KYC (paliers de 100M€)",MAX(0,Nb_Investisseurs-Nb_KYC_Gratuites_Par_Tranche*(FLOOR(G$20/Taille_Tranche_KYC,1)+1))*Cout_Par_KYC_Supplementaire,(IF('01_Input'!$L$55="Forfait",IF(G$20>='01_Input'!$J$55,'01_Input'!$M$55,0),IF('01_Input'!$L$55="Palier",IF(AND(G$20>='01_Input'!$J$55,G$20<'01_Input'!$K$55),'01_Input'!$M$55,0),MAX(MIN(G$20,'01_Input'!$K$55)-'01_Input'!$J$55,0)*'01_Input'!$M$55))+IF('01_Input'!$P$55="Forfait",IF(G$20>='01_Input'!$N$55,'01_Input'!$Q$55,0),IF('01_Input'!$P$55="Palier",IF(AND(G$20>='01_Input'!$N$55,G$20<'01_Input'!$O$55),'01_Input'!$Q$55,0),MAX(MIN(G$20,'01_Input'!$O$55)-'01_Input'!$N$55,0)*'01_Input'!$Q$55))+IF('01_Input'!$T$55="Forfait",IF(G$20>='01_Input'!$R$55,'01_Input'!$U$55,0),IF('01_Input'!$T$55="Palier",IF(AND(G$20>='01_Input'!$R$55,G$20<'01_Input'!$S$55),'01_Input'!$U$55,0),MAX(MIN(G$20,'01_Input'!$S$55)-'01_Input'!$R$55,0)*'01_Input'!$U$55))+IF('01_Input'!$X$55="Forfait",IF(G$20>='01_Input'!$V$55,'01_Input'!$Y$55,0),IF('01_Input'!$X$55="Palier",IF(AND(G$20>='01_Input'!$V$55,G$20<'01_Input'!$W$55),'01_Input'!$Y$55,0),MAX(MIN(G$20,'01_Input'!$W$55)-'01_Input'!$V$55,0)*'01_Input'!$Y$55))+IF('01_Input'!$AB$55="Forfait",IF(G$20>='01_Input'!$Z$55,'01_Input'!$AC$55,0),IF('01_Input'!$AB$55="Palier",IF(AND(G$20>='01_Input'!$Z$55,G$20<'01_Input'!$AA$55),'01_Input'!$AC$55,0),MAX(MIN(G$20,'01_Input'!$AA$55)-'01_Input'!$Z$55,0)*'01_Input'!$AC$55))))))))) -> 15000 | H23: =IF('01_Input'!$C$55="Non",0,MIN('01_Input'!$I$55,MAX('01_Input'!$H$55,IF('01_Input'!$G$55="Résiduel vs Gestion",0,IF('01_Input'!$G$55="Taux Classe sélectionnée",Distrib_Global_Classe_Selectionnee*H$20,IF('01_Input'!$G$55="Frais KYC (paliers de 100M€)",MAX(0,Nb_Investisseurs-Nb_KYC_Gratuites_Par_Tranche*(FLOOR(H$20/Taille_Tranche_KYC,1)+1))*Cout_Par_KYC_Supplementaire,(IF('01_Input'!$L$55="Forfait",IF(H$20>='01_Input'!$J$55,'01_Input'!$M$55,0),IF('01_Input'!$L$55="Palier",IF(AND(H$20>='01_Input'!$J$55,H$20<'01_Input'!$K$55),'01_Input'!$M$55,0),MAX(MIN(H$20,'01_Input'!$K$55)-'01_Input'!$J$55,0)*'01_Input'!$M$55))+IF('01_Input'!$P$55="Forfait",IF(H$20>='01_Input'!$N$55,'01_Input'!$Q$55,0),IF('01_Input'!$P$55="Palier",IF(AND(H$20>='01_Input'!$N$55,H$20<'01_Input'!$O$55),'01_Input'!$Q$55,0),MAX(MIN(H$20,'01_Input'!$O$55)-'01_Input'!$N$55,0)*'01_Input'!$Q$55))+IF('01_Input'!$T$55="Forfait",IF(H$20>='01_Input'!$R$55,'01_Input'!$U$55,0),IF('01_Input'!$T$55="Palier",IF(AND(H$20>='01_Input'!$R$55,H$20<'01_Input'!$S$55),'01_Input'!$U$55,0),MAX(MIN(H$20,'01_Input'!$S$55)-'01_Input'!$R$55,0)*'01_Input'!$U$55))+IF('01_Input'!$X$55="Forfait",IF(H$20>='01_Input'!$V$55,'01_Input'!$Y$55,0),IF('01_Input'!$X$55="Palier",IF(AND(H$20>='01_Input'!$V$55,H$20<'01_Input'!$W$55),'01_Input'!$Y$55,0),MAX(MIN(H$20,'01_Input'!$W$55)-'01_Input'!$V$55,0)*'01_Input'!$Y$55))+IF('01_Input'!$AB$55="Forfait",IF(H$20>='01_Input'!$Z$55,'01_Input'!$AC$55,0),IF('01_Input'!$AB$55="Palier",IF(AND(H$20>='01_Input'!$Z$55,H$20<'01_Input'!$AA$55),'01_Input'!$AC$55,0),MAX(MIN(H$20,'01_Input'!$AA$55)-'01_Input'!$Z$55,0)*'01_Input'!$AC$55))))))))) -> 20000 | I23: =IF('01_Input'!$C$55="Non",0,MIN('01_Input'!$I$55,MAX('01_Input'!$H$55,IF('01_Input'!$G$55="Résiduel vs Gestion",0,IF('01_Input'!$G$55="Taux Classe sélectionnée",Distrib_Global_Classe_Selectionnee*I$20,IF('01_Input'!$G$55="Frais KYC (paliers de 100M€)",MAX(0,Nb_Investisseurs-Nb_KYC_Gratuites_Par_Tranche*(FLOOR(I$20/Taille_Tranche_KYC,1)+1))*Cout_Par_KYC_Supplementaire,(IF('01_Input'!$L$55="Forfait",IF(I$20>='01_Input'!$J$55,'01_Input'!$M$55,0),IF('01_Input'!$L$55="Palier",IF(AND(I$20>='01_Input'!$J$55,I$20<'01_Input'!$K$55),'01_Input'!$M$55,0),MAX(MIN(I$20,'01_Input'!$K$55)-'01_Input'!$J$55,0)*'01_Input'!$M$55))+IF('01_Input'!$P$55="Forfait",IF(I$20>='01_Input'!$N$55,'01_Input'!$Q$55,0),IF('01_Input'!$P$55="Palier",IF(AND(I$20>='01_Input'!$N$55,I$20<'01_Input'!$O$55),'01_Input'!$Q$55,0),MAX(MIN(I$20,'01_Input'!$O$55)-'01_Input'!$N$55,0)*'01_Input'!$Q$55))+IF('01_Input'!$T$55="Forfait",IF(I$20>='01_Input'!$R$55,'01_Input'!$U$55,0),IF('01_Input'!$T$55="Palier",IF(AND(I$20>='01_Input'!$R$55,I$20<'01_Input'!$S$55),'01_Input'!$U$55,0),MAX(MIN(I$20,'01_Input'!$S$55)-'01_Input'!$R$55,0)*'01_Input'!$U$55))+IF('01_Input'!$X$55="Forfait",IF(I$20>='01_Input'!$V$55,'01_Input'!$Y$55,0),IF('01_Input'!$X$55="Palier",IF(AND(I$20>='01_Input'!$V$55,I$20<'01_Input'!$W$55),'01_Input'!$Y$55,0),MAX(MIN(I$20,'01_Input'!$W$55)-'01_Input'!$V$55,0)*'01_Input'!$Y$55))+IF('01_Input'!$AB$55="Forfait",IF(I$20>='01_Input'!$Z$55,'01_Input'!$AC$55,0),IF('01_Input'!$AB$55="Palier",IF(AND(I$20>='01_Input'!$Z$55,I$20<'01_Input'!$AA$55),'01_Input'!$AC$55,0),MAX(MIN(I$20,'01_Input'!$AA$55)-'01_Input'!$Z$55,0)*'01_Input'!$AC$55))))))))) -> 25000 | J23: =IF('01_Input'!$C$55="Non",0,MIN('01_Input'!$I$55,MAX('01_Input'!$H$55,IF('01_Input'!$G$55="Résiduel vs Gestion",0,IF('01_Input'!$G$55="Taux Classe sélectionnée",Distrib_Global_Classe_Selectionnee*J$20,IF('01_Input'!$G$55="Frais KYC (paliers de 100M€)",MAX(0,Nb_Investisseurs-Nb_KYC_Gratuites_Par_Tranche*(FLOOR(J$20/Taille_Tranche_KYC,1)+1))*Cout_Par_KYC_Supplementaire,(IF('01_Input'!$L$55="Forfait",IF(J$20>='01_Input'!$J$55,'01_Input'!$M$55,0),IF('01_Input'!$L$55="Palier",IF(AND(J$20>='01_Input'!$J$55,J$20<'01_Input'!$K$55),'01_Input'!$M$55,0),MAX(MIN(J$20,'01_Input'!$K$55)-'01_Input'!$J$55,0)*'01_Input'!$M$55))+IF('01_Input'!$P$55="Forfait",IF(J$20>='01_Input'!$N$55,'01_Input'!$Q$55,0),IF('01_Input'!$P$55="Palier",IF(AND(J$20>='01_Input'!$N$55,J$20<'01_Input'!$O$55),'01_Input'!$Q$55,0),MAX(MIN(J$20,'01_Input'!$O$55)-'01_Input'!$N$55,0)*'01_Input'!$Q$55))+IF('01_Input'!$T$55="Forfait",IF(J$20>='01_Input'!$R$55,'01_Input'!$U$55,0),IF('01_Input'!$T$55="Palier",IF(AND(J$20>='01_Input'!$R$55,J$20<'01_Input'!$S$55),'01_Input'!$U$55,0),MAX(MIN(J$20,'01_Input'!$S$55)-'01_Input'!$R$55,0)*'01_Input'!$U$55))+IF('01_Input'!$X$55="Forfait",IF(J$20>='01_Input'!$V$55,'01_Input'!$Y$55,0),IF('01_Input'!$X$55="Palier",IF(AND(J$20>='01_Input'!$V$55,J$20<'01_Input'!$W$55),'01_Input'!$Y$55,0),MAX(MIN(J$20,'01_Input'!$W$55)-'01_Input'!$V$55,0)*'01_Input'!$Y$55))+IF('01_Input'!$AB$55="Forfait",IF(J$20>='01_Input'!$Z$55,'01_Input'!$AC$55,0),IF('01_Input'!$AB$55="Palier",IF(AND(J$20>='01_Input'!$Z$55,J$20<'01_Input'!$AA$55),'01_Input'!$AC$55,0),MAX(MIN(J$20,'01_Input'!$AA$55)-'01_Input'!$Z$55,0)*'01_Input'!$AC$55))))))))) -> 30000 | K23: =IF('01_Input'!$C$55="Non",0,MIN('01_Input'!$I$55,MAX('01_Input'!$H$55,IF('01_Input'!$G$55="Résiduel vs Gestion",0,IF('01_Input'!$G$55="Taux Classe sélectionnée",Distrib_Global_Classe_Selectionnee*K$20,IF('01_Input'!$G$55="Frais KYC (paliers de 100M€)",MAX(0,Nb_Investisseurs-Nb_KYC_Gratuites_Par_Tranche*(FLOOR(K$20/Taille_Tranche_KYC,1)+1))*Cout_Par_KYC_Supplementaire,(IF('01_Input'!$L$55="Forfait",IF(K$20>='01_Input'!$J$55,'01_Input'!$M$55,0),IF('01_Input'!$L$55="Palier",IF(AND(K$20>='01_Input'!$J$55,K$20<'01_Input'!$K$55),'01_Input'!$M$55,0),MAX(MIN(K$20,'01_Input'!$K$55)-'01_Input'!$J$55,0)*'01_Input'!$M$55))+IF('01_Input'!$P$55="Forfait",IF(K$20>='01_Input'!$N$55,'01_Input'!$Q$55,0),IF('01_Input'!$P$55="Palier",IF(AND(K$20>='01_Input'!$N$55,K$20<'01_Input'!$O$55),'01_Input'!$Q$55,0),MAX(MIN(K$20,'01_Input'!$O$55)-'01_Input'!$N$55,0)*'01_Input'!$Q$55))+IF('01_Input'!$T$55="Forfait",IF(K$20>='01_Input'!$R$55,'01_Input'!$U$55,0),IF('01_Input'!$T$55="Palier",IF(AND(K$20>='01_Input'!$R$55,K$20<'01_Input'!$S$55),'01_Input'!$U$55,0),MAX(MIN(K$20,'01_Input'!$S$55)-'01_Input'!$R$55,0)*'01_Input'!$U$55))+IF('01_Input'!$X$55="Forfait",IF(K$20>='01_Input'!$V$55,'01_Input'!$Y$55,0),IF('01_Input'!$X$55="Palier",IF(AND(K$20>='01_Input'!$V$55,K$20<'01_Input'!$W$55),'01_Input'!$Y$55,0),MAX(MIN(K$20,'01_Input'!$W$55)-'01_Input'!$V$55,0)*'01_Input'!$Y$55))+IF('01_Input'!$AB$55="Forfait",IF(K$20>='01_Input'!$Z$55,'01_Input'!$AC$55,0),IF('01_Input'!$AB$55="Palier",IF(AND(K$20>='01_Input'!$Z$55,K$20<'01_Input'!$AA$55),'01_Input'!$AC$55,0),MAX(MIN(K$20,'01_Input'!$AA$55)-'01_Input'!$Z$55,0)*'01_Input'!$AC$55))))))))) -> 35000 | L23: =IF('01_Input'!$C$55="Non",0,MIN('01_Input'!$I$55,MAX('01_Input'!$H$55,IF('01_Input'!$G$55="Résiduel vs Gestion",0,IF('01_Input'!$G$55="Taux Classe sélectionnée",Distrib_Global_Classe_Selectionnee*L$20,IF('01_Input'!$G$55="Frais KYC (paliers de 100M€)",MAX(0,Nb_Investisseurs-Nb_KYC_Gratuites_Par_Tranche*(FLOOR(L$20/Taille_Tranche_KYC,1)+1))*Cout_Par_KYC_Supplementaire,(IF('01_Input'!$L$55="Forfait",IF(L$20>='01_Input'!$J$55,'01_Input'!$M$55,0),IF('01_Input'!$L$55="Palier",IF(AND(L$20>='01_Input'!$J$55,L$20<'01_Input'!$K$55),'01_Input'!$M$55,0),MAX(MIN(L$20,'01_Input'!$K$55)-'01_Input'!$J$55,0)*'01_Input'!$M$55))+IF('01_Input'!$P$55="Forfait",IF(L$20>='01_Input'!$N$55,'01_Input'!$Q$55,0),IF('01_Input'!$P$55="Palier",IF(AND(L$20>='01_Input'!$N$55,L$20<'01_Input'!$O$55),'01_Input'!$Q$55,0),MAX(MIN(L$20,'01_Input'!$O$55)-'01_Input'!$N$55,0)*'01_Input'!$Q$55))+IF('01_Input'!$T$55="Forfait",IF(L$20>='01_Input'!$R$55,'01_Input'!$U$55,0),IF('01_Input'!$T$55="Palier",IF(AND(L$20>='01_Input'!$R$55,L$20<'01_Input'!$S$55),'01_Input'!$U$55,0),MAX(MIN(L$20,'01_Input'!$S$55)-'01_Input'!$R$55,0)*'01_Input'!$U$55))+IF('01_Input'!$X$55="Forfait",IF(L$20>='01_Input'!$V$55,'01_Input'!$Y$55,0),IF('01_Input'!$X$55="Palier",IF(AND(L$20>='01_Input'!$V$55,L$20<'01_Input'!$W$55),'01_Input'!$Y$55,0),MAX(MIN(L$20,'01_Input'!$W$55)-'01_Input'!$V$55,0)*'01_Input'!$Y$55))+IF('01_Input'!$AB$55="Forfait",IF(L$20>='01_Input'!$Z$55,'01_Input'!$AC$55,0),IF('01_Input'!$AB$55="Palier",IF(AND(L$20>='01_Input'!$Z$55,L$20<'01_Input'!$AA$55),'01_Input'!$AC$55,0),MAX(MIN(L$20,'01_Input'!$AA$55)-'01_Input'!$Z$55,0)*'01_Input'!$AC$55))))))))) -> 40000 | ... EX23: =IF('01_Input'!$C$55="Non",0,MIN('01_Input'!$I$55,MAX('01_Input'!$H$55,IF('01_Input'!$G$55="Résiduel vs Gestion",0,IF('01_Input'!$G$55="Taux Classe sélectionnée",Distrib_Global_Classe_Selectionnee*EX$20,IF('01_Input'!$G$55="Frais KYC (paliers de 100M€)",MAX(0,Nb_Investisseurs-Nb_KYC_Gratuites_Par_Tranche*(FLOOR(EX$20/Taille_Tranche_KYC,1)+1))*Cout_Par_KYC_Supplementaire,(IF('01_Input'!$L$55="Forfait",IF(EX$20>='01_Input'!$J$55,'01_Input'!$M$55,0),IF('01_Input'!$L$55="Palier",IF(AND(EX$20>='01_Input'!$J$55,EX$20<'01_Input'!$K$55),'01_Input'!$M$55,0),MAX(MIN(EX$20,'01_Input'!$K$55)-'01_Input'!$J$55,0)*'01_Input'!$M$55))+IF('01_Input'!$P$55="Forfait",IF(EX$20>='01_Input'!$N$55,'01_Input'!$Q$55,0),IF('01_Input'!$P$55="Palier",IF(AND(EX$20>='01_Input'!$N$55,EX$20<'01_Input'!$O$55),'01_Input'!$Q$55,0),MAX(MIN(EX$20,'01_Input'!$O$55)-'01_Input'!$N$55,0)*'01_Input'!$Q$55))+IF('01_Input'!$T$55="Forfait",IF(EX$20>='01_Input'!$R$55,'01_Input'!$U$55,0),IF('01_Input'!$T$55="Palier",IF(AND(EX$20>='01_Input'!$R$55,EX$20<'01_Input'!$S$55),'01_Input'!$U$55,0),MAX(MIN(EX$20,'01_Input'!$S$55)-'01_Input'!$R$55,0)*'01_Input'!$U$55))+IF('01_Input'!$X$55="Forfait",IF(EX$20>='01_Input'!$V$55,'01_Input'!$Y$55,0),IF('01_Input'!$X$55="Palier",IF(AND(EX$20>='01_Input'!$V$55,EX$20<'01_Input'!$W$55),'01_Input'!$Y$55,0),MAX(MIN(EX$20,'01_Input'!$W$55)-'01_Input'!$V$55,0)*'01_Input'!$Y$55))+IF('01_Input'!$AB$55="Forfait",IF(EX$20>='01_Input'!$Z$55,'01_Input'!$AC$55,0),IF('01_Input'!$AB$55="Palier",IF(AND(EX$20>='01_Input'!$Z$55,EX$20<'01_Input'!$AA$55),'01_Input'!$AC$55,0),MAX(MIN(EX$20,'01_Input'!$AA$55)-'01_Input'!$Z$55,0)*'01_Input'!$AC$55))))))))) -> 0
B24: =IF('01_Input'!D56="","(inactif)",'01_Input'!D56) -> Distribution — Sous-distributeurs | C24: =IF('01_Input'!E56="","",'01_Input'!E56) | D24: ='01_Input'!C56 -> Oui | E24: =IF('01_Input'!$C$56="Non",0,MIN('01_Input'!$I$56,MAX('01_Input'!$H$56,IF('01_Input'!$G$56="Résiduel vs Gestion",0,IF('01_Input'!$G$56="Taux Classe sélectionnée",Distrib_SousDistrib_Classe_Selectionnee*E$20,IF('01_Input'!$G$56="Frais KYC (paliers de 100M€)",MAX(0,Nb_Investisseurs-Nb_KYC_Gratuites_Par_Tranche*(FLOOR(E$20/Taille_Tranche_KYC,1)+1))*Cout_Par_KYC_Supplementaire,(IF('01_Input'!$L$56="Forfait",IF(E$20>='01_Input'!$J$56,'01_Input'!$M$56,0),IF('01_Input'!$L$56="Palier",IF(AND(E$20>='01_Input'!$J$56,E$20<'01_Input'!$K$56),'01_Input'!$M$56,0),MAX(MIN(E$20,'01_Input'!$K$56)-'01_Input'!$J$56,0)*'01_Input'!$M$56))+IF('01_Input'!$P$56="Forfait",IF(E$20>='01_Input'!$N$56,'01_Input'!$Q$56,0),IF('01_Input'!$P$56="Palier",IF(AND(E$20>='01_Input'!$N$56,E$20<'01_Input'!$O$56),'01_Input'!$Q$56,0),MAX(MIN(E$20,'01_Input'!$O$56)-'01_Input'!$N$56,0)*'01_Input'!$Q$56))+IF('01_Input'!$T$56="Forfait",IF(E$20>='01_Input'!$R$56,'01_Input'!$U$56,0),IF('01_Input'!$T$56="Palier",IF(AND(E$20>='01_Input'!$R$56,E$20<'01_Input'!$S$56),'01_Input'!$U$56,0),MAX(MIN(E$20,'01_Input'!$S$56)-'01_Input'!$R$56,0)*'01_Input'!$U$56))+IF('01_Input'!$X$56="Forfait",IF(E$20>='01_Input'!$V$56,'01_Input'!$Y$56,0),IF('01_Input'!$X$56="Palier",IF(AND(E$20>='01_Input'!$V$56,E$20<'01_Input'!$W$56),'01_Input'!$Y$56,0),MAX(MIN(E$20,'01_Input'!$W$56)-'01_Input'!$V$56,0)*'01_Input'!$Y$56))+IF('01_Input'!$AB$56="Forfait",IF(E$20>='01_Input'!$Z$56,'01_Input'!$AC$56,0),IF('01_Input'!$AB$56="Palier",IF(AND(E$20>='01_Input'!$Z$56,E$20<'01_Input'!$AA$56),'01_Input'!$AC$56,0),MAX(MIN(E$20,'01_Input'!$AA$56)-'01_Input'!$Z$56,0)*'01_Input'!$AC$56))))))))) -> 45000 | F24: =IF('01_Input'!$C$56="Non",0,MIN('01_Input'!$I$56,MAX('01_Input'!$H$56,IF('01_Input'!$G$56="Résiduel vs Gestion",0,IF('01_Input'!$G$56="Taux Classe sélectionnée",Distrib_SousDistrib_Classe_Selectionnee*F$20,IF('01_Input'!$G$56="Frais KYC (paliers de 100M€)",MAX(0,Nb_Investisseurs-Nb_KYC_Gratuites_Par_Tranche*(FLOOR(F$20/Taille_Tranche_KYC,1)+1))*Cout_Par_KYC_Supplementaire,(IF('01_Input'!$L$56="Forfait",IF(F$20>='01_Input'!$J$56,'01_Input'!$M$56,0),IF('01_Input'!$L$56="Palier",IF(AND(F$20>='01_Input'!$J$56,F$20<'01_Input'!$K$56),'01_Input'!$M$56,0),MAX(MIN(F$20,'01_Input'!$K$56)-'01_Input'!$J$56,0)*'01_Input'!$M$56))+IF('01_Input'!$P$56="Forfait",IF(F$20>='01_Input'!$N$56,'01_Input'!$Q$56,0),IF('01_Input'!$P$56="Palier",IF(AND(F$20>='01_Input'!$N$56,F$20<'01_Input'!$O$56),'01_Input'!$Q$56,0),MAX(MIN(F$20,'01_Input'!$O$56)-'01_Input'!$N$56,0)*'01_Input'!$Q$56))+IF('01_Input'!$T$56="Forfait",IF(F$20>='01_Input'!$R$56,'01_Input'!$U$56,0),IF('01_Input'!$T$56="Palier",IF(AND(F$20>='01_Input'!$R$56,F$20<'01_Input'!$S$56),'01_Input'!$U$56,0),MAX(MIN(F$20,'01_Input'!$S$56)-'01_Input'!$R$56,0)*'01_Input'!$U$56))+IF('01_Input'!$X$56="Forfait",IF(F$20>='01_Input'!$V$56,'01_Input'!$Y$56,0),IF('01_Input'!$X$56="Palier",IF(AND(F$20>='01_Input'!$V$56,F$20<'01_Input'!$W$56),'01_Input'!$Y$56,0),MAX(MIN(F$20,'01_Input'!$W$56)-'01_Input'!$V$56,0)*'01_Input'!$Y$56))+IF('01_Input'!$AB$56="Forfait",IF(F$20>='01_Input'!$Z$56,'01_Input'!$AC$56,0),IF('01_Input'!$AB$56="Palier",IF(AND(F$20>='01_Input'!$Z$56,F$20<'01_Input'!$AA$56),'01_Input'!$AC$56,0),MAX(MIN(F$20,'01_Input'!$AA$56)-'01_Input'!$Z$56,0)*'01_Input'!$AC$56))))))))) -> 90000 | G24: =IF('01_Input'!$C$56="Non",0,MIN('01_Input'!$I$56,MAX('01_Input'!$H$56,IF('01_Input'!$G$56="Résiduel vs Gestion",0,IF('01_Input'!$G$56="Taux Classe sélectionnée",Distrib_SousDistrib_Classe_Selectionnee*G$20,IF('01_Input'!$G$56="Frais KYC (paliers de 100M€)",MAX(0,Nb_Investisseurs-Nb_KYC_Gratuites_Par_Tranche*(FLOOR(G$20/Taille_Tranche_KYC,1)+1))*Cout_Par_KYC_Supplementaire,(IF('01_Input'!$L$56="Forfait",IF(G$20>='01_Input'!$J$56,'01_Input'!$M$56,0),IF('01_Input'!$L$56="Palier",IF(AND(G$20>='01_Input'!$J$56,G$20<'01_Input'!$K$56),'01_Input'!$M$56,0),MAX(MIN(G$20,'01_Input'!$K$56)-'01_Input'!$J$56,0)*'01_Input'!$M$56))+IF('01_Input'!$P$56="Forfait",IF(G$20>='01_Input'!$N$56,'01_Input'!$Q$56,0),IF('01_Input'!$P$56="Palier",IF(AND(G$20>='01_Input'!$N$56,G$20<'01_Input'!$O$56),'01_Input'!$Q$56,0),MAX(MIN(G$20,'01_Input'!$O$56)-'01_Input'!$N$56,0)*'01_Input'!$Q$56))+IF('01_Input'!$T$56="Forfait",IF(G$20>='01_Input'!$R$56,'01_Input'!$U$56,0),IF('01_Input'!$T$56="Palier",IF(AND(G$20>='01_Input'!$R$56,G$20<'01_Input'!$S$56),'01_Input'!$U$56,0),MAX(MIN(G$20,'01_Input'!$S$56)-'01_Input'!$R$56,0)*'01_Input'!$U$56))+IF('01_Input'!$X$56="Forfait",IF(G$20>='01_Input'!$V$56,'01_Input'!$Y$56,0),IF('01_Input'!$X$56="Palier",IF(AND(G$20>='01_Input'!$V$56,G$20<'01_Input'!$W$56),'01_Input'!$Y$56,0),MAX(MIN(G$20,'01_Input'!$W$56)-'01_Input'!$V$56,0)*'01_Input'!$Y$56))+IF('01_Input'!$AB$56="Forfait",IF(G$20>='01_Input'!$Z$56,'01_Input'!$AC$56,0),IF('01_Input'!$AB$56="Palier",IF(AND(G$20>='01_Input'!$Z$56,G$20<'01_Input'!$AA$56),'01_Input'!$AC$56,0),MAX(MIN(G$20,'01_Input'!$AA$56)-'01_Input'!$Z$56,0)*'01_Input'!$AC$56))))))))) -> 135000 | H24: =IF('01_Input'!$C$56="Non",0,MIN('01_Input'!$I$56,MAX('01_Input'!$H$56,IF('01_Input'!$G$56="Résiduel vs Gestion",0,IF('01_Input'!$G$56="Taux Classe sélectionnée",Distrib_SousDistrib_Classe_Selectionnee*H$20,IF('01_Input'!$G$56="Frais KYC (paliers de 100M€)",MAX(0,Nb_Investisseurs-Nb_KYC_Gratuites_Par_Tranche*(FLOOR(H$20/Taille_Tranche_KYC,1)+1))*Cout_Par_KYC_Supplementaire,(IF('01_Input'!$L$56="Forfait",IF(H$20>='01_Input'!$J$56,'01_Input'!$M$56,0),IF('01_Input'!$L$56="Palier",IF(AND(H$20>='01_Input'!$J$56,H$20<'01_Input'!$K$56),'01_Input'!$M$56,0),MAX(MIN(H$20,'01_Input'!$K$56)-'01_Input'!$J$56,0)*'01_Input'!$M$56))+IF('01_Input'!$P$56="Forfait",IF(H$20>='01_Input'!$N$56,'01_Input'!$Q$56,0),IF('01_Input'!$P$56="Palier",IF(AND(H$20>='01_Input'!$N$56,H$20<'01_Input'!$O$56),'01_Input'!$Q$56,0),MAX(MIN(H$20,'01_Input'!$O$56)-'01_Input'!$N$56,0)*'01_Input'!$Q$56))+IF('01_Input'!$T$56="Forfait",IF(H$20>='01_Input'!$R$56,'01_Input'!$U$56,0),IF('01_Input'!$T$56="Palier",IF(AND(H$20>='01_Input'!$R$56,H$20<'01_Input'!$S$56),'01_Input'!$U$56,0),MAX(MIN(H$20,'01_Input'!$S$56)-'01_Input'!$R$56,0)*'01_Input'!$U$56))+IF('01_Input'!$X$56="Forfait",IF(H$20>='01_Input'!$V$56,'01_Input'!$Y$56,0),IF('01_Input'!$X$56="Palier",IF(AND(H$20>='01_Input'!$V$56,H$20<'01_Input'!$W$56),'01_Input'!$Y$56,0),MAX(MIN(H$20,'01_Input'!$W$56)-'01_Input'!$V$56,0)*'01_Input'!$Y$56))+IF('01_Input'!$AB$56="Forfait",IF(H$20>='01_Input'!$Z$56,'01_Input'!$AC$56,0),IF('01_Input'!$AB$56="Palier",IF(AND(H$20>='01_Input'!$Z$56,H$20<'01_Input'!$AA$56),'01_Input'!$AC$56,0),MAX(MIN(H$20,'01_Input'!$AA$56)-'01_Input'!$Z$56,0)*'01_Input'!$AC$56))))))))) -> 180000 | I24: =IF('01_Input'!$C$56="Non",0,MIN('01_Input'!$I$56,MAX('01_Input'!$H$56,IF('01_Input'!$G$56="Résiduel vs Gestion",0,IF('01_Input'!$G$56="Taux Classe sélectionnée",Distrib_SousDistrib_Classe_Selectionnee*I$20,IF('01_Input'!$G$56="Frais KYC (paliers de 100M€)",MAX(0,Nb_Investisseurs-Nb_KYC_Gratuites_Par_Tranche*(FLOOR(I$20/Taille_Tranche_KYC,1)+1))*Cout_Par_KYC_Supplementaire,(IF('01_Input'!$L$56="Forfait",IF(I$20>='01_Input'!$J$56,'01_Input'!$M$56,0),IF('01_Input'!$L$56="Palier",IF(AND(I$20>='01_Input'!$J$56,I$20<'01_Input'!$K$56),'01_Input'!$M$56,0),MAX(MIN(I$20,'01_Input'!$K$56)-'01_Input'!$J$56,0)*'01_Input'!$M$56))+IF('01_Input'!$P$56="Forfait",IF(I$20>='01_Input'!$N$56,'01_Input'!$Q$56,0),IF('01_Input'!$P$56="Palier",IF(AND(I$20>='01_Input'!$N$56,I$20<'01_Input'!$O$56),'01_Input'!$Q$56,0),MAX(MIN(I$20,'01_Input'!$O$56)-'01_Input'!$N$56,0)*'01_Input'!$Q$56))+IF('01_Input'!$T$56="Forfait",IF(I$20>='01_Input'!$R$56,'01_Input'!$U$56,0),IF('01_Input'!$T$56="Palier",IF(AND(I$20>='01_Input'!$R$56,I$20<'01_Input'!$S$56),'01_Input'!$U$56,0),MAX(MIN(I$20,'01_Input'!$S$56)-'01_Input'!$R$56,0)*'01_Input'!$U$56))+IF('01_Input'!$X$56="Forfait",IF(I$20>='01_Input'!$V$56,'01_Input'!$Y$56,0),IF('01_Input'!$X$56="Palier",IF(AND(I$20>='01_Input'!$V$56,I$20<'01_Input'!$W$56),'01_Input'!$Y$56,0),MAX(MIN(I$20,'01_Input'!$W$56)-'01_Input'!$V$56,0)*'01_Input'!$Y$56))+IF('01_Input'!$AB$56="Forfait",IF(I$20>='01_Input'!$Z$56,'01_Input'!$AC$56,0),IF('01_Input'!$AB$56="Palier",IF(AND(I$20>='01_Input'!$Z$56,I$20<'01_Input'!$AA$56),'01_Input'!$AC$56,0),MAX(MIN(I$20,'01_Input'!$AA$56)-'01_Input'!$Z$56,0)*'01_Input'!$AC$56))))))))) -> 225000 | J24: =IF('01_Input'!$C$56="Non",0,MIN('01_Input'!$I$56,MAX('01_Input'!$H$56,IF('01_Input'!$G$56="Résiduel vs Gestion",0,IF('01_Input'!$G$56="Taux Classe sélectionnée",Distrib_SousDistrib_Classe_Selectionnee*J$20,IF('01_Input'!$G$56="Frais KYC (paliers de 100M€)",MAX(0,Nb_Investisseurs-Nb_KYC_Gratuites_Par_Tranche*(FLOOR(J$20/Taille_Tranche_KYC,1)+1))*Cout_Par_KYC_Supplementaire,(IF('01_Input'!$L$56="Forfait",IF(J$20>='01_Input'!$J$56,'01_Input'!$M$56,0),IF('01_Input'!$L$56="Palier",IF(AND(J$20>='01_Input'!$J$56,J$20<'01_Input'!$K$56),'01_Input'!$M$56,0),MAX(MIN(J$20,'01_Input'!$K$56)-'01_Input'!$J$56,0)*'01_Input'!$M$56))+IF('01_Input'!$P$56="Forfait",IF(J$20>='01_Input'!$N$56,'01_Input'!$Q$56,0),IF('01_Input'!$P$56="Palier",IF(AND(J$20>='01_Input'!$N$56,J$20<'01_Input'!$O$56),'01_Input'!$Q$56,0),MAX(MIN(J$20,'01_Input'!$O$56)-'01_Input'!$N$56,0)*'01_Input'!$Q$56))+IF('01_Input'!$T$56="Forfait",IF(J$20>='01_Input'!$R$56,'01_Input'!$U$56,0),IF('01_Input'!$T$56="Palier",IF(AND(J$20>='01_Input'!$R$56,J$20<'01_Input'!$S$56),'01_Input'!$U$56,0),MAX(MIN(J$20,'01_Input'!$S$56)-'01_Input'!$R$56,0)*'01_Input'!$U$56))+IF('01_Input'!$X$56="Forfait",IF(J$20>='01_Input'!$V$56,'01_Input'!$Y$56,0),IF('01_Input'!$X$56="Palier",IF(AND(J$20>='01_Input'!$V$56,J$20<'01_Input'!$W$56),'01_Input'!$Y$56,0),MAX(MIN(J$20,'01_Input'!$W$56)-'01_Input'!$V$56,0)*'01_Input'!$Y$56))+IF('01_Input'!$AB$56="Forfait",IF(J$20>='01_Input'!$Z$56,'01_Input'!$AC$56,0),IF('01_Input'!$AB$56="Palier",IF(AND(J$20>='01_Input'!$Z$56,J$20<'01_Input'!$AA$56),'01_Input'!$AC$56,0),MAX(MIN(J$20,'01_Input'!$AA$56)-'01_Input'!$Z$56,0)*'01_Input'!$AC$56))))))))) -> 270000 | K24: =IF('01_Input'!$C$56="Non",0,MIN('01_Input'!$I$56,MAX('01_Input'!$H$56,IF('01_Input'!$G$56="Résiduel vs Gestion",0,IF('01_Input'!$G$56="Taux Classe sélectionnée",Distrib_SousDistrib_Classe_Selectionnee*K$20,IF('01_Input'!$G$56="Frais KYC (paliers de 100M€)",MAX(0,Nb_Investisseurs-Nb_KYC_Gratuites_Par_Tranche*(FLOOR(K$20/Taille_Tranche_KYC,1)+1))*Cout_Par_KYC_Supplementaire,(IF('01_Input'!$L$56="Forfait",IF(K$20>='01_Input'!$J$56,'01_Input'!$M$56,0),IF('01_Input'!$L$56="Palier",IF(AND(K$20>='01_Input'!$J$56,K$20<'01_Input'!$K$56),'01_Input'!$M$56,0),MAX(MIN(K$20,'01_Input'!$K$56)-'01_Input'!$J$56,0)*'01_Input'!$M$56))+IF('01_Input'!$P$56="Forfait",IF(K$20>='01_Input'!$N$56,'01_Input'!$Q$56,0),IF('01_Input'!$P$56="Palier",IF(AND(K$20>='01_Input'!$N$56,K$20<'01_Input'!$O$56),'01_Input'!$Q$56,0),MAX(MIN(K$20,'01_Input'!$O$56)-'01_Input'!$N$56,0)*'01_Input'!$Q$56))+IF('01_Input'!$T$56="Forfait",IF(K$20>='01_Input'!$R$56,'01_Input'!$U$56,0),IF('01_Input'!$T$56="Palier",IF(AND(K$20>='01_Input'!$R$56,K$20<'01_Input'!$S$56),'01_Input'!$U$56,0),MAX(MIN(K$20,'01_Input'!$S$56)-'01_Input'!$R$56,0)*'01_Input'!$U$56))+IF('01_Input'!$X$56="Forfait",IF(K$20>='01_Input'!$V$56,'01_Input'!$Y$56,0),IF('01_Input'!$X$56="Palier",IF(AND(K$20>='01_Input'!$V$56,K$20<'01_Input'!$W$56),'01_Input'!$Y$56,0),MAX(MIN(K$20,'01_Input'!$W$56)-'01_Input'!$V$56,0)*'01_Input'!$Y$56))+IF('01_Input'!$AB$56="Forfait",IF(K$20>='01_Input'!$Z$56,'01_Input'!$AC$56,0),IF('01_Input'!$AB$56="Palier",IF(AND(K$20>='01_Input'!$Z$56,K$20<'01_Input'!$AA$56),'01_Input'!$AC$56,0),MAX(MIN(K$20,'01_Input'!$AA$56)-'01_Input'!$Z$56,0)*'01_Input'!$AC$56))))))))) -> 315000 | L24: =IF('01_Input'!$C$56="Non",0,MIN('01_Input'!$I$56,MAX('01_Input'!$H$56,IF('01_Input'!$G$56="Résiduel vs Gestion",0,IF('01_Input'!$G$56="Taux Classe sélectionnée",Distrib_SousDistrib_Classe_Selectionnee*L$20,IF('01_Input'!$G$56="Frais KYC (paliers de 100M€)",MAX(0,Nb_Investisseurs-Nb_KYC_Gratuites_Par_Tranche*(FLOOR(L$20/Taille_Tranche_KYC,1)+1))*Cout_Par_KYC_Supplementaire,(IF('01_Input'!$L$56="Forfait",IF(L$20>='01_Input'!$J$56,'01_Input'!$M$56,0),IF('01_Input'!$L$56="Palier",IF(AND(L$20>='01_Input'!$J$56,L$20<'01_Input'!$K$56),'01_Input'!$M$56,0),MAX(MIN(L$20,'01_Input'!$K$56)-'01_Input'!$J$56,0)*'01_Input'!$M$56))+IF('01_Input'!$P$56="Forfait",IF(L$20>='01_Input'!$N$56,'01_Input'!$Q$56,0),IF('01_Input'!$P$56="Palier",IF(AND(L$20>='01_Input'!$N$56,L$20<'01_Input'!$O$56),'01_Input'!$Q$56,0),MAX(MIN(L$20,'01_Input'!$O$56)-'01_Input'!$N$56,0)*'01_Input'!$Q$56))+IF('01_Input'!$T$56="Forfait",IF(L$20>='01_Input'!$R$56,'01_Input'!$U$56,0),IF('01_Input'!$T$56="Palier",IF(AND(L$20>='01_Input'!$R$56,L$20<'01_Input'!$S$56),'01_Input'!$U$56,0),MAX(MIN(L$20,'01_Input'!$S$56)-'01_Input'!$R$56,0)*'01_Input'!$U$56))+IF('01_Input'!$X$56="Forfait",IF(L$20>='01_Input'!$V$56,'01_Input'!$Y$56,0),IF('01_Input'!$X$56="Palier",IF(AND(L$20>='01_Input'!$V$56,L$20<'01_Input'!$W$56),'01_Input'!$Y$56,0),MAX(MIN(L$20,'01_Input'!$W$56)-'01_Input'!$V$56,0)*'01_Input'!$Y$56))+IF('01_Input'!$AB$56="Forfait",IF(L$20>='01_Input'!$Z$56,'01_Input'!$AC$56,0),IF('01_Input'!$AB$56="Palier",IF(AND(L$20>='01_Input'!$Z$56,L$20<'01_Input'!$AA$56),'01_Input'!$AC$56,0),MAX(MIN(L$20,'01_Input'!$AA$56)-'01_Input'!$Z$56,0)*'01_Input'!$AC$56))))))))) -> 360000 | ... EX24: =IF('01_Input'!$C$56="Non",0,MIN('01_Input'!$I$56,MAX('01_Input'!$H$56,IF('01_Input'!$G$56="Résiduel vs Gestion",0,IF('01_Input'!$G$56="Taux Classe sélectionnée",Distrib_SousDistrib_Classe_Selectionnee*EX$20,IF('01_Input'!$G$56="Frais KYC (paliers de 100M€)",MAX(0,Nb_Investisseurs-Nb_KYC_Gratuites_Par_Tranche*(FLOOR(EX$20/Taille_Tranche_KYC,1)+1))*Cout_Par_KYC_Supplementaire,(IF('01_Input'!$L$56="Forfait",IF(EX$20>='01_Input'!$J$56,'01_Input'!$M$56,0),IF('01_Input'!$L$56="Palier",IF(AND(EX$20>='01_Input'!$J$56,EX$20<'01_Input'!$K$56),'01_Input'!$M$56,0),MAX(MIN(EX$20,'01_Input'!$K$56)-'01_Input'!$J$56,0)*'01_Input'!$M$56))+IF('01_Input'!$P$56="Forfait",IF(EX$20>='01_Input'!$N$56,'01_Input'!$Q$56,0),IF('01_Input'!$P$56="Palier",IF(AND(EX$20>='01_Input'!$N$56,EX$20<'01_Input'!$O$56),'01_Input'!$Q$56,0),MAX(MIN(EX$20,'01_Input'!$O$56)-'01_Input'!$N$56,0)*'01_Input'!$Q$56))+IF('01_Input'!$T$56="Forfait",IF(EX$20>='01_Input'!$R$56,'01_Input'!$U$56,0),IF('01_Input'!$T$56="Palier",IF(AND(EX$20>='01_Input'!$R$56,EX$20<'01_Input'!$S$56),'01_Input'!$U$56,0),MAX(MIN(EX$20,'01_Input'!$S$56)-'01_Input'!$R$56,0)*'01_Input'!$U$56))+IF('01_Input'!$X$56="Forfait",IF(EX$20>='01_Input'!$V$56,'01_Input'!$Y$56,0),IF('01_Input'!$X$56="Palier",IF(AND(EX$20>='01_Input'!$V$56,EX$20<'01_Input'!$W$56),'01_Input'!$Y$56,0),MAX(MIN(EX$20,'01_Input'!$W$56)-'01_Input'!$V$56,0)*'01_Input'!$Y$56))+IF('01_Input'!$AB$56="Forfait",IF(EX$20>='01_Input'!$Z$56,'01_Input'!$AC$56,0),IF('01_Input'!$AB$56="Palier",IF(AND(EX$20>='01_Input'!$Z$56,EX$20<'01_Input'!$AA$56),'01_Input'!$AC$56,0),MAX(MIN(EX$20,'01_Input'!$AA$56)-'01_Input'!$Z$56,0)*'01_Input'!$AC$56))))))))) -> 0
B25: =IF('01_Input'!D57="","(inactif)",'01_Input'!D57) -> Commission Dépositaire (BFCM) | C25: =IF('01_Input'!E57="","",'01_Input'!E57) -> Dépositaire (BFCM) | D25: ='01_Input'!C57 -> Oui | E25: =IF('01_Input'!$C$57="Non",0,MIN('01_Input'!$I$57,MAX('01_Input'!$H$57,IF('01_Input'!$G$57="Résiduel vs Gestion",0,IF('01_Input'!$G$57="Taux Classe sélectionnée",Distrib_Global_Classe_Selectionnee*E$20,IF('01_Input'!$G$57="Frais KYC (paliers de 100M€)",MAX(0,Nb_Investisseurs-Nb_KYC_Gratuites_Par_Tranche*(FLOOR(E$20/Taille_Tranche_KYC,1)+1))*Cout_Par_KYC_Supplementaire,(IF('01_Input'!$L$57="Forfait",IF(E$20>='01_Input'!$J$57,'01_Input'!$M$57,0),IF('01_Input'!$L$57="Palier",IF(AND(E$20>='01_Input'!$J$57,E$20<'01_Input'!$K$57),'01_Input'!$M$57,0),MAX(MIN(E$20,'01_Input'!$K$57)-'01_Input'!$J$57,0)*'01_Input'!$M$57))+IF('01_Input'!$P$57="Forfait",IF(E$20>='01_Input'!$N$57,'01_Input'!$Q$57,0),IF('01_Input'!$P$57="Palier",IF(AND(E$20>='01_Input'!$N$57,E$20<'01_Input'!$O$57),'01_Input'!$Q$57,0),MAX(MIN(E$20,'01_Input'!$O$57)-'01_Input'!$N$57,0)*'01_Input'!$Q$57))+IF('01_Input'!$T$57="Forfait",IF(E$20>='01_Input'!$R$57,'01_Input'!$U$57,0),IF('01_Input'!$T$57="Palier",IF(AND(E$20>='01_Input'!$R$57,E$20<'01_Input'!$S$57),'01_Input'!$U$57,0),MAX(MIN(E$20,'01_Input'!$S$57)-'01_Input'!$R$57,0)*'01_Input'!$U$57))+IF('01_Input'!$X$57="Forfait",IF(E$20>='01_Input'!$V$57,'01_Input'!$Y$57,0),IF('01_Input'!$X$57="Palier",IF(AND(E$20>='01_Input'!$V$57,E$20<'01_Input'!$W$57),'01_Input'!$Y$57,0),MAX(MIN(E$20,'01_Input'!$W$57)-'01_Input'!$V$57,0)*'01_Input'!$Y$57))+IF('01_Input'!$AB$57="Forfait",IF(E$20>='01_Input'!$Z$57,'01_Input'!$AC$57,0),IF('01_Input'!$AB$57="Palier",IF(AND(E$20>='01_Input'!$Z$57,E$20<'01_Input'!$AA$57),'01_Input'!$AC$57,0),MAX(MIN(E$20,'01_Input'!$AA$57)-'01_Input'!$Z$57,0)*'01_Input'!$AC$57))))))))) -> 12000 | F25: =IF('01_Input'!$C$57="Non",0,MIN('01_Input'!$I$57,MAX('01_Input'!$H$57,IF('01_Input'!$G$57="Résiduel vs Gestion",0,IF('01_Input'!$G$57="Taux Classe sélectionnée",Distrib_Global_Classe_Selectionnee*F$20,IF('01_Input'!$G$57="Frais KYC (paliers de 100M€)",MAX(0,Nb_Investisseurs-Nb_KYC_Gratuites_Par_Tranche*(FLOOR(F$20/Taille_Tranche_KYC,1)+1))*Cout_Par_KYC_Supplementaire,(IF('01_Input'!$L$57="Forfait",IF(F$20>='01_Input'!$J$57,'01_Input'!$M$57,0),IF('01_Input'!$L$57="Palier",IF(AND(F$20>='01_Input'!$J$57,F$20<'01_Input'!$K$57),'01_Input'!$M$57,0),MAX(MIN(F$20,'01_Input'!$K$57)-'01_Input'!$J$57,0)*'01_Input'!$M$57))+IF('01_Input'!$P$57="Forfait",IF(F$20>='01_Input'!$N$57,'01_Input'!$Q$57,0),IF('01_Input'!$P$57="Palier",IF(AND(F$20>='01_Input'!$N$57,F$20<'01_Input'!$O$57),'01_Input'!$Q$57,0),MAX(MIN(F$20,'01_Input'!$O$57)-'01_Input'!$N$57,0)*'01_Input'!$Q$57))+IF('01_Input'!$T$57="Forfait",IF(F$20>='01_Input'!$R$57,'01_Input'!$U$57,0),IF('01_Input'!$T$57="Palier",IF(AND(F$20>='01_Input'!$R$57,F$20<'01_Input'!$S$57),'01_Input'!$U$57,0),MAX(MIN(F$20,'01_Input'!$S$57)-'01_Input'!$R$57,0)*'01_Input'!$U$57))+IF('01_Input'!$X$57="Forfait",IF(F$20>='01_Input'!$V$57,'01_Input'!$Y$57,0),IF('01_Input'!$X$57="Palier",IF(AND(F$20>='01_Input'!$V$57,F$20<'01_Input'!$W$57),'01_Input'!$Y$57,0),MAX(MIN(F$20,'01_Input'!$W$57)-'01_Input'!$V$57,0)*'01_Input'!$Y$57))+IF('01_Input'!$AB$57="Forfait",IF(F$20>='01_Input'!$Z$57,'01_Input'!$AC$57,0),IF('01_Input'!$AB$57="Palier",IF(AND(F$20>='01_Input'!$Z$57,F$20<'01_Input'!$AA$57),'01_Input'!$AC$57,0),MAX(MIN(F$20,'01_Input'!$AA$57)-'01_Input'!$Z$57,0)*'01_Input'!$AC$57))))))))) -> 12000 | G25: =IF('01_Input'!$C$57="Non",0,MIN('01_Input'!$I$57,MAX('01_Input'!$H$57,IF('01_Input'!$G$57="Résiduel vs Gestion",0,IF('01_Input'!$G$57="Taux Classe sélectionnée",Distrib_Global_Classe_Selectionnee*G$20,IF('01_Input'!$G$57="Frais KYC (paliers de 100M€)",MAX(0,Nb_Investisseurs-Nb_KYC_Gratuites_Par_Tranche*(FLOOR(G$20/Taille_Tranche_KYC,1)+1))*Cout_Par_KYC_Supplementaire,(IF('01_Input'!$L$57="Forfait",IF(G$20>='01_Input'!$J$57,'01_Input'!$M$57,0),IF('01_Input'!$L$57="Palier",IF(AND(G$20>='01_Input'!$J$57,G$20<'01_Input'!$K$57),'01_Input'!$M$57,0),MAX(MIN(G$20,'01_Input'!$K$57)-'01_Input'!$J$57,0)*'01_Input'!$M$57))+IF('01_Input'!$P$57="Forfait",IF(G$20>='01_Input'!$N$57,'01_Input'!$Q$57,0),IF('01_Input'!$P$57="Palier",IF(AND(G$20>='01_Input'!$N$57,G$20<'01_Input'!$O$57),'01_Input'!$Q$57,0),MAX(MIN(G$20,'01_Input'!$O$57)-'01_Input'!$N$57,0)*'01_Input'!$Q$57))+IF('01_Input'!$T$57="Forfait",IF(G$20>='01_Input'!$R$57,'01_Input'!$U$57,0),IF('01_Input'!$T$57="Palier",IF(AND(G$20>='01_Input'!$R$57,G$20<'01_Input'!$S$57),'01_Input'!$U$57,0),MAX(MIN(G$20,'01_Input'!$S$57)-'01_Input'!$R$57,0)*'01_Input'!$U$57))+IF('01_Input'!$X$57="Forfait",IF(G$20>='01_Input'!$V$57,'01_Input'!$Y$57,0),IF('01_Input'!$X$57="Palier",IF(AND(G$20>='01_Input'!$V$57,G$20<'01_Input'!$W$57),'01_Input'!$Y$57,0),MAX(MIN(G$20,'01_Input'!$W$57)-'01_Input'!$V$57,0)*'01_Input'!$Y$57))+IF('01_Input'!$AB$57="Forfait",IF(G$20>='01_Input'!$Z$57,'01_Input'!$AC$57,0),IF('01_Input'!$AB$57="Palier",IF(AND(G$20>='01_Input'!$Z$57,G$20<'01_Input'!$AA$57),'01_Input'!$AC$57,0),MAX(MIN(G$20,'01_Input'!$AA$57)-'01_Input'!$Z$57,0)*'01_Input'!$AC$57))))))))) -> 12000 | H25: =IF('01_Input'!$C$57="Non",0,MIN('01_Input'!$I$57,MAX('01_Input'!$H$57,IF('01_Input'!$G$57="Résiduel vs Gestion",0,IF('01_Input'!$G$57="Taux Classe sélectionnée",Distrib_Global_Classe_Selectionnee*H$20,IF('01_Input'!$G$57="Frais KYC (paliers de 100M€)",MAX(0,Nb_Investisseurs-Nb_KYC_Gratuites_Par_Tranche*(FLOOR(H$20/Taille_Tranche_KYC,1)+1))*Cout_Par_KYC_Supplementaire,(IF('01_Input'!$L$57="Forfait",IF(H$20>='01_Input'!$J$57,'01_Input'!$M$57,0),IF('01_Input'!$L$57="Palier",IF(AND(H$20>='01_Input'!$J$57,H$20<'01_Input'!$K$57),'01_Input'!$M$57,0),MAX(MIN(H$20,'01_Input'!$K$57)-'01_Input'!$J$57,0)*'01_Input'!$M$57))+IF('01_Input'!$P$57="Forfait",IF(H$20>='01_Input'!$N$57,'01_Input'!$Q$57,0),IF('01_Input'!$P$57="Palier",IF(AND(H$20>='01_Input'!$N$57,H$20<'01_Input'!$O$57),'01_Input'!$Q$57,0),MAX(MIN(H$20,'01_Input'!$O$57)-'01_Input'!$N$57,0)*'01_Input'!$Q$57))+IF('01_Input'!$T$57="Forfait",IF(H$20>='01_Input'!$R$57,'01_Input'!$U$57,0),IF('01_Input'!$T$57="Palier",IF(AND(H$20>='01_Input'!$R$57,H$20<'01_Input'!$S$57),'01_Input'!$U$57,0),MAX(MIN(H$20,'01_Input'!$S$57)-'01_Input'!$R$57,0)*'01_Input'!$U$57))+IF('01_Input'!$X$57="Forfait",IF(H$20>='01_Input'!$V$57,'01_Input'!$Y$57,0),IF('01_Input'!$X$57="Palier",IF(AND(H$20>='01_Input'!$V$57,H$20<'01_Input'!$W$57),'01_Input'!$Y$57,0),MAX(MIN(H$20,'01_Input'!$W$57)-'01_Input'!$V$57,0)*'01_Input'!$Y$57))+IF('01_Input'!$AB$57="Forfait",IF(H$20>='01_Input'!$Z$57,'01_Input'!$AC$57,0),IF('01_Input'!$AB$57="Palier",IF(AND(H$20>='01_Input'!$Z$57,H$20<'01_Input'!$AA$57),'01_Input'!$AC$57,0),MAX(MIN(H$20,'01_Input'!$AA$57)-'01_Input'!$Z$57,0)*'01_Input'!$AC$57))))))))) -> 12000 | I25: =IF('01_Input'!$C$57="Non",0,MIN('01_Input'!$I$57,MAX('01_Input'!$H$57,IF('01_Input'!$G$57="Résiduel vs Gestion",0,IF('01_Input'!$G$57="Taux Classe sélectionnée",Distrib_Global_Classe_Selectionnee*I$20,IF('01_Input'!$G$57="Frais KYC (paliers de 100M€)",MAX(0,Nb_Investisseurs-Nb_KYC_Gratuites_Par_Tranche*(FLOOR(I$20/Taille_Tranche_KYC,1)+1))*Cout_Par_KYC_Supplementaire,(IF('01_Input'!$L$57="Forfait",IF(I$20>='01_Input'!$J$57,'01_Input'!$M$57,0),IF('01_Input'!$L$57="Palier",IF(AND(I$20>='01_Input'!$J$57,I$20<'01_Input'!$K$57),'01_Input'!$M$57,0),MAX(MIN(I$20,'01_Input'!$K$57)-'01_Input'!$J$57,0)*'01_Input'!$M$57))+IF('01_Input'!$P$57="Forfait",IF(I$20>='01_Input'!$N$57,'01_Input'!$Q$57,0),IF('01_Input'!$P$57="Palier",IF(AND(I$20>='01_Input'!$N$57,I$20<'01_Input'!$O$57),'01_Input'!$Q$57,0),MAX(MIN(I$20,'01_Input'!$O$57)-'01_Input'!$N$57,0)*'01_Input'!$Q$57))+IF('01_Input'!$T$57="Forfait",IF(I$20>='01_Input'!$R$57,'01_Input'!$U$57,0),IF('01_Input'!$T$57="Palier",IF(AND(I$20>='01_Input'!$R$57,I$20<'01_Input'!$S$57),'01_Input'!$U$57,0),MAX(MIN(I$20,'01_Input'!$S$57)-'01_Input'!$R$57,0)*'01_Input'!$U$57))+IF('01_Input'!$X$57="Forfait",IF(I$20>='01_Input'!$V$57,'01_Input'!$Y$57,0),IF('01_Input'!$X$57="Palier",IF(AND(I$20>='01_Input'!$V$57,I$20<'01_Input'!$W$57),'01_Input'!$Y$57,0),MAX(MIN(I$20,'01_Input'!$W$57)-'01_Input'!$V$57,0)*'01_Input'!$Y$57))+IF('01_Input'!$AB$57="Forfait",IF(I$20>='01_Input'!$Z$57,'01_Input'!$AC$57,0),IF('01_Input'!$AB$57="Palier",IF(AND(I$20>='01_Input'!$Z$57,I$20<'01_Input'!$AA$57),'01_Input'!$AC$57,0),MAX(MIN(I$20,'01_Input'!$AA$57)-'01_Input'!$Z$57,0)*'01_Input'!$AC$57))))))))) -> 12000 | J25: =IF('01_Input'!$C$57="Non",0,MIN('01_Input'!$I$57,MAX('01_Input'!$H$57,IF('01_Input'!$G$57="Résiduel vs Gestion",0,IF('01_Input'!$G$57="Taux Classe sélectionnée",Distrib_Global_Classe_Selectionnee*J$20,IF('01_Input'!$G$57="Frais KYC (paliers de 100M€)",MAX(0,Nb_Investisseurs-Nb_KYC_Gratuites_Par_Tranche*(FLOOR(J$20/Taille_Tranche_KYC,1)+1))*Cout_Par_KYC_Supplementaire,(IF('01_Input'!$L$57="Forfait",IF(J$20>='01_Input'!$J$57,'01_Input'!$M$57,0),IF('01_Input'!$L$57="Palier",IF(AND(J$20>='01_Input'!$J$57,J$20<'01_Input'!$K$57),'01_Input'!$M$57,0),MAX(MIN(J$20,'01_Input'!$K$57)-'01_Input'!$J$57,0)*'01_Input'!$M$57))+IF('01_Input'!$P$57="Forfait",IF(J$20>='01_Input'!$N$57,'01_Input'!$Q$57,0),IF('01_Input'!$P$57="Palier",IF(AND(J$20>='01_Input'!$N$57,J$20<'01_Input'!$O$57),'01_Input'!$Q$57,0),MAX(MIN(J$20,'01_Input'!$O$57)-'01_Input'!$N$57,0)*'01_Input'!$Q$57))+IF('01_Input'!$T$57="Forfait",IF(J$20>='01_Input'!$R$57,'01_Input'!$U$57,0),IF('01_Input'!$T$57="Palier",IF(AND(J$20>='01_Input'!$R$57,J$20<'01_Input'!$S$57),'01_Input'!$U$57,0),MAX(MIN(J$20,'01_Input'!$S$57)-'01_Input'!$R$57,0)*'01_Input'!$U$57))+IF('01_Input'!$X$57="Forfait",IF(J$20>='01_Input'!$V$57,'01_Input'!$Y$57,0),IF('01_Input'!$X$57="Palier",IF(AND(J$20>='01_Input'!$V$57,J$20<'01_Input'!$W$57),'01_Input'!$Y$57,0),MAX(MIN(J$20,'01_Input'!$W$57)-'01_Input'!$V$57,0)*'01_Input'!$Y$57))+IF('01_Input'!$AB$57="Forfait",IF(J$20>='01_Input'!$Z$57,'01_Input'!$AC$57,0),IF('01_Input'!$AB$57="Palier",IF(AND(J$20>='01_Input'!$Z$57,J$20<'01_Input'!$AA$57),'01_Input'!$AC$57,0),MAX(MIN(J$20,'01_Input'!$AA$57)-'01_Input'!$Z$57,0)*'01_Input'!$AC$57))))))))) -> 12000 | K25: =IF('01_Input'!$C$57="Non",0,MIN('01_Input'!$I$57,MAX('01_Input'!$H$57,IF('01_Input'!$G$57="Résiduel vs Gestion",0,IF('01_Input'!$G$57="Taux Classe sélectionnée",Distrib_Global_Classe_Selectionnee*K$20,IF('01_Input'!$G$57="Frais KYC (paliers de 100M€)",MAX(0,Nb_Investisseurs-Nb_KYC_Gratuites_Par_Tranche*(FLOOR(K$20/Taille_Tranche_KYC,1)+1))*Cout_Par_KYC_Supplementaire,(IF('01_Input'!$L$57="Forfait",IF(K$20>='01_Input'!$J$57,'01_Input'!$M$57,0),IF('01_Input'!$L$57="Palier",IF(AND(K$20>='01_Input'!$J$57,K$20<'01_Input'!$K$57),'01_Input'!$M$57,0),MAX(MIN(K$20,'01_Input'!$K$57)-'01_Input'!$J$57,0)*'01_Input'!$M$57))+IF('01_Input'!$P$57="Forfait",IF(K$20>='01_Input'!$N$57,'01_Input'!$Q$57,0),IF('01_Input'!$P$57="Palier",IF(AND(K$20>='01_Input'!$N$57,K$20<'01_Input'!$O$57),'01_Input'!$Q$57,0),MAX(MIN(K$20,'01_Input'!$O$57)-'01_Input'!$N$57,0)*'01_Input'!$Q$57))+IF('01_Input'!$T$57="Forfait",IF(K$20>='01_Input'!$R$57,'01_Input'!$U$57,0),IF('01_Input'!$T$57="Palier",IF(AND(K$20>='01_Input'!$R$57,K$20<'01_Input'!$S$57),'01_Input'!$U$57,0),MAX(MIN(K$20,'01_Input'!$S$57)-'01_Input'!$R$57,0)*'01_Input'!$U$57))+IF('01_Input'!$X$57="Forfait",IF(K$20>='01_Input'!$V$57,'01_Input'!$Y$57,0),IF('01_Input'!$X$57="Palier",IF(AND(K$20>='01_Input'!$V$57,K$20<'01_Input'!$W$57),'01_Input'!$Y$57,0),MAX(MIN(K$20,'01_Input'!$W$57)-'01_Input'!$V$57,0)*'01_Input'!$Y$57))+IF('01_Input'!$AB$57="Forfait",IF(K$20>='01_Input'!$Z$57,'01_Input'!$AC$57,0),IF('01_Input'!$AB$57="Palier",IF(AND(K$20>='01_Input'!$Z$57,K$20<'01_Input'!$AA$57),'01_Input'!$AC$57,0),MAX(MIN(K$20,'01_Input'!$AA$57)-'01_Input'!$Z$57,0)*'01_Input'!$AC$57))))))))) -> 12000 | L25: =IF('01_Input'!$C$57="Non",0,MIN('01_Input'!$I$57,MAX('01_Input'!$H$57,IF('01_Input'!$G$57="Résiduel vs Gestion",0,IF('01_Input'!$G$57="Taux Classe sélectionnée",Distrib_Global_Classe_Selectionnee*L$20,IF('01_Input'!$G$57="Frais KYC (paliers de 100M€)",MAX(0,Nb_Investisseurs-Nb_KYC_Gratuites_Par_Tranche*(FLOOR(L$20/Taille_Tranche_KYC,1)+1))*Cout_Par_KYC_Supplementaire,(IF('01_Input'!$L$57="Forfait",IF(L$20>='01_Input'!$J$57,'01_Input'!$M$57,0),IF('01_Input'!$L$57="Palier",IF(AND(L$20>='01_Input'!$J$57,L$20<'01_Input'!$K$57),'01_Input'!$M$57,0),MAX(MIN(L$20,'01_Input'!$K$57)-'01_Input'!$J$57,0)*'01_Input'!$M$57))+IF('01_Input'!$P$57="Forfait",IF(L$20>='01_Input'!$N$57,'01_Input'!$Q$57,0),IF('01_Input'!$P$57="Palier",IF(AND(L$20>='01_Input'!$N$57,L$20<'01_Input'!$O$57),'01_Input'!$Q$57,0),MAX(MIN(L$20,'01_Input'!$O$57)-'01_Input'!$N$57,0)*'01_Input'!$Q$57))+IF('01_Input'!$T$57="Forfait",IF(L$20>='01_Input'!$R$57,'01_Input'!$U$57,0),IF('01_Input'!$T$57="Palier",IF(AND(L$20>='01_Input'!$R$57,L$20<'01_Input'!$S$57),'01_Input'!$U$57,0),MAX(MIN(L$20,'01_Input'!$S$57)-'01_Input'!$R$57,0)*'01_Input'!$U$57))+IF('01_Input'!$X$57="Forfait",IF(L$20>='01_Input'!$V$57,'01_Input'!$Y$57,0),IF('01_Input'!$X$57="Palier",IF(AND(L$20>='01_Input'!$V$57,L$20<'01_Input'!$W$57),'01_Input'!$Y$57,0),MAX(MIN(L$20,'01_Input'!$W$57)-'01_Input'!$V$57,0)*'01_Input'!$Y$57))+IF('01_Input'!$AB$57="Forfait",IF(L$20>='01_Input'!$Z$57,'01_Input'!$AC$57,0),IF('01_Input'!$AB$57="Palier",IF(AND(L$20>='01_Input'!$Z$57,L$20<'01_Input'!$AA$57),'01_Input'!$AC$57,0),MAX(MIN(L$20,'01_Input'!$AA$57)-'01_Input'!$Z$57,0)*'01_Input'!$AC$57))))))))) -> 12000 | ... EX25: =IF('01_Input'!$C$57="Non",0,MIN('01_Input'!$I$57,MAX('01_Input'!$H$57,IF('01_Input'!$G$57="Résiduel vs Gestion",0,IF('01_Input'!$G$57="Taux Classe sélectionnée",Distrib_Global_Classe_Selectionnee*EX$20,IF('01_Input'!$G$57="Frais KYC (paliers de 100M€)",MAX(0,Nb_Investisseurs-Nb_KYC_Gratuites_Par_Tranche*(FLOOR(EX$20/Taille_Tranche_KYC,1)+1))*Cout_Par_KYC_Supplementaire,(IF('01_Input'!$L$57="Forfait",IF(EX$20>='01_Input'!$J$57,'01_Input'!$M$57,0),IF('01_Input'!$L$57="Palier",IF(AND(EX$20>='01_Input'!$J$57,EX$20<'01_Input'!$K$57),'01_Input'!$M$57,0),MAX(MIN(EX$20,'01_Input'!$K$57)-'01_Input'!$J$57,0)*'01_Input'!$M$57))+IF('01_Input'!$P$57="Forfait",IF(EX$20>='01_Input'!$N$57,'01_Input'!$Q$57,0),IF('01_Input'!$P$57="Palier",IF(AND(EX$20>='01_Input'!$N$57,EX$20<'01_Input'!$O$57),'01_Input'!$Q$57,0),MAX(MIN(EX$20,'01_Input'!$O$57)-'01_Input'!$N$57,0)*'01_Input'!$Q$57))+IF('01_Input'!$T$57="Forfait",IF(EX$20>='01_Input'!$R$57,'01_Input'!$U$57,0),IF('01_Input'!$T$57="Palier",IF(AND(EX$20>='01_Input'!$R$57,EX$20<'01_Input'!$S$57),'01_Input'!$U$57,0),MAX(MIN(EX$20,'01_Input'!$S$57)-'01_Input'!$R$57,0)*'01_Input'!$U$57))+IF('01_Input'!$X$57="Forfait",IF(EX$20>='01_Input'!$V$57,'01_Input'!$Y$57,0),IF('01_Input'!$X$57="Palier",IF(AND(EX$20>='01_Input'!$V$57,EX$20<'01_Input'!$W$57),'01_Input'!$Y$57,0),MAX(MIN(EX$20,'01_Input'!$W$57)-'01_Input'!$V$57,0)*'01_Input'!$Y$57))+IF('01_Input'!$AB$57="Forfait",IF(EX$20>='01_Input'!$Z$57,'01_Input'!$AC$57,0),IF('01_Input'!$AB$57="Palier",IF(AND(EX$20>='01_Input'!$Z$57,EX$20<'01_Input'!$AA$57),'01_Input'!$AC$57,0),MAX(MIN(EX$20,'01_Input'!$AA$57)-'01_Input'!$Z$57,0)*'01_Input'!$AC$57))))))))) -> 50000
B26: =IF('01_Input'!D58="","(inactif)",'01_Input'!D58) -> Commissaire aux Comptes | C26: =IF('01_Input'!E58="","",'01_Input'!E58) -> CAC | D26: ='01_Input'!C58 -> Oui | E26: =IF('01_Input'!$C$58="Non",0,MIN('01_Input'!$I$58,MAX('01_Input'!$H$58,IF('01_Input'!$G$58="Résiduel vs Gestion",0,IF('01_Input'!$G$58="Taux Classe sélectionnée",Distrib_Global_Classe_Selectionnee*E$20,IF('01_Input'!$G$58="Frais KYC (paliers de 100M€)",MAX(0,Nb_Investisseurs-Nb_KYC_Gratuites_Par_Tranche*(FLOOR(E$20/Taille_Tranche_KYC,1)+1))*Cout_Par_KYC_Supplementaire,(IF('01_Input'!$L$58="Forfait",IF(E$20>='01_Input'!$J$58,'01_Input'!$M$58,0),IF('01_Input'!$L$58="Palier",IF(AND(E$20>='01_Input'!$J$58,E$20<'01_Input'!$K$58),'01_Input'!$M$58,0),MAX(MIN(E$20,'01_Input'!$K$58)-'01_Input'!$J$58,0)*'01_Input'!$M$58))+IF('01_Input'!$P$58="Forfait",IF(E$20>='01_Input'!$N$58,'01_Input'!$Q$58,0),IF('01_Input'!$P$58="Palier",IF(AND(E$20>='01_Input'!$N$58,E$20<'01_Input'!$O$58),'01_Input'!$Q$58,0),MAX(MIN(E$20,'01_Input'!$O$58)-'01_Input'!$N$58,0)*'01_Input'!$Q$58))+IF('01_Input'!$T$58="Forfait",IF(E$20>='01_Input'!$R$58,'01_Input'!$U$58,0),IF('01_Input'!$T$58="Palier",IF(AND(E$20>='01_Input'!$R$58,E$20<'01_Input'!$S$58),'01_Input'!$U$58,0),MAX(MIN(E$20,'01_Input'!$S$58)-'01_Input'!$R$58,0)*'01_Input'!$U$58))+IF('01_Input'!$X$58="Forfait",IF(E$20>='01_Input'!$V$58,'01_Input'!$Y$58,0),IF('01_Input'!$X$58="Palier",IF(AND(E$20>='01_Input'!$V$58,E$20<'01_Input'!$W$58),'01_Input'!$Y$58,0),MAX(MIN(E$20,'01_Input'!$W$58)-'01_Input'!$V$58,0)*'01_Input'!$Y$58))+IF('01_Input'!$AB$58="Forfait",IF(E$20>='01_Input'!$Z$58,'01_Input'!$AC$58,0),IF('01_Input'!$AB$58="Palier",IF(AND(E$20>='01_Input'!$Z$58,E$20<'01_Input'!$AA$58),'01_Input'!$AC$58,0),MAX(MIN(E$20,'01_Input'!$AA$58)-'01_Input'!$Z$58,0)*'01_Input'!$AC$58))))))))) -> 5500 | F26: =IF('01_Input'!$C$58="Non",0,MIN('01_Input'!$I$58,MAX('01_Input'!$H$58,IF('01_Input'!$G$58="Résiduel vs Gestion",0,IF('01_Input'!$G$58="Taux Classe sélectionnée",Distrib_Global_Classe_Selectionnee*F$20,IF('01_Input'!$G$58="Frais KYC (paliers de 100M€)",MAX(0,Nb_Investisseurs-Nb_KYC_Gratuites_Par_Tranche*(FLOOR(F$20/Taille_Tranche_KYC,1)+1))*Cout_Par_KYC_Supplementaire,(IF('01_Input'!$L$58="Forfait",IF(F$20>='01_Input'!$J$58,'01_Input'!$M$58,0),IF('01_Input'!$L$58="Palier",IF(AND(F$20>='01_Input'!$J$58,F$20<'01_Input'!$K$58),'01_Input'!$M$58,0),MAX(MIN(F$20,'01_Input'!$K$58)-'01_Input'!$J$58,0)*'01_Input'!$M$58))+IF('01_Input'!$P$58="Forfait",IF(F$20>='01_Input'!$N$58,'01_Input'!$Q$58,0),IF('01_Input'!$P$58="Palier",IF(AND(F$20>='01_Input'!$N$58,F$20<'01_Input'!$O$58),'01_Input'!$Q$58,0),MAX(MIN(F$20,'01_Input'!$O$58)-'01_Input'!$N$58,0)*'01_Input'!$Q$58))+IF('01_Input'!$T$58="Forfait",IF(F$20>='01_Input'!$R$58,'01_Input'!$U$58,0),IF('01_Input'!$T$58="Palier",IF(AND(F$20>='01_Input'!$R$58,F$20<'01_Input'!$S$58),'01_Input'!$U$58,0),MAX(MIN(F$20,'01_Input'!$S$58)-'01_Input'!$R$58,0)*'01_Input'!$U$58))+IF('01_Input'!$X$58="Forfait",IF(F$20>='01_Input'!$V$58,'01_Input'!$Y$58,0),IF('01_Input'!$X$58="Palier",IF(AND(F$20>='01_Input'!$V$58,F$20<'01_Input'!$W$58),'01_Input'!$Y$58,0),MAX(MIN(F$20,'01_Input'!$W$58)-'01_Input'!$V$58,0)*'01_Input'!$Y$58))+IF('01_Input'!$AB$58="Forfait",IF(F$20>='01_Input'!$Z$58,'01_Input'!$AC$58,0),IF('01_Input'!$AB$58="Palier",IF(AND(F$20>='01_Input'!$Z$58,F$20<'01_Input'!$AA$58),'01_Input'!$AC$58,0),MAX(MIN(F$20,'01_Input'!$AA$58)-'01_Input'!$Z$58,0)*'01_Input'!$AC$58))))))))) -> 5500 | G26: =IF('01_Input'!$C$58="Non",0,MIN('01_Input'!$I$58,MAX('01_Input'!$H$58,IF('01_Input'!$G$58="Résiduel vs Gestion",0,IF('01_Input'!$G$58="Taux Classe sélectionnée",Distrib_Global_Classe_Selectionnee*G$20,IF('01_Input'!$G$58="Frais KYC (paliers de 100M€)",MAX(0,Nb_Investisseurs-Nb_KYC_Gratuites_Par_Tranche*(FLOOR(G$20/Taille_Tranche_KYC,1)+1))*Cout_Par_KYC_Supplementaire,(IF('01_Input'!$L$58="Forfait",IF(G$20>='01_Input'!$J$58,'01_Input'!$M$58,0),IF('01_Input'!$L$58="Palier",IF(AND(G$20>='01_Input'!$J$58,G$20<'01_Input'!$K$58),'01_Input'!$M$58,0),MAX(MIN(G$20,'01_Input'!$K$58)-'01_Input'!$J$58,0)*'01_Input'!$M$58))+IF('01_Input'!$P$58="Forfait",IF(G$20>='01_Input'!$N$58,'01_Input'!$Q$58,0),IF('01_Input'!$P$58="Palier",IF(AND(G$20>='01_Input'!$N$58,G$20<'01_Input'!$O$58),'01_Input'!$Q$58,0),MAX(MIN(G$20,'01_Input'!$O$58)-'01_Input'!$N$58,0)*'01_Input'!$Q$58))+IF('01_Input'!$T$58="Forfait",IF(G$20>='01_Input'!$R$58,'01_Input'!$U$58,0),IF('01_Input'!$T$58="Palier",IF(AND(G$20>='01_Input'!$R$58,G$20<'01_Input'!$S$58),'01_Input'!$U$58,0),MAX(MIN(G$20,'01_Input'!$S$58)-'01_Input'!$R$58,0)*'01_Input'!$U$58))+IF('01_Input'!$X$58="Forfait",IF(G$20>='01_Input'!$V$58,'01_Input'!$Y$58,0),IF('01_Input'!$X$58="Palier",IF(AND(G$20>='01_Input'!$V$58,G$20<'01_Input'!$W$58),'01_Input'!$Y$58,0),MAX(MIN(G$20,'01_Input'!$W$58)-'01_Input'!$V$58,0)*'01_Input'!$Y$58))+IF('01_Input'!$AB$58="Forfait",IF(G$20>='01_Input'!$Z$58,'01_Input'!$AC$58,0),IF('01_Input'!$AB$58="Palier",IF(AND(G$20>='01_Input'!$Z$58,G$20<'01_Input'!$AA$58),'01_Input'!$AC$58,0),MAX(MIN(G$20,'01_Input'!$AA$58)-'01_Input'!$Z$58,0)*'01_Input'!$AC$58))))))))) -> 5500 | H26: =IF('01_Input'!$C$58="Non",0,MIN('01_Input'!$I$58,MAX('01_Input'!$H$58,IF('01_Input'!$G$58="Résiduel vs Gestion",0,IF('01_Input'!$G$58="Taux Classe sélectionnée",Distrib_Global_Classe_Selectionnee*H$20,IF('01_Input'!$G$58="Frais KYC (paliers de 100M€)",MAX(0,Nb_Investisseurs-Nb_KYC_Gratuites_Par_Tranche*(FLOOR(H$20/Taille_Tranche_KYC,1)+1))*Cout_Par_KYC_Supplementaire,(IF('01_Input'!$L$58="Forfait",IF(H$20>='01_Input'!$J$58,'01_Input'!$M$58,0),IF('01_Input'!$L$58="Palier",IF(AND(H$20>='01_Input'!$J$58,H$20<'01_Input'!$K$58),'01_Input'!$M$58,0),MAX(MIN(H$20,'01_Input'!$K$58)-'01_Input'!$J$58,0)*'01_Input'!$M$58))+IF('01_Input'!$P$58="Forfait",IF(H$20>='01_Input'!$N$58,'01_Input'!$Q$58,0),IF('01_Input'!$P$58="Palier",IF(AND(H$20>='01_Input'!$N$58,H$20<'01_Input'!$O$58),'01_Input'!$Q$58,0),MAX(MIN(H$20,'01_Input'!$O$58)-'01_Input'!$N$58,0)*'01_Input'!$Q$58))+IF('01_Input'!$T$58="Forfait",IF(H$20>='01_Input'!$R$58,'01_Input'!$U$58,0),IF('01_Input'!$T$58="Palier",IF(AND(H$20>='01_Input'!$R$58,H$20<'01_Input'!$S$58),'01_Input'!$U$58,0),MAX(MIN(H$20,'01_Input'!$S$58)-'01_Input'!$R$58,0)*'01_Input'!$U$58))+IF('01_Input'!$X$58="Forfait",IF(H$20>='01_Input'!$V$58,'01_Input'!$Y$58,0),IF('01_Input'!$X$58="Palier",IF(AND(H$20>='01_Input'!$V$58,H$20<'01_Input'!$W$58),'01_Input'!$Y$58,0),MAX(MIN(H$20,'01_Input'!$W$58)-'01_Input'!$V$58,0)*'01_Input'!$Y$58))+IF('01_Input'!$AB$58="Forfait",IF(H$20>='01_Input'!$Z$58,'01_Input'!$AC$58,0),IF('01_Input'!$AB$58="Palier",IF(AND(H$20>='01_Input'!$Z$58,H$20<'01_Input'!$AA$58),'01_Input'!$AC$58,0),MAX(MIN(H$20,'01_Input'!$AA$58)-'01_Input'!$Z$58,0)*'01_Input'!$AC$58))))))))) -> 5500 | I26: =IF('01_Input'!$C$58="Non",0,MIN('01_Input'!$I$58,MAX('01_Input'!$H$58,IF('01_Input'!$G$58="Résiduel vs Gestion",0,IF('01_Input'!$G$58="Taux Classe sélectionnée",Distrib_Global_Classe_Selectionnee*I$20,IF('01_Input'!$G$58="Frais KYC (paliers de 100M€)",MAX(0,Nb_Investisseurs-Nb_KYC_Gratuites_Par_Tranche*(FLOOR(I$20/Taille_Tranche_KYC,1)+1))*Cout_Par_KYC_Supplementaire,(IF('01_Input'!$L$58="Forfait",IF(I$20>='01_Input'!$J$58,'01_Input'!$M$58,0),IF('01_Input'!$L$58="Palier",IF(AND(I$20>='01_Input'!$J$58,I$20<'01_Input'!$K$58),'01_Input'!$M$58,0),MAX(MIN(I$20,'01_Input'!$K$58)-'01_Input'!$J$58,0)*'01_Input'!$M$58))+IF('01_Input'!$P$58="Forfait",IF(I$20>='01_Input'!$N$58,'01_Input'!$Q$58,0),IF('01_Input'!$P$58="Palier",IF(AND(I$20>='01_Input'!$N$58,I$20<'01_Input'!$O$58),'01_Input'!$Q$58,0),MAX(MIN(I$20,'01_Input'!$O$58)-'01_Input'!$N$58,0)*'01_Input'!$Q$58))+IF('01_Input'!$T$58="Forfait",IF(I$20>='01_Input'!$R$58,'01_Input'!$U$58,0),IF('01_Input'!$T$58="Palier",IF(AND(I$20>='01_Input'!$R$58,I$20<'01_Input'!$S$58),'01_Input'!$U$58,0),MAX(MIN(I$20,'01_Input'!$S$58)-'01_Input'!$R$58,0)*'01_Input'!$U$58))+IF('01_Input'!$X$58="Forfait",IF(I$20>='01_Input'!$V$58,'01_Input'!$Y$58,0),IF('01_Input'!$X$58="Palier",IF(AND(I$20>='01_Input'!$V$58,I$20<'01_Input'!$W$58),'01_Input'!$Y$58,0),MAX(MIN(I$20,'01_Input'!$W$58)-'01_Input'!$V$58,0)*'01_Input'!$Y$58))+IF('01_Input'!$AB$58="Forfait",IF(I$20>='01_Input'!$Z$58,'01_Input'!$AC$58,0),IF('01_Input'!$AB$58="Palier",IF(AND(I$20>='01_Input'!$Z$58,I$20<'01_Input'!$AA$58),'01_Input'!$AC$58,0),MAX(MIN(I$20,'01_Input'!$AA$58)-'01_Input'!$Z$58,0)*'01_Input'!$AC$58))))))))) -> 5500 | J26: =IF('01_Input'!$C$58="Non",0,MIN('01_Input'!$I$58,MAX('01_Input'!$H$58,IF('01_Input'!$G$58="Résiduel vs Gestion",0,IF('01_Input'!$G$58="Taux Classe sélectionnée",Distrib_Global_Classe_Selectionnee*J$20,IF('01_Input'!$G$58="Frais KYC (paliers de 100M€)",MAX(0,Nb_Investisseurs-Nb_KYC_Gratuites_Par_Tranche*(FLOOR(J$20/Taille_Tranche_KYC,1)+1))*Cout_Par_KYC_Supplementaire,(IF('01_Input'!$L$58="Forfait",IF(J$20>='01_Input'!$J$58,'01_Input'!$M$58,0),IF('01_Input'!$L$58="Palier",IF(AND(J$20>='01_Input'!$J$58,J$20<'01_Input'!$K$58),'01_Input'!$M$58,0),MAX(MIN(J$20,'01_Input'!$K$58)-'01_Input'!$J$58,0)*'01_Input'!$M$58))+IF('01_Input'!$P$58="Forfait",IF(J$20>='01_Input'!$N$58,'01_Input'!$Q$58,0),IF('01_Input'!$P$58="Palier",IF(AND(J$20>='01_Input'!$N$58,J$20<'01_Input'!$O$58),'01_Input'!$Q$58,0),MAX(MIN(J$20,'01_Input'!$O$58)-'01_Input'!$N$58,0)*'01_Input'!$Q$58))+IF('01_Input'!$T$58="Forfait",IF(J$20>='01_Input'!$R$58,'01_Input'!$U$58,0),IF('01_Input'!$T$58="Palier",IF(AND(J$20>='01_Input'!$R$58,J$20<'01_Input'!$S$58),'01_Input'!$U$58,0),MAX(MIN(J$20,'01_Input'!$S$58)-'01_Input'!$R$58,0)*'01_Input'!$U$58))+IF('01_Input'!$X$58="Forfait",IF(J$20>='01_Input'!$V$58,'01_Input'!$Y$58,0),IF('01_Input'!$X$58="Palier",IF(AND(J$20>='01_Input'!$V$58,J$20<'01_Input'!$W$58),'01_Input'!$Y$58,0),MAX(MIN(J$20,'01_Input'!$W$58)-'01_Input'!$V$58,0)*'01_Input'!$Y$58))+IF('01_Input'!$AB$58="Forfait",IF(J$20>='01_Input'!$Z$58,'01_Input'!$AC$58,0),IF('01_Input'!$AB$58="Palier",IF(AND(J$20>='01_Input'!$Z$58,J$20<'01_Input'!$AA$58),'01_Input'!$AC$58,0),MAX(MIN(J$20,'01_Input'!$AA$58)-'01_Input'!$Z$58,0)*'01_Input'!$AC$58))))))))) -> 5500 | K26: =IF('01_Input'!$C$58="Non",0,MIN('01_Input'!$I$58,MAX('01_Input'!$H$58,IF('01_Input'!$G$58="Résiduel vs Gestion",0,IF('01_Input'!$G$58="Taux Classe sélectionnée",Distrib_Global_Classe_Selectionnee*K$20,IF('01_Input'!$G$58="Frais KYC (paliers de 100M€)",MAX(0,Nb_Investisseurs-Nb_KYC_Gratuites_Par_Tranche*(FLOOR(K$20/Taille_Tranche_KYC,1)+1))*Cout_Par_KYC_Supplementaire,(IF('01_Input'!$L$58="Forfait",IF(K$20>='01_Input'!$J$58,'01_Input'!$M$58,0),IF('01_Input'!$L$58="Palier",IF(AND(K$20>='01_Input'!$J$58,K$20<'01_Input'!$K$58),'01_Input'!$M$58,0),MAX(MIN(K$20,'01_Input'!$K$58)-'01_Input'!$J$58,0)*'01_Input'!$M$58))+IF('01_Input'!$P$58="Forfait",IF(K$20>='01_Input'!$N$58,'01_Input'!$Q$58,0),IF('01_Input'!$P$58="Palier",IF(AND(K$20>='01_Input'!$N$58,K$20<'01_Input'!$O$58),'01_Input'!$Q$58,0),MAX(MIN(K$20,'01_Input'!$O$58)-'01_Input'!$N$58,0)*'01_Input'!$Q$58))+IF('01_Input'!$T$58="Forfait",IF(K$20>='01_Input'!$R$58,'01_Input'!$U$58,0),IF('01_Input'!$T$58="Palier",IF(AND(K$20>='01_Input'!$R$58,K$20<'01_Input'!$S$58),'01_Input'!$U$58,0),MAX(MIN(K$20,'01_Input'!$S$58)-'01_Input'!$R$58,0)*'01_Input'!$U$58))+IF('01_Input'!$X$58="Forfait",IF(K$20>='01_Input'!$V$58,'01_Input'!$Y$58,0),IF('01_Input'!$X$58="Palier",IF(AND(K$20>='01_Input'!$V$58,K$20<'01_Input'!$W$58),'01_Input'!$Y$58,0),MAX(MIN(K$20,'01_Input'!$W$58)-'01_Input'!$V$58,0)*'01_Input'!$Y$58))+IF('01_Input'!$AB$58="Forfait",IF(K$20>='01_Input'!$Z$58,'01_Input'!$AC$58,0),IF('01_Input'!$AB$58="Palier",IF(AND(K$20>='01_Input'!$Z$58,K$20<'01_Input'!$AA$58),'01_Input'!$AC$58,0),MAX(MIN(K$20,'01_Input'!$AA$58)-'01_Input'!$Z$58,0)*'01_Input'!$AC$58))))))))) -> 5500 | L26: =IF('01_Input'!$C$58="Non",0,MIN('01_Input'!$I$58,MAX('01_Input'!$H$58,IF('01_Input'!$G$58="Résiduel vs Gestion",0,IF('01_Input'!$G$58="Taux Classe sélectionnée",Distrib_Global_Classe_Selectionnee*L$20,IF('01_Input'!$G$58="Frais KYC (paliers de 100M€)",MAX(0,Nb_Investisseurs-Nb_KYC_Gratuites_Par_Tranche*(FLOOR(L$20/Taille_Tranche_KYC,1)+1))*Cout_Par_KYC_Supplementaire,(IF('01_Input'!$L$58="Forfait",IF(L$20>='01_Input'!$J$58,'01_Input'!$M$58,0),IF('01_Input'!$L$58="Palier",IF(AND(L$20>='01_Input'!$J$58,L$20<'01_Input'!$K$58),'01_Input'!$M$58,0),MAX(MIN(L$20,'01_Input'!$K$58)-'01_Input'!$J$58,0)*'01_Input'!$M$58))+IF('01_Input'!$P$58="Forfait",IF(L$20>='01_Input'!$N$58,'01_Input'!$Q$58,0),IF('01_Input'!$P$58="Palier",IF(AND(L$20>='01_Input'!$N$58,L$20<'01_Input'!$O$58),'01_Input'!$Q$58,0),MAX(MIN(L$20,'01_Input'!$O$58)-'01_Input'!$N$58,0)*'01_Input'!$Q$58))+IF('01_Input'!$T$58="Forfait",IF(L$20>='01_Input'!$R$58,'01_Input'!$U$58,0),IF('01_Input'!$T$58="Palier",IF(AND(L$20>='01_Input'!$R$58,L$20<'01_Input'!$S$58),'01_Input'!$U$58,0),MAX(MIN(L$20,'01_Input'!$S$58)-'01_Input'!$R$58,0)*'01_Input'!$U$58))+IF('01_Input'!$X$58="Forfait",IF(L$20>='01_Input'!$V$58,'01_Input'!$Y$58,0),IF('01_Input'!$X$58="Palier",IF(AND(L$20>='01_Input'!$V$58,L$20<'01_Input'!$W$58),'01_Input'!$Y$58,0),MAX(MIN(L$20,'01_Input'!$W$58)-'01_Input'!$V$58,0)*'01_Input'!$Y$58))+IF('01_Input'!$AB$58="Forfait",IF(L$20>='01_Input'!$Z$58,'01_Input'!$AC$58,0),IF('01_Input'!$AB$58="Palier",IF(AND(L$20>='01_Input'!$Z$58,L$20<'01_Input'!$AA$58),'01_Input'!$AC$58,0),MAX(MIN(L$20,'01_Input'!$AA$58)-'01_Input'!$Z$58,0)*'01_Input'!$AC$58))))))))) -> 5500 | ... EX26: =IF('01_Input'!$C$58="Non",0,MIN('01_Input'!$I$58,MAX('01_Input'!$H$58,IF('01_Input'!$G$58="Résiduel vs Gestion",0,IF('01_Input'!$G$58="Taux Classe sélectionnée",Distrib_Global_Classe_Selectionnee*EX$20,IF('01_Input'!$G$58="Frais KYC (paliers de 100M€)",MAX(0,Nb_Investisseurs-Nb_KYC_Gratuites_Par_Tranche*(FLOOR(EX$20/Taille_Tranche_KYC,1)+1))*Cout_Par_KYC_Supplementaire,(IF('01_Input'!$L$58="Forfait",IF(EX$20>='01_Input'!$J$58,'01_Input'!$M$58,0),IF('01_Input'!$L$58="Palier",IF(AND(EX$20>='01_Input'!$J$58,EX$20<'01_Input'!$K$58),'01_Input'!$M$58,0),MAX(MIN(EX$20,'01_Input'!$K$58)-'01_Input'!$J$58,0)*'01_Input'!$M$58))+IF('01_Input'!$P$58="Forfait",IF(EX$20>='01_Input'!$N$58,'01_Input'!$Q$58,0),IF('01_Input'!$P$58="Palier",IF(AND(EX$20>='01_Input'!$N$58,EX$20<'01_Input'!$O$58),'01_Input'!$Q$58,0),MAX(MIN(EX$20,'01_Input'!$O$58)-'01_Input'!$N$58,0)*'01_Input'!$Q$58))+IF('01_Input'!$T$58="Forfait",IF(EX$20>='01_Input'!$R$58,'01_Input'!$U$58,0),IF('01_Input'!$T$58="Palier",IF(AND(EX$20>='01_Input'!$R$58,EX$20<'01_Input'!$S$58),'01_Input'!$U$58,0),MAX(MIN(EX$20,'01_Input'!$S$58)-'01_Input'!$R$58,0)*'01_Input'!$U$58))+IF('01_Input'!$X$58="Forfait",IF(EX$20>='01_Input'!$V$58,'01_Input'!$Y$58,0),IF('01_Input'!$X$58="Palier",IF(AND(EX$20>='01_Input'!$V$58,EX$20<'01_Input'!$W$58),'01_Input'!$Y$58,0),MAX(MIN(EX$20,'01_Input'!$W$58)-'01_Input'!$V$58,0)*'01_Input'!$Y$58))+IF('01_Input'!$AB$58="Forfait",IF(EX$20>='01_Input'!$Z$58,'01_Input'!$AC$58,0),IF('01_Input'!$AB$58="Palier",IF(AND(EX$20>='01_Input'!$Z$58,EX$20<'01_Input'!$AA$58),'01_Input'!$AC$58,0),MAX(MIN(EX$20,'01_Input'!$AA$58)-'01_Input'!$Z$58,0)*'01_Input'!$AC$58))))))))) -> 5500
B27: =IF('01_Input'!D59="","(inactif)",'01_Input'!D59) -> CAC — Frais par Distribution | C27: =IF('01_Input'!E59="","",'01_Input'!E59) | D27: ='01_Input'!C59 -> Oui | E27: =IF('01_Input'!$C$59="Non",0,MIN('01_Input'!$I$59,MAX('01_Input'!$H$59,IF('01_Input'!$G$59="Résiduel vs Gestion",0,IF('01_Input'!$G$59="Taux Classe sélectionnée",Distrib_Global_Classe_Selectionnee*E$20,IF('01_Input'!$G$59="Frais KYC (paliers de 100M€)",MAX(0,Nb_Investisseurs-Nb_KYC_Gratuites_Par_Tranche*(FLOOR(E$20/Taille_Tranche_KYC,1)+1))*Cout_Par_KYC_Supplementaire,(IF('01_Input'!$L$59="Forfait",IF(E$20>='01_Input'!$J$59,'01_Input'!$M$59,0),IF('01_Input'!$L$59="Palier",IF(AND(E$20>='01_Input'!$J$59,E$20<'01_Input'!$K$59),'01_Input'!$M$59,0),MAX(MIN(E$20,'01_Input'!$K$59)-'01_Input'!$J$59,0)*'01_Input'!$M$59))+IF('01_Input'!$P$59="Forfait",IF(E$20>='01_Input'!$N$59,'01_Input'!$Q$59,0),IF('01_Input'!$P$59="Palier",IF(AND(E$20>='01_Input'!$N$59,E$20<'01_Input'!$O$59),'01_Input'!$Q$59,0),MAX(MIN(E$20,'01_Input'!$O$59)-'01_Input'!$N$59,0)*'01_Input'!$Q$59))+IF('01_Input'!$T$59="Forfait",IF(E$20>='01_Input'!$R$59,'01_Input'!$U$59,0),IF('01_Input'!$T$59="Palier",IF(AND(E$20>='01_Input'!$R$59,E$20<'01_Input'!$S$59),'01_Input'!$U$59,0),MAX(MIN(E$20,'01_Input'!$S$59)-'01_Input'!$R$59,0)*'01_Input'!$U$59))+IF('01_Input'!$X$59="Forfait",IF(E$20>='01_Input'!$V$59,'01_Input'!$Y$59,0),IF('01_Input'!$X$59="Palier",IF(AND(E$20>='01_Input'!$V$59,E$20<'01_Input'!$W$59),'01_Input'!$Y$59,0),MAX(MIN(E$20,'01_Input'!$W$59)-'01_Input'!$V$59,0)*'01_Input'!$Y$59))+IF('01_Input'!$AB$59="Forfait",IF(E$20>='01_Input'!$Z$59,'01_Input'!$AC$59,0),IF('01_Input'!$AB$59="Palier",IF(AND(E$20>='01_Input'!$Z$59,E$20<'01_Input'!$AA$59),'01_Input'!$AC$59,0),MAX(MIN(E$20,'01_Input'!$AA$59)-'01_Input'!$Z$59,0)*'01_Input'!$AC$59))))))))) -> 0 | F27: =IF('01_Input'!$C$59="Non",0,MIN('01_Input'!$I$59,MAX('01_Input'!$H$59,IF('01_Input'!$G$59="Résiduel vs Gestion",0,IF('01_Input'!$G$59="Taux Classe sélectionnée",Distrib_Global_Classe_Selectionnee*F$20,IF('01_Input'!$G$59="Frais KYC (paliers de 100M€)",MAX(0,Nb_Investisseurs-Nb_KYC_Gratuites_Par_Tranche*(FLOOR(F$20/Taille_Tranche_KYC,1)+1))*Cout_Par_KYC_Supplementaire,(IF('01_Input'!$L$59="Forfait",IF(F$20>='01_Input'!$J$59,'01_Input'!$M$59,0),IF('01_Input'!$L$59="Palier",IF(AND(F$20>='01_Input'!$J$59,F$20<'01_Input'!$K$59),'01_Input'!$M$59,0),MAX(MIN(F$20,'01_Input'!$K$59)-'01_Input'!$J$59,0)*'01_Input'!$M$59))+IF('01_Input'!$P$59="Forfait",IF(F$20>='01_Input'!$N$59,'01_Input'!$Q$59,0),IF('01_Input'!$P$59="Palier",IF(AND(F$20>='01_Input'!$N$59,F$20<'01_Input'!$O$59),'01_Input'!$Q$59,0),MAX(MIN(F$20,'01_Input'!$O$59)-'01_Input'!$N$59,0)*'01_Input'!$Q$59))+IF('01_Input'!$T$59="Forfait",IF(F$20>='01_Input'!$R$59,'01_Input'!$U$59,0),IF('01_Input'!$T$59="Palier",IF(AND(F$20>='01_Input'!$R$59,F$20<'01_Input'!$S$59),'01_Input'!$U$59,0),MAX(MIN(F$20,'01_Input'!$S$59)-'01_Input'!$R$59,0)*'01_Input'!$U$59))+IF('01_Input'!$X$59="Forfait",IF(F$20>='01_Input'!$V$59,'01_Input'!$Y$59,0),IF('01_Input'!$X$59="Palier",IF(AND(F$20>='01_Input'!$V$59,F$20<'01_Input'!$W$59),'01_Input'!$Y$59,0),MAX(MIN(F$20,'01_Input'!$W$59)-'01_Input'!$V$59,0)*'01_Input'!$Y$59))+IF('01_Input'!$AB$59="Forfait",IF(F$20>='01_Input'!$Z$59,'01_Input'!$AC$59,0),IF('01_Input'!$AB$59="Palier",IF(AND(F$20>='01_Input'!$Z$59,F$20<'01_Input'!$AA$59),'01_Input'!$AC$59,0),MAX(MIN(F$20,'01_Input'!$AA$59)-'01_Input'!$Z$59,0)*'01_Input'!$AC$59))))))))) -> 0 | G27: =IF('01_Input'!$C$59="Non",0,MIN('01_Input'!$I$59,MAX('01_Input'!$H$59,IF('01_Input'!$G$59="Résiduel vs Gestion",0,IF('01_Input'!$G$59="Taux Classe sélectionnée",Distrib_Global_Classe_Selectionnee*G$20,IF('01_Input'!$G$59="Frais KYC (paliers de 100M€)",MAX(0,Nb_Investisseurs-Nb_KYC_Gratuites_Par_Tranche*(FLOOR(G$20/Taille_Tranche_KYC,1)+1))*Cout_Par_KYC_Supplementaire,(IF('01_Input'!$L$59="Forfait",IF(G$20>='01_Input'!$J$59,'01_Input'!$M$59,0),IF('01_Input'!$L$59="Palier",IF(AND(G$20>='01_Input'!$J$59,G$20<'01_Input'!$K$59),'01_Input'!$M$59,0),MAX(MIN(G$20,'01_Input'!$K$59)-'01_Input'!$J$59,0)*'01_Input'!$M$59))+IF('01_Input'!$P$59="Forfait",IF(G$20>='01_Input'!$N$59,'01_Input'!$Q$59,0),IF('01_Input'!$P$59="Palier",IF(AND(G$20>='01_Input'!$N$59,G$20<'01_Input'!$O$59),'01_Input'!$Q$59,0),MAX(MIN(G$20,'01_Input'!$O$59)-'01_Input'!$N$59,0)*'01_Input'!$Q$59))+IF('01_Input'!$T$59="Forfait",IF(G$20>='01_Input'!$R$59,'01_Input'!$U$59,0),IF('01_Input'!$T$59="Palier",IF(AND(G$20>='01_Input'!$R$59,G$20<'01_Input'!$S$59),'01_Input'!$U$59,0),MAX(MIN(G$20,'01_Input'!$S$59)-'01_Input'!$R$59,0)*'01_Input'!$U$59))+IF('01_Input'!$X$59="Forfait",IF(G$20>='01_Input'!$V$59,'01_Input'!$Y$59,0),IF('01_Input'!$X$59="Palier",IF(AND(G$20>='01_Input'!$V$59,G$20<'01_Input'!$W$59),'01_Input'!$Y$59,0),MAX(MIN(G$20,'01_Input'!$W$59)-'01_Input'!$V$59,0)*'01_Input'!$Y$59))+IF('01_Input'!$AB$59="Forfait",IF(G$20>='01_Input'!$Z$59,'01_Input'!$AC$59,0),IF('01_Input'!$AB$59="Palier",IF(AND(G$20>='01_Input'!$Z$59,G$20<'01_Input'!$AA$59),'01_Input'!$AC$59,0),MAX(MIN(G$20,'01_Input'!$AA$59)-'01_Input'!$Z$59,0)*'01_Input'!$AC$59))))))))) -> 0 | H27: =IF('01_Input'!$C$59="Non",0,MIN('01_Input'!$I$59,MAX('01_Input'!$H$59,IF('01_Input'!$G$59="Résiduel vs Gestion",0,IF('01_Input'!$G$59="Taux Classe sélectionnée",Distrib_Global_Classe_Selectionnee*H$20,IF('01_Input'!$G$59="Frais KYC (paliers de 100M€)",MAX(0,Nb_Investisseurs-Nb_KYC_Gratuites_Par_Tranche*(FLOOR(H$20/Taille_Tranche_KYC,1)+1))*Cout_Par_KYC_Supplementaire,(IF('01_Input'!$L$59="Forfait",IF(H$20>='01_Input'!$J$59,'01_Input'!$M$59,0),IF('01_Input'!$L$59="Palier",IF(AND(H$20>='01_Input'!$J$59,H$20<'01_Input'!$K$59),'01_Input'!$M$59,0),MAX(MIN(H$20,'01_Input'!$K$59)-'01_Input'!$J$59,0)*'01_Input'!$M$59))+IF('01_Input'!$P$59="Forfait",IF(H$20>='01_Input'!$N$59,'01_Input'!$Q$59,0),IF('01_Input'!$P$59="Palier",IF(AND(H$20>='01_Input'!$N$59,H$20<'01_Input'!$O$59),'01_Input'!$Q$59,0),MAX(MIN(H$20,'01_Input'!$O$59)-'01_Input'!$N$59,0)*'01_Input'!$Q$59))+IF('01_Input'!$T$59="Forfait",IF(H$20>='01_Input'!$R$59,'01_Input'!$U$59,0),IF('01_Input'!$T$59="Palier",IF(AND(H$20>='01_Input'!$R$59,H$20<'01_Input'!$S$59),'01_Input'!$U$59,0),MAX(MIN(H$20,'01_Input'!$S$59)-'01_Input'!$R$59,0)*'01_Input'!$U$59))+IF('01_Input'!$X$59="Forfait",IF(H$20>='01_Input'!$V$59,'01_Input'!$Y$59,0),IF('01_Input'!$X$59="Palier",IF(AND(H$20>='01_Input'!$V$59,H$20<'01_Input'!$W$59),'01_Input'!$Y$59,0),MAX(MIN(H$20,'01_Input'!$W$59)-'01_Input'!$V$59,0)*'01_Input'!$Y$59))+IF('01_Input'!$AB$59="Forfait",IF(H$20>='01_Input'!$Z$59,'01_Input'!$AC$59,0),IF('01_Input'!$AB$59="Palier",IF(AND(H$20>='01_Input'!$Z$59,H$20<'01_Input'!$AA$59),'01_Input'!$AC$59,0),MAX(MIN(H$20,'01_Input'!$AA$59)-'01_Input'!$Z$59,0)*'01_Input'!$AC$59))))))))) -> 0 | I27: =IF('01_Input'!$C$59="Non",0,MIN('01_Input'!$I$59,MAX('01_Input'!$H$59,IF('01_Input'!$G$59="Résiduel vs Gestion",0,IF('01_Input'!$G$59="Taux Classe sélectionnée",Distrib_Global_Classe_Selectionnee*I$20,IF('01_Input'!$G$59="Frais KYC (paliers de 100M€)",MAX(0,Nb_Investisseurs-Nb_KYC_Gratuites_Par_Tranche*(FLOOR(I$20/Taille_Tranche_KYC,1)+1))*Cout_Par_KYC_Supplementaire,(IF('01_Input'!$L$59="Forfait",IF(I$20>='01_Input'!$J$59,'01_Input'!$M$59,0),IF('01_Input'!$L$59="Palier",IF(AND(I$20>='01_Input'!$J$59,I$20<'01_Input'!$K$59),'01_Input'!$M$59,0),MAX(MIN(I$20,'01_Input'!$K$59)-'01_Input'!$J$59,0)*'01_Input'!$M$59))+IF('01_Input'!$P$59="Forfait",IF(I$20>='01_Input'!$N$59,'01_Input'!$Q$59,0),IF('01_Input'!$P$59="Palier",IF(AND(I$20>='01_Input'!$N$59,I$20<'01_Input'!$O$59),'01_Input'!$Q$59,0),MAX(MIN(I$20,'01_Input'!$O$59)-'01_Input'!$N$59,0)*'01_Input'!$Q$59))+IF('01_Input'!$T$59="Forfait",IF(I$20>='01_Input'!$R$59,'01_Input'!$U$59,0),IF('01_Input'!$T$59="Palier",IF(AND(I$20>='01_Input'!$R$59,I$20<'01_Input'!$S$59),'01_Input'!$U$59,0),MAX(MIN(I$20,'01_Input'!$S$59)-'01_Input'!$R$59,0)*'01_Input'!$U$59))+IF('01_Input'!$X$59="Forfait",IF(I$20>='01_Input'!$V$59,'01_Input'!$Y$59,0),IF('01_Input'!$X$59="Palier",IF(AND(I$20>='01_Input'!$V$59,I$20<'01_Input'!$W$59),'01_Input'!$Y$59,0),MAX(MIN(I$20,'01_Input'!$W$59)-'01_Input'!$V$59,0)*'01_Input'!$Y$59))+IF('01_Input'!$AB$59="Forfait",IF(I$20>='01_Input'!$Z$59,'01_Input'!$AC$59,0),IF('01_Input'!$AB$59="Palier",IF(AND(I$20>='01_Input'!$Z$59,I$20<'01_Input'!$AA$59),'01_Input'!$AC$59,0),MAX(MIN(I$20,'01_Input'!$AA$59)-'01_Input'!$Z$59,0)*'01_Input'!$AC$59))))))))) -> 0 | J27: =IF('01_Input'!$C$59="Non",0,MIN('01_Input'!$I$59,MAX('01_Input'!$H$59,IF('01_Input'!$G$59="Résiduel vs Gestion",0,IF('01_Input'!$G$59="Taux Classe sélectionnée",Distrib_Global_Classe_Selectionnee*J$20,IF('01_Input'!$G$59="Frais KYC (paliers de 100M€)",MAX(0,Nb_Investisseurs-Nb_KYC_Gratuites_Par_Tranche*(FLOOR(J$20/Taille_Tranche_KYC,1)+1))*Cout_Par_KYC_Supplementaire,(IF('01_Input'!$L$59="Forfait",IF(J$20>='01_Input'!$J$59,'01_Input'!$M$59,0),IF('01_Input'!$L$59="Palier",IF(AND(J$20>='01_Input'!$J$59,J$20<'01_Input'!$K$59),'01_Input'!$M$59,0),MAX(MIN(J$20,'01_Input'!$K$59)-'01_Input'!$J$59,0)*'01_Input'!$M$59))+IF('01_Input'!$P$59="Forfait",IF(J$20>='01_Input'!$N$59,'01_Input'!$Q$59,0),IF('01_Input'!$P$59="Palier",IF(AND(J$20>='01_Input'!$N$59,J$20<'01_Input'!$O$59),'01_Input'!$Q$59,0),MAX(MIN(J$20,'01_Input'!$O$59)-'01_Input'!$N$59,0)*'01_Input'!$Q$59))+IF('01_Input'!$T$59="Forfait",IF(J$20>='01_Input'!$R$59,'01_Input'!$U$59,0),IF('01_Input'!$T$59="Palier",IF(AND(J$20>='01_Input'!$R$59,J$20<'01_Input'!$S$59),'01_Input'!$U$59,0),MAX(MIN(J$20,'01_Input'!$S$59)-'01_Input'!$R$59,0)*'01_Input'!$U$59))+IF('01_Input'!$X$59="Forfait",IF(J$20>='01_Input'!$V$59,'01_Input'!$Y$59,0),IF('01_Input'!$X$59="Palier",IF(AND(J$20>='01_Input'!$V$59,J$20<'01_Input'!$W$59),'01_Input'!$Y$59,0),MAX(MIN(J$20,'01_Input'!$W$59)-'01_Input'!$V$59,0)*'01_Input'!$Y$59))+IF('01_Input'!$AB$59="Forfait",IF(J$20>='01_Input'!$Z$59,'01_Input'!$AC$59,0),IF('01_Input'!$AB$59="Palier",IF(AND(J$20>='01_Input'!$Z$59,J$20<'01_Input'!$AA$59),'01_Input'!$AC$59,0),MAX(MIN(J$20,'01_Input'!$AA$59)-'01_Input'!$Z$59,0)*'01_Input'!$AC$59))))))))) -> 0 | K27: =IF('01_Input'!$C$59="Non",0,MIN('01_Input'!$I$59,MAX('01_Input'!$H$59,IF('01_Input'!$G$59="Résiduel vs Gestion",0,IF('01_Input'!$G$59="Taux Classe sélectionnée",Distrib_Global_Classe_Selectionnee*K$20,IF('01_Input'!$G$59="Frais KYC (paliers de 100M€)",MAX(0,Nb_Investisseurs-Nb_KYC_Gratuites_Par_Tranche*(FLOOR(K$20/Taille_Tranche_KYC,1)+1))*Cout_Par_KYC_Supplementaire,(IF('01_Input'!$L$59="Forfait",IF(K$20>='01_Input'!$J$59,'01_Input'!$M$59,0),IF('01_Input'!$L$59="Palier",IF(AND(K$20>='01_Input'!$J$59,K$20<'01_Input'!$K$59),'01_Input'!$M$59,0),MAX(MIN(K$20,'01_Input'!$K$59)-'01_Input'!$J$59,0)*'01_Input'!$M$59))+IF('01_Input'!$P$59="Forfait",IF(K$20>='01_Input'!$N$59,'01_Input'!$Q$59,0),IF('01_Input'!$P$59="Palier",IF(AND(K$20>='01_Input'!$N$59,K$20<'01_Input'!$O$59),'01_Input'!$Q$59,0),MAX(MIN(K$20,'01_Input'!$O$59)-'01_Input'!$N$59,0)*'01_Input'!$Q$59))+IF('01_Input'!$T$59="Forfait",IF(K$20>='01_Input'!$R$59,'01_Input'!$U$59,0),IF('01_Input'!$T$59="Palier",IF(AND(K$20>='01_Input'!$R$59,K$20<'01_Input'!$S$59),'01_Input'!$U$59,0),MAX(MIN(K$20,'01_Input'!$S$59)-'01_Input'!$R$59,0)*'01_Input'!$U$59))+IF('01_Input'!$X$59="Forfait",IF(K$20>='01_Input'!$V$59,'01_Input'!$Y$59,0),IF('01_Input'!$X$59="Palier",IF(AND(K$20>='01_Input'!$V$59,K$20<'01_Input'!$W$59),'01_Input'!$Y$59,0),MAX(MIN(K$20,'01_Input'!$W$59)-'01_Input'!$V$59,0)*'01_Input'!$Y$59))+IF('01_Input'!$AB$59="Forfait",IF(K$20>='01_Input'!$Z$59,'01_Input'!$AC$59,0),IF('01_Input'!$AB$59="Palier",IF(AND(K$20>='01_Input'!$Z$59,K$20<'01_Input'!$AA$59),'01_Input'!$AC$59,0),MAX(MIN(K$20,'01_Input'!$AA$59)-'01_Input'!$Z$59,0)*'01_Input'!$AC$59))))))))) -> 0 | L27: =IF('01_Input'!$C$59="Non",0,MIN('01_Input'!$I$59,MAX('01_Input'!$H$59,IF('01_Input'!$G$59="Résiduel vs Gestion",0,IF('01_Input'!$G$59="Taux Classe sélectionnée",Distrib_Global_Classe_Selectionnee*L$20,IF('01_Input'!$G$59="Frais KYC (paliers de 100M€)",MAX(0,Nb_Investisseurs-Nb_KYC_Gratuites_Par_Tranche*(FLOOR(L$20/Taille_Tranche_KYC,1)+1))*Cout_Par_KYC_Supplementaire,(IF('01_Input'!$L$59="Forfait",IF(L$20>='01_Input'!$J$59,'01_Input'!$M$59,0),IF('01_Input'!$L$59="Palier",IF(AND(L$20>='01_Input'!$J$59,L$20<'01_Input'!$K$59),'01_Input'!$M$59,0),MAX(MIN(L$20,'01_Input'!$K$59)-'01_Input'!$J$59,0)*'01_Input'!$M$59))+IF('01_Input'!$P$59="Forfait",IF(L$20>='01_Input'!$N$59,'01_Input'!$Q$59,0),IF('01_Input'!$P$59="Palier",IF(AND(L$20>='01_Input'!$N$59,L$20<'01_Input'!$O$59),'01_Input'!$Q$59,0),MAX(MIN(L$20,'01_Input'!$O$59)-'01_Input'!$N$59,0)*'01_Input'!$Q$59))+IF('01_Input'!$T$59="Forfait",IF(L$20>='01_Input'!$R$59,'01_Input'!$U$59,0),IF('01_Input'!$T$59="Palier",IF(AND(L$20>='01_Input'!$R$59,L$20<'01_Input'!$S$59),'01_Input'!$U$59,0),MAX(MIN(L$20,'01_Input'!$S$59)-'01_Input'!$R$59,0)*'01_Input'!$U$59))+IF('01_Input'!$X$59="Forfait",IF(L$20>='01_Input'!$V$59,'01_Input'!$Y$59,0),IF('01_Input'!$X$59="Palier",IF(AND(L$20>='01_Input'!$V$59,L$20<'01_Input'!$W$59),'01_Input'!$Y$59,0),MAX(MIN(L$20,'01_Input'!$W$59)-'01_Input'!$V$59,0)*'01_Input'!$Y$59))+IF('01_Input'!$AB$59="Forfait",IF(L$20>='01_Input'!$Z$59,'01_Input'!$AC$59,0),IF('01_Input'!$AB$59="Palier",IF(AND(L$20>='01_Input'!$Z$59,L$20<'01_Input'!$AA$59),'01_Input'!$AC$59,0),MAX(MIN(L$20,'01_Input'!$AA$59)-'01_Input'!$Z$59,0)*'01_Input'!$AC$59))))))))) -> 0 | ... EX27: =IF('01_Input'!$C$59="Non",0,MIN('01_Input'!$I$59,MAX('01_Input'!$H$59,IF('01_Input'!$G$59="Résiduel vs Gestion",0,IF('01_Input'!$G$59="Taux Classe sélectionnée",Distrib_Global_Classe_Selectionnee*EX$20,IF('01_Input'!$G$59="Frais KYC (paliers de 100M€)",MAX(0,Nb_Investisseurs-Nb_KYC_Gratuites_Par_Tranche*(FLOOR(EX$20/Taille_Tranche_KYC,1)+1))*Cout_Par_KYC_Supplementaire,(IF('01_Input'!$L$59="Forfait",IF(EX$20>='01_Input'!$J$59,'01_Input'!$M$59,0),IF('01_Input'!$L$59="Palier",IF(AND(EX$20>='01_Input'!$J$59,EX$20<'01_Input'!$K$59),'01_Input'!$M$59,0),MAX(MIN(EX$20,'01_Input'!$K$59)-'01_Input'!$J$59,0)*'01_Input'!$M$59))+IF('01_Input'!$P$59="Forfait",IF(EX$20>='01_Input'!$N$59,'01_Input'!$Q$59,0),IF('01_Input'!$P$59="Palier",IF(AND(EX$20>='01_Input'!$N$59,EX$20<'01_Input'!$O$59),'01_Input'!$Q$59,0),MAX(MIN(EX$20,'01_Input'!$O$59)-'01_Input'!$N$59,0)*'01_Input'!$Q$59))+IF('01_Input'!$T$59="Forfait",IF(EX$20>='01_Input'!$R$59,'01_Input'!$U$59,0),IF('01_Input'!$T$59="Palier",IF(AND(EX$20>='01_Input'!$R$59,EX$20<'01_Input'!$S$59),'01_Input'!$U$59,0),MAX(MIN(EX$20,'01_Input'!$S$59)-'01_Input'!$R$59,0)*'01_Input'!$U$59))+IF('01_Input'!$X$59="Forfait",IF(EX$20>='01_Input'!$V$59,'01_Input'!$Y$59,0),IF('01_Input'!$X$59="Palier",IF(AND(EX$20>='01_Input'!$V$59,EX$20<'01_Input'!$W$59),'01_Input'!$Y$59,0),MAX(MIN(EX$20,'01_Input'!$W$59)-'01_Input'!$V$59,0)*'01_Input'!$Y$59))+IF('01_Input'!$AB$59="Forfait",IF(EX$20>='01_Input'!$Z$59,'01_Input'!$AC$59,0),IF('01_Input'!$AB$59="Palier",IF(AND(EX$20>='01_Input'!$Z$59,EX$20<'01_Input'!$AA$59),'01_Input'!$AC$59,0),MAX(MIN(EX$20,'01_Input'!$AA$59)-'01_Input'!$Z$59,0)*'01_Input'!$AC$59))))))))) -> 0
B28: =IF('01_Input'!D60="","(inactif)",'01_Input'!D60) -> Reporting — Rapport Annuel (CIC) | C28: =IF('01_Input'!E60="","",'01_Input'!E60) -> CIC Administration de Fonds | D28: ='01_Input'!C60 -> Oui | E28: =IF('01_Input'!$C$60="Non",0,MIN('01_Input'!$I$60,MAX('01_Input'!$H$60,IF('01_Input'!$G$60="Résiduel vs Gestion",0,IF('01_Input'!$G$60="Taux Classe sélectionnée",Distrib_Global_Classe_Selectionnee*E$20,IF('01_Input'!$G$60="Frais KYC (paliers de 100M€)",MAX(0,Nb_Investisseurs-Nb_KYC_Gratuites_Par_Tranche*(FLOOR(E$20/Taille_Tranche_KYC,1)+1))*Cout_Par_KYC_Supplementaire,(IF('01_Input'!$L$60="Forfait",IF(E$20>='01_Input'!$J$60,'01_Input'!$M$60,0),IF('01_Input'!$L$60="Palier",IF(AND(E$20>='01_Input'!$J$60,E$20<'01_Input'!$K$60),'01_Input'!$M$60,0),MAX(MIN(E$20,'01_Input'!$K$60)-'01_Input'!$J$60,0)*'01_Input'!$M$60))+IF('01_Input'!$P$60="Forfait",IF(E$20>='01_Input'!$N$60,'01_Input'!$Q$60,0),IF('01_Input'!$P$60="Palier",IF(AND(E$20>='01_Input'!$N$60,E$20<'01_Input'!$O$60),'01_Input'!$Q$60,0),MAX(MIN(E$20,'01_Input'!$O$60)-'01_Input'!$N$60,0)*'01_Input'!$Q$60))+IF('01_Input'!$T$60="Forfait",IF(E$20>='01_Input'!$R$60,'01_Input'!$U$60,0),IF('01_Input'!$T$60="Palier",IF(AND(E$20>='01_Input'!$R$60,E$20<'01_Input'!$S$60),'01_Input'!$U$60,0),MAX(MIN(E$20,'01_Input'!$S$60)-'01_Input'!$R$60,0)*'01_Input'!$U$60))+IF('01_Input'!$X$60="Forfait",IF(E$20>='01_Input'!$V$60,'01_Input'!$Y$60,0),IF('01_Input'!$X$60="Palier",IF(AND(E$20>='01_Input'!$V$60,E$20<'01_Input'!$W$60),'01_Input'!$Y$60,0),MAX(MIN(E$20,'01_Input'!$W$60)-'01_Input'!$V$60,0)*'01_Input'!$Y$60))+IF('01_Input'!$AB$60="Forfait",IF(E$20>='01_Input'!$Z$60,'01_Input'!$AC$60,0),IF('01_Input'!$AB$60="Palier",IF(AND(E$20>='01_Input'!$Z$60,E$20<'01_Input'!$AA$60),'01_Input'!$AC$60,0),MAX(MIN(E$20,'01_Input'!$AA$60)-'01_Input'!$Z$60,0)*'01_Input'!$AC$60))))))))) -> 800 | F28: =IF('01_Input'!$C$60="Non",0,MIN('01_Input'!$I$60,MAX('01_Input'!$H$60,IF('01_Input'!$G$60="Résiduel vs Gestion",0,IF('01_Input'!$G$60="Taux Classe sélectionnée",Distrib_Global_Classe_Selectionnee*F$20,IF('01_Input'!$G$60="Frais KYC (paliers de 100M€)",MAX(0,Nb_Investisseurs-Nb_KYC_Gratuites_Par_Tranche*(FLOOR(F$20/Taille_Tranche_KYC,1)+1))*Cout_Par_KYC_Supplementaire,(IF('01_Input'!$L$60="Forfait",IF(F$20>='01_Input'!$J$60,'01_Input'!$M$60,0),IF('01_Input'!$L$60="Palier",IF(AND(F$20>='01_Input'!$J$60,F$20<'01_Input'!$K$60),'01_Input'!$M$60,0),MAX(MIN(F$20,'01_Input'!$K$60)-'01_Input'!$J$60,0)*'01_Input'!$M$60))+IF('01_Input'!$P$60="Forfait",IF(F$20>='01_Input'!$N$60,'01_Input'!$Q$60,0),IF('01_Input'!$P$60="Palier",IF(AND(F$20>='01_Input'!$N$60,F$20<'01_Input'!$O$60),'01_Input'!$Q$60,0),MAX(MIN(F$20,'01_Input'!$O$60)-'01_Input'!$N$60,0)*'01_Input'!$Q$60))+IF('01_Input'!$T$60="Forfait",IF(F$20>='01_Input'!$R$60,'01_Input'!$U$60,0),IF('01_Input'!$T$60="Palier",IF(AND(F$20>='01_Input'!$R$60,F$20<'01_Input'!$S$60),'01_Input'!$U$60,0),MAX(MIN(F$20,'01_Input'!$S$60)-'01_Input'!$R$60,0)*'01_Input'!$U$60))+IF('01_Input'!$X$60="Forfait",IF(F$20>='01_Input'!$V$60,'01_Input'!$Y$60,0),IF('01_Input'!$X$60="Palier",IF(AND(F$20>='01_Input'!$V$60,F$20<'01_Input'!$W$60),'01_Input'!$Y$60,0),MAX(MIN(F$20,'01_Input'!$W$60)-'01_Input'!$V$60,0)*'01_Input'!$Y$60))+IF('01_Input'!$AB$60="Forfait",IF(F$20>='01_Input'!$Z$60,'01_Input'!$AC$60,0),IF('01_Input'!$AB$60="Palier",IF(AND(F$20>='01_Input'!$Z$60,F$20<'01_Input'!$AA$60),'01_Input'!$AC$60,0),MAX(MIN(F$20,'01_Input'!$AA$60)-'01_Input'!$Z$60,0)*'01_Input'!$AC$60))))))))) -> 800 | G28: =IF('01_Input'!$C$60="Non",0,MIN('01_Input'!$I$60,MAX('01_Input'!$H$60,IF('01_Input'!$G$60="Résiduel vs Gestion",0,IF('01_Input'!$G$60="Taux Classe sélectionnée",Distrib_Global_Classe_Selectionnee*G$20,IF('01_Input'!$G$60="Frais KYC (paliers de 100M€)",MAX(0,Nb_Investisseurs-Nb_KYC_Gratuites_Par_Tranche*(FLOOR(G$20/Taille_Tranche_KYC,1)+1))*Cout_Par_KYC_Supplementaire,(IF('01_Input'!$L$60="Forfait",IF(G$20>='01_Input'!$J$60,'01_Input'!$M$60,0),IF('01_Input'!$L$60="Palier",IF(AND(G$20>='01_Input'!$J$60,G$20<'01_Input'!$K$60),'01_Input'!$M$60,0),MAX(MIN(G$20,'01_Input'!$K$60)-'01_Input'!$J$60,0)*'01_Input'!$M$60))+IF('01_Input'!$P$60="Forfait",IF(G$20>='01_Input'!$N$60,'01_Input'!$Q$60,0),IF('01_Input'!$P$60="Palier",IF(AND(G$20>='01_Input'!$N$60,G$20<'01_Input'!$O$60),'01_Input'!$Q$60,0),MAX(MIN(G$20,'01_Input'!$O$60)-'01_Input'!$N$60,0)*'01_Input'!$Q$60))+IF('01_Input'!$T$60="Forfait",IF(G$20>='01_Input'!$R$60,'01_Input'!$U$60,0),IF('01_Input'!$T$60="Palier",IF(AND(G$20>='01_Input'!$R$60,G$20<'01_Input'!$S$60),'01_Input'!$U$60,0),MAX(MIN(G$20,'01_Input'!$S$60)-'01_Input'!$R$60,0)*'01_Input'!$U$60))+IF('01_Input'!$X$60="Forfait",IF(G$20>='01_Input'!$V$60,'01_Input'!$Y$60,0),IF('01_Input'!$X$60="Palier",IF(AND(G$20>='01_Input'!$V$60,G$20<'01_Input'!$W$60),'01_Input'!$Y$60,0),MAX(MIN(G$20,'01_Input'!$W$60)-'01_Input'!$V$60,0)*'01_Input'!$Y$60))+IF('01_Input'!$AB$60="Forfait",IF(G$20>='01_Input'!$Z$60,'01_Input'!$AC$60,0),IF('01_Input'!$AB$60="Palier",IF(AND(G$20>='01_Input'!$Z$60,G$20<'01_Input'!$AA$60),'01_Input'!$AC$60,0),MAX(MIN(G$20,'01_Input'!$AA$60)-'01_Input'!$Z$60,0)*'01_Input'!$AC$60))))))))) -> 800 | H28: =IF('01_Input'!$C$60="Non",0,MIN('01_Input'!$I$60,MAX('01_Input'!$H$60,IF('01_Input'!$G$60="Résiduel vs Gestion",0,IF('01_Input'!$G$60="Taux Classe sélectionnée",Distrib_Global_Classe_Selectionnee*H$20,IF('01_Input'!$G$60="Frais KYC (paliers de 100M€)",MAX(0,Nb_Investisseurs-Nb_KYC_Gratuites_Par_Tranche*(FLOOR(H$20/Taille_Tranche_KYC,1)+1))*Cout_Par_KYC_Supplementaire,(IF('01_Input'!$L$60="Forfait",IF(H$20>='01_Input'!$J$60,'01_Input'!$M$60,0),IF('01_Input'!$L$60="Palier",IF(AND(H$20>='01_Input'!$J$60,H$20<'01_Input'!$K$60),'01_Input'!$M$60,0),MAX(MIN(H$20,'01_Input'!$K$60)-'01_Input'!$J$60,0)*'01_Input'!$M$60))+IF('01_Input'!$P$60="Forfait",IF(H$20>='01_Input'!$N$60,'01_Input'!$Q$60,0),IF('01_Input'!$P$60="Palier",IF(AND(H$20>='01_Input'!$N$60,H$20<'01_Input'!$O$60),'01_Input'!$Q$60,0),MAX(MIN(H$20,'01_Input'!$O$60)-'01_Input'!$N$60,0)*'01_Input'!$Q$60))+IF('01_Input'!$T$60="Forfait",IF(H$20>='01_Input'!$R$60,'01_Input'!$U$60,0),IF('01_Input'!$T$60="Palier",IF(AND(H$20>='01_Input'!$R$60,H$20<'01_Input'!$S$60),'01_Input'!$U$60,0),MAX(MIN(H$20,'01_Input'!$S$60)-'01_Input'!$R$60,0)*'01_Input'!$U$60))+IF('01_Input'!$X$60="Forfait",IF(H$20>='01_Input'!$V$60,'01_Input'!$Y$60,0),IF('01_Input'!$X$60="Palier",IF(AND(H$20>='01_Input'!$V$60,H$20<'01_Input'!$W$60),'01_Input'!$Y$60,0),MAX(MIN(H$20,'01_Input'!$W$60)-'01_Input'!$V$60,0)*'01_Input'!$Y$60))+IF('01_Input'!$AB$60="Forfait",IF(H$20>='01_Input'!$Z$60,'01_Input'!$AC$60,0),IF('01_Input'!$AB$60="Palier",IF(AND(H$20>='01_Input'!$Z$60,H$20<'01_Input'!$AA$60),'01_Input'!$AC$60,0),MAX(MIN(H$20,'01_Input'!$AA$60)-'01_Input'!$Z$60,0)*'01_Input'!$AC$60))))))))) -> 800 | I28: =IF('01_Input'!$C$60="Non",0,MIN('01_Input'!$I$60,MAX('01_Input'!$H$60,IF('01_Input'!$G$60="Résiduel vs Gestion",0,IF('01_Input'!$G$60="Taux Classe sélectionnée",Distrib_Global_Classe_Selectionnee*I$20,IF('01_Input'!$G$60="Frais KYC (paliers de 100M€)",MAX(0,Nb_Investisseurs-Nb_KYC_Gratuites_Par_Tranche*(FLOOR(I$20/Taille_Tranche_KYC,1)+1))*Cout_Par_KYC_Supplementaire,(IF('01_Input'!$L$60="Forfait",IF(I$20>='01_Input'!$J$60,'01_Input'!$M$60,0),IF('01_Input'!$L$60="Palier",IF(AND(I$20>='01_Input'!$J$60,I$20<'01_Input'!$K$60),'01_Input'!$M$60,0),MAX(MIN(I$20,'01_Input'!$K$60)-'01_Input'!$J$60,0)*'01_Input'!$M$60))+IF('01_Input'!$P$60="Forfait",IF(I$20>='01_Input'!$N$60,'01_Input'!$Q$60,0),IF('01_Input'!$P$60="Palier",IF(AND(I$20>='01_Input'!$N$60,I$20<'01_Input'!$O$60),'01_Input'!$Q$60,0),MAX(MIN(I$20,'01_Input'!$O$60)-'01_Input'!$N$60,0)*'01_Input'!$Q$60))+IF('01_Input'!$T$60="Forfait",IF(I$20>='01_Input'!$R$60,'01_Input'!$U$60,0),IF('01_Input'!$T$60="Palier",IF(AND(I$20>='01_Input'!$R$60,I$20<'01_Input'!$S$60),'01_Input'!$U$60,0),MAX(MIN(I$20,'01_Input'!$S$60)-'01_Input'!$R$60,0)*'01_Input'!$U$60))+IF('01_Input'!$X$60="Forfait",IF(I$20>='01_Input'!$V$60,'01_Input'!$Y$60,0),IF('01_Input'!$X$60="Palier",IF(AND(I$20>='01_Input'!$V$60,I$20<'01_Input'!$W$60),'01_Input'!$Y$60,0),MAX(MIN(I$20,'01_Input'!$W$60)-'01_Input'!$V$60,0)*'01_Input'!$Y$60))+IF('01_Input'!$AB$60="Forfait",IF(I$20>='01_Input'!$Z$60,'01_Input'!$AC$60,0),IF('01_Input'!$AB$60="Palier",IF(AND(I$20>='01_Input'!$Z$60,I$20<'01_Input'!$AA$60),'01_Input'!$AC$60,0),MAX(MIN(I$20,'01_Input'!$AA$60)-'01_Input'!$Z$60,0)*'01_Input'!$AC$60))))))))) -> 800 | J28: =IF('01_Input'!$C$60="Non",0,MIN('01_Input'!$I$60,MAX('01_Input'!$H$60,IF('01_Input'!$G$60="Résiduel vs Gestion",0,IF('01_Input'!$G$60="Taux Classe sélectionnée",Distrib_Global_Classe_Selectionnee*J$20,IF('01_Input'!$G$60="Frais KYC (paliers de 100M€)",MAX(0,Nb_Investisseurs-Nb_KYC_Gratuites_Par_Tranche*(FLOOR(J$20/Taille_Tranche_KYC,1)+1))*Cout_Par_KYC_Supplementaire,(IF('01_Input'!$L$60="Forfait",IF(J$20>='01_Input'!$J$60,'01_Input'!$M$60,0),IF('01_Input'!$L$60="Palier",IF(AND(J$20>='01_Input'!$J$60,J$20<'01_Input'!$K$60),'01_Input'!$M$60,0),MAX(MIN(J$20,'01_Input'!$K$60)-'01_Input'!$J$60,0)*'01_Input'!$M$60))+IF('01_Input'!$P$60="Forfait",IF(J$20>='01_Input'!$N$60,'01_Input'!$Q$60,0),IF('01_Input'!$P$60="Palier",IF(AND(J$20>='01_Input'!$N$60,J$20<'01_Input'!$O$60),'01_Input'!$Q$60,0),MAX(MIN(J$20,'01_Input'!$O$60)-'01_Input'!$N$60,0)*'01_Input'!$Q$60))+IF('01_Input'!$T$60="Forfait",IF(J$20>='01_Input'!$R$60,'01_Input'!$U$60,0),IF('01_Input'!$T$60="Palier",IF(AND(J$20>='01_Input'!$R$60,J$20<'01_Input'!$S$60),'01_Input'!$U$60,0),MAX(MIN(J$20,'01_Input'!$S$60)-'01_Input'!$R$60,0)*'01_Input'!$U$60))+IF('01_Input'!$X$60="Forfait",IF(J$20>='01_Input'!$V$60,'01_Input'!$Y$60,0),IF('01_Input'!$X$60="Palier",IF(AND(J$20>='01_Input'!$V$60,J$20<'01_Input'!$W$60),'01_Input'!$Y$60,0),MAX(MIN(J$20,'01_Input'!$W$60)-'01_Input'!$V$60,0)*'01_Input'!$Y$60))+IF('01_Input'!$AB$60="Forfait",IF(J$20>='01_Input'!$Z$60,'01_Input'!$AC$60,0),IF('01_Input'!$AB$60="Palier",IF(AND(J$20>='01_Input'!$Z$60,J$20<'01_Input'!$AA$60),'01_Input'!$AC$60,0),MAX(MIN(J$20,'01_Input'!$AA$60)-'01_Input'!$Z$60,0)*'01_Input'!$AC$60))))))))) -> 800 | K28: =IF('01_Input'!$C$60="Non",0,MIN('01_Input'!$I$60,MAX('01_Input'!$H$60,IF('01_Input'!$G$60="Résiduel vs Gestion",0,IF('01_Input'!$G$60="Taux Classe sélectionnée",Distrib_Global_Classe_Selectionnee*K$20,IF('01_Input'!$G$60="Frais KYC (paliers de 100M€)",MAX(0,Nb_Investisseurs-Nb_KYC_Gratuites_Par_Tranche*(FLOOR(K$20/Taille_Tranche_KYC,1)+1))*Cout_Par_KYC_Supplementaire,(IF('01_Input'!$L$60="Forfait",IF(K$20>='01_Input'!$J$60,'01_Input'!$M$60,0),IF('01_Input'!$L$60="Palier",IF(AND(K$20>='01_Input'!$J$60,K$20<'01_Input'!$K$60),'01_Input'!$M$60,0),MAX(MIN(K$20,'01_Input'!$K$60)-'01_Input'!$J$60,0)*'01_Input'!$M$60))+IF('01_Input'!$P$60="Forfait",IF(K$20>='01_Input'!$N$60,'01_Input'!$Q$60,0),IF('01_Input'!$P$60="Palier",IF(AND(K$20>='01_Input'!$N$60,K$20<'01_Input'!$O$60),'01_Input'!$Q$60,0),MAX(MIN(K$20,'01_Input'!$O$60)-'01_Input'!$N$60,0)*'01_Input'!$Q$60))+IF('01_Input'!$T$60="Forfait",IF(K$20>='01_Input'!$R$60,'01_Input'!$U$60,0),IF('01_Input'!$T$60="Palier",IF(AND(K$20>='01_Input'!$R$60,K$20<'01_Input'!$S$60),'01_Input'!$U$60,0),MAX(MIN(K$20,'01_Input'!$S$60)-'01_Input'!$R$60,0)*'01_Input'!$U$60))+IF('01_Input'!$X$60="Forfait",IF(K$20>='01_Input'!$V$60,'01_Input'!$Y$60,0),IF('01_Input'!$X$60="Palier",IF(AND(K$20>='01_Input'!$V$60,K$20<'01_Input'!$W$60),'01_Input'!$Y$60,0),MAX(MIN(K$20,'01_Input'!$W$60)-'01_Input'!$V$60,0)*'01_Input'!$Y$60))+IF('01_Input'!$AB$60="Forfait",IF(K$20>='01_Input'!$Z$60,'01_Input'!$AC$60,0),IF('01_Input'!$AB$60="Palier",IF(AND(K$20>='01_Input'!$Z$60,K$20<'01_Input'!$AA$60),'01_Input'!$AC$60,0),MAX(MIN(K$20,'01_Input'!$AA$60)-'01_Input'!$Z$60,0)*'01_Input'!$AC$60))))))))) -> 800 | L28: =IF('01_Input'!$C$60="Non",0,MIN('01_Input'!$I$60,MAX('01_Input'!$H$60,IF('01_Input'!$G$60="Résiduel vs Gestion",0,IF('01_Input'!$G$60="Taux Classe sélectionnée",Distrib_Global_Classe_Selectionnee*L$20,IF('01_Input'!$G$60="Frais KYC (paliers de 100M€)",MAX(0,Nb_Investisseurs-Nb_KYC_Gratuites_Par_Tranche*(FLOOR(L$20/Taille_Tranche_KYC,1)+1))*Cout_Par_KYC_Supplementaire,(IF('01_Input'!$L$60="Forfait",IF(L$20>='01_Input'!$J$60,'01_Input'!$M$60,0),IF('01_Input'!$L$60="Palier",IF(AND(L$20>='01_Input'!$J$60,L$20<'01_Input'!$K$60),'01_Input'!$M$60,0),MAX(MIN(L$20,'01_Input'!$K$60)-'01_Input'!$J$60,0)*'01_Input'!$M$60))+IF('01_Input'!$P$60="Forfait",IF(L$20>='01_Input'!$N$60,'01_Input'!$Q$60,0),IF('01_Input'!$P$60="Palier",IF(AND(L$20>='01_Input'!$N$60,L$20<'01_Input'!$O$60),'01_Input'!$Q$60,0),MAX(MIN(L$20,'01_Input'!$O$60)-'01_Input'!$N$60,0)*'01_Input'!$Q$60))+IF('01_Input'!$T$60="Forfait",IF(L$20>='01_Input'!$R$60,'01_Input'!$U$60,0),IF('01_Input'!$T$60="Palier",IF(AND(L$20>='01_Input'!$R$60,L$20<'01_Input'!$S$60),'01_Input'!$U$60,0),MAX(MIN(L$20,'01_Input'!$S$60)-'01_Input'!$R$60,0)*'01_Input'!$U$60))+IF('01_Input'!$X$60="Forfait",IF(L$20>='01_Input'!$V$60,'01_Input'!$Y$60,0),IF('01_Input'!$X$60="Palier",IF(AND(L$20>='01_Input'!$V$60,L$20<'01_Input'!$W$60),'01_Input'!$Y$60,0),MAX(MIN(L$20,'01_Input'!$W$60)-'01_Input'!$V$60,0)*'01_Input'!$Y$60))+IF('01_Input'!$AB$60="Forfait",IF(L$20>='01_Input'!$Z$60,'01_Input'!$AC$60,0),IF('01_Input'!$AB$60="Palier",IF(AND(L$20>='01_Input'!$Z$60,L$20<'01_Input'!$AA$60),'01_Input'!$AC$60,0),MAX(MIN(L$20,'01_Input'!$AA$60)-'01_Input'!$Z$60,0)*'01_Input'!$AC$60))))))))) -> 800 | ... EX28: =IF('01_Input'!$C$60="Non",0,MIN('01_Input'!$I$60,MAX('01_Input'!$H$60,IF('01_Input'!$G$60="Résiduel vs Gestion",0,IF('01_Input'!$G$60="Taux Classe sélectionnée",Distrib_Global_Classe_Selectionnee*EX$20,IF('01_Input'!$G$60="Frais KYC (paliers de 100M€)",MAX(0,Nb_Investisseurs-Nb_KYC_Gratuites_Par_Tranche*(FLOOR(EX$20/Taille_Tranche_KYC,1)+1))*Cout_Par_KYC_Supplementaire,(IF('01_Input'!$L$60="Forfait",IF(EX$20>='01_Input'!$J$60,'01_Input'!$M$60,0),IF('01_Input'!$L$60="Palier",IF(AND(EX$20>='01_Input'!$J$60,EX$20<'01_Input'!$K$60),'01_Input'!$M$60,0),MAX(MIN(EX$20,'01_Input'!$K$60)-'01_Input'!$J$60,0)*'01_Input'!$M$60))+IF('01_Input'!$P$60="Forfait",IF(EX$20>='01_Input'!$N$60,'01_Input'!$Q$60,0),IF('01_Input'!$P$60="Palier",IF(AND(EX$20>='01_Input'!$N$60,EX$20<'01_Input'!$O$60),'01_Input'!$Q$60,0),MAX(MIN(EX$20,'01_Input'!$O$60)-'01_Input'!$N$60,0)*'01_Input'!$Q$60))+IF('01_Input'!$T$60="Forfait",IF(EX$20>='01_Input'!$R$60,'01_Input'!$U$60,0),IF('01_Input'!$T$60="Palier",IF(AND(EX$20>='01_Input'!$R$60,EX$20<'01_Input'!$S$60),'01_Input'!$U$60,0),MAX(MIN(EX$20,'01_Input'!$S$60)-'01_Input'!$R$60,0)*'01_Input'!$U$60))+IF('01_Input'!$X$60="Forfait",IF(EX$20>='01_Input'!$V$60,'01_Input'!$Y$60,0),IF('01_Input'!$X$60="Palier",IF(AND(EX$20>='01_Input'!$V$60,EX$20<'01_Input'!$W$60),'01_Input'!$Y$60,0),MAX(MIN(EX$20,'01_Input'!$W$60)-'01_Input'!$V$60,0)*'01_Input'!$Y$60))+IF('01_Input'!$AB$60="Forfait",IF(EX$20>='01_Input'!$Z$60,'01_Input'!$AC$60,0),IF('01_Input'!$AB$60="Palier",IF(AND(EX$20>='01_Input'!$Z$60,EX$20<'01_Input'!$AA$60),'01_Input'!$AC$60,0),MAX(MIN(EX$20,'01_Input'!$AA$60)-'01_Input'!$Z$60,0)*'01_Input'!$AC$60))))))))) -> 800
B29: =IF('01_Input'!D61="","(inactif)",'01_Input'!D61) -> Valorisation (CIC) | C29: =IF('01_Input'!E61="","",'01_Input'!E61) -> Valorisateur (CIC / SOC Asset Servicing) | D29: ='01_Input'!C61 -> Oui | E29: =IF('01_Input'!$C$61="Non",0,MIN('01_Input'!$I$61,MAX('01_Input'!$H$61,IF('01_Input'!$G$61="Résiduel vs Gestion",0,IF('01_Input'!$G$61="Taux Classe sélectionnée",Distrib_Global_Classe_Selectionnee*E$20,IF('01_Input'!$G$61="Frais KYC (paliers de 100M€)",MAX(0,Nb_Investisseurs-Nb_KYC_Gratuites_Par_Tranche*(FLOOR(E$20/Taille_Tranche_KYC,1)+1))*Cout_Par_KYC_Supplementaire,(IF('01_Input'!$L$61="Forfait",IF(E$20>='01_Input'!$J$61,'01_Input'!$M$61,0),IF('01_Input'!$L$61="Palier",IF(AND(E$20>='01_Input'!$J$61,E$20<'01_Input'!$K$61),'01_Input'!$M$61,0),MAX(MIN(E$20,'01_Input'!$K$61)-'01_Input'!$J$61,0)*'01_Input'!$M$61))+IF('01_Input'!$P$61="Forfait",IF(E$20>='01_Input'!$N$61,'01_Input'!$Q$61,0),IF('01_Input'!$P$61="Palier",IF(AND(E$20>='01_Input'!$N$61,E$20<'01_Input'!$O$61),'01_Input'!$Q$61,0),MAX(MIN(E$20,'01_Input'!$O$61)-'01_Input'!$N$61,0)*'01_Input'!$Q$61))+IF('01_Input'!$T$61="Forfait",IF(E$20>='01_Input'!$R$61,'01_Input'!$U$61,0),IF('01_Input'!$T$61="Palier",IF(AND(E$20>='01_Input'!$R$61,E$20<'01_Input'!$S$61),'01_Input'!$U$61,0),MAX(MIN(E$20,'01_Input'!$S$61)-'01_Input'!$R$61,0)*'01_Input'!$U$61))+IF('01_Input'!$X$61="Forfait",IF(E$20>='01_Input'!$V$61,'01_Input'!$Y$61,0),IF('01_Input'!$X$61="Palier",IF(AND(E$20>='01_Input'!$V$61,E$20<'01_Input'!$W$61),'01_Input'!$Y$61,0),MAX(MIN(E$20,'01_Input'!$W$61)-'01_Input'!$V$61,0)*'01_Input'!$Y$61))+IF('01_Input'!$AB$61="Forfait",IF(E$20>='01_Input'!$Z$61,'01_Input'!$AC$61,0),IF('01_Input'!$AB$61="Palier",IF(AND(E$20>='01_Input'!$Z$61,E$20<'01_Input'!$AA$61),'01_Input'!$AC$61,0),MAX(MIN(E$20,'01_Input'!$AA$61)-'01_Input'!$Z$61,0)*'01_Input'!$AC$61))))))))) -> 12000 | F29: =IF('01_Input'!$C$61="Non",0,MIN('01_Input'!$I$61,MAX('01_Input'!$H$61,IF('01_Input'!$G$61="Résiduel vs Gestion",0,IF('01_Input'!$G$61="Taux Classe sélectionnée",Distrib_Global_Classe_Selectionnee*F$20,IF('01_Input'!$G$61="Frais KYC (paliers de 100M€)",MAX(0,Nb_Investisseurs-Nb_KYC_Gratuites_Par_Tranche*(FLOOR(F$20/Taille_Tranche_KYC,1)+1))*Cout_Par_KYC_Supplementaire,(IF('01_Input'!$L$61="Forfait",IF(F$20>='01_Input'!$J$61,'01_Input'!$M$61,0),IF('01_Input'!$L$61="Palier",IF(AND(F$20>='01_Input'!$J$61,F$20<'01_Input'!$K$61),'01_Input'!$M$61,0),MAX(MIN(F$20,'01_Input'!$K$61)-'01_Input'!$J$61,0)*'01_Input'!$M$61))+IF('01_Input'!$P$61="Forfait",IF(F$20>='01_Input'!$N$61,'01_Input'!$Q$61,0),IF('01_Input'!$P$61="Palier",IF(AND(F$20>='01_Input'!$N$61,F$20<'01_Input'!$O$61),'01_Input'!$Q$61,0),MAX(MIN(F$20,'01_Input'!$O$61)-'01_Input'!$N$61,0)*'01_Input'!$Q$61))+IF('01_Input'!$T$61="Forfait",IF(F$20>='01_Input'!$R$61,'01_Input'!$U$61,0),IF('01_Input'!$T$61="Palier",IF(AND(F$20>='01_Input'!$R$61,F$20<'01_Input'!$S$61),'01_Input'!$U$61,0),MAX(MIN(F$20,'01_Input'!$S$61)-'01_Input'!$R$61,0)*'01_Input'!$U$61))+IF('01_Input'!$X$61="Forfait",IF(F$20>='01_Input'!$V$61,'01_Input'!$Y$61,0),IF('01_Input'!$X$61="Palier",IF(AND(F$20>='01_Input'!$V$61,F$20<'01_Input'!$W$61),'01_Input'!$Y$61,0),MAX(MIN(F$20,'01_Input'!$W$61)-'01_Input'!$V$61,0)*'01_Input'!$Y$61))+IF('01_Input'!$AB$61="Forfait",IF(F$20>='01_Input'!$Z$61,'01_Input'!$AC$61,0),IF('01_Input'!$AB$61="Palier",IF(AND(F$20>='01_Input'!$Z$61,F$20<'01_Input'!$AA$61),'01_Input'!$AC$61,0),MAX(MIN(F$20,'01_Input'!$AA$61)-'01_Input'!$Z$61,0)*'01_Input'!$AC$61))))))))) -> 12000 | G29: =IF('01_Input'!$C$61="Non",0,MIN('01_Input'!$I$61,MAX('01_Input'!$H$61,IF('01_Input'!$G$61="Résiduel vs Gestion",0,IF('01_Input'!$G$61="Taux Classe sélectionnée",Distrib_Global_Classe_Selectionnee*G$20,IF('01_Input'!$G$61="Frais KYC (paliers de 100M€)",MAX(0,Nb_Investisseurs-Nb_KYC_Gratuites_Par_Tranche*(FLOOR(G$20/Taille_Tranche_KYC,1)+1))*Cout_Par_KYC_Supplementaire,(IF('01_Input'!$L$61="Forfait",IF(G$20>='01_Input'!$J$61,'01_Input'!$M$61,0),IF('01_Input'!$L$61="Palier",IF(AND(G$20>='01_Input'!$J$61,G$20<'01_Input'!$K$61),'01_Input'!$M$61,0),MAX(MIN(G$20,'01_Input'!$K$61)-'01_Input'!$J$61,0)*'01_Input'!$M$61))+IF('01_Input'!$P$61="Forfait",IF(G$20>='01_Input'!$N$61,'01_Input'!$Q$61,0),IF('01_Input'!$P$61="Palier",IF(AND(G$20>='01_Input'!$N$61,G$20<'01_Input'!$O$61),'01_Input'!$Q$61,0),MAX(MIN(G$20,'01_Input'!$O$61)-'01_Input'!$N$61,0)*'01_Input'!$Q$61))+IF('01_Input'!$T$61="Forfait",IF(G$20>='01_Input'!$R$61,'01_Input'!$U$61,0),IF('01_Input'!$T$61="Palier",IF(AND(G$20>='01_Input'!$R$61,G$20<'01_Input'!$S$61),'01_Input'!$U$61,0),MAX(MIN(G$20,'01_Input'!$S$61)-'01_Input'!$R$61,0)*'01_Input'!$U$61))+IF('01_Input'!$X$61="Forfait",IF(G$20>='01_Input'!$V$61,'01_Input'!$Y$61,0),IF('01_Input'!$X$61="Palier",IF(AND(G$20>='01_Input'!$V$61,G$20<'01_Input'!$W$61),'01_Input'!$Y$61,0),MAX(MIN(G$20,'01_Input'!$W$61)-'01_Input'!$V$61,0)*'01_Input'!$Y$61))+IF('01_Input'!$AB$61="Forfait",IF(G$20>='01_Input'!$Z$61,'01_Input'!$AC$61,0),IF('01_Input'!$AB$61="Palier",IF(AND(G$20>='01_Input'!$Z$61,G$20<'01_Input'!$AA$61),'01_Input'!$AC$61,0),MAX(MIN(G$20,'01_Input'!$AA$61)-'01_Input'!$Z$61,0)*'01_Input'!$AC$61))))))))) -> 12000 | H29: =IF('01_Input'!$C$61="Non",0,MIN('01_Input'!$I$61,MAX('01_Input'!$H$61,IF('01_Input'!$G$61="Résiduel vs Gestion",0,IF('01_Input'!$G$61="Taux Classe sélectionnée",Distrib_Global_Classe_Selectionnee*H$20,IF('01_Input'!$G$61="Frais KYC (paliers de 100M€)",MAX(0,Nb_Investisseurs-Nb_KYC_Gratuites_Par_Tranche*(FLOOR(H$20/Taille_Tranche_KYC,1)+1))*Cout_Par_KYC_Supplementaire,(IF('01_Input'!$L$61="Forfait",IF(H$20>='01_Input'!$J$61,'01_Input'!$M$61,0),IF('01_Input'!$L$61="Palier",IF(AND(H$20>='01_Input'!$J$61,H$20<'01_Input'!$K$61),'01_Input'!$M$61,0),MAX(MIN(H$20,'01_Input'!$K$61)-'01_Input'!$J$61,0)*'01_Input'!$M$61))+IF('01_Input'!$P$61="Forfait",IF(H$20>='01_Input'!$N$61,'01_Input'!$Q$61,0),IF('01_Input'!$P$61="Palier",IF(AND(H$20>='01_Input'!$N$61,H$20<'01_Input'!$O$61),'01_Input'!$Q$61,0),MAX(MIN(H$20,'01_Input'!$O$61)-'01_Input'!$N$61,0)*'01_Input'!$Q$61))+IF('01_Input'!$T$61="Forfait",IF(H$20>='01_Input'!$R$61,'01_Input'!$U$61,0),IF('01_Input'!$T$61="Palier",IF(AND(H$20>='01_Input'!$R$61,H$20<'01_Input'!$S$61),'01_Input'!$U$61,0),MAX(MIN(H$20,'01_Input'!$S$61)-'01_Input'!$R$61,0)*'01_Input'!$U$61))+IF('01_Input'!$X$61="Forfait",IF(H$20>='01_Input'!$V$61,'01_Input'!$Y$61,0),IF('01_Input'!$X$61="Palier",IF(AND(H$20>='01_Input'!$V$61,H$20<'01_Input'!$W$61),'01_Input'!$Y$61,0),MAX(MIN(H$20,'01_Input'!$W$61)-'01_Input'!$V$61,0)*'01_Input'!$Y$61))+IF('01_Input'!$AB$61="Forfait",IF(H$20>='01_Input'!$Z$61,'01_Input'!$AC$61,0),IF('01_Input'!$AB$61="Palier",IF(AND(H$20>='01_Input'!$Z$61,H$20<'01_Input'!$AA$61),'01_Input'!$AC$61,0),MAX(MIN(H$20,'01_Input'!$AA$61)-'01_Input'!$Z$61,0)*'01_Input'!$AC$61))))))))) -> 12000 | I29: =IF('01_Input'!$C$61="Non",0,MIN('01_Input'!$I$61,MAX('01_Input'!$H$61,IF('01_Input'!$G$61="Résiduel vs Gestion",0,IF('01_Input'!$G$61="Taux Classe sélectionnée",Distrib_Global_Classe_Selectionnee*I$20,IF('01_Input'!$G$61="Frais KYC (paliers de 100M€)",MAX(0,Nb_Investisseurs-Nb_KYC_Gratuites_Par_Tranche*(FLOOR(I$20/Taille_Tranche_KYC,1)+1))*Cout_Par_KYC_Supplementaire,(IF('01_Input'!$L$61="Forfait",IF(I$20>='01_Input'!$J$61,'01_Input'!$M$61,0),IF('01_Input'!$L$61="Palier",IF(AND(I$20>='01_Input'!$J$61,I$20<'01_Input'!$K$61),'01_Input'!$M$61,0),MAX(MIN(I$20,'01_Input'!$K$61)-'01_Input'!$J$61,0)*'01_Input'!$M$61))+IF('01_Input'!$P$61="Forfait",IF(I$20>='01_Input'!$N$61,'01_Input'!$Q$61,0),IF('01_Input'!$P$61="Palier",IF(AND(I$20>='01_Input'!$N$61,I$20<'01_Input'!$O$61),'01_Input'!$Q$61,0),MAX(MIN(I$20,'01_Input'!$O$61)-'01_Input'!$N$61,0)*'01_Input'!$Q$61))+IF('01_Input'!$T$61="Forfait",IF(I$20>='01_Input'!$R$61,'01_Input'!$U$61,0),IF('01_Input'!$T$61="Palier",IF(AND(I$20>='01_Input'!$R$61,I$20<'01_Input'!$S$61),'01_Input'!$U$61,0),MAX(MIN(I$20,'01_Input'!$S$61)-'01_Input'!$R$61,0)*'01_Input'!$U$61))+IF('01_Input'!$X$61="Forfait",IF(I$20>='01_Input'!$V$61,'01_Input'!$Y$61,0),IF('01_Input'!$X$61="Palier",IF(AND(I$20>='01_Input'!$V$61,I$20<'01_Input'!$W$61),'01_Input'!$Y$61,0),MAX(MIN(I$20,'01_Input'!$W$61)-'01_Input'!$V$61,0)*'01_Input'!$Y$61))+IF('01_Input'!$AB$61="Forfait",IF(I$20>='01_Input'!$Z$61,'01_Input'!$AC$61,0),IF('01_Input'!$AB$61="Palier",IF(AND(I$20>='01_Input'!$Z$61,I$20<'01_Input'!$AA$61),'01_Input'!$AC$61,0),MAX(MIN(I$20,'01_Input'!$AA$61)-'01_Input'!$Z$61,0)*'01_Input'!$AC$61))))))))) -> 12000 | J29: =IF('01_Input'!$C$61="Non",0,MIN('01_Input'!$I$61,MAX('01_Input'!$H$61,IF('01_Input'!$G$61="Résiduel vs Gestion",0,IF('01_Input'!$G$61="Taux Classe sélectionnée",Distrib_Global_Classe_Selectionnee*J$20,IF('01_Input'!$G$61="Frais KYC (paliers de 100M€)",MAX(0,Nb_Investisseurs-Nb_KYC_Gratuites_Par_Tranche*(FLOOR(J$20/Taille_Tranche_KYC,1)+1))*Cout_Par_KYC_Supplementaire,(IF('01_Input'!$L$61="Forfait",IF(J$20>='01_Input'!$J$61,'01_Input'!$M$61,0),IF('01_Input'!$L$61="Palier",IF(AND(J$20>='01_Input'!$J$61,J$20<'01_Input'!$K$61),'01_Input'!$M$61,0),MAX(MIN(J$20,'01_Input'!$K$61)-'01_Input'!$J$61,0)*'01_Input'!$M$61))+IF('01_Input'!$P$61="Forfait",IF(J$20>='01_Input'!$N$61,'01_Input'!$Q$61,0),IF('01_Input'!$P$61="Palier",IF(AND(J$20>='01_Input'!$N$61,J$20<'01_Input'!$O$61),'01_Input'!$Q$61,0),MAX(MIN(J$20,'01_Input'!$O$61)-'01_Input'!$N$61,0)*'01_Input'!$Q$61))+IF('01_Input'!$T$61="Forfait",IF(J$20>='01_Input'!$R$61,'01_Input'!$U$61,0),IF('01_Input'!$T$61="Palier",IF(AND(J$20>='01_Input'!$R$61,J$20<'01_Input'!$S$61),'01_Input'!$U$61,0),MAX(MIN(J$20,'01_Input'!$S$61)-'01_Input'!$R$61,0)*'01_Input'!$U$61))+IF('01_Input'!$X$61="Forfait",IF(J$20>='01_Input'!$V$61,'01_Input'!$Y$61,0),IF('01_Input'!$X$61="Palier",IF(AND(J$20>='01_Input'!$V$61,J$20<'01_Input'!$W$61),'01_Input'!$Y$61,0),MAX(MIN(J$20,'01_Input'!$W$61)-'01_Input'!$V$61,0)*'01_Input'!$Y$61))+IF('01_Input'!$AB$61="Forfait",IF(J$20>='01_Input'!$Z$61,'01_Input'!$AC$61,0),IF('01_Input'!$AB$61="Palier",IF(AND(J$20>='01_Input'!$Z$61,J$20<'01_Input'!$AA$61),'01_Input'!$AC$61,0),MAX(MIN(J$20,'01_Input'!$AA$61)-'01_Input'!$Z$61,0)*'01_Input'!$AC$61))))))))) -> 12000 | K29: =IF('01_Input'!$C$61="Non",0,MIN('01_Input'!$I$61,MAX('01_Input'!$H$61,IF('01_Input'!$G$61="Résiduel vs Gestion",0,IF('01_Input'!$G$61="Taux Classe sélectionnée",Distrib_Global_Classe_Selectionnee*K$20,IF('01_Input'!$G$61="Frais KYC (paliers de 100M€)",MAX(0,Nb_Investisseurs-Nb_KYC_Gratuites_Par_Tranche*(FLOOR(K$20/Taille_Tranche_KYC,1)+1))*Cout_Par_KYC_Supplementaire,(IF('01_Input'!$L$61="Forfait",IF(K$20>='01_Input'!$J$61,'01_Input'!$M$61,0),IF('01_Input'!$L$61="Palier",IF(AND(K$20>='01_Input'!$J$61,K$20<'01_Input'!$K$61),'01_Input'!$M$61,0),MAX(MIN(K$20,'01_Input'!$K$61)-'01_Input'!$J$61,0)*'01_Input'!$M$61))+IF('01_Input'!$P$61="Forfait",IF(K$20>='01_Input'!$N$61,'01_Input'!$Q$61,0),IF('01_Input'!$P$61="Palier",IF(AND(K$20>='01_Input'!$N$61,K$20<'01_Input'!$O$61),'01_Input'!$Q$61,0),MAX(MIN(K$20,'01_Input'!$O$61)-'01_Input'!$N$61,0)*'01_Input'!$Q$61))+IF('01_Input'!$T$61="Forfait",IF(K$20>='01_Input'!$R$61,'01_Input'!$U$61,0),IF('01_Input'!$T$61="Palier",IF(AND(K$20>='01_Input'!$R$61,K$20<'01_Input'!$S$61),'01_Input'!$U$61,0),MAX(MIN(K$20,'01_Input'!$S$61)-'01_Input'!$R$61,0)*'01_Input'!$U$61))+IF('01_Input'!$X$61="Forfait",IF(K$20>='01_Input'!$V$61,'01_Input'!$Y$61,0),IF('01_Input'!$X$61="Palier",IF(AND(K$20>='01_Input'!$V$61,K$20<'01_Input'!$W$61),'01_Input'!$Y$61,0),MAX(MIN(K$20,'01_Input'!$W$61)-'01_Input'!$V$61,0)*'01_Input'!$Y$61))+IF('01_Input'!$AB$61="Forfait",IF(K$20>='01_Input'!$Z$61,'01_Input'!$AC$61,0),IF('01_Input'!$AB$61="Palier",IF(AND(K$20>='01_Input'!$Z$61,K$20<'01_Input'!$AA$61),'01_Input'!$AC$61,0),MAX(MIN(K$20,'01_Input'!$AA$61)-'01_Input'!$Z$61,0)*'01_Input'!$AC$61))))))))) -> 12000 | L29: =IF('01_Input'!$C$61="Non",0,MIN('01_Input'!$I$61,MAX('01_Input'!$H$61,IF('01_Input'!$G$61="Résiduel vs Gestion",0,IF('01_Input'!$G$61="Taux Classe sélectionnée",Distrib_Global_Classe_Selectionnee*L$20,IF('01_Input'!$G$61="Frais KYC (paliers de 100M€)",MAX(0,Nb_Investisseurs-Nb_KYC_Gratuites_Par_Tranche*(FLOOR(L$20/Taille_Tranche_KYC,1)+1))*Cout_Par_KYC_Supplementaire,(IF('01_Input'!$L$61="Forfait",IF(L$20>='01_Input'!$J$61,'01_Input'!$M$61,0),IF('01_Input'!$L$61="Palier",IF(AND(L$20>='01_Input'!$J$61,L$20<'01_Input'!$K$61),'01_Input'!$M$61,0),MAX(MIN(L$20,'01_Input'!$K$61)-'01_Input'!$J$61,0)*'01_Input'!$M$61))+IF('01_Input'!$P$61="Forfait",IF(L$20>='01_Input'!$N$61,'01_Input'!$Q$61,0),IF('01_Input'!$P$61="Palier",IF(AND(L$20>='01_Input'!$N$61,L$20<'01_Input'!$O$61),'01_Input'!$Q$61,0),MAX(MIN(L$20,'01_Input'!$O$61)-'01_Input'!$N$61,0)*'01_Input'!$Q$61))+IF('01_Input'!$T$61="Forfait",IF(L$20>='01_Input'!$R$61,'01_Input'!$U$61,0),IF('01_Input'!$T$61="Palier",IF(AND(L$20>='01_Input'!$R$61,L$20<'01_Input'!$S$61),'01_Input'!$U$61,0),MAX(MIN(L$20,'01_Input'!$S$61)-'01_Input'!$R$61,0)*'01_Input'!$U$61))+IF('01_Input'!$X$61="Forfait",IF(L$20>='01_Input'!$V$61,'01_Input'!$Y$61,0),IF('01_Input'!$X$61="Palier",IF(AND(L$20>='01_Input'!$V$61,L$20<'01_Input'!$W$61),'01_Input'!$Y$61,0),MAX(MIN(L$20,'01_Input'!$W$61)-'01_Input'!$V$61,0)*'01_Input'!$Y$61))+IF('01_Input'!$AB$61="Forfait",IF(L$20>='01_Input'!$Z$61,'01_Input'!$AC$61,0),IF('01_Input'!$AB$61="Palier",IF(AND(L$20>='01_Input'!$Z$61,L$20<'01_Input'!$AA$61),'01_Input'!$AC$61,0),MAX(MIN(L$20,'01_Input'!$AA$61)-'01_Input'!$Z$61,0)*'01_Input'!$AC$61))))))))) -> 14000 | ... EX29: =IF('01_Input'!$C$61="Non",0,MIN('01_Input'!$I$61,MAX('01_Input'!$H$61,IF('01_Input'!$G$61="Résiduel vs Gestion",0,IF('01_Input'!$G$61="Taux Classe sélectionnée",Distrib_Global_Classe_Selectionnee*EX$20,IF('01_Input'!$G$61="Frais KYC (paliers de 100M€)",MAX(0,Nb_Investisseurs-Nb_KYC_Gratuites_Par_Tranche*(FLOOR(EX$20/Taille_Tranche_KYC,1)+1))*Cout_Par_KYC_Supplementaire,(IF('01_Input'!$L$61="Forfait",IF(EX$20>='01_Input'!$J$61,'01_Input'!$M$61,0),IF('01_Input'!$L$61="Palier",IF(AND(EX$20>='01_Input'!$J$61,EX$20<'01_Input'!$K$61),'01_Input'!$M$61,0),MAX(MIN(EX$20,'01_Input'!$K$61)-'01_Input'!$J$61,0)*'01_Input'!$M$61))+IF('01_Input'!$P$61="Forfait",IF(EX$20>='01_Input'!$N$61,'01_Input'!$Q$61,0),IF('01_Input'!$P$61="Palier",IF(AND(EX$20>='01_Input'!$N$61,EX$20<'01_Input'!$O$61),'01_Input'!$Q$61,0),MAX(MIN(EX$20,'01_Input'!$O$61)-'01_Input'!$N$61,0)*'01_Input'!$Q$61))+IF('01_Input'!$T$61="Forfait",IF(EX$20>='01_Input'!$R$61,'01_Input'!$U$61,0),IF('01_Input'!$T$61="Palier",IF(AND(EX$20>='01_Input'!$R$61,EX$20<'01_Input'!$S$61),'01_Input'!$U$61,0),MAX(MIN(EX$20,'01_Input'!$S$61)-'01_Input'!$R$61,0)*'01_Input'!$U$61))+IF('01_Input'!$X$61="Forfait",IF(EX$20>='01_Input'!$V$61,'01_Input'!$Y$61,0),IF('01_Input'!$X$61="Palier",IF(AND(EX$20>='01_Input'!$V$61,EX$20<'01_Input'!$W$61),'01_Input'!$Y$61,0),MAX(MIN(EX$20,'01_Input'!$W$61)-'01_Input'!$V$61,0)*'01_Input'!$Y$61))+IF('01_Input'!$AB$61="Forfait",IF(EX$20>='01_Input'!$Z$61,'01_Input'!$AC$61,0),IF('01_Input'!$AB$61="Palier",IF(AND(EX$20>='01_Input'!$Z$61,EX$20<'01_Input'!$AA$61),'01_Input'!$AC$61,0),MAX(MIN(EX$20,'01_Input'!$AA$61)-'01_Input'!$Z$61,0)*'01_Input'!$AC$61))))))))) -> 0
